Workbook

Sheet Summary
A1: FlashKa Keychain v0.7 - what it really costs
A2: Complete cost of building the light from scratch: electronics (one JLCPCB panel: main PCB + key board), housing (JLCCNC: aluminium tray + lid, a PMMA kit with the main keys, a POM-C kit; JLC3DP, in the same order: the resin casting mould for the rubber side keys, once per builder), bought parts (the 14500 cell, LED board, TIR optic, laser, screws), consumables (including the nickel strip and the casting supplies), shipping, EU VAT and customs for Lithuania. Scenario A = you build ONE light (JLCPCB still sells 5 bare panels and assembles at least 2), scenario B = you build FIVE (type 2 in B to see two lights). Prices that did not change keep the date they were read (2026-10-14 for v0.5, 2026-10-18 for v0.6, 2026-10-21 for the first v0.7 layout); the parts of the 1000 lm power stage were read on 2026-10-22, the cell, the nickel strip and R3 on 2026-10-23. Blue on amber cells are ESTIMATES because the shop shows its price only after you upload the files (or no listing was read) - replace them with the real quote.
A3: Colour code: blue = typed-in number, blue on amber = ESTIMATE, black = formula, green = taken from another sheet. USD is the main currency, EUR = USD / rate.
A5: Inputs
A6: Exchange rate (USD per EUR) | B6: 1.1188 | C6: USD per EUR | D6: ECB euro reference rate of 13 Oct 2026 (not refreshed since v0.5). Change it to the rate of your bank/card. Source: https://www.ecb.europa.eu/stats/policy_and_exchange_rates/euro_reference_exchange_rates/html/eurofxref-graph-usd.en.html (read 2026-10-13)
A7: Scenario A: lights you build | B7: 1 | C7: lights | D7: Scenario A: you build one light.
A8: Scenario B: lights you build | B8: 5 | C8: lights | D8: Scenario B: you build five lights (all JLC minimums are used up). Type 2 to see two lights.
A9: Price check date (v0.7) | B9: 2026-10-23 | C9: One-cell layout (2026-10-23): the Vapcell F15 cell and the nickel strip (nkon.nl), R3 (C4109, LCSC) and the Vapcell K10 (illumn.com) were read on this date; nkon's shipping rate could not be read (ESTIMATE). 1000 lm power stage (2026-10-22): the buck TPS62095 and the protection IC DW01A (LCSC), the LED board, the TIR optic, the ECON 80 urethane, Sugru, JLC3DP's resin rate, JLCCNC's merged ordering and the EU customs rules; the page of the MOSFET SE8830A could not be read (ESTIMATE). First v0.7 check (2026-10-21): the pogo pin, the JLCPCB panel fee for two designs, JLCCNC's minimum size for plastic parts. Prices and fees that did not change keep the date they were read: 2026-10-14 (v0.5 check; LCSC and JLC pages) and 2026-10-18 (v0.6; the pages of C115357 and C25104 could not be read, those lines are ESTIMATES). Re-check before ordering.
A11: Total cost
A12: Cost group | B12: A: total (USD) | C12: A: total (EUR) | D12: A: per light (USD) | E12: A: per light (EUR) | F12: B: total (USD) | G12: B: total (EUR) | H12: B: per light (USD) | I12: B: per light (EUR) | J12: Share of B | K12: Basis
A13: Lights built | B13: =$B$7 -> 1 | F13: =$B$8 -> 5
A14: 1. PCB + assembly (JLCPCB, one panel: main PCB + key board) | B14: ='JLCPCB order'!$E$81 -> 236.89618 | C14: =B14/$B$6 -> 211.74131 | D14: =B14/$B$7 -> 236.89618 | E14: =D14/$B$6 -> 211.74131 | F14: ='JLCPCB order'!$G$81 -> 282.06529 | G14: =F14/$B$6 -> 252.11413 | H14: =F14/$B$8 -> 56.413059 | I14: =H14/$B$6 -> 50.422827 | J14: =F14/F32 -> 0.18850215 | K14: Fees: JLCPCB price page, read 2026-10-14, main rates and the panel fee re-read 2026-10-21. Parts: LCSC prices read 2026-10-14, the pogo pin 2026-10-21, the buck and the protection IC 2026-10-22, R3 2026-10-23; C238645, C25104, C115357 are ESTIMATES. Bare panels and the two-design surcharge: ESTIMATES.
A15: of which bare panels + two-design surcharge (4 layers, 0.8 mm, ENIG, black solder mask) | B15: ='JLCPCB order'!$E$49+'JLCPCB order'!$E$50 -> 45 | C15: =B15/$B$6 -> 40.221666 | D15: =B15/$B$7 -> 45 | E15: =D15/$B$6 -> 40.221666 | F15: ='JLCPCB order'!$G$49+'JLCPCB order'!$G$50 -> 45 | G15: =F15/$B$6 -> 40.221666 | H15: =F15/$B$8 -> 9 | I15: =H15/$B$6 -> 8.0443332 | K15: ESTIMATE - the price appears only after the Gerber upload.
A16: of which assembly fees (set-up, stencil, joints, feeder, panel fee, X-ray, ...) | B16: ='JLCPCB order'!$E$72 -> 145.14528 | C16: =B16/$B$6 -> 129.733 | D16: =B16/$B$7 -> 145.14528 | E16: =D16/$B$6 -> 129.733 | F16: ='JLCPCB order'!$G$72 -> 151.08819 | G16: =F16/$B$6 -> 135.04486 | H16: =F16/$B$8 -> 30.217639 | I16: =H16/$B$6 -> 27.008973 | K16: JLCPCB fee page, sheet 'JLCPCB order'.
A17: of which components (35 lines, 79 parts per panel, incl. spares for placement loss) | B17: ='Panel BOM'!$T$44 -> 46.7509 | C17: =B17/$B$6 -> 41.786646 | D17: =B17/$B$7 -> 46.7509 | E17: =D17/$B$6 -> 41.786646 | F17: ='Panel BOM'!$W$44 -> 85.9771 | G17: =F17/$B$6 -> 76.847605 | H17: =F17/$B$8 -> 17.19542 | I17: =H17/$B$6 -> 15.369521 | K17: LCSC price tiers, sheet 'Panel BOM'.
A18: 2. Housing (JLCCNC + JLC3DP: aluminium tray + lid, PMMA and POM-C kits, resin casting mould) | B18: =Housing!$B$129 -> 132.90562 | C18: =B18/$B$6 -> 118.79301 | D18: =B18/$B$7 -> 132.90562 | E18: =D18/$B$6 -> 118.79301 | F18: =Housing!$C$129 -> 432.50404 | G18: =F18/$B$6 -> 386.57851 | H18: =F18/$B$8 -> 86.500807 | I18: =H18/$B$6 -> 77.315702 | J18: =F18/F32 -> 0.28903924 | K18: ESTIMATE - replace by the JLCCNC and JLC3DP instant quotes.
A19: of which aluminium tray + lid (bead blast + black anodize, no marking) | B19: =Housing!$B$96 -> 98.337105 | C19: =B19/$B$6 -> 87.89516 | D19: =B19/$B$7 -> 98.337105 | E19: =D19/$B$6 -> 87.89516 | F19: =Housing!$C$96 -> 347.68553 | G19: =F19/$B$6 -> 310.76647 | H19: =F19/$B$8 -> 69.537105 | I19: =H19/$B$6 -> 62.153294 | K19: ESTIMATE from volume, box, fine features and finish, sheet 'Housing' sections 2-6 (the panel texture included: 'texture_on').
A20: of which PMMA kit (main keys) + POM-C kit (RF insert, antenna spacer) | B20: =Housing!$E$122 -> 31.25 | C20: =B20/$B$6 -> 27.931713 | D20: =B20/$B$7 -> 31.25 | E20: =D20/$B$6 -> 27.931713 | F20: =Housing!$G$122 -> 81.5 | G20: =F20/$B$6 -> 72.845906 | H20: =F20/$B$8 -> 16.3 | I20: =H20/$B$6 -> 14.569181 | K20: ESTIMATE - JLCCNC publishes no price for plastic parts; sheet 'Housing' section 7.
A21: of which resin casting mould for the rubber side keys (two SLA plates, JLC3DP, once per builder) | B21: =Housing!$B$110 -> 3.31851 | C21: =B21/$B$6 -> 2.9661334 | D21: =B21/$B$7 -> 3.31851 | E21: =D21/$B$6 -> 2.9661334 | F21: =Housing!$C$110 -> 3.31851 | G21: =F21/$B$6 -> 2.9661334 | H21: =F21/$B$8 -> 0.663702 | I21: =H21/$B$6 -> 0.59322667 | K21: ESTIMATE from JLC3DP's headline rate, sheet 'Housing' section 6b. Leave it out if you already have a mould.
A22: 3. Bought parts (the cell, LED board, TIR optic, laser, screws, set screw, split ring, mould hardware) | B22: ='Bought parts'!$L$31 -> 65.79 | C22: =B22/$B$6 -> 58.804076 | D22: =B22/$B$7 -> 65.79 | E22: =D22/$B$6 -> 58.804076 | F22: ='Bought parts'!$N$31 -> 203 | G22: =F22/$B$6 -> 181.4444 | H22: =F22/$B$8 -> 40.6 | I22: =H22/$B$6 -> 36.288881 | J22: =F22/F32 -> 0.1356634 | K22: The cell, the LED board and the optic READ; the rest typical prices (ESTIMATES), sheet 'Bought parts'.
A23: 4. Consumables (nickel strip, wire, thermal paste, tapes, foam, silicone pads, adhesives, casting supplies) | B23: ='Bought parts'!$L$32 -> 115.53 | C23: =B23/$B$6 -> 103.26242 | D23: =B23/$B$7 -> 115.53 | E23: =D23/$B$6 -> 103.26242 | F23: ='Bought parts'!$N$32 -> 115.53 | G23: =F23/$B$6 -> 103.26242 | H23: =F23/$B$8 -> 23.106 | I23: =H23/$B$6 -> 20.652485 | J23: =F23/F32 -> 0.077207843 | K23: Typical prices (ESTIMATES); the nickel strip read at nkon.nl, the urethane rubber at kaupo.de. Sheet 'Bought parts'.
A24: of which casting supplies for the side keys (urethane, pigment, release, shim, glue, cups, polishes) | B24: ='Bought parts'!$L$37 -> 85.95 | C24: =B24/$B$6 -> 76.823382 | D24: =B24/$B$7 -> 85.95 | E24: =D24/$B$6 -> 76.823382 | F24: ='Bought parts'!$N$37 -> 85.95 | G24: =F24/$B$6 -> 76.823382 | H24: =F24/$B$8 -> 17.19 | I24: =H24/$B$6 -> 15.364676 | K24: Once per builder; one unit of rubber casts many keys.
A25: 5. Shipping, VAT, customs duty, carrier and bank fees | B25: ='Hidden costs'!$J$45 -> 308.16073 | C25: =B25/$B$6 -> 275.43862 | D25: =B25/$B$7 -> 308.16073 | E25: =D25/$B$6 -> 275.43862 | F25: ='Hidden costs'!$J$57 -> 463.25124 | G25: =F25/$B$6 -> 414.06082 | H25: =F25/$B$8 -> 92.650249 | I25: =H25/$B$6 -> 82.812164 | J25: =F25/F32 -> 0.30958737 | K25: Computed from EU rules and shipping ESTIMATES, sheet 'Hidden costs'.
A26: of which shipping (JLCPCB, JLCCNC + JLC3DP, the EU casting shop, the optic distributor, the battery shop, web-shop parcels) | B26: ='Hidden costs'!$F$43 -> 110.93 | C26: =B26/$B$6 -> 99.150876 | D26: =B26/$B$7 -> 110.93 | E26: =D26/$B$6 -> 99.150876 | F26: ='Hidden costs'!$F$55 -> 113.93 | G26: =F26/$B$6 -> 101.83232 | H26: =F26/$B$8 -> 22.786 | I26: =H26/$B$6 -> 20.366464 | K26: Shipping per parcel are ESTIMATES (JLC shows them in the cart).
A27: of which VAT 21 % | B27: ='Hidden costs'!$H$43 -> 139.03088 | C27: =B27/$B$6 -> 124.26786 | D27: =B27/$B$7 -> 139.03088 | E27: =D27/$B$6 -> 124.26786 | F27: ='Hidden costs'!$H$55 -> 246.64071 | G27: =F27/$B$6 -> 220.45112 | H27: =F27/$B$8 -> 49.328142 | I27: =H27/$B$6 -> 44.090224 | K27: Lithuania 21 %, collected by JLC at checkout up to EUR 150 per parcel.
A28: of which customs duty and carrier fees | B28: ='Hidden costs'!$G$43+'Hidden costs'!$I$43 -> 50.346 | C28: =B28/$B$6 -> 45 | D28: =B28/$B$7 -> 50.346 | E28: =D28/$B$6 -> 45 | F28: ='Hidden costs'!$G$55+'Hidden costs'!$I$55 -> 87.865442 | G28: =F28/$B$6 -> 78.535433 | H28: =F28/$B$8 -> 17.573088 | I28: =H28/$B$6 -> 15.707087 | K28: Flat EUR 3 per customs line up to EUR 150 per parcel; formal clearance + carrier fee above.
A29: of which card / currency conversion fee | B29: ='Hidden costs'!$J$44 -> 7.8538495 | C29: =B29/$B$6 -> 7.019887 | D29: =B29/$B$7 -> 7.8538495 | E29: =D29/$B$6 -> 7.019887 | F29: ='Hidden costs'!$J$56 -> 14.81509 | G29: =F29/$B$6 -> 13.241947 | H29: =F29/$B$8 -> 2.963018 | I29: =H29/$B$6 -> 2.6483894 | K29: ESTIMATE 1.5 % on the USD payments to JLC.
A30: JLCPCB order vs the EUR 150 IOSS line (EUR left; negative = above, formal customs) | B30: ='JLCPCB order'!$E$83 -> -61.74131 | F30: ='JLCPCB order'!$G$83 -> -102.11413 | G30: Above the line the parcel pays a carrier fee of about EUR 15 (sheet 'Hidden costs', sections 4-6).
A31: JLCCNC + JLC3DP order vs the EUR 150 IOSS line (EUR left; negative = above, formal customs) | B31: =Housing!$B$128 -> 31.206994 | F31: =Housing!$C$128 -> -236.57851 | G31: One light: below the line (VAT and EUR 3 per customs line only). More lights: above it (6 % duty, VAT and a carrier fee).
A32: TOTAL for the lights (1 + 2 + 3 + 4 + 5) | B32: =B14+B18+B22+B23+B25 -> 859.28252 | C32: =B32/$B$6 -> 768.03943 | D32: =B32/$B$7 -> 859.28252 | E32: =D32/$B$6 -> 768.03943 | F32: =F14+F18+F22+F23+F25 -> 1496.3506 | G32: =F32/$B$6 -> 1337.4603 | H32: =F32/$B$8 -> 299.27011 | I32: =H32/$B$6 -> 267.49206 | K32: Per-light columns divide by the number of lights built.
A33: Extra cost of each additional light (scenario B vs A) | B33: =IF($B$8=$B$7,0,(F32-B32)/($B$8-$B$7)) -> 159.26701 | C33: =B33/$B$6 -> 142.35521 | D33: Set-up fees, stencil, panel fee, feeder loading, the anodizing lot fee, the casting mould, the casting supplies and most shipping are paid once, so the 2nd to 5th light is much cheaper than the first.
A35: What changed since the first v0.7 layout (same scenarios and exchange rate; USD)
A36: The 'first layout' values are typed in from the cost workbook of the first v0.7 layout (price check 2026-10-21: SST-20 behind a glass window, 2 x 400 mAh cells with protection boards, a 3 A buck, the aluminium casting mould, PMC-780 DRY rubber; 1 light in A, 5 in B). Since then the light got the parts for 1000 lm and 100 m (TIR optic, 4 A buck with board protection, 24 AWG wire), one 14500 cell in an octagonal body, and cost was taken out where it does not hurt the design. A negative change is a saving. docs/bom_notes.md has the same table for 1, 2 and 5 lights.
A37: Cost group | B37: First layout: A | C37: Now: A | D37: Change A | E37: First layout: B | F37: Now: B | G37: Change B | H37: What changed (savings, new costs, quality)
A38: 1. PCB + assembly (JLCPCB) | B38: 228.66 | C38: =B14 -> 236.89618 | D38: =C38-B38 -> 8.2361775 | E38: 269.12 | F38: =F14 -> 282.06529 | G38: =F38-E38 -> 12.945294 | H38: No saving here: the 1000 lm power stage is new. The 4 A buck TPS62095 costs $1.35 per board (the TLV62585 it replaces cost $0.26), the protection IC DW01A $0.03 and the dual MOSFET SE8830A $0.10 (ESTIMATE), plus five small parts; U2 is a QFN, so X-ray counts 4 parts per panel instead of 3 ($13.12 instead of $9.84 for 2 panels). The cheaper pogo pin is an option (table below).
A39: 2. Housing | B39: 169.16 | C39: =B18 -> 132.90562 | D39: =C39-B39 -> -36.254385 | E39: 473.59 | F39: =F18 -> 432.50404 | G39: =F39-E39 -> -41.085963 | H39: Resin casting mould from JLC3DP ($3.32, ESTIMATE) instead of the aluminium mould ($35.12): $31.80 less, once per builder. The POM-C kit lost the LED spacer ring (one part type less: $31.25 instead of $37.75 for the kits). The body is 4.8 mm longer (for the optic and the cell) and an octagon 20 x 18 mm instead of a 20 x 16 mm rectangle (tray + lid $98.34 instead of $96.29). Quality: the resin print does not hold the aluminium mould's +/-0.02 mm (try the first key in its opening) and wears out sooner; the aluminium mould stays an option.
A40: 3. Bought parts | B40: 63.75 | C40: =B22 -> 65.79 | D40: =C40-B40 -> 2.04 | E40: 218.3 | F40: =F22 -> 203 | G40: =F40-E40 -> -15.3 | H40: LED board $2.99 instead of $5.40 (SST-20 Gen 2, Kaidomain, read); no glass window ($2.95 per 5). New: the TIR optic ($17.37 per pack of 5); one 14500 cell (Vapcell F15, $3.47 at nkon.nl, read) instead of two 400 mAh cells with protection boards ($4.50 each); the resin mould's bolts, washers and nuts ($4.00) instead of the aluminium mould's dowel pins and screws ($5.00).
A41: 4. Consumables | B41: 142.19 | C41: =B23 -> 115.53 | D41: =C41-B41 -> -26.66 | E41: 142.19 | F41: =F23 -> 115.53 | G41: =F41-E41 -> -26.66 | H41: ECON 80 urethane ($31.95 for 0.86 kg) instead of PMC-780 DRY ($60.40 for 1.36 kg): the same Shore 80A, mixed 1:1 by volume, so the 0.01 g scale is no longer needed; casting supplies $85.95 instead of $114.40. Thermal paste instead of thermal tape, 24 AWG wire for the 3 A paths, nickel strip for the cell ($2.08 per metre), 0.5 mm foam sheet. Quality: none - ECON 80 meets the 75-85 Shore A of the drawing; its pot life is 13 minutes instead of 25 (pour without delay).
A42: 5. Shipping, VAT, customs, fees | B42: 315.13 | C42: =B25 -> 308.16073 | D42: =C42-B42 -> -6.969274 | E42: 452.61 | F42: =F25 -> 463.25124 | G42: =F42-E42 -> 10.641243 | H42: The merged JLCCNC + JLC3DP order of one light is EUR 118.79, below the EUR 150 line (the first layout: EUR 151.20 with the aluminium mould, so 6 % duty, VAT and a carrier fee of about EUR 15); 8 web-shop parcels instead of 10 (no glass window; the cell comes from an EU shop). New: the optic distributor's parcel and the battery shop's parcel (ESTIMATE $20.00 and $13.43 shipping, VAT only). Duty and carrier fees $50.35 instead of $78.60, VAT $139.03 instead of $146.31, shipping $110.93 instead of $81.50.
A43: TOTAL for the lights | B43: 918.89 | C43: =B32 -> 859.28252 | D43: =C43-B43 -> -59.607481 | E43: 1555.81 | F43: =F32 -> 1496.3506 | G43: =F43-E43 -> -59.459427 | H43: Sum of the lines above.
A44: TOTAL per light (A: 1, B: 5) | B44: 918.89 | C44: =D32 -> 859.28252 | D44: =C44-B44 -> -59.607481 | E44: 311.16 | F44: =H32 -> 299.27011 | G44: =F44-E44 -> -11.889885 | H44: The 'first layout' B values are typed in for 5 lights (the B of this build). With another number in B8 compare only column A, or rebuild the workbook with tools/parts_list.py --lights-b N (2 lights: 532.04 -> 507.46 per light). Tools: $204.00 instead of $174.00 (no scale; a spot welder for the cell's nickel strips).
A46: What the battery and body change costs (two pouch cells in the 20 x 16 mm body -> one Vapcell INR14500 F15 in the 20 x 18 mm octagon; USD)
A47: The 'two pouch cells' values are typed in from this workbook as it was just before the change (price check 2026-10-22: two 320 mAh pouch cells, ESTIMATE $5.00 each, from a web shop; the 20 x 16 mm body with its 1.5 mm plate lid; 1 light in A, 5 in B). Everything else is the same in both columns. A negative change is a saving. docs/bom_notes.md has the same table for 1, 2 and 5 lights.
A48: Cost group | B48: Two pouch cells: A | C48: One 14500 cell: A | D48: Change A | E48: Two pouch cells: B | F48: One 14500 cell: B | G48: Change B | H48: What changed (savings, new costs, quality)
A49: 1. PCB + assembly (JLCPCB) | B49: 236.91 | C49: =B14 -> 236.89618 | D49: =C49-B49 -> -0.0138225 | E49: 282.08 | F49: =F14 -> 282.06529 | G49: =F49-E49 -> -0.01470625 | H49: R3 is 2.0 k (C4109, $0.0026 each from 100 pieces) instead of 3.3 k (C25890, $0.0036): the charger gives about 494 mA instead of 280 mA (a full charge in about 3.5 h). The same 35 lines and 79 parts per panel: the fees do not change.
A50: 2. Housing | B50: 131.89 | C50: =B18 -> 132.90562 | D50: =C50-B50 -> 1.0156154 | E50: 427.41 | F50: =F18 -> 432.50404 | G50: =F50-E50 -> 5.0940368 | H50: Tray + lid $98.34 instead of $97.32: the section is 2 mm taller (20 x 18 mm octagon), the lid a 3.4 mm cap (7.25 mm tall with its bosses) instead of a 1.5 mm plate, plus the diagonal facets and the cap pocket (sheet 'Housing', section 4). The kits ($31.25) and the resin mould cost the same.
A51: 3. Bought parts | B51: 73.85 | C51: =B22 -> 65.79 | D51: =C51-B51 -> -8.06 | E51: 237.18 | F51: =F22 -> 203 | G51: =F51-E51 -> -34.18 | H51: One Vapcell INR14500 F15 ($3.47 at nkon.nl, read 2026-10-23) instead of two 320 mAh pouch cells (ESTIMATE $5.00 each: no public price), each with one spare: $6.94 instead of $15.00 for one light. The longer lid screws (M1.6 x 6) are priced like the old ones.
A52: 4. Consumables | B52: 113.45 | C52: =B23 -> 115.53 | D52: =C52-B52 -> 2.08 | E52: 113.45 | F52: =F23 -> 115.53 | G52: =F52-E52 -> 2.08 | H52: New: 1 m of pure nickel strip for the two tabs ($2.08, read); the foam is now 0.5 mm sheet (same ESTIMATE). Without welded tabs on the cell you also need a small spot welder: tools $204.00 instead of $164.00 (+$40.00, not in the per-light cost; 0 with a pre-tabbed cell).
A53: 5. Shipping, VAT, customs, fees | B53: 298.71 | C53: =B25 -> 308.16073 | D53: =C53-B53 -> 9.450726 | E53: 457.99 | F53: =F25 -> 463.25124 | G53: =F53-E53 -> 5.2612427 | H53: The cell and the strip come in their own parcel from an EU battery shop (ESTIMATE $13.43 shipping + 21 % VAT, no duty) instead of one of the web-shop parcels (8 instead of 9, each $2.00 shipping + EUR 3 duty). Shipping $110.93 instead of $99.50, VAT $139.03 instead of $137.68, duty and carrier fees $50.35 instead of $53.70.
A54: TOTAL for the lights | B54: 854.81 | C54: =B32 -> 859.28252 | D54: =C54-B54 -> 4.4725189 | E54: 1518.11 | F54: =F32 -> 1496.3506 | G54: =F54-E54 -> -21.759427 | H54: Sum of the lines above.
A55: TOTAL per light (A: 1, B: 5) | B55: 854.81 | C55: =D32 -> 859.28252 | D55: =C55-B55 -> 4.4725189 | E55: 303.62 | F55: =H32 -> 299.27011 | G55: =F55-E55 -> -4.3498853 | H55: The 'two pouch cells' B values are typed in for 5 lights (the B of this build) (2 lights: 508.47 -> 507.46 per light). The cell itself got cheaper and has 2.3 times the capacity (1500 mAh instead of two 320 mAh cells); the bigger body, the nickel strip and the battery shop's own parcel cost more.
A57: Options: what each one saves against the defaults above, and what it costs in quality (USD, VAT, duty and shipping included)
A58: Computed by tools/parts_list.py with the default inputs of this workbook (each option alone; they do not follow later changes of the inputs). A positive number is a saving, a negative one an extra cost. The defaults are the cheapest choices that keep the design as drawn: the texture stays because the order files carry it and it is part of the exterior style; the Harwin pogo pin stays because the cheaper pin is not verified.
A59: Option | B59: Saves A | C59: Saves B | D59: What it costs in quality / what to do
A60: Leave out the panel texture (type 0 in 'texture_on', sheet 'Housing') | B60: 12.591357 | C60: 66.734194 | D60: Plain recessed panels instead of the V texture: the light looks different from the pictures, nothing else changes. The STEP files carry the texture: ask the shop to skip feature 17 of drawing FK-H-01 (or have texture-free STEP files made) - otherwise the quote still includes it.
A61: Economy shipping instead of express (type 1 in 'ship_mode', sheet 'Hidden costs') | B61: 47.7345 | C61: 50.141674 | D61: Two to five weeks instead of about one; tracking and the customs handling are less predictable, and the EUR 3 per line may be asked at your door.
A62: Cheaper pogo pins: Xinyangze YZ00615050R-08 (LCSC C7429459) instead of the Harwin P70-1010045R | B62: 25.082507 | C62: 42.679441 | D62: LCSC does not state the plating or whether it has a locating peg (the key board has no hole for one); rated 1 A (plenty for these signals); 720 in stock. Not verified, so not the default: to use it, change the LCSC number in tools/kicad/flashka_parts.py and the panel BOM, and check the footprint first.
A63: Sugru instead of ECON 80 for the side keys (no pigment, no urethane release: petroleum jelly) | B63: 61.7221 | C63: 61.7221 | D63: Shore 70A, softer than the 75-85 of the drawing: the keys feel softer. 48 h cure in the closed mould; the stiffener is bedded in fresh Sugru because cyanoacrylate does not hold on cured Sugru.
A64: Aluminium casting mould (JLCCNC) instead of the resin mould (a negative saving: it costs more) | B64: -40.26565 | C64: -42.608989 | D64: Better, not worse: +/-0.02 mm instead of the print's tolerance, lasts for many pours, bead-blasted matte key faces without sanding. Needs 2 dowel pins and 4 M3 x 12 screws instead of the M3 x 16 bolts, washers and nuts.
A66: What changed from v0.6 (same scenarios and exchange rate; USD)
A67: The v0.6 values are typed in from the v0.6 cost workbook (sheet 'Summary', price check 2026-10-18; the v0.6 package keeps that workbook). Electronics: one panel with two boards, 35 BOM lines, 79 placements, 267 solder joints per panel (v0.6: 34 lines, 68 placements, 232 joints on one board) - the six pogo pins and the 1000 lm power stage are new, the switches, ring LEDs and eight resistors moved to the key board. Housing: no stainless caps, no laser marking, no glass window; new are the octagonal body, the PMMA and POM-C kits, the resin casting mould and the panel texture and grooves. Battery: one 14500 cell instead of two pouch cells with protection boards.
A68: Cost group | B68: v0.6: A | C68: v0.7: A | D68: Change A | E68: v0.6: B | F68: v0.7: B | G68: Change B | H68: What changed
A69: 1. PCB + assembly (JLCPCB) | B69: 174.32774 | C69: =B14 -> 236.89618 | D69: =C69-B69 -> 62.568441 | E69: 194.68669 | F69: =F14 -> 282.06529 | G69: =F69-E69 -> 87.378602 | H69: A bigger bare panel with two designs (ESTIMATE $30 for 5 instead of $25, plus a two-design surcharge, ESTIMATE $15) and the panel fee for two designs ($8.21, read). New parts: the six pogo pins (C22100007) and the 1000 lm power stage (4 A buck TPS62095, protection DW01A + SE8830A); X-ray for 4 parts per panel.
A70: 2. Housing | B70: 122.55751 | C70: =B18 -> 132.90562 | D70: =C70-B70 -> 10.348106 | E70: 382.38755 | F70: =F18 -> 432.50404 | G70: =F70-E70 -> 50.116491 | H70: The stainless caps, the laser marking and the resin print kit are gone. New: the octagonal body (20 x 18 mm, the lid a 3.4 mm cap), the PMMA kit with the clear main keys, the POM-C kit, the resin casting mould for the rubber side keys (once per builder) and the recessed panels with the V texture and the transverse grooves on the tray and the lid (sheet 'Housing', sections 4-7).
A71: 3. Bought parts | B71: 56.75 | C71: =B22 -> 65.79 | D71: =C71-B71 -> 9.04 | E71: 211.3 | F71: =F22 -> 203 | G71: =F71-E71 -> -8.3 | H71: New: the TIR optic instead of the glass window, one Vapcell INR14500 F15 cell (1500 mAh, protected on the main board) instead of two 400 mAh pouch cells with protection boards, two M1.6 x 2.5 key-board screws per light, the mould's M3 bolts (once per builder); the SST-20 Gen 2 LED board costs less.
A72: 4. Consumables | B72: 27.79 | C72: =B23 -> 115.53 | D72: =C72-B72 -> 87.74 | E72: 27.79 | F72: =F23 -> 115.53 | G72: =F72-E72 -> 87.74 | H72: New: the casting supplies for the rubber side keys (urethane rubber, pigment, mould release, stainless shim, glue, cups, polishes), the nickel strip for the cell, 24 AWG wire, thermal paste, 0.5 mm foam; the can hold-down pad is now 1.5 mm thick.
A73: 5. Shipping, VAT, customs, fees | B73: 238.78269 | C73: =B25 -> 308.16073 | D73: =C73-B73 -> 69.378039 | E73: 378.82269 | F73: =F25 -> 463.25124 | G73: =F73-E73 -> 84.428549 | H73: Follows from the orders: no 3D-print parcel of its own (the resin mould travels with JLCCNC), a parcel each from the EU casting shop, the optic distributor and the battery shop (VAT only, no customs), two customs lines on the JLCCNC parcel, the card fee on two JLC payments.
A74: TOTAL for the lights | B74: 620.20793 | C74: =B32 -> 859.28252 | D74: =C74-B74 -> 239.07459 | E74: 1194.9869 | F74: =F32 -> 1496.3506 | G74: =F74-E74 -> 301.36364 | H74: Sum of the lines above.
A75: TOTAL per light (A: 1 light, B: 5 lights) | B75: 620.20793 | C75: =D32 -> 859.28252 | D75: =C75-B75 -> 239.07459 | E75: 238.99739 | F75: =H32 -> 299.27011 | G75: =F75-E75 -> 60.272728 | H75: Per-light price in USD; the EUR values are in the table above. The v0.6 values are for 1 and 5 lights: compare B only while B is 5.
A77: Not in the per-light cost
A78: Tools (one-time purchase, only the tools marked 'needed') | B78: =Tools!$I$29 -> 204 | C78: =B78/$B$6 -> 182.33822 | D78: Sheet 'Tools'. If you already own soldering equipment, set 'Needed' to 0 there.
A79: TOTAL including tools | B79: =B32+B78 -> 1063.2825 | C79: =B79/$B$6 -> 950.37765 | F79: =F32+B78 -> 1700.3506 | G79: =F79/$B$6 -> 1519.7985
A80: Optional tools not counted | B80: =Tools!$I$30 -> 170 | C80: =B80/$B$6 -> 151.94852
A81: Risk reserve: second PCB + assembly order (not in any total) | B81: ='Hidden costs'!$B$64 -> 329.44137 | C81: =B81/$B$6 -> 294.45958 | D81: A new board often needs a second round (the key board, the pogo contact and the power stage are new). Landed cost of a second JLCPCB order like scenario A.
A82: Risk reserve: second housing order (not in any total) | B82: ='Hidden costs'!$B$65 -> 194.14859 | C82: =B82/$B$6 -> 173.53289 | D82: If the first tray does not fit the delivered laser / cell / optic.
A84: How reliable is each part of the total?
A85: Item | B85: Status | E85: Where to replace it with a real number
A86: JLCPCB assembly fees | B86: READ from the JLCPCB price page (last updated Sep 09, 2026); the panel fee for two designs read 2026-10-21 | E86: Sheet 'JLCPCB order' section 5; the cart shows the final fee list.
A87: Components at LCSC / JLC | B87: READ from the LCSC product pages for 32 lines (2026-10-14; the pogo pin 2026-10-21; the buck and the protection IC 2026-10-22; R3 2026-10-23); ESTIMATE for the 3 lines C238645, C25104, C115357 (pages not readable) | E87: Sheet 'Panel BOM' (amber cells); the JLC cart shows the real component price after the BOM upload.
A88: Bare panels and the two-design surcharge | B88: ESTIMATE (shown only after the Gerber upload) | E88: Sheet 'JLCPCB order' section 4: type the prices from the cart.
A89: Aluminium tray + lid | B89: ESTIMATE from volume, box, fine features and finish | E89: Sheet 'Housing' section 6: type the JLCCNC instant quote.
A90: PMMA and POM-C kits | B90: ESTIMATE (JLCCNC publishes no price for plastic parts) | E90: Sheet 'Housing' section 7: type the JLCCNC instant quote.
A91: Casting mould | B91: ESTIMATE from JLC3DP's headline resin rate (once per builder) | E91: Sheet 'Housing' section 6b: type the JLC3DP quote (or the JLCCNC quote of the aluminium mould), or 0 if you have a mould.
A92: Bought parts and consumables | B92: READ: the LED board (Kaidomain), the TIR optic (RS) and the ECON 80 urethane (kaupo.de), 2026-10-22; the cell and the nickel strip (nkon.nl), 2026-10-23; ESTIMATES: the AliExpress search snippets of 2026-10-14 and typical prices | E92: Sheet 'Bought parts': change the blue prices.
A93: Shipping | B93: ESTIMATES (JLC publishes no rate table; the courier fees of the distributor and of the battery shop not read) | E93: Sheet 'Hidden costs' section 2: type the 'Shipping Estimate' of each cart.
A94: VAT and customs | B94: COMPUTED from the EU rules; duty rates of the formal route are assumptions | E94: Sheet 'Hidden costs'. Watch the EUR 150 line of both JLC orders.
A95: Tools | B95: ESTIMATES (typical prices) | E95: Sheet 'Tools'.
A97: Sheets: Summary | JLCPCB order | Panel BOM | Housing | Bought parts | Hidden costs | Tools | Ordering checklist. Notes on sources, estimates and what to re-check: docs/bom_notes.md; rebuild: python3 tools/parts_list.py.

Sheet JLCPCB order
A1: JLCPCB order - one panel (key board + main PCB), bare panels + Standard PCBA (parts on both faces)
A2: What you order at jlcpcb.com in ONE order: 5 bare 4-layer panels (each holds the key board and the main PCB, black solder mask) and the assembly (soldering of all SMD parts) of 2 or 5 of them. Column E = scenario A (you build 1 light), column G = scenario B (you build 5 lights). Every fee is a blue input with the date it was read and its URL: the fee page says 'Last updated on Sep 09, 2026'; it was read on 2026-10-14 and its main rates were checked again on 2026-10-21 (the panel fee for two designs was read then). Prices change - re-check before you pay.
A3: Colour code: blue = typed-in number, blue on amber = ESTIMATE (no public price), black = formula, green = taken from another sheet.
A5: 1. What to select in the JLCPCB cart (https://cart.jlcpcb.com/quote)
A6: Setting | B6: Value | E6: Why / what to watch
A7: Base material / layers | B7: FR-4, 4 layers | E7: Both boards use the same 4-layer stack-up with an inner ground plane. Do not change the layer count.
A8: Dimensions | B8: 45.0 x 32.5 mm (JLC reads it from the Gerber) | E8: One panel: key board left, main PCB right, two 6 mm rails with 3 fiducials and 4 tooling holes (section 2).
A9: PCB quantity | B9: 5 | E9: JLCPCB minimum. Four spare panels cost little and cover first-article problems.
A10: Delivery format / panel format | B10: Panel by Customer, 1 x 1 | E10: The Gerber already is the panel; do not let JLCPCB panelise it again.
A11: Different design | B11: 2 | E11: Two different boards in one file: JLCPCB adds a surcharge, shown after the upload (section 4, ESTIMATE).
A12: PCB thickness | B12: 0.8 mm | E12: The housing is built around 0.8 mm boards (main PCB on its ledges, key board on its bosses).
A13: Surface finish | B13: ENIG (immersion gold) | E13: Flat pads for the module and the fine-pitch parts, and gold pads J6 under the pogo pins.
A14: Solder mask / silkscreen | B14: BLACK solder mask, WHITE silkscreen | E14: The design and all renders use black boards. A colour surcharge, if the cart shows one, belongs to the bare-panel price.
A15: Copper / via covering | B15: 1 oz outer, 0.5 oz inner; tented vias | E15: Defaults; the board is designed for them. Option: inner copper 1 oz (a small surcharge in the quote) halves the resistance of the 2 mm battery strip inside the board.
A16: Edge rails / fiducials | B16: by customer (on the rails) | E16: If JLCPCB's review asks for a bigger panel for Standard assembly (it names 70 x 70 mm as the smallest), accept the edge rails it offers.
A17: Order number on the board | B17: Default (JLC prints a code in a free area) | E17: Removing the code costs extra; it stays inside the closed body.
... A24: Shipping | B24: Your choice (see sheet 'Hidden costs') | E24: Choose DDP / 'taxes paid' so the VAT is collected at checkout and nothing is asked at your door.
A26: 2. The panel and the two boards (mm)
A27: Panel width (mm) | B27: 45 | C27: tools/kicad/panel_jlc.py: key board left, main PCB right, 2.0 mm routed gaps, 6 mm rails top and bottom; the Gerber job file gives 45.1 x 32.6 mm (the 0.1 mm outline stroke included).
A28: Panel height (mm) | B28: 32.5
A29: Panel area (cm2) | B29: =B27*B28/100 -> 14.625 | C29: Only feeds the tiny packing fee. JLCPCB measures the Gerber itself. The panel stays inside the cheapest 4-layer size class (up to 50 x 50 mm).
A30: Main PCB (information) | B30: 24.0 x 16.5 mm, two corners chamfered 1.3 mm, 3.94 cm2 (housing_interface.json 'pcb_outline'); unchanged from v0.6.
A31: Key board (information) | B31: 19.0 x 14.8 mm, corners R1.0, 0.8 mm, 4 layers: switches and ring LEDs on the bottom face, six pogo pins and eight resistors on the top face.
A33: 3. Quantities (JLCPCB minimums: 5 bare panels, assembly from 2 panels)
A34: Minimum panels JLCPCB assembles | B34: 2 | C34: panels | D34: JLCPCB assembles from 2 boards; one light therefore still pays for 2 assembled panels (1 spare). The 'board' JLCPCB counts is the panel: key board + main PCB. Source: https://jlcpcb.com/pcb-assembly (read 2026-10-14)
A35: Minimum bare panels per design | B35: 5 | C35: panels | D35: JLCPCB sells at least 5 bare boards (here: panels) per design. Source: https://cart.jlcpcb.com/quote (read 2026-10-14)
A36: Assembled sides (double-sided) | B36: 2 | C36: sides | D36: Parts are on both faces of both boards = double-sided Standard PCBA (Economic PCBA is single-sided only).
A37: X-ray inspected parts per panel (optional) | B37: 4 | C37: parts per panel | D37: Fee page: 'X-ray inspection is required for components such as BGA, QFN and other leadless packages', charged per component. The COUNT is an assumption: U4 (ESP32 module, pads under it) and U2 (the buck TPS62095, a QFN without leads, new with the 1000 lm power stage) on the main PCB, LED3 and LED4 (pads under the package) on the key board = 4 per panel. Set 0 if your cart does not ask for it. Source: https://jlcpcb.com/help/article/pcb-assembly-price (read 2026-10-22)
E38: Scenario A | G38: Scenario B
A39: Lights you build | E39: =Summary!$B$7 -> 1 | G39: =Summary!$B$8 -> 5
A40: Panels assembled by JLCPCB = MAX(lights, minimum) | E40: =MAX(E39,$B$34) -> 2 | G40: =MAX(G39,$B$34) -> 5
A41: Bare panels ordered (sold in steps of 5) | E41: =CEILING(MAX($B$35,E40),5) -> 5 | G41: =CEILING(MAX($B$35,G40),5) -> 5
A43: 4. Bare panel fabrication (4 layers, 0.8 mm, ENIG, black solder mask, 45.0 x 32.5 mm) - shown by JLCPCB only AFTER the Gerber upload
A44: Bare panels, price for 5 (ESTIMATE) | B44: 30 | C44: USD for 5 panels | D44: ESTIMATE ($25-35 for 5): bare panels 45.0 x 32.5 mm, 4 layers, 0.8 mm, ENIG, black solder mask, white silkscreen. JLCPCB shows the price only after the Gerber upload (v0.6 estimated $25 for five 24 x 16.5 mm main PCBs). A colour surcharge, if the cart shows one, belongs here. Source: https://cart.jlcpcb.com/quote (read 2026-10-21)
A45: low end of the range (information) | B45: 25 | C45: USD for 5 panels | D45: ESTIMATE. Low end of the estimate range (information only). (2026-10-21)
A46: high end of the range (information) | B46: 35 | C46: USD for 5 panels | D46: ESTIMATE. High end of the estimate range (information only). (2026-10-21)
A47: Surcharge for two designs in one file (ESTIMATE) | B47: 15 | C47: USD per order | D47: ESTIMATE ($10-20): JLCPCB charges extra for more than one design in one Gerber file ('different design' fee, order option 'Different Design: 2'); the amount appears only in the calculator after the upload. Source: https://jlcpcb.com/help/article/In-what-cases-will-there-be-charged-extra (read 2026-10-21)
A48: Anchors: a 100 x 100 mm 4-layer board costs about $32.90 for 5 (https://pcbsync.com/pcb-prototype-services-compared/, 2026); a forum guide puts ENIG at +$5-10 on small orders (https://zbotic.in/how-to-order-pcb-from-jlcpcb-and-pcbway-india-cost-guide/); v0.6 estimated $25 for 5 single main PCBs. The 'different design' fee exists on JLCPCB's panelisation pages (https://jlcpcb.com/help/article/96-PCB-Panelization) but its amount appears only in the calculator. Real price: upload order_files/1_JLCPCB/FlashKa_panel_gerbers.zip at https://cart.jlcpcb.com/quote, choose the options of section 1 and type the prices shown into the two amber cells above.
A49: Bare panel cost (price for 5 x panels ordered / 5) | E49: =$B$44*$E$41/5 -> 30 | G49: =$B$44*$G$41/5 -> 30
A50: Two-design surcharge (once per order) | E50: =$B$47 -> 15 | G50: =$B$47 -> 15
A52: 5. Standard PCBA fees (JLCPCB 'PCB assembly price' page, last updated Sep 09, 2026) - https://jlcpcb.com/help/article/pcb-assembly-price
A53: Fee | B53: Rate (USD) | C53: Unit | D53: Qty A | E53: Cost A (USD) | F53: Qty B | G53: Cost B (USD) | H53: Date read | I53: Source | J53: Note
A54: Set-up fee (Standard PCBA), per assembled side | B54: 25.56 | C54: USD per side | D54: =$B$36 -> 2 | E54: =B54*D54 -> 51.12 | F54: =$B$36 -> 2 | G54: =B54*F54 -> 51.12 | H54: 2026-10-14 | I54: https://jlcpcb.com/help/article/pcb-assembly-price | J54: Standard PCBA set-up fee: $25.56 single-sided / $51.12 double-sided. Covers the engineering check (no separate engineering fee). Re-read on 2026-10-21: unchanged.
A55: Stencil (Standard PCBA), per assembled side | B55: 8.21 | C55: USD per side | D55: =$B$36 -> 2 | E55: =B55*D55 -> 16.42 | F55: =$B$36 -> 2 | G55: =B55*F55 -> 16.42 | H55: 2026-10-14 | I55: https://jlcpcb.com/help/article/pcb-assembly-price | J55: Standard PCBA stencil: $8.21 single-sided / $16.42 double-sided. Re-read on 2026-10-21: unchanged.
A56: SMT assembly, per solder joint (joints per panel x panels) | B56: 0.0016 | C56: USD per joint | D56: ='Panel BOM'!$K$44*$E$40 -> 534 | E56: =B56*D56 -> 0.8544 | F56: ='Panel BOM'!$K$44*$G$40 -> 1335 | G56: =B56*F56 -> 2.136 | H56: 2026-10-14 | I56: https://jlcpcb.com/help/article/pcb-assembly-price | J56: SMT assembly price per solder joint (1-50,000 joints).
A57: Feeder loading, per unique part (Basic and Extended alike) | B57: 1.53 | C57: USD per unique part | D57: ='Panel BOM'!$J$45 -> 35 | E57: =B57*D57 -> 53.55 | F57: ='Panel BOM'!$J$45 -> 35 | G57: =B57*F57 -> 53.55 | H57: 2026-10-14 | I57: https://jlcpcb.com/help/article/pcb-assembly-price | J57: Feeder loading, Standard PCBA: $1.53 for every unique part number, Basic and Extended alike (no separate engineering fee and no separate extended-part fee). Re-read on 2026-10-21: unchanged.
A58: Extra fee per unique Extended part (Economic PCBA only - none in Standard) | B58: 0 | C58: USD per unique Extended part | D58: ='Panel BOM'!$J$46 -> 17 | E58: =B58*D58 -> 0 | F58: ='Panel BOM'!$J$46 -> 17 | G58: =B58*F58 -> 0 | H58: 2026-10-14 | I58: https://jlcpcb.com/help/article/pcb-assembly-price | J58: Only Economic PCBA charges an extra $3.07 per Extended part. In Standard PCBA (this order) every unique part, Basic or Extended, pays the same feeder-loading fee instead, so there is no separate extended-part fee. Type 3.00 here to test the effect of such a fee.
A59: Engineering fee (not on the 2026 page) | B59: 0 | C59: USD per order | D59: 1 | E59: =B59*D59 -> 0 | F59: 1 | G59: =B59*F59 -> 0 | H59: 2026-10-14 | I59: https://jlcpcb.com/help/article/pcb-assembly-price | J59: No separate engineering fee on the 2026 page; the set-up fee covers it.
A60: Confirm parts placement (optional, recommended) | B60: 0.45 | C60: USD per order | D60: 1 | E60: =B60*D60 -> 0.45 | F60: 1 | G60: =B60*F60 -> 0.45 | H60: 2026-10-14 | I60: https://jlcpcb.com/help/article/pcb-assembly-price | J60: 'Confirm parts placement': JLC sends a photo of the placement for your OK. Strongly recommended for a first order.
A61: Panel fee: more than one design in the file (key board + main PCB) | B61: 8.21 | C61: USD per order | D61: 1 | E61: =B61*D61 -> 8.21 | F61: 1 | G61: =B61*F61 -> 8.21 | H61: 2026-10-21 | I61: https://jlcpcb.com/help/article/pcb-assembly-price | J61: Panel fee of Standard PCBA when the file holds more than one design (the panel carries the key board and the main PCB). Read on the fee page (last updated Sep 09, 2026).
A62: X-ray inspection (optional): parts inspected = parts per panel x panels | B62: tiered (section 7) | C62: USD per part (tiered) | D62: =$B$37*$E$40 -> 8 | E62: =IF(D62=0,0,D62*INDEX($B$88:$B$94,MATCH(D62,$A$88:$A$94,1))) -> 13.12 | F62: =$B$37*$G$40 -> 20 | G62: =IF(F62=0,0,F62*INDEX($B$88:$B$94,MATCH(F62,$A$88:$A$94,1))) -> 16.4 | H62: 2026-10-22 | I62: https://jlcpcb.com/help/article/pcb-assembly-price | J62: Fee page: 'X-ray inspection is required for components such as BGA, QFN and other leadless packages', charged per component. The COUNT is an assumption: U4 (ESP32 module, pads under it) and U2 (the buck TPS62095, a QFN without leads, new with the 1000 lm power stage) on the main PCB, LED3 and LED4 (pads under the package) on the key board = 4 per panel. Set 0 if your cart does not ask for it.
A63: Panelisation processing by JLC (small board), per panel | B63: 0.46 | C63: USD per panel | D63: =$E$40 -> 2 | E63: =B63*D63 -> 0.92 | F63: =$G$40 -> 5 | G63: =B63*F63 -> 2.3 | H63: 2026-10-14 | I63: https://jlcpcb.com/help/article/Panelizing-your-PCB-for-Assembly | J63: JLC panelises small boards for assembly; the page quotes a minimum processing cost of $0.46 per board. ASSUMED to apply per panel (45.0 x 32.5 mm is below the 70 x 70 mm that JLCPCB names as the smallest Standard-assembly panel).
A64: Packing (Standard PCBA), base per order | B64: 0.5 | C64: USD per order | D64: 1 | E64: =B64*D64 -> 0.5 | F64: 1 | G64: =B64*F64 -> 0.5 | H64: 2026-10-14 | I64: https://jlcpcb.com/help/article/pcb-assembly-price | J64: Packing, Standard PCBA: $0.50 + $0.00003 per cm2 of board.
A65: Packing, per cm2 of panel (panel area x panels) | B65: 3e-05 | C65: USD per cm2 | D65: =$B$29*$E$40 -> 29.25 | E65: =B65*D65 -> 0.0008775 | F65: =$B$29*$G$40 -> 73.125 | G65: =B65*F65 -> 0.00219375 | H65: 2026-10-14 | I65: https://jlcpcb.com/help/article/pcb-assembly-price | J65: See above (negligible for a 15 cm2 panel).
A66: Hand-soldering labour (not needed) - quantity 0 | B66: 3.58 | C66: USD per order | D66: 0 | E66: =B66*D66 -> 0 | F66: 0 | G66: =B66*F66 -> 0 | H66: 2026-10-14 | I66: https://jlcpcb.com/help/article/pcb-assembly-price | J66: Hand-soldering labour. Not needed: no through-hole parts. Quantity 0.
A67: 'Pre-reflow soldering' per joint (unexplained row) - quantity 0 | B67: 0.016 | C67: USD per joint | D67: 0 | E67: =B67*D67 -> 0 | F67: 0 | G67: =B67*F67 -> 0 | H67: 2026-10-14 | I67: https://jlcpcb.com/help/article/pcb-assembly-price | J67: Row 'pre-reflow soldering' on the fee page, not explained there. Quantity 0 - check your quote.
A68: Single-board surcharge (the panel avoids it) - quantity 0 | B68: 0.48 | C68: USD per order | D68: 0 | E68: =B68*D68 -> 0 | F68: 0 | G68: =B68*F68 -> 0 | H68: 2026-10-14 | I68: https://jlcpcb.com/help/article/pcb-assembly-price | J68: Single-board surcharge; the panel avoids it. Quantity 0.
A69: Fixtures (not needed) - quantity 0 | B69: 8.21 | C69: USD per fixture | D69: 0 | E69: =B69*D69 -> 0 | F69: 0 | G69: =B69*F69 -> 0 | H69: 2026-10-14 | I69: https://jlcpcb.com/help/article/pcb-assembly-price | J69: Test/assembly fixture (minimum 2). Not needed. Quantity 0.
A70: Stencil / fixture storage (not needed) - quantity 0 | B70: 4.93 | C70: USD per item | D70: 0 | E70: =B70*D70 -> 0 | F70: 0 | G70: =B70*F70 -> 0 | H70: 2026-10-14 | I70: https://jlcpcb.com/help/article/pcb-assembly-price | J70: Stencil or fixture storage. Not needed. Quantity 0.
A71: Large-size surcharge (not applicable) - quantity 0 | B71: 57.46 | C71: USD per order | D71: 0 | E71: =B71*D71 -> 0 | F71: 0 | G71: =B71*F71 -> 0 | H71: 2026-10-14 | I71: https://jlcpcb.com/help/article/pcb-assembly-price | J71: Large-size surcharge for boards above 650 cm2. Not applicable (the panel is 45.0 x 32.5 mm). Quantity 0.
A72: Assembly fees, subtotal | E72: =SUM(E54:E71) -> 145.14528 | G72: =SUM(G54:G71) -> 151.08819
A74: 6. Total of the JLCPCB order (before shipping, VAT and customs)
E75: Scenario A | G75: Scenario B
A76: Bare panels | E76: =$E$49 -> 30 | G76: =$G$49 -> 30
A77: Two-design surcharge (section 4) | E77: =$E$50 -> 15 | G77: =$G$50 -> 15
A78: Assembly fees (section 5) | E78: =$E$72 -> 145.14528 | G78: =$G$72 -> 151.08819
A79: Components bought by JLCPCB (sheet 'Panel BOM') | E79: ='Panel BOM'!$T$44 -> 46.7509 | G79: ='Panel BOM'!$W$44 -> 85.9771 | I79: Includes the extra pieces JLC buys for placement loss (they are billed and thrown away).
A80: of which extra pieces for placement loss (information) | E80: ='Panel BOM'!$T$48 -> 11.3001 | G80: ='Panel BOM'!$W$48 -> 10.8501
A81: TOTAL JLCPCB order before shipping/VAT (USD) | E81: =E76+E77+E78+E79 -> 236.89618 | G81: =G76+G77+G78+G79 -> 282.06529
A82: the same in EUR | E82: =E81/Summary!$B$6 -> 211.74131 | G82: =G81/Summary!$B$6 -> 252.11413
A83: Distance below the EUR 150 IOSS line (negative = above) | E83: ='Hidden costs'!$B$6-E82 -> -61.74131 | G83: ='Hidden costs'!$B$6-G82 -> -102.11413 | I83: Up to EUR 150 JLC collects 21 % VAT at checkout and the flat EUR 3 duty; above EUR 150 the parcel needs formal customs clearance and the carrier adds a fee of about EUR 15 - see sheet 'Hidden costs'.
A84: Route | E84: =IF(E83<0,"formal clearance","IOSS") -> formal clearance | G84: =IF(G83<0,"formal clearance","IOSS") -> formal clearance
A86: 7. X-ray price table (per inspected part, by the total number of inspected parts in the order) - https://jlcpcb.com/help/article/pcb-assembly-price, read 2026-10-14
A87: Total parts inspected from | B87: USD per part
A88: 1 | B88: 1.64
A89: 11 | B89: 0.82
A90: 51 | B90: 0.49
A91: 201 | B91: 0.33
A92: 501 | B92: 0.25
A93: 1001 | B93: 0.16
A94: 3001 | B94: 0.082
A96: 8. Things to know
A97: Why one panel: both boards carry parts on both faces, so each needs Standard assembly with a set-up fee and a stencil per side. In one panel they share one order, one set-up per side, one stencil per side and the feeders of the parts they have in common, and the key board gets the main PCB's 4-layer 0.8 mm ENIG stack-up. Ordered separately (fall-back files in production/: FlashKa_main_gerbers.zip + BOM/CPL_JLCPCB_main.csv, FlashKa_keys_gerbers.zip + BOM/CPL_JLCPCB_keys.csv) the two orders would pay four set-ups and four stencils and two bare-board orders: about $208 in assembly fees (estimate) instead of the fees in section 5.
A98: Basic vs Extended: 18 of the 35 BOM lines are Basic, 17 are Extended (JLC part type read on jlcpcb.com/partdetail/<LCSC> on 2026-10-14; C115357, C25104, C22100007 and C238645 are ASSUMED). In the 2026 Standard PCBA price list every unique part pays the same feeder-loading fee, Basic or Extended, so Extended parts cost no extra here (the separate $3.07 per Extended part belongs to Economic PCBA; the input above is kept at 0).
A99: Parts that JLC cannot supply (out of stock) stop the order: JLC tells you by e-mail and you may substitute. Low-stock lines are marked in sheet 'Panel BOM'. Retail stock at LCSC is not JLC's warehouse stock. The pogo pins (C22100007) had only 100 pcs at LCSC on 2026-10-21; the stock of the SE8830A (C238645) could not be read on 2026-10-22.
A100: Placement loss: JLC buys a few pieces more than needed (they are billed inside the component price, see https://jlcpcb.com/help/article/pcb-assembly-faqs-part-2). The extra counts are estimates in sheet 'Panel BOM'.
A101: After delivery: break both boards out of the rails at the small perforated tabs and file the 0.3 mm nubs flush (two on each long side of each board).
A102: ENIG, 0.8 mm, 4 layers and black solder mask are standard options at JLCPCB (https://jlcpcb.com/capabilities/pcb-capabilities); only the price of the bare panel is unknown until you upload the Gerber.

Sheet Panel BOM
A1: Panel bill of materials - what JLCPCB assembles on the two boards (main PCB + key board)
A2: One line per component type (grouped by LCSC number), derived from tools/kicad/flashka_parts.py with the same grouping and ordering as tools/kicad/build_all.py, which writes the BOM you upload as order_files/1_JLCPCB/BOM_JLCPCB.csv: 35 lines, 79 placements, 267 solder joints per panel. Wire pads (J2 cell, J3 LED, J5 laser), the pogo target pads J6 and the key board's screw holes H1, H2 have no LCSC number: they are NOT assembled. The LED board, the TIR optic, the 14500 cell and the laser are bought parts (sheet 'Bought parts'). New in v0.7: the six pogo pins P1-P6 (Harwin P70-1010045R); SW1-SW3, LED3, LED4 and eight resistors moved from the main PCB to the key board, which JLCPCB makes in the same panel; the 1000 lm power stage added the 4 A buck TPS62095 (U2), the cell protection DW01A (U6) with the dual MOSFET SE8830A (Q3) and five small parts; for the 14500 cell R3 is 2.0 k (C4109) instead of 3.3 k, so the charger gives about 494 mA instead of 280 mA.
A3: Unit price = the LCSC price tier that matches the quantity JLCPCB has to buy = (quantity per panel x panels assembled) + extra pieces for placement loss (columns P-Q). Prices were read from the LCSC product pages on 2026-10-14 (v0.5 price check; the lines that did not change keep that date), for the pogo pin C22100007 on 2026-10-21, for the buck C139643 and the protection IC C351410 on 2026-10-22 and for R3 (C4109) on 2026-10-23 (columns X-AI hold the tier tables, typed in from the page). The three lines whose pages could not be read (C115357 and C25104 on 2026-10-18, C238645 on 2026-10-22) are blue on amber = ESTIMATE: tiers from the parts named in the 'Price source' column. JLC buys from LCSC/its own warehouse; the real component price shows in the JLC cart after the BOM upload.
A4: Basic / Extended = JLCPCB library type read on jlcpcb.com/partdetail/<LCSC number> on 2026-10-14 (assumed, amber, for four lines: Extended for C115357, C22100007 and C238645, Basic for C25104 - check them in the JLC BOM upload). In 2026 Standard PCBA every unique part costs the same feeder fee, Basic or Extended (see sheet 'JLCPCB order'); the 'Preferred' tag (only relevant for the single-sided Economic PCBA) was not shown on any of these pages. 'LCSC stock' is LCSC's retail stock, NOT JLC's warehouse; JLC flags real shortages when you upload the BOM.
B5: Panels assembled, scenario A | C5: ='JLCPCB order'!$E$40 -> 2
B6: Panels assembled, scenario B | C6: ='JLCPCB order'!$G$40 -> 5
A8: # | B8: Designators | C8: Value | D8: Footprint | E8: LCSC # | F8: Manufacturer part no. | G8: Manufacturer | H8: Description (flashka_parts.py) | I8: What it does (and on which board) | J8: Qty / panel | K8: Solder joints / part | L8: JLC part type | M8: JLC part page | N8: LCSC stock (retail) | O8: Stock note | P8: Loss class | Q8: Extra pcs | R8: Buy qty A | S8: Unit USD A | T8: Line USD A | U8: Buy qty B | V8: Unit USD B | W8: Line USD B | X8: Tier 1 from qty | Y8: Tier 2 from qty | Z8: Tier 3 from qty | AA8: Tier 4 from qty | AB8: Tier 5 from qty | AC8: Tier 6 from qty | AD8: Tier 1 USD | AE8: Tier 2 USD | AF8: Tier 3 USD | AG8: Tier 4 USD | AH8: Tier 5 USD | AI8: Tier 6 USD | AJ8: Price source
A9: 1 | B9: C1 | C9: 10uF | D9: C_0805_2012Metric | E9: C15850 | F9: CL21A106KAYNNNE | G9: Samsung Electro-Mechanics | H9: 10uF 25V X5R 0805 | I9: Smoothing capacitor on the USB 5 V input (25 V rating needed). Main PCB. | J9: =LEN(B9)-LEN(SUBSTITUTE(B9,",",""))+1 -> 1 | K9: 2 | L9: Basic | M9: JLC page | N9: 20 | O9: LOW: only 20 pcs at LCSC retail; JLC's own stock is separate - the BOM upload flags a shortage. Any 10 uF 25 V X5R 0805 Basic part is a substitute. | P9: p0603 | Q9: =INDEX($C$53:$C$56,MATCH(P9,$B$53:$B$56,0)) -> 5 | R9: =J9*$C$5+Q9 -> 7 | S9: =INDEX($AD9:$AI9,MAX(1,COUNTIF($X9:$AC9,"<="&R9))) -> 0.0695 | T9: =R9*S9 -> 0.4865 | U9: =J9*$C$6+Q9 -> 10 | V9: =INDEX($AD9:$AI9,MAX(1,COUNTIF($X9:$AC9,"<="&U9))) -> 0.0695 | W9: =U9*V9 -> 0.695 | X9: 20 | Y9: 200 | Z9: 600 | AA9: 2000 | AB9: 10000 | AC9: 20000 | AD9: 0.0695 | AE9: 0.0513 | AF9: 0.0419 | AG9: 0.0342 | AH9: 0.0315 | AI9: 0.0297 | AJ9: https://www.lcsc.com/product-detail/C15850.html (read 2026-10-14)
A10: 2 | B10: C2,C13,C15 | C10: 10uF | D10: C_0603_1608Metric | E10: C19702 | F10: CL10A106KP8NNNC | G10: Samsung Electro-Mechanics | H10: 10uF 10V X5R 0603 | I10: 10 uF capacitors that smooth the supply next to the chips (C2, C13, C15). Main PCB. | J10: =LEN(B10)-LEN(SUBSTITUTE(B10,",",""))+1 -> 3 | K10: 2 | L10: Basic | M10: JLC page | N10: 181020 | O10: OK | P10: p0603 | Q10: =INDEX($C$53:$C$56,MATCH(P10,$B$53:$B$56,0)) -> 5 | R10: =J10*$C$5+Q10 -> 11 | S10: =INDEX($AD10:$AI10,MAX(1,COUNTIF($X10:$AC10,"<="&R10))) -> 0.0311 | T10: =R10*S10 -> 0.3421 | U10: =J10*$C$6+Q10 -> 20 | V10: =INDEX($AD10:$AI10,MAX(1,COUNTIF($X10:$AC10,"<="&U10))) -> 0.0311 | W10: =U10*V10 -> 0.622 | X10: 20 | Y10: 200 | Z10: 600 | AA10: 4000 | AB10: 8000 | AC10: 20000 | AD10: 0.0311 | AE10: 0.023 | AF10: 0.0195 | AG10: 0.0168 | AH10: 0.0157 | AI10: 0.015 | AJ10: https://www.lcsc.com/product-detail/C19702.html (read 2026-10-14)
A11: 3 | B11: C5,C8,C22 | C11: 22uF | D11: C_0603_1608Metric | E11: C59461 | F11: CL10A226MQ8NRNC | G11: Samsung Electro-Mechanics | H11: 22uF 6.3V X5R 0603 | I11: 22 uF capacitors for the buck converter / power rails (C5, C8, C22). Main PCB. | J11: =LEN(B11)-LEN(SUBSTITUTE(B11,",",""))+1 -> 3 | K11: 2 | L11: Basic | M11: JLC page | N11: 4416440 | O11: OK | P11: p0603 | Q11: =INDEX($C$53:$C$56,MATCH(P11,$B$53:$B$56,0)) -> 5 | R11: =J11*$C$5+Q11 -> 11 | S11: =INDEX($AD11:$AI11,MAX(1,COUNTIF($X11:$AC11,"<="&R11))) -> 0.0315 | T11: =R11*S11 -> 0.3465 | U11: =J11*$C$6+Q11 -> 20 | V11: =INDEX($AD11:$AI11,MAX(1,COUNTIF($X11:$AC11,"<="&U11))) -> 0.0315 | W11: =U11*V11 -> 0.63 | X11: 20 | Y11: 200 | Z11: 600 | AA11: 4000 | AB11: 8000 | AC11: 20000 | AD11: 0.0315 | AE11: 0.0236 | AF11: 0.0201 | AG11: 0.0174 | AH11: 0.0164 | AI11: 0.0157 | AJ11: https://www.lcsc.com/product-detail/C59461.html (read 2026-10-14)
A12: 4 | B12: C12,C14,C17,C18 | C12: 1uF | D12: C_0402_1005Metric | E12: C52923 | F12: CL05A105KA5NQNC | G12: Samsung Electro-Mechanics | H12: 1uF 25V X5R 0402 | I12: 1 uF 25 V capacitors for supply decoupling (C12, C14, C17, C18). Main PCB. | J12: =LEN(B12)-LEN(SUBSTITUTE(B12,",",""))+1 -> 4 | K12: 2 | L12: Basic | M12: JLC page | N12: 598000 | O12: OK | P12: p0402 | Q12: =INDEX($C$53:$C$56,MATCH(P12,$B$53:$B$56,0)) -> 10 | R12: =J12*$C$5+Q12 -> 18 | S12: =INDEX($AD12:$AI12,MAX(1,COUNTIF($X12:$AC12,"<="&R12))) -> 0.0085 | T12: =R12*S12 -> 0.153 | U12: =J12*$C$6+Q12 -> 30 | V12: =INDEX($AD12:$AI12,MAX(1,COUNTIF($X12:$AC12,"<="&U12))) -> 0.0085 | W12: =U12*V12 -> 0.255 | X12: 50 | Y12: 500 | Z12: 1500 | AA12: 10000 | AB12: 20000 | AC12: 50000 | AD12: 0.0085 | AE12: 0.0067 | AF12: 0.0059 | AG12: 0.0053 | AH12: 0.005 | AI12: 0.0049 | AJ12: https://www.lcsc.com/product-detail/C52923.html (read 2026-10-14)
A13: 5 | B13: C11,C23 | C13: 10nF | D13: C_0402_1005Metric | E13: C15195 | F13: CL05B103KB5NNNC | G13: Samsung Electro-Mechanics | H13: 10nF 50V X7R 0402 | I13: 10 nF capacitors: C11 (filter in the LED-current loop) and C23 (charge-pump capacitor of the buck U2). Main PCB. | J13: =LEN(B13)-LEN(SUBSTITUTE(B13,",",""))+1 -> 2 | K13: 2 | L13: Basic | M13: JLC page | N13: 0 | O13: LCSC retail shows OUT OF STOCK; JLC lists it as Basic and has its own warehouse - the BOM upload shows the real JLC stock. If flagged, pick another Basic 10 nF 0402 and update flashka_parts.py. | P13: p0402 | Q13: =INDEX($C$53:$C$56,MATCH(P13,$B$53:$B$56,0)) -> 10 | R13: =J13*$C$5+Q13 -> 14 | S13: =INDEX($AD13:$AI13,MAX(1,COUNTIF($X13:$AC13,"<="&R13))) -> 0.005 | T13: =R13*S13 -> 0.07 | U13: =J13*$C$6+Q13 -> 20 | V13: =INDEX($AD13:$AI13,MAX(1,COUNTIF($X13:$AC13,"<="&U13))) -> 0.005 | W13: =U13*V13 -> 0.1 | X13: 100 | Y13: 1000 | Z13: 3000 | AA13: 10000 | AB13: 50000 | AC13: 100000 | AD13: 0.005 | AE13: 0.0038 | AF13: 0.0033 | AG13: 0.0029 | AH13: 0.0028 | AI13: 0.0027 | AJ13: https://www.lcsc.com/product-detail/C15195.html (read 2026-10-14)
A14: 6 | B14: C10,C16,C19,C20,C24 | C14: 100nF | D14: C_0402_1005Metric | E14: C1525 | F14: CL05B104KO5NNNC | G14: Samsung Electro-Mechanics | H14: 100nF 16V X7R 0402 | I14: 100 nF capacitors: next to the chips' supply pins (C10, C16, C19, C20) and the supply filter of the protection IC U6 (C24). Main PCB. | J14: =LEN(B14)-LEN(SUBSTITUTE(B14,",",""))+1 -> 5 | K14: 2 | L14: Basic | M14: JLC page | N14: 0 | O14: LCSC retail shows OUT OF STOCK, but the JLC basic-parts list shows 23,496,493 pcs (read 2026-10-14), so JLC can assemble it. | P14: p0402 | Q14: =INDEX($C$53:$C$56,MATCH(P14,$B$53:$B$56,0)) -> 10 | R14: =J14*$C$5+Q14 -> 20 | S14: =INDEX($AD14:$AI14,MAX(1,COUNTIF($X14:$AC14,"<="&R14))) -> 0.0046 | T14: =R14*S14 -> 0.092 | U14: =J14*$C$6+Q14 -> 35 | V14: =INDEX($AD14:$AI14,MAX(1,COUNTIF($X14:$AC14,"<="&U14))) -> 0.0046 | W14: =U14*V14 -> 0.161 | X14: 100 | Y14: 1000 | Z14: 3000 | AA14: 10000 | AB14: 50000 | AC14: 100000 | AD14: 0.0046 | AE14: 0.0035 | AF14: 0.003 | AG14: 0.0026 | AH14: 0.0025 | AI14: 0.0024 | AJ14: https://www.lcsc.com/product-detail/C1525.html (read 2026-10-14)
A15: 7 | B15: D1 | C15: ESD5Z5.0T1G | D15: D_SOD-523 | E15: C82044 | F15: ESD5Z5.0T1G | G15: onsemi | H15: 5 V unidirectional TVS (VBUS), SOD-523 | I15: D1: protects the board from static / voltage spikes on the USB 5 V line. Main PCB. | J15: =LEN(B15)-LEN(SUBSTITUTE(B15,",",""))+1 -> 1 | K15: 2 | L15: Extended | M15: JLC page | N15: 370780 | O15: OK | P15: semi | Q15: =INDEX($C$53:$C$56,MATCH(P15,$B$53:$B$56,0)) -> 2 | R15: =J15*$C$5+Q15 -> 4 | S15: =INDEX($AD15:$AI15,MAX(1,COUNTIF($X15:$AC15,"<="&R15))) -> 0.0371 | T15: =R15*S15 -> 0.1484 | U15: =J15*$C$6+Q15 -> 7 | V15: =INDEX($AD15:$AI15,MAX(1,COUNTIF($X15:$AC15,"<="&U15))) -> 0.0371 | W15: =U15*V15 -> 0.2597 | X15: 20 | Y15: 200 | Z15: 600 | AA15: 3000 | AB15: 9000 | AC15: 21000 | AD15: 0.0371 | AE15: 0.029 | AF15: 0.0245 | AG15: 0.0204 | AH15: 0.0181 | AI15: 0.0168 | AJ15: https://www.lcsc.com/product-detail/C82044.html (read 2026-10-14)
A16: 8 | B16: J1 | C16: TYPE-C-31-M-12 | D16: USB_C_Receptacle_HRO_TYPE-C-31-M-12 | E16: C165948 | F16: TYPE-C-31-M-12 | G16: Korean Hroparts Elec | H16: USB-C 16P receptacle (USB 2.0 data), SMD + 4 shell legs | I16: J1: USB-C socket (charging and data). 16 signal pads + 4 shell legs = 20 joints. Main PCB. | J16: =LEN(B16)-LEN(SUBSTITUTE(B16,",",""))+1 -> 1 | K16: 20 | L16: Extended | M16: JLC page | N16: 375745 | O16: OK | P16: mod | Q16: =INDEX($C$53:$C$56,MATCH(P16,$B$53:$B$56,0)) -> 1 | R16: =J16*$C$5+Q16 -> 3 | S16: =INDEX($AD16:$AI16,MAX(1,COUNTIF($X16:$AC16,"<="&R16))) -> 0.1729 | T16: =R16*S16 -> 0.5187 | U16: =J16*$C$6+Q16 -> 6 | V16: =INDEX($AD16:$AI16,MAX(1,COUNTIF($X16:$AC16,"<="&U16))) -> 0.1729 | W16: =U16*V16 -> 1.0374 | X16: 5 | Y16: 50 | Z16: 150 | AA16: 1000 | AB16: 2000 | AC16: 5000 | AD16: 0.1729 | AE16: 0.1365 | AF16: 0.1187 | AG16: 0.0963 | AH16: 0.092 | AI16: 0.0894 | AJ16: https://www.lcsc.com/product-detail/C165948.html (read 2026-10-14)
A17: 9 | B17: L1 | C17: 1uH | D17: L_Changjiang_FNR4020S | E17: C602028 | F17: FHD4020S-1R0MT | G17: cjiang | H17: 1 uH 4x4 mm, Isat 11 A, 23 mOhm (cjiang FHD4020S-1R0MT) | I17: L1: 1 uH power inductor of the buck converter U2 (LED driver). Main PCB. | J17: =LEN(B17)-LEN(SUBSTITUTE(B17,",",""))+1 -> 1 | K17: 2 | L17: Extended | M17: JLC page | N17: 8210 | O17: OK | P17: mod | Q17: =INDEX($C$53:$C$56,MATCH(P17,$B$53:$B$56,0)) -> 1 | R17: =J17*$C$5+Q17 -> 3 | S17: =INDEX($AD17:$AI17,MAX(1,COUNTIF($X17:$AC17,"<="&R17))) -> 0.1102 | T17: =R17*S17 -> 0.3306 | U17: =J17*$C$6+Q17 -> 6 | V17: =INDEX($AD17:$AI17,MAX(1,COUNTIF($X17:$AC17,"<="&U17))) -> 0.1102 | W17: =U17*V17 -> 0.6612 | X17: 10 | Y17: 100 | Z17: 300 | AA17: 3000 | AB17: 6000 | AC17: 9000 | AD17: 0.1102 | AE17: 0.086 | AF17: 0.0726 | AG17: 0.0645 | AH17: 0.0575 | AI17: 0.0538 | AJ17: https://www.lcsc.com/product-detail/C602028.html (read 2026-10-14)
A18: 10 | B18: LED3,LED4 | C18: NH-B1010RGBT-HF | D18: LED_RGB_1010_NH-B1010RGBT | E18: C2874113 | F18: NH-B1010RGBT-HF | G18: NATIONSTAR | H18: ring RGB LED 1x1 mm, common anode (pin 1), KB bottom face, shines into the clear main key | I18: LED3, LED4: the two RGB ring LEDs (1 x 1 mm, 4 pads under the package) on the bottom face of the key board; they shine into the clear main key. | J18: =LEN(B18)-LEN(SUBSTITUTE(B18,",",""))+1 -> 2 | K18: 4 | L18: Extended | M18: JLC page | N18: 345020 | O18: OK | P18: semi | Q18: =INDEX($C$53:$C$56,MATCH(P18,$B$53:$B$56,0)) -> 2 | R18: =J18*$C$5+Q18 -> 6 | S18: =INDEX($AD18:$AI18,MAX(1,COUNTIF($X18:$AC18,"<="&R18))) -> 0.0081 | T18: =R18*S18 -> 0.0486 | U18: =J18*$C$6+Q18 -> 12 | V18: =INDEX($AD18:$AI18,MAX(1,COUNTIF($X18:$AC18,"<="&U18))) -> 0.0081 | W18: =U18*V18 -> 0.0972 | X18: 20 | Y18: 200 | Z18: 600 | AA18: 2000 | AB18: 10000 | AC18: 20000 | AD18: 0.0081 | AE18: 0.0072 | AF18: 0.0068 | AG18: 0.0065 | AH18: 0.0063 | AI18: 0.0053 | AJ18: https://www.lcsc.com/product-detail/C2874113.html (read 2026-10-14)
A19: 11 | B19: P1,P2,P3,P4,P5,P6 | C19: P70-1010045R | D19: Pogo_Harwin_P70-1010045R | E19: C22100007 | F19: P70-1010045R | G19: Harwin | H19: SMT pogo pin, gold, no peg, free 5.0 / working 4.0 mm, 1.17 N (Harwin P70-1010045R), KB top face | I19: P1-P6: the six gold spring contacts (pogo pins) on the top face of the key board; they press on the six round pads J6 of the main PCB (SMT, no peg, free height 5.0 mm, working height 4.0 mm, 1.17 N). | J19: =LEN(B19)-LEN(SUBSTITUTE(B19,",",""))+1 -> 6 | K19: 1 | L19: Extended | M19: JLC page | N19: 100 | O19: New in v0.7. LCSC retail stock 100 pcs on 2026-10-21 (enough for 2 or 5 panels). JLCPCB's own stock and library type were not read ('Extended' assumed): if the BOM upload shows no stock, buy the pins into your JLCPCB parts library first (Parts Manager, order from LCSC stock). Other source: Digikey USD 0.696 at 100 pcs, 21 weeks lead time (https://azcus.digikey.com/en/products/detail/harwin-inc/P70-1010045R/6211190). | P19: mod | Q19: =INDEX($C$53:$C$56,MATCH(P19,$B$53:$B$56,0)) -> 1 | R19: =J19*$C$5+Q19 -> 13 | S19: =INDEX($AD19:$AI19,MAX(1,COUNTIF($X19:$AC19,"<="&R19))) -> 1.89 | T19: =R19*S19 -> 24.57 | U19: =J19*$C$6+Q19 -> 31 | V19: =INDEX($AD19:$AI19,MAX(1,COUNTIF($X19:$AC19,"<="&U19))) -> 1.44 | W19: =U19*V19 -> 44.64 | X19: 1 | Y19: 30 | Z19: 100 | AD19: 1.89 | AE19: 1.44 | AF19: 1.26 | AJ19: https://www.lcsc.com/product-detail/C22100007.html (read 2026-10-21)
A20: 12 | B20: Q1 | C20: AO3401A | D20: SOT-23 | E20: C15127 | F20: AO3401A | G20: AOS | H20: P-MOSFET laser load switch | I20: Q1: P-channel MOSFET, the on/off switch of the laser. Main PCB. | J20: =LEN(B20)-LEN(SUBSTITUTE(B20,",",""))+1 -> 1 | K20: 3 | L20: Basic | M20: JLC page | N20: 164910 | O20: OK | P20: semi | Q20: =INDEX($C$53:$C$56,MATCH(P20,$B$53:$B$56,0)) -> 2 | R20: =J20*$C$5+Q20 -> 4 | S20: =INDEX($AD20:$AI20,MAX(1,COUNTIF($X20:$AC20,"<="&R20))) -> 0.1026 | T20: =R20*S20 -> 0.4104 | U20: =J20*$C$6+Q20 -> 7 | V20: =INDEX($AD20:$AI20,MAX(1,COUNTIF($X20:$AC20,"<="&U20))) -> 0.1026 | W20: =U20*V20 -> 0.7182 | X20: 5 | Y20: 50 | Z20: 150 | AA20: 500 | AB20: 3000 | AC20: 6000 | AD20: 0.1026 | AE20: 0.0829 | AF20: 0.0728 | AG20: 0.0644 | AH20: 0.0615 | AI20: 0.0596 | AJ20: https://www.lcsc.com/product-detail/C15127.html (read 2026-10-14)
A21: 13 | B21: Q3 | C21: SE8830A | D21: SOT-23-6 | E21: C238645 | F21: SE8830A | G21: SINO-IC | H21: dual N-MOSFET 20 V common drain, 11/14.5 mOhm at 4.5 V, SOT-23-6 (SINO-IC SE8830A): Q3A discharge (S1 = cell minus), Q3B charge (S2 = board GND) | I21: Q3: dual N-MOSFET (13 / 14.5 mOhm typical / maximum at 4.5 V) in the cell minus, switched by U6, which senses its drop directly (Kelvin tracks); the DW01A trips at about 4.3-4.5 A with hot MOSFETs (5.3-5.6 A at 25 C; 3.0-3.15 A in the worst case). Main PCB, bottom face. | J21: =LEN(B21)-LEN(SUBSTITUTE(B21,",",""))+1 -> 1 | K21: 6 | L21: Extended | M21: JLC page | N21: unknown | O21: ESTIMATE, page not read: the LCSC page of C238645 could not be read on 2026-10-22 (price and stock unknown; library type 'Extended' assumed). No drop-in substitute: an 8205A-type dual MOSFET has about twice the on-resistance, and the DW01A would then cut the light off in turbo (trip at about 2-3 A). If the BOM upload shows no stock, buy it into your JLCPCB parts library from LCSC stock or wait for stock. Before ordering, check the pin order in the data sheet: pins 1-6 must be S1, D, S2, G2, D, G1 (as on the FS8205A; the LCSC data sheet shows it only as a picture). The board is laid out for exactly this order. | P21: semi | Q21: =INDEX($C$53:$C$56,MATCH(P21,$B$53:$B$56,0)) -> 2 | R21: =J21*$C$5+Q21 -> 4 | S21: =INDEX($AD21:$AI21,MAX(1,COUNTIF($X21:$AC21,"<="&R21))) -> 0.1 | T21: =R21*S21 -> 0.4 | U21: =J21*$C$6+Q21 -> 7 | V21: =INDEX($AD21:$AI21,MAX(1,COUNTIF($X21:$AC21,"<="&U21))) -> 0.1 | W21: =U21*V21 -> 0.7 | X21: 10 | Y21: 100 | AD21: 0.1 | AE21: 0.08 | AJ21: ESTIMATE - the LCSC page of C238645 could not be read on 2026-10-22. Priced at about twice the common FS8205A dual MOSFET (C2830320: USD 0.050 from 10 pieces, LCSC, read 2026-10-22).
A22: 14 | B22: Q2,Q4,Q5 | C22: 2N7002W | D22: SOT-323_SC-70 | E22: C5224240 | F22: 2N7002W-7-F-ES | G22: ElecSuper | H22: Q2: N-MOSFET current sink into FB (SOT-323); Q4: N-MOSFET (SOT-323): 3.3 V LASER_ON -> pulls the Q1 gate path low; Q5: VBUS-edge reset (SOT-323): pulls EN low for ~0.1 s when USB is plugged in | I22: Q2, Q4, Q5: small N-channel MOSFET switches (LED current sink, laser gate, reset pulse). Main PCB. | J22: =LEN(B22)-LEN(SUBSTITUTE(B22,",",""))+1 -> 3 | K22: 3 | L22: Extended | M22: JLC page | N22: 17000 | O22: OK | P22: semi | Q22: =INDEX($C$53:$C$56,MATCH(P22,$B$53:$B$56,0)) -> 2 | R22: =J22*$C$5+Q22 -> 8 | S22: =INDEX($AD22:$AI22,MAX(1,COUNTIF($X22:$AC22,"<="&R22))) -> 0.0224 | T22: =R22*S22 -> 0.1792 | U22: =J22*$C$6+Q22 -> 17 | V22: =INDEX($AD22:$AI22,MAX(1,COUNTIF($X22:$AC22,"<="&U22))) -> 0.0224 | W22: =U22*V22 -> 0.3808 | X22: 50 | Y22: 500 | Z22: 3000 | AA22: 6000 | AB22: 24000 | AC22: 51000 | AD22: 0.0224 | AE22: 0.017 | AF22: 0.0141 | AG22: 0.0123 | AH22: 0.0108 | AI22: 0.0099 | AJ22: https://www.lcsc.com/product-detail/C5224240.html (read 2026-10-14)
A23: 15 | B23: R1,R2 | C23: 5.1k | D23: R_0402_1005Metric | E23: C25905 | F23: 0402WGF5101TCE | G23: UNI-ROYAL | H23: 5.1k 1% 0402 resistor | I23: R1, R2: 5.1 k resistors on the USB-C CC pins (tell a charger to supply 5 V). Main PCB. | J23: =LEN(B23)-LEN(SUBSTITUTE(B23,",",""))+1 -> 2 | K23: 2 | L23: Basic | M23: JLC page | N23: 2302500 | O23: OK | P23: p0402 | Q23: =INDEX($C$53:$C$56,MATCH(P23,$B$53:$B$56,0)) -> 10 | R23: =J23*$C$5+Q23 -> 14 | S23: =INDEX($AD23:$AI23,MAX(1,COUNTIF($X23:$AC23,"<="&R23))) -> 0.0024 | T23: =R23*S23 -> 0.0336 | U23: =J23*$C$6+Q23 -> 20 | V23: =INDEX($AD23:$AI23,MAX(1,COUNTIF($X23:$AC23,"<="&U23))) -> 0.0024 | W23: =U23*V23 -> 0.048 | X23: 100 | Y23: 1000 | Z23: 3000 | AA23: 10000 | AB23: 50000 | AD23: 0.0024 | AE23: 0.0019 | AF23: 0.0015 | AG23: 0.0014 | AH23: 0.0012 | AJ23: https://www.lcsc.com/product-detail/C25905.html (read 2026-10-14)
A24: 16 | B24: R3 | C24: 2k | D24: R_0402_1005Metric | E24: C4109 | F24: 0402WGF2001TCE | G24: UNI-ROYAL | H24: 2k 1% 0402 resistor | I24: R3: 2.0 k resistor, sets the battery charge current (about 494 mA, the standard charge of the 14500 cell). Main PCB. | J24: =LEN(B24)-LEN(SUBSTITUTE(B24,",",""))+1 -> 1 | K24: 2 | L24: Basic | M24: JLC page | N24: 5175800 | O24: New for the 14500 cell (R3 was 3.3 k, C25890, about 280 mA). Tiers and stock read on LCSC's product-image page https://www.lcsc.com/product-image/C4109.html (the product page could not be opened); library type Basic as read on 2026-10-14 (the same part was R16 of v0.6). | P24: p0402 | Q24: =INDEX($C$53:$C$56,MATCH(P24,$B$53:$B$56,0)) -> 10 | R24: =J24*$C$5+Q24 -> 12 | S24: =INDEX($AD24:$AI24,MAX(1,COUNTIF($X24:$AC24,"<="&R24))) -> 0.0026 | T24: =R24*S24 -> 0.0312 | U24: =J24*$C$6+Q24 -> 15 | V24: =INDEX($AD24:$AI24,MAX(1,COUNTIF($X24:$AC24,"<="&U24))) -> 0.0026 | W24: =U24*V24 -> 0.039 | X24: 100 | Y24: 1000 | Z24: 3000 | AA24: 10000 | AB24: 50000 | AD24: 0.0026 | AE24: 0.002 | AF24: 0.0016 | AG24: 0.0015 | AH24: 0.0012 | AJ24: https://www.lcsc.com/product-detail/C4109.html (read 2026-10-23)
A25: 17 | B25: R10 | C25: 200k | D25: R_0402_1005Metric | E25: C25764 | F25: 0402WGF2003TCE | G25: UNI-ROYAL | H25: 200k 1% 0402 resistor | I25: R10: 200 k resistor (voltage divider of the buck converter). Main PCB. | J25: =LEN(B25)-LEN(SUBSTITUTE(B25,",",""))+1 -> 1 | K25: 2 | L25: Basic | M25: JLC page | N25: 1520700 | O25: OK | P25: p0402 | Q25: =INDEX($C$53:$C$56,MATCH(P25,$B$53:$B$56,0)) -> 10 | R25: =J25*$C$5+Q25 -> 12 | S25: =INDEX($AD25:$AI25,MAX(1,COUNTIF($X25:$AC25,"<="&R25))) -> 0.0018 | T25: =R25*S25 -> 0.0216 | U25: =J25*$C$6+Q25 -> 15 | V25: =INDEX($AD25:$AI25,MAX(1,COUNTIF($X25:$AC25,"<="&U25))) -> 0.0018 | W25: =U25*V25 -> 0.027 | X25: 100 | Y25: 1000 | Z25: 3000 | AA25: 10000 | AB25: 50000 | AD25: 0.0018 | AE25: 0.0014 | AF25: 0.0011 | AG25: 0.001 | AH25: 0.0009 | AJ25: https://www.lcsc.com/product-detail/C25764.html (read 2026-10-14)
A26: 18 | B26: R12 | C26: 47k | D26: R_0402_1005Metric | E26: C25792 | F26: 0402WGF4702TCE | G26: UNI-ROYAL | H26: 47k 1% 0402 resistor | I26: R12: 47 k resistor. Main PCB. | J26: =LEN(B26)-LEN(SUBSTITUTE(B26,",",""))+1 -> 1 | K26: 2 | L26: Basic | M26: JLC page | N26: 3114700 | O26: OK | P26: p0402 | Q26: =INDEX($C$53:$C$56,MATCH(P26,$B$53:$B$56,0)) -> 10 | R26: =J26*$C$5+Q26 -> 12 | S26: =INDEX($AD26:$AI26,MAX(1,COUNTIF($X26:$AC26,"<="&R26))) -> 0.0026 | T26: =R26*S26 -> 0.0312 | U26: =J26*$C$6+Q26 -> 15 | V26: =INDEX($AD26:$AI26,MAX(1,COUNTIF($X26:$AC26,"<="&U26))) -> 0.0026 | W26: =U26*V26 -> 0.039 | X26: 100 | Y26: 1000 | Z26: 3000 | AA26: 10000 | AB26: 50000 | AD26: 0.0026 | AE26: 0.002 | AF26: 0.0017 | AG26: 0.0015 | AH26: 0.0013 | AJ26: https://www.lcsc.com/product-detail/C25792.html (read 2026-10-14)
A27: 19 | B27: R8,R9,R13,R18,R21,R22 | C27: 10k | D27: R_0402_1005Metric | E27: C25744 | F27: 0402WGF1002TCE | G27: UNI-ROYAL | H27: 10k 1% 0402 resistor | I27: 10 k resistors: pull-ups / pull-downs (R8, R9, R13, R18, R21, R22). Main PCB. | J27: =LEN(B27)-LEN(SUBSTITUTE(B27,",",""))+1 -> 6 | K27: 2 | L27: Basic | M27: JLC page | N27: 2846900 | O27: OK | P27: p0402 | Q27: =INDEX($C$53:$C$56,MATCH(P27,$B$53:$B$56,0)) -> 10 | R27: =J27*$C$5+Q27 -> 22 | S27: =INDEX($AD27:$AI27,MAX(1,COUNTIF($X27:$AC27,"<="&R27))) -> 0.0033 | T27: =R27*S27 -> 0.0726 | U27: =J27*$C$6+Q27 -> 40 | V27: =INDEX($AD27:$AI27,MAX(1,COUNTIF($X27:$AC27,"<="&U27))) -> 0.0033 | W27: =U27*V27 -> 0.132 | X27: 100 | Y27: 1000 | Z27: 3000 | AA27: 10000 | AB27: 50000 | AD27: 0.0033 | AE27: 0.0026 | AF27: 0.0022 | AG27: 0.0021 | AH27: 0.0017 | AJ27: https://www.lcsc.com/product-detail/C25744.html (read 2026-10-14)
A28: 20 | B28: R14,R16,R31 | C28: 2.2k | D28: R_0402_1005Metric | E28: C25879 | F28: 0402WGF2201TCE | G28: UNI-ROYAL | H28: 2.2k 1% 0402 resistor | I28: 2.2 k resistors: R14 (LED-current loop) and R16 (VSET divider: sets the full-scale LED current to 3,552 mA), main PCB; R31 (button ladder, previous key), key board. | J28: =LEN(B28)-LEN(SUBSTITUTE(B28,",",""))+1 -> 3 | K28: 2 | L28: Basic | M28: JLC page | N28: 586000 | O28: OK | P28: p0402 | Q28: =INDEX($C$53:$C$56,MATCH(P28,$B$53:$B$56,0)) -> 10 | R28: =J28*$C$5+Q28 -> 16 | S28: =INDEX($AD28:$AI28,MAX(1,COUNTIF($X28:$AC28,"<="&R28))) -> 0.0018 | T28: =R28*S28 -> 0.0288 | U28: =J28*$C$6+Q28 -> 25 | V28: =INDEX($AD28:$AI28,MAX(1,COUNTIF($X28:$AC28,"<="&U28))) -> 0.0018 | W28: =U28*V28 -> 0.045 | X28: 100 | Y28: 1000 | Z28: 3000 | AA28: 50000 | AD28: 0.0018 | AE28: 0.0013 | AF28: 0.0011 | AG28: 0.0009 | AJ28: https://www.lcsc.com/product-detail/C25879.html (read 2026-10-14)
A29: 21 | B29: R23,R32 | C29: 330Ω | D29: R_0402_1005Metric | E29: C25104 | F29: 0402WGF3300TCE | G29: UNI-ROYAL | H29: 330 1% 0402 resistor | I29: R23, R32: 330 ohm resistors (red leg of the two ring LEDs). Key board. | J29: =LEN(B29)-LEN(SUBSTITUTE(B29,",",""))+1 -> 2 | K29: 2 | L29: Basic | M29: JLC page | N29: unknown | O29: ESTIMATE, page not read: JLCPCB and LCSC pages of C25104 could not be read on 2026-10-18 (not read again in v0.7). Tiers copied from the sibling 5.1 k resistor C25905 (read 2026-10-14); part number inferred from the UNI-ROYAL naming; library type 'Basic' assumed (same series as the other Basic 0402 resistors). Stock unknown. | P29: p0402 | Q29: =INDEX($C$53:$C$56,MATCH(P29,$B$53:$B$56,0)) -> 10 | R29: =J29*$C$5+Q29 -> 14 | S29: =INDEX($AD29:$AI29,MAX(1,COUNTIF($X29:$AC29,"<="&R29))) -> 0.0024 | T29: =R29*S29 -> 0.0336 | U29: =J29*$C$6+Q29 -> 20 | V29: =INDEX($AD29:$AI29,MAX(1,COUNTIF($X29:$AC29,"<="&U29))) -> 0.0024 | W29: =U29*V29 -> 0.048 | X29: 100 | Y29: 1000 | Z29: 3000 | AA29: 10000 | AB29: 50000 | AD29: 0.0024 | AE29: 0.0019 | AF29: 0.0015 | AG29: 0.0014 | AH29: 0.0012 | AJ29: ESTIMATE - LCSC and JLCPCB pages of C25104 could not be read on 2026-10-18. Tiers of the sibling C25905 (LCSC, read 2026-10-14).
A30: 22 | B30: R27,R28 | C30: 1M | D30: R_0402_1005Metric | E30: C26083 | F30: 0402WGF1004TCE | G30: UNI-ROYAL | H30: 1M 1% 0402 resistor | I30: R27, R28: 1 M resistors. Main PCB. | J30: =LEN(B30)-LEN(SUBSTITUTE(B30,",",""))+1 -> 2 | K30: 2 | L30: Basic | M30: JLC page | N30: 541000 | O30: OK | P30: p0402 | Q30: =INDEX($C$53:$C$56,MATCH(P30,$B$53:$B$56,0)) -> 10 | R30: =J30*$C$5+Q30 -> 14 | S30: =INDEX($AD30:$AI30,MAX(1,COUNTIF($X30:$AC30,"<="&R30))) -> 0.0024 | T30: =R30*S30 -> 0.0336 | U30: =J30*$C$6+Q30 -> 20 | V30: =INDEX($AD30:$AI30,MAX(1,COUNTIF($X30:$AC30,"<="&U30))) -> 0.0024 | W30: =U30*V30 -> 0.048 | X30: 100 | Y30: 1000 | Z30: 3000 | AA30: 10000 | AB30: 50000 | AD30: 0.0024 | AE30: 0.0018 | AF30: 0.0016 | AG30: 0.0014 | AH30: 0.0011 | AJ30: https://www.lcsc.com/product-detail/C26083.html (read 2026-10-14)
A31: 23 | B31: R7,R11,R15,R17,R20,R26,R29 | C31: 100k | D31: R_0402_1005Metric | E31: C25741 | F31: 0402WGF1003TCE | G31: UNI-ROYAL | H31: 100k 1% 0402 resistor | I31: 100 k resistors: pull-ups / dividers (7 of them). Main PCB. | J31: =LEN(B31)-LEN(SUBSTITUTE(B31,",",""))+1 -> 7 | K31: 2 | L31: Basic | M31: JLC page | N31: 3791500 | O31: OK | P31: p0402 | Q31: =INDEX($C$53:$C$56,MATCH(P31,$B$53:$B$56,0)) -> 10 | R31: =J31*$C$5+Q31 -> 24 | S31: =INDEX($AD31:$AI31,MAX(1,COUNTIF($X31:$AC31,"<="&R31))) -> 0.0015 | T31: =R31*S31 -> 0.036 | U31: =J31*$C$6+Q31 -> 45 | V31: =INDEX($AD31:$AI31,MAX(1,COUNTIF($X31:$AC31,"<="&U31))) -> 0.0015 | W31: =U31*V31 -> 0.0675 | X31: 100 | Y31: 1000 | Z31: 3000 | AA31: 10000 | AB31: 50000 | AD31: 0.0015 | AE31: 0.0012 | AF31: 0.001 | AG31: 0.0009 | AH31: 0.0008 | AJ31: https://www.lcsc.com/product-detail/C25741.html (read 2026-10-14)
A32: 24 | B32: R24,R25,R33,R34,R35 | C32: 100Ω | D32: R_0402_1005Metric | E32: C25076 | F32: 0402WGF1000TCE | G32: UNI-ROYAL | H32: 100 1% 0402 resistor | I32: 100 ohm resistors: R24, R25, R33, R34 (green and blue leg of each ring LED), key board; R35 (supply filter of the protection IC U6), main PCB. | J32: =LEN(B32)-LEN(SUBSTITUTE(B32,",",""))+1 -> 5 | K32: 2 | L32: Basic | M32: JLC page | N32: 4360400 | O32: OK | P32: p0402 | Q32: =INDEX($C$53:$C$56,MATCH(P32,$B$53:$B$56,0)) -> 10 | R32: =J32*$C$5+Q32 -> 20 | S32: =INDEX($AD32:$AI32,MAX(1,COUNTIF($X32:$AC32,"<="&R32))) -> 0.0013 | T32: =R32*S32 -> 0.026 | U32: =J32*$C$6+Q32 -> 35 | V32: =INDEX($AD32:$AI32,MAX(1,COUNTIF($X32:$AC32,"<="&U32))) -> 0.0013 | W32: =U32*V32 -> 0.0455 | X32: 100 | Y32: 1000 | Z32: 3000 | AA32: 10000 | AD32: 0.0013 | AE32: 0.001 | AF32: 0.0009 | AG32: 0.0008 | AJ32: https://www.lcsc.com/product-detail/C25076.html (read 2026-10-14)
A33: 25 | B33: R19,R30,R36 | C33: 1k | D33: R_0402_1005Metric | E33: C11702 | F33: 0402WGF1001TCE | G33: UNI-ROYAL | H33: 1k 1% 0402 resistor | I33: 1 k resistors: R19 (laser gate) and R36 (current-sense input of the protection IC U6), main PCB; R30 (button ladder, next key), key board. | J33: =LEN(B33)-LEN(SUBSTITUTE(B33,",",""))+1 -> 3 | K33: 2 | L33: Basic | M33: JLC page | N33: 0 | O33: LCSC retail shows OUT OF STOCK; JLC lists it as Basic - check the JLC stock at BOM upload. | P33: p0402 | Q33: =INDEX($C$53:$C$56,MATCH(P33,$B$53:$B$56,0)) -> 10 | R33: =J33*$C$5+Q33 -> 16 | S33: =INDEX($AD33:$AI33,MAX(1,COUNTIF($X33:$AC33,"<="&R33))) -> 0.0031 | T33: =R33*S33 -> 0.0496 | U33: =J33*$C$6+Q33 -> 25 | V33: =INDEX($AD33:$AI33,MAX(1,COUNTIF($X33:$AC33,"<="&U33))) -> 0.0031 | W33: =U33*V33 -> 0.0775 | X33: 100 | Y33: 1000 | Z33: 3000 | AA33: 10000 | AB33: 50000 | AD33: 0.0031 | AE33: 0.0024 | AF33: 0.002 | AG33: 0.0018 | AH33: 0.0016 | AJ33: https://www.lcsc.com/product-detail/C11702.html (read 2026-10-14)
A34: 26 | B34: RS1 | C34: 20mΩ | D34: R_0805_2012Metric | E34: C92740 | F34: MS05W2F200MT5E | G34: UNI-ROYAL | H34: 20 mOhm 1 % 0.5 W 0805 current sense (Kelvin) | I34: RS1: 20 milliohm current-sense resistor, 0.5 W (measures the LED current; 0.18 W at 3 A). Main PCB. | J34: =LEN(B34)-LEN(SUBSTITUTE(B34,",",""))+1 -> 1 | K34: 2 | L34: Extended | M34: JLC page | N34: 4880 | O34: OK | P34: p0603 | Q34: =INDEX($C$53:$C$56,MATCH(P34,$B$53:$B$56,0)) -> 5 | R34: =J34*$C$5+Q34 -> 7 | S34: =INDEX($AD34:$AI34,MAX(1,COUNTIF($X34:$AC34,"<="&R34))) -> 0.0183 | T34: =R34*S34 -> 0.1281 | U34: =J34*$C$6+Q34 -> 10 | V34: =INDEX($AD34:$AI34,MAX(1,COUNTIF($X34:$AC34,"<="&U34))) -> 0.0183 | W34: =U34*V34 -> 0.183 | X34: 20 | Y34: 200 | Z34: 600 | AA34: 2000 | AD34: 0.0183 | AE34: 0.018 | AF34: 0.0177 | AG34: 0.0174 | AJ34: https://www.lcsc.com/product-detail/C92740.html (read 2026-10-14)
A35: 27 | B35: RT1 | C35: 100k B4250 | D35: R_0402_1005Metric | E35: C77130 | F35: NCP15WF104F03RC | G35: muRata | H35: NTC 100 k B25/50 4250 0402 (Murata NCP15WF104F03RC), PCB front edge | I35: RT1: 100 k NTC thermistor = temperature sensor at the front edge of the main PCB. | J35: =LEN(B35)-LEN(SUBSTITUTE(B35,",",""))+1 -> 1 | K35: 2 | L35: Extended | M35: JLC page | N35: 298120 | O35: OK | P35: p0402 | Q35: =INDEX($C$53:$C$56,MATCH(P35,$B$53:$B$56,0)) -> 10 | R35: =J35*$C$5+Q35 -> 12 | S35: =INDEX($AD35:$AI35,MAX(1,COUNTIF($X35:$AC35,"<="&R35))) -> 0.0219 | T35: =R35*S35 -> 0.2628 | U35: =J35*$C$6+Q35 -> 15 | V35: =INDEX($AD35:$AI35,MAX(1,COUNTIF($X35:$AC35,"<="&U35))) -> 0.0219 | W35: =U35*V35 -> 0.3285 | X35: 20 | Y35: 200 | Z35: 600 | AA35: 2000 | AB35: 10000 | AC35: 20000 | AD35: 0.0219 | AE35: 0.0173 | AF35: 0.0147 | AG35: 0.0132 | AH35: 0.0119 | AI35: 0.0112 | AJ35: https://www.lcsc.com/product-detail/C77130.html (read 2026-10-14)
A36: 28 | B36: S2 | C36: MSK12C02 | D36: SW_SPDT_PCM12 | E36: C431540 | F36: MSK12C02 | G36: SHOU HAN | H36: SPDT slide switch, laser interlock (gate path only) | I36: S2: slide switch = the laser safety interlock. Main PCB. | J36: =LEN(B36)-LEN(SUBSTITUTE(B36,",",""))+1 -> 1 | K36: 7 | L36: Extended | M36: JLC page | N36: 170330 | O36: OK | P36: mod | Q36: =INDEX($C$53:$C$56,MATCH(P36,$B$53:$B$56,0)) -> 1 | R36: =J36*$C$5+Q36 -> 3 | S36: =INDEX($AD36:$AI36,MAX(1,COUNTIF($X36:$AC36,"<="&R36))) -> 0.0543 | T36: =R36*S36 -> 0.1629 | U36: =J36*$C$6+Q36 -> 6 | V36: =INDEX($AD36:$AI36,MAX(1,COUNTIF($X36:$AC36,"<="&U36))) -> 0.0543 | W36: =U36*V36 -> 0.3258 | X36: 10 | Y36: 100 | Z36: 300 | AA36: 3000 | AB36: 6000 | AC36: 9000 | AD36: 0.0543 | AE36: 0.0444 | AF36: 0.0394 | AG36: 0.0337 | AH36: 0.0323 | AI36: 0.0312 | AJ36: https://www.lcsc.com/product-detail/C431540.html (read 2026-10-14)
A37: 29 | B37: SW1,SW2,SW3 | C37: SKRKAEE020 | D37: SW_Push_SPST_NO_Alps_SKRK | E37: C115357 | F37: SKRKAEE020 | G37: ALPSALPINE | H37: SW1: main button: Alps top-push tact switch, 1.6 N, KB bottom face (main key); SW2: next button (>): Alps top-push tact switch, KB bottom face; SW3: previous button (<): Alps top-push tact switch, KB bottom face | I37: SW1, SW2, SW3: the three key switches (main, next, previous) on the bottom face of the key board. Alps top-push tact switch 3.9 x 2.9 x 2.0 mm, 1.6 N, 200k cycles. | J37: =LEN(B37)-LEN(SUBSTITUTE(B37,",",""))+1 -> 3 | K37: 2 | L37: Extended | M37: JLC page | N37: unknown | O37: ESTIMATE, page not read: JLCPCB and LCSC pages of C115357 could not be read on 2026-10-18 (not read again in v0.7). Tiers = the sibling Alps SKRPABE010 (C115360) read on LCSC on 2026-10-16 (qty 10 $0.0759, qty 100 $0.0616). Stock unknown. Library type 'Extended' assumed (every Alps tact switch checked on JLCPCB is Extended). | P37: mod | Q37: =INDEX($C$53:$C$56,MATCH(P37,$B$53:$B$56,0)) -> 1 | R37: =J37*$C$5+Q37 -> 7 | S37: =INDEX($AD37:$AI37,MAX(1,COUNTIF($X37:$AC37,"<="&R37))) -> 0.0759 | T37: =R37*S37 -> 0.5313 | U37: =J37*$C$6+Q37 -> 16 | V37: =INDEX($AD37:$AI37,MAX(1,COUNTIF($X37:$AC37,"<="&U37))) -> 0.0759 | W37: =U37*V37 -> 1.2144 | X37: 10 | Y37: 100 | AD37: 0.0759 | AE37: 0.0616 | AJ37: ESTIMATE - LCSC and JLCPCB pages of C115357 could not be read on 2026-10-18. Tiers of the sibling C115360 (LCSC, read 2026-10-16): qty 10 $0.0759, qty 100 $0.0616.
A38: 30 | B38: U1 | C38: TP4057 | D38: SOT-23-6 | E38: C12044 | F38: TP4057-42-SOT26-R | G38: TOP POWER ASIC | H38: TP4057-42-SOT26-R 500 mA Li-ion linear charger (R3 2.0k = ~500 mA) | I38: U1: battery charger chip (500 mA linear Li-ion charger). Main PCB. | J38: =LEN(B38)-LEN(SUBSTITUTE(B38,",",""))+1 -> 1 | K38: 6 | L38: Extended | M38: JLC page | N38: 32025 | O38: OK | P38: semi | Q38: =INDEX($C$53:$C$56,MATCH(P38,$B$53:$B$56,0)) -> 2 | R38: =J38*$C$5+Q38 -> 4 | S38: =INDEX($AD38:$AI38,MAX(1,COUNTIF($X38:$AC38,"<="&R38))) -> 0.1426 | T38: =R38*S38 -> 0.5704 | U38: =J38*$C$6+Q38 -> 7 | V38: =INDEX($AD38:$AI38,MAX(1,COUNTIF($X38:$AC38,"<="&U38))) -> 0.1426 | W38: =U38*V38 -> 0.9982 | X38: 5 | Y38: 50 | Z38: 150 | AA38: 500 | AB38: 3000 | AC38: 6000 | AD38: 0.1426 | AE38: 0.1166 | AF38: 0.1036 | AG38: 0.0938 | AH38: 0.0761 | AI38: 0.0722 | AJ38: https://www.lcsc.com/product-detail/C12044.html (read 2026-10-14)
A39: 31 | B39: U2 | C39: TPS62095RGTR | D39: VQFN-16-1EP_3x3mm_P0.5mm_EP1.68x1.68mm_TV2 | E39: C139643 | F39: TPS62095RGTR | G39: Texas Instruments | H39: 4 A sync buck (TI TPS62095), 100 % duty mode, VFB 0.8 V, 1.4 MHz, VQFN-16 3x3 (RGT) | I39: U2: 4 A synchronous buck converter that drives the LED (100 % duty mode, VQFN-16 3 x 3 mm: 16 pins + exposed pad = 17 joints). Main PCB. | J39: =LEN(B39)-LEN(SUBSTITUTE(B39,",",""))+1 -> 1 | K39: 17 | L39: Extended | M39: JLC page | N39: 2092 | O39: New with the 1000 lm power stage. LCSC stock 2,092 on 2026-10-22; only the price for 1 piece was read (used for every quantity). | P39: semi | Q39: =INDEX($C$53:$C$56,MATCH(P39,$B$53:$B$56,0)) -> 2 | R39: =J39*$C$5+Q39 -> 4 | S39: =INDEX($AD39:$AI39,MAX(1,COUNTIF($X39:$AC39,"<="&R39))) -> 1.35 | T39: =R39*S39 -> 5.4 | U39: =J39*$C$6+Q39 -> 7 | V39: =INDEX($AD39:$AI39,MAX(1,COUNTIF($X39:$AC39,"<="&U39))) -> 1.35 | W39: =U39*V39 -> 9.45 | X39: 1 | AD39: 1.35 | AJ39: https://www.lcsc.com/product-detail/C139643.html (read 2026-10-22)
A40: 32 | B40: U3 | C40: TLV333IDCKR | D40: SOT-353_SC-70-5 | E40: C181502 | F40: TLV333IDCKR | G40: Texas Instruments | H40: zero-drift op-amp SC-70-5 (DCK), powered from LED_EN | I40: U3: precision op-amp in the LED-current control loop. Main PCB. | J40: =LEN(B40)-LEN(SUBSTITUTE(B40,",",""))+1 -> 1 | K40: 5 | L40: Extended | M40: JLC page | N40: 18425 | O40: OK | P40: semi | Q40: =INDEX($C$53:$C$56,MATCH(P40,$B$53:$B$56,0)) -> 2 | R40: =J40*$C$5+Q40 -> 4 | S40: =INDEX($AD40:$AI40,MAX(1,COUNTIF($X40:$AC40,"<="&R40))) -> 0.3543 | T40: =R40*S40 -> 1.4172 | U40: =J40*$C$6+Q40 -> 7 | V40: =INDEX($AD40:$AI40,MAX(1,COUNTIF($X40:$AC40,"<="&U40))) -> 0.3543 | W40: =U40*V40 -> 2.4801 | X40: 5 | Y40: 50 | Z40: 150 | AA40: 500 | AB40: 3000 | AC40: 6000 | AD40: 0.3543 | AE40: 0.2788 | AF40: 0.2465 | AG40: 0.1927 | AH40: 0.1747 | AI40: 0.1639 | AJ40: https://www.lcsc.com/product-detail/C181502.html (read 2026-10-14)
A41: 33 | B41: U4 | C41: ESP32-C3-MINI-1-N4 | D41: ESP32-C3-MINI-1 | E41: C2838502 | F41: ESP32-C3-MINI-1-N4 | G41: Espressif | H41: ESP32-C3 BLE 5 / Wi-Fi module, 4 MB flash, PCB antenna (alt. -H4X C41349510) | I41: U4: the brain - ESP32-C3 module with Bluetooth LE / Wi-Fi, 4 MB flash and antenna. Main PCB. | J41: =LEN(B41)-LEN(SUBSTITUTE(B41,",",""))+1 -> 1 | K41: 53 | L41: Extended | M41: JLC page | N41: 8387 | O41: Marked NRND (not recommended for new designs) by Espressif; the successor ESP32-C3-MINI-1-H4X (C41349510) is the drop-in alternative if this one disappears. | P41: mod | Q41: =INDEX($C$53:$C$56,MATCH(P41,$B$53:$B$56,0)) -> 1 | R41: =J41*$C$5+Q41 -> 3 | S41: =INDEX($AD41:$AI41,MAX(1,COUNTIF($X41:$AC41,"<="&R41))) -> 3.0672 | T41: =R41*S41 -> 9.2016 | U41: =J41*$C$6+Q41 -> 6 | V41: =INDEX($AD41:$AI41,MAX(1,COUNTIF($X41:$AC41,"<="&U41))) -> 3.0672 | W41: =U41*V41 -> 18.4032 | X41: 1 | Y41: 10 | Z41: 30 | AA41: 100 | AB41: 650 | AC41: 1300 | AD41: 3.0672 | AE41: 2.7002 | AF41: 2.5127 | AG41: 2.1441 | AH41: 2.0536 | AI41: 2.0141 | AJ41: https://www.lcsc.com/product-detail/C2838502.html (read 2026-10-14)
A42: 34 | B42: U5 | C42: RT9080-33GJ5 | D42: TSOT-23-5 | E42: C841192 | F42: RT9080-33GJ5 | G42: Richtek | H42: 3.3 V 600 mA LDO, Iq 2 uA (EN tied to VIN) | I42: U5: 3.3 V voltage regulator for the ESP32 module. Main PCB. | J42: =LEN(B42)-LEN(SUBSTITUTE(B42,",",""))+1 -> 1 | K42: 5 | L42: Extended | M42: JLC page | N42: 27375 | O42: OK | P42: semi | Q42: =INDEX($C$53:$C$56,MATCH(P42,$B$53:$B$56,0)) -> 2 | R42: =J42*$C$5+Q42 -> 4 | S42: =INDEX($AD42:$AI42,MAX(1,COUNTIF($X42:$AC42,"<="&R42))) -> 0.1207 | T42: =R42*S42 -> 0.4828 | U42: =J42*$C$6+Q42 -> 7 | V42: =INDEX($AD42:$AI42,MAX(1,COUNTIF($X42:$AC42,"<="&U42))) -> 0.1207 | W42: =U42*V42 -> 0.8449 | X42: 5 | Y42: 50 | Z42: 150 | AA42: 500 | AB42: 3000 | AC42: 6000 | AD42: 0.1207 | AE42: 0.0982 | AF42: 0.087 | AG42: 0.0786 | AH42: 0.0613 | AI42: 0.058 | AJ42: https://www.lcsc.com/product-detail/C841192.html (read 2026-10-14)
A43: 35 | B43: U6 | C43: DW01A | D43: SOT-23-6 | E43: C351410 | F43: DW01A | G43: PUOLOP | H43: 1-cell Li-ion protection IC (PUOLOP DW01A): 4.30 V / 2.4 V, over-current 150 mV, SOT-23-6 | I43: U6: 1-cell Li-ion protection IC (over-charge, over-discharge, over-current, short circuit) for the 14500 cell, which has no protection board of its own. Main PCB, bottom face. | J43: =LEN(B43)-LEN(SUBSTITUTE(B43,",",""))+1 -> 1 | K43: 6 | L43: Extended | M43: JLC page | N43: 109860 | O43: New with the 1000 lm power stage. Only the tier from 20 pieces was read (used for smaller quantities too). | P43: semi | Q43: =INDEX($C$53:$C$56,MATCH(P43,$B$53:$B$56,0)) -> 2 | R43: =J43*$C$5+Q43 -> 4 | S43: =INDEX($AD43:$AI43,MAX(1,COUNTIF($X43:$AC43,"<="&R43))) -> 0.025 | T43: =R43*S43 -> 0.1 | U43: =J43*$C$6+Q43 -> 7 | V43: =INDEX($AD43:$AI43,MAX(1,COUNTIF($X43:$AC43,"<="&U43))) -> 0.025 | W43: =U43*V43 -> 0.175 | X43: 20 | AD43: 0.025 | AJ43: https://www.lcsc.com/product-detail/C351410.html (read 2026-10-22)
B44: TOTAL per panel / per order | J44: =SUM(J9:J43) -> 79 | K44: =SUMPRODUCT(J9:J43,K9:K43) -> 267 | T44: =SUM(T9:T43) -> 46.7509 | W44: =SUM(W9:W43) -> 85.9771
B45: Lines (unique LCSC numbers = feeder-fee count) | J45: =COUNTA(E9:E43) -> 35
B46: of which Extended library parts | J46: =COUNTIF(L9:L43,"Extended") -> 17
B47: of which Basic library parts | J47: =COUNTIF(L9:L43,"Basic") -> 18
B48: Extra pieces for placement loss, included in the totals above (USD) | T48: =SUMPRODUCT(Q9:Q43,S9:S43) -> 11.3001 | W48: =SUMPRODUCT(Q9:Q43,V9:V43) -> 10.8501
B51: Placement-loss classes (ESTIMATES - JLC publishes no table; the cart shows the real quantities)
B52: Class | C52: Extra pieces | D52: Applies to
B53: p0402 | C53: 10 | D53: 0402 resistors / capacitors / NTC (tiny, easily lost by the pick-and-place machine)
B54: p0603 | C54: 5 | D54: 0603 and 0805 capacitors, current-sense resistor
B55: semi | C55: 2 | D55: small semiconductors: MOSFETs, ICs, TVS diode, RGB LED
B56: mod | C56: 1 | D56: big or expensive parts: ESP32 module, USB-C socket, inductor, switches, pogo pins
B58: Parts without an LCSC number - NOT assembled by JLCPCB (wire pads, pogo target pads, screw holes)
B59: Ref | C59: Value | D59: Footprint | H59: Description
B60: J2 | C60: CELL | D60: WirePad_SMD_2_P3.0mm_24AWG | H60: cell wire pads BAT+ / BAT- (BATN): one 14500 cell, one 24 AWG wire per pad (room for two)
B61: J3 | C61: LED | D61: WirePad_LED_Split_24AWG | H61: LED wire pads (24 AWG to the DTP board): LED+ on the top side between the USB-C shell legs (pad 1), LED- on the bottom side behind the USB-C receptacle (pad 2)
B62: J5 | C62: LASER | D62: WirePad_SMD_2_P3.0mm_N | H62: laser module wire pads (+ nearer the front, 28 AWG)
B63: J6 | C63: KB contacts | D63: PogoTarget_6_D1.6_FlashKa | H63: 6 round ENIG target pads d1.6 (mask d1.8, no paste), bottom face, for pogo pins P1-P6
B64: H1 | C64: M1.6 | D64: MountingHole_1.8mm_M1.6 | H64: mounting hole d1.8 (NPTH), M1.6 x 2.5 pan head
B65: H2 | C65: M1.6 | D65: MountingHole_1.8mm_M1.6 | H65: mounting hole d1.8 (NPTH), M1.6 x 2.5 pan head
B67: Bought parts (EXTERNAL_BOM in flashka_parts.py) - see sheet 'Bought parts'
B68: Ref | C68: What | H68: How it is bought
B69: D2 | C69: Luminus SST-20-W Gen 2, 6500 K, G1 bin, on 10 mm DTP copper board | H69: bought ready-made
B70: BT1 | C70: 1 x Vapcell INR14500 F15 3.6 V 1500 mAh Li-ion (3 A, flat top, no protection board), nickel strips spot-welded; alt. Vapcell INR14500 K10 1000 mAh (8 A) | H70: bought (shop)
B71: LS1 | C71: 6 x 12 mm laser module with driver, 3 V | H71: bought (AliExpress)

Sheet Housing
A1: Housing - aluminium tray + lid, PMMA and POM-C machining kits (JLCCNC), resin casting mould (JLC3DP, in the same order)
A2: The machined parts of v0.7 come from JLCCNC: the tray and the lid in aluminium 6061-T6 (bead blast + black anodise, no marking of any kind), the clear PMMA main keys in one machining kit and the two black POM-C parts of a light (with a spare lid insert) in a second kit. The casting mould for the rubber side keys - once per builder - is a resin print from JLC3DP by default; JLCCNC merges its orders with JLC3DP, so it comes in the same parcel. The aluminium mould from JLCCNC is the durable option (priced in section 6b, not in the totals). JLCCNC and JLC3DP show their prices only after you upload the files and publish no per-part price list, so every price on this sheet is an ESTIMATE made with the method written below. When you have the instant quotes, type them into the 'real quote' cells (sections 6, 6b and 7): the workbook then uses your numbers.
A3: Geometry source: cad/housing_interface.json (version 0.7) + cad/key_mould_checks.json + cad/*.stl. Files to upload: order_files/2_JLCCNC/ (tray, lid, the two kits) and the mould plates in order_files/3_rubber_keys/; each drawing PDF there has the name of its STEP file (cad/FlashKa_tray_drawing.pdf -> FlashKa_tray.pdf, ...). The two rubber side keys are cast at home: their material is in sheet 'Bought parts'.
A5: 1. Parts and geometry (volumes from housing_interface.json 'volumes_mm3' and key_mould_checks.json; boxes from 'tray_bbox', 'machining_kits', key_mould_checks.json and the STL files)
A6: Part | B6: Process | C6: Box X (mm) | D6: Box Y (mm) | E6: Box Z (mm) | F6: Volume (mm3) | G6: Mass (g) | H6: Per light | I6: Fixed per order | J6: File (STEP / STL / PDF) | K6: Note
A7: Tray (main body, 99.2 x 20 x 18 mm) | B7: CNC aluminium | C7: 99.2 | D7: 20 | E7: 18 | F7: 8328.5 | G7: 22.487 | H7: 1 | I7: 0 | J7: order_files/2_JLCCNC/FlashKa_tray.step + FlashKa_tray.pdf | K7: Octagon section 20 x 18 mm (eight facets, 45 deg legs of 3.4 mm). 7 threads (4 x M1.6 lid screws, 2 x M1.6 BLIND in the key-board bosses, 1 x M1.6 for the laser set screw from the head-block top, under the lid), the optic bore (d10.1, flat floor, two LED wire grooves) and the laser bore, the cell bay (51.6 mm long, two floor rails), key bezel with three key openings, floor RF window, 8 recessed panels with the V texture, 6 transverse grooves, lanyard slot 3.6 x 4.6 mm. No marking.
A8: Lid (95 x 20 x 7.25 mm) | B8: CNC aluminium | C8: 95 | D8: 20 | E8: 7.25 | F8: 3120.7 | G8: 8.426 | H8: 1 | I8: 0 | J8: order_files/2_JLCCNC/FlashKa_lid.step + FlashKa_lid.pdf | K8: A cap 3.4 mm tall (the top facet and the two upper diagonal facets) that closes on a flat seat on the tray walls: pocketed from below over the cavity (1.5 mm plate, 45 deg walls), solid over the head and the tail blocks; two hold-down bosses (7.25 mm tall overall), 4 countersunk holes for the M1.6 x 6 screws, RF-window opening and pocket, 3 recessed panels with the V texture, 3 tail grooves. A thin-walled part is harder to clamp, hence the factor 1.30.
A9: PMMA kit: 3 main keys on tabs in a frame (52.8 x 22 x 8.5 mm) | B9: CNC plastic kit | C9: 52.8 | D9: 22 | E9: 8.5 | F9: - | G9: - | H9: section 7 | I9: section 7 | J9: order_files/2_JLCCNC/FlashKa_pmma_kit.step + FlashKa_pmma_kit.pdf | K9: Clear cast PMMA (acrylic, not extruded), polished as drawing FK-H-03 asks (vapour or flame polish; the frosted ring stays matte). Kits = ROUNDUP((lights + 1 spare key) / 3): one kit for 1 or 2 lights, two kits for 5 lights.
A10: main key, clear PMMA - in the PMMA kit (3 per kit) | B10: in a kit | C10: 7.6 | D10: 7.6 | E10: 2.75 | F10: 112.4 | G10: 0.134 | H10: 3 per kit | I10: - | J10: order_files/2_JLCCNC/FlashKa_key_main.step (single file for shops that take small parts) | K10: In the kit (cut the tabs, file flush). 6.8 x 6.8 R1.0, 2.75 tall, flange 7.6 x 7.6 x 0.45; the light guide of the RGB ring (frosted ring d4.4 x 0.5 on the outer face).
A11: POM-C kit: lid RF insert x2 and the antenna spacer (45.4 x 39.3 x 17 mm) | B11: CNC plastic kit | C11: 45.4 | D11: 39.3 | E11: 17 | F11: - | G11: - | H11: section 7 | I11: section 7 | J11: order_files/2_JLCCNC/FlashKa_pom_kit.step + FlashKa_pom_kit.pdf | K11: Black POM-C (acetal copolymer). One kit per light: the two POM-C parts of a light plus a spare lid insert (the first v0.7 layout also carried an LED spacer ring: gone with the glass window). The textured faces carry the same V texture as the aluminium panels.
A12: lid RF window insert - in the POM-C kit (2 per kit) | B12: in a kit | C12: 8.3 | D12: 12.2 | E12: 1.4 | F12: 117.5 | G12: 0.166 | H12: 2 per kit | I12: - | J12: order_files/2_JLCCNC/FlashKa_rf_window.step (single file for shops that take small parts) | K12: In the kit (cut the tabs, file flush). Lets the Bluetooth signal out through the lid; held by its flange and the antenna spacer (POM-C does not bond well: no glue).
A13: antenna spacer with the floor plug - in the POM-C kit | B13: in a kit | C13: 6 | D13: 16.8 | E13: 15.85 | F13: 825.4 | G13: 1.164 | H13: 1 per kit | I13: - | J13: order_files/2_JLCCNC/FlashKa_antenna_spacer.step (single file for shops that take small parts) | K13: In the kit (cut the tabs, file flush). Keeps the cell away from the ESP32 antenna; its textured plug closes the floor RF window; the front nickel strip (BAT+) is soldered to its wire in the spacer's rebate, and both cell wires run there.
A14: Casting mould (default), resin cavity half (48 x 28 x 8.51 mm) | B14: SLA resin print (JLC3DP) | C14: 48 | D14: 28 | E14: 8.506 | F14: 6240.3 | G14: - | H14: 0 | I14: 1 | J14: order_files/3_rubber_keys/FlashKa_key_mould_resin_cavity.stl (drawing FlashKa_key_mould.pdf) | K14: SLA resin print from JLC3DP, in the merged JLCCNC order, ONCE PER BUILDER (not per light). Plate 48 x 28 x 6.0 mm with a ribbed back, four cavities key face down (the chevron is a groove in the cavity floor), two printed pins d4.0 (the box includes them). Print with the parting face up, supports on the back only (drawing FK-H-08).
A15: Casting mould (default), resin lid (48 x 28 x 5.47 mm) | B15: SLA resin print (JLC3DP) | C15: 48 | D15: 28 | E15: 5.472 | F15: 4821.4 | G15: - | H15: 0 | I15: 1 | J15: order_files/3_rubber_keys/FlashKa_key_mould_resin_lid.stl (drawing FlashKa_key_mould.pdf) | K15: SLA resin print from JLC3DP, once per builder. Plate 48 x 28 x 5.0 mm with a ribbed back; four plateaus form the plate recesses; pour and vent holes, two sockets d4.2 for the pins, four holes for the M3 x 16 bolts (no threads in the resin).
A16: Casting mould OPTION, aluminium cavity half (48 x 28 x 8 mm) - not in the totals | B16: CNC aluminium (option) | C16: 48 | D16: 28 | E16: 8.002 | F16: 10234.9 | G16: 27.6 | H16: 0 | I16: 1 | J16: order_files/3_rubber_keys/FlashKa_key_mould_cavity.step + FlashKa_key_mould.pdf | K16: The durable option instead of the resin mould: aluminium 6061-T6 from JLCCNC, once per builder. Four cavities, key face down; the chevron groove needs a 0.6 mm end mill; 2 reamed dowel holes, 4 x M3; fine glass-bead blast (matte key face), no anodising (drawing FK-H-08). Holds +/-0.02 mm and lasts for many pours.
A17: Casting mould OPTION, aluminium lid (48 x 28 x 8.47 mm) - not in the totals | B17: CNC aluminium (option) | C17: 48 | D17: 28 | E17: 8.471 | F17: 10186 | G17: 27.5 | H17: 0 | I17: 1 | J17: order_files/3_rubber_keys/FlashKa_key_mould_lid.step + FlashKa_key_mould.pdf | K17: Aluminium 6061-T6, once per builder (option). Four plateaus form the plate recesses; pour and vent holes, dowel and screw holes; as machined.
A18: Laser sleeve (optional, single POM-C part, not in a kit) | B18: CNC POM-C (option) | C18: 10 | D18: 6 | E18: 5.97 | F18: 110.9 | G18: 0.156 | H18: 0 | I18: - | J18: order_files/2_JLCCNC/FlashKa_laser_sleeve.step | K18: ONLY for a laser module thinner than 6 mm. Too small for the JLCCNC instant quote and not in a kit (its slit needs a side setup): order it from a shop that takes small parts (order_files/2_JLCCNC/FlashKa_laser_sleeve.step). Not in the totals.
A19: Side key, cast urethane rubber Shore A 80 (made at home) | B19: made at home | C19: 5.2 | D19: 11 | E19: 1.85 | F19: 55.8 | G19: 0.064 | H19: 2 | I19: - | J19: order_files/3_rubber_keys/FlashKa_key_side.step + FlashKa_key_side.pdf | K19: 4.2 x 10.0 R1.5, the same part for next and previous (turned 180 deg; the chevron points along the body); cast in the mould, 4 per pour (2 + 2 spares). Material in sheet 'Bought parts' (urethane rubber, pigment, release).
A20: Stiffener: plate + doubler, 0.3 mm stainless shim (made at home) | B20: made at home | C20: 3.6 | D20: 9.4 | E20: 0.6 | F20: 11 | G20: 0.087 | H20: 2 | I20: - | J20: order_files/3_rubber_keys/FlashKa_key_stiffener.step | K20: Plate 3.6 x 9.4 (corners clipped 0.8 x 45 deg) + doubler 2.0 x 2.0, cut with tin snips and glued into each side key with cyanoacrylate. Shim and glue in sheet 'Bought parts'.
A22: 2. JLCCNC aluminium estimate - method (all inputs are ESTIMATES; JLCCNC publishes no price list, https://jlccnc.com/blog/cnc-machining-cost-factors)
A23: Cost of one aluminium part = aluminium (stock block weight x price) + machining (minutes x rate x complexity) + threads + finish. Stock block = bounding box + allowance on every side. Machining minutes = material to remove / removal rate + minutes for fine features (pockets, holes, grooves, texture: section 4). Per order you also pay the set-ups (each re-clamping of the part) and the anodizing lot fee once. Calibrated in v0.5 so that one tray + lid costs about the same as the v0.4 estimate; v0.6 and v0.7 keep these inputs and change only what the design changes (sections 4 and 5). The same model prices the two plates of the aluminium mould (option).
A24: Aluminium 6061 price (USD per kg) | B24: 8 | C24: USD per kg | D24: ESTIMATE: 6061-T6 plate/bar incl. cutting waste. JLCCNC publishes no price list. Source: https://jlccnc.com/blog/cnc-machining-cost-factors (read 2026-10-14)
A25: Aluminium density (g per cm3) | B25: 2.7 | C25: g per cm3 | D25: Density of 6061 aluminium.
A26: Stock allowance per side (mm) | B26: 2 | C26: mm per side | D26: ESTIMATE: stock block is the part's bounding box plus this on every side.
A27: Material removal rate (cm3 per minute) | B27: 6 | C27: cm3 per min | D27: ESTIMATE: material removal rate of a small 3-axis mill in aluminium.
A28: Machine time rate (USD per minute) | B28: 0.6 | C28: USD per min | D28: ESTIMATE: machine time rate (calibrated in v0.5 so that one tray+lid costs about what the v0.4 estimate gave: $31 + $12). Source: https://jlccnc.com/blog/cnc-machining-cost-factors (read 2026-10-14)
A29: Set-up cost (USD per set-up) | B29: 3.5 | C29: USD per set-up | D29: ESTIMATE: one-off cost per workpiece set-up (each re-clamping of the part).
A30: Tapping (USD per thread) | B30: 0.25 | C30: USD per thread | D30: ESTIMATE: tapping one M1.6 or M3 thread.
A31: V-groove machining time (minutes per metre) | B31: 6 | C31: min per metre | D31: ESTIMATE (since v0.6): machine time per metre of V-groove (90 deg cutter, short pieces). The SAME rate prices the v0.6 seams that are removed and the v0.7 texture and grooves that are added (section 4). Source: https://jlccnc.com/blog/cnc-machining-cost-factors (read 2026-10-16)
A32: Bead blast of the aluminium mould's cavity half (USD per part) | B32: 1 | C32: USD per part | D32: ESTIMATE: fine glass-bead blast of the aluminium mould's cavity half (matte key face) = the 'Bead blast only' price of a lid-size part (section 3). The mould lid stays as machined. Source: https://jlccnc.com/finishes (read 2026-10-14)
A33: Panel texture: 1 = cut it, 0 = leave it out (priced option) | B33: 1 | C33: 1 or 0 | D33: The panel texture is a priced option: 1 = the shop cuts the 0.2 mm V texture in the recessed panels of the tray and the lid (the order files carry it, the pictures show it), 0 = leave it out and price the tray and lid without it (plain panels; the parts fit and work the same). Section 4 multiplies the texture minutes by this switch; the saving is in the options table of the Summary.
A35: 3. Surface finish choices at JLCCNC for the tray and the lid (prices are ESTIMATES; https://jlccnc.com/finishes, read 2026-10-14 and again 2026-10-16)
A36: Finish | B36: Tray (USD per part) | C36: Lid (USD per part) | D36: Lot fee (USD per order) | E36: What you get
A37: As machined (no finish) | B37: 0 | C37: 0 | D37: 0 | E37: Tool marks visible, bare aluminium dulls and marks with fingerprints. Cheapest, fine for a fit test.
A38: Bead blast only | B38: 1.5 | C38: 1 | D38: 3 | E38: Uniform matt grey surface, hides tool marks. Not corrosion-protected.
A39: Black anodize only | B39: 2 | C39: 1.2 | D39: 8 | E39: Black coating on the machined surface (tool marks still visible); the drawings ask for type II, 8-12 um (JLCCNC range 8-25 um). Thickness changes the holes slightly: say so in the quote.
A40: Bead blast + black anodize | B40: 2.5 | C40: 1.5 | D40: 8 | E40: THE DESIGN CHOICE: matt black, scratch-resistant. On JLCCNC bead blast is not included in the plain anodize option - pick the combined option.
A41: Bead blast + clear anodize | B41: 2.5 | C41: 1.5 | D41: 8 | E41: Silver matt aluminium look, protected.
A42: Chosen finish (drop-down) | B42: Bead blast + black anodize | E42: Pick the finish here; the tray/lid/lot prices below follow. The design assumes 'Bead blast + black anodize' (type II, 8-12 um on the drawings; JLCCNC range 8-25 um). The 0.2 mm texture and the 0.3 mm grooves stay visible after blasting and anodizing. The aluminium mould (option) is not anodised: its cavity half is bead blasted (section 2).
A43: Finish cost per tray (USD) | B43: =INDEX($B$37:$B$41,MATCH($B$42,$A$37:$A$41,0)) -> 2.5
A44: Finish cost per lid (USD) | B44: =INDEX($C$37:$C$41,MATCH($B$42,$A$37:$A$41,0)) -> 1.5
A45: Anodizing lot fee per order (USD) | B45: =INDEX($D$37:$D$41,MATCH($B$42,$A$37:$A$41,0)) -> 8
A47: 4. Fine-feature time of the tray and the lid - what changed from v0.6 (ESTIMATES; the v0.7 exterior adds panels, a V texture and transverse grooves, the v0.6 seams are gone)
A48: v0.6 priced all fine work as tray 38.09 min and lid 7.52 min. v0.7 keeps that, takes out the features that no longer exist and adds the new ones. V-groove work is counted in millimetres at ONE rate (minutes per metre, section 2) for the seams that go and the texture and grooves that come, so the groove part of the change follows the real geometry (lengths computed from housing_interface.json 'panel_layout' and the groove parameters). Other changes are typed-in minutes. The texture row is multiplied by the switch 'texture_on' (section 2).
A49: Feature | B49: Tray (mm or min) | C49: Lid (mm or min) | D49: Unit | E49: Tray (min) | F49: Lid (min) | G49: Basis
A50: v0.6 fine-feature time (the result of the v0.6 workbook) | B50: 38.09 | C50: 7.52 | D50: min | E50: =B50 -> 38.09 | F50: =C50 -> 7.52 | G50: v0.6 workbook, sheet 'Housing', section 4: the v0.5 lump (tray 36 min, lid 8 min) without the knurl and the side grooves, plus the skin seams, the floor holes, the floor RF window, the lid rabbet and the two hold-down bosses. Unchanged ESTIMATE.
A51: minus the v0.6 skin seams (frames and stringers, 0.25 deep) | B51: -646.5 | C51: -220.2 | D51: mm of V-groove | E51: =B51/1000*$B$31 -> -3.879 | F51: =C51/1000*$B$31 -> -1.3212 | G51: The v0.6 'fighter-jet' seams are gone: tray 646.5 mm, lid 220.2 mm of V-groove (v0.6 housing_interface.json 'skin_layout').
A52: minus the v0.6 floor holes for the caps and the light tube | B52: -3 | C52: 0 | D52: min | E52: =B52 -> -3 | F52: =C52 -> 0 | G52: Main bore with counterbore and two slide holes: 3 stepped or chamfered holes, about 1 min each in the v0.6 estimate. Gone in v0.7.
A53: plus the key bezel (stadium recess 0.5 deep, 45 deg walls) and the three key openings with their flange seats | B53: 4 | C53: 0 | D53: min | E53: =B53 -> 4 | F53: =C53 -> 0 | G53: Bezel X 15.75-35.55, 11.6 wide; openings 7.0 x 7.0 (main key) and 2 x 4.4 x 10.3 (side keys) through the 1.0-1.5 mm floor, flange seats from the inside. About 1 min per opening and 1 min for the bezel.
A54: plus the octagon: the four diagonal facets, the lid's cap pocket (45 deg walls, flat seat) and the two floor rails of the cell bay | B54: 1.5 | C54: 1.5 | D54: min | E54: =B54 -> 1.5 | F54: =C54 -> 1.5 | G54: Section 20 x 18 mm with 45 deg legs of 3.4 mm (facets 13.2 / 11.2 / 4.81 mm); the bulk removal is in 'material to remove'. Tray: the two lower diagonal facets with a 90 deg chamfer cutter and the two rails 1.2 x 1.1 mm the cell lies on; lid: the two upper diagonal facets, the 45 deg walls of the pocket under them and the flat seat (FK-H-02: flat 0.05). About 0.5 min per long facet or wall, ESTIMATE.
A55: plus the two key-board bosses (blind M1.6) and the four support ribs on the floor | B55: 1.5 | C55: 0 | D55: min | E55: =B55 -> 1.5 | F55: =C55 -> 0 | G55: Bosses d3.4 joined to the trough walls, ribs 1.4 wide at X 18.65 and 32.65; the two blind threads are counted in section 5 (threads).
A56: plus the recessed panels, 0.3 deep, corners R0.8 (8 on the tray, 3 on the lid) | B56: 4 | C56: 1.5 | D56: min | E56: =B56 -> 4 | F56: =C56 -> 1.5 | G56: Pocket contours of the panels with a flat end mill, 0.5 min per panel (housing_interface.json 'panel_layout'). The bulk removal is in 'material to remove'.
A57: plus the V texture in the panels (90 deg V, 0.2 deep, pitch 0.9, at 45 deg) - a priced option: x 'texture_on' (section 2) | B57: 1719.5 | C57: 735.7 | D57: mm of V-groove | E57: =B57/1000*$B$31*$B$33 -> 10.317 | F57: =C57/1000*$B$31*$B$33 -> 4.4142 | G57: Groove length = panel area / pitch, from 'panel_layout' (the floor RF window opening is a textured POM-C plug, not aluminium). One 90 deg V engraving cutter; drawing FK-H-01 sheet 2, note 1. The minutes are multiplied by the switch 'texture_on' (1 = cut it, 0 = leave it out: the parts still fit and work, the panels stay plain).
A58: plus the transverse V grooves, 0.3 deep: 3 at the head (top, bottom and diagonal facets), 3 at the tail (all round) | B58: 272.5 | C58: 68.4 | D58: mm of V-groove | E58: =B58/1000*$B$31 -> 1.635 | F58: =C58/1000*$B$31 -> 0.4104 | G58: Octagon: 68.0 mm all round, 45.6 mm without the side facets; at the tail the lid takes its top facet and the two upper diagonal facets (22.8 mm), the tray the rest.
A59: Fine-feature time, v0.7 (min) | E59: =SUM(E50:E58) -> 54.163 | F59: =SUM(F50:F58) -> 14.0234 | G59: V-groove length: v0.6 867 mm of seams; v0.7 2455 mm of texture and 341 mm of transverse grooves.
A61: 4b. Fine-feature time of the two plates of the aluminium mould (option; ESTIMATES; drawing FK-H-08)
A62: Feature | B62: Cavity half (min) | C62: Lid (min) | D62: Basis
A63: 4 cavities: cap and flange pockets with 1 deg draft, chevron groove (0.6 mm end mill), runner, gate and vent groove | B63: 12 | C63: 0 | D63: 3 min per cavity: the chevron groove needs a 0.6 mm end mill (R0.3, the smallest radius); outlines and depths +/-0.02 (drawing FK-H-08).
A64: dowel holes (reamed in the cavity half, slip fit in the lid), 4 M3 holes, 2 pry slots | B64: 2 | C64: 1 | D64: The four M3 threads in the cavity half are counted in section 5 (threads).
A65: 4 plateaus that form the plate recesses, each with a pour hole and a vent hole | B65: 0 | C65: 5 | D65: 1.25 min per plateau (0.47 mm high, 3.8 x 9.6 R1.0).
A66: Fine-feature time of the aluminium mould plates (min) | B66: =SUM(B63:B65) -> 14 | C66: =SUM(C63:C65) -> 6
A68: 5. JLCCNC estimate - one aluminium part
A69: Step | B69: Tray | C69: Lid | D69: Alu mould cavity half (option) | E69: Alu mould lid (option) | F69: How it is computed
A70: Stock block volume (cm3) | B70: =($C$7+2*$B$26)*($D$7+2*$B$26)*($E$7+2*$B$26)/1000 -> 54.4896 | C70: =($C$8+2*$B$26)*($D$8+2*$B$26)*($E$8+2*$B$26)/1000 -> 26.73 | D70: =($C$16+2*$B$26)*($D$16+2*$B$26)*($E$16+2*$B$26)/1000 -> 19.971328 | E70: =($C$17+2*$B$26)*($D$17+2*$B$26)*($E$17+2*$B$26)/1000 -> 20.751744 | F70: (X + 2 x allowance) x (Y + 2 x allowance) x (Z + 2 x allowance) / 1000
A71: Part volume (cm3) | B71: =$F$7/1000 -> 8.3285 | C71: =$F$8/1000 -> 3.1207 | D71: =$F$16/1000 -> 10.2349 | E71: =$F$17/1000 -> 10.186 | F71: volume / 1000
A72: Material to remove (cm3) | B72: =B70-B71 -> 46.1611 | C72: =C70-C71 -> 23.6093 | D72: =D70-D71 -> 9.736428 | E72: =E70-E71 -> 10.565744 | F72: stock block - part
A73: Aluminium cost (USD) | B73: =B70*$B$25/1000*$B$24 -> 1.1769754 | C73: =C70*$B$25/1000*$B$24 -> 0.577368 | D73: =D70*$B$25/1000*$B$24 -> 0.43138068 | E73: =E70*$B$25/1000*$B$24 -> 0.44823767 | F73: stock volume x density / 1000 x price per kg (you pay for the whole block)
A74: Fine-feature time (min) | B74: =$E$59 -> 54.163 | C74: =$F$59 -> 14.0234 | D74: =$B$66 -> 14 | E74: =$C$66 -> 6 | F74: from section 4 (tray, lid) and 4b (aluminium mould plates)
A75: Machining time (min) | B75: =B72/$B$27+B74 -> 61.856517 | C75: =C72/$B$27+C74 -> 17.958283 | D75: =D72/$B$27+D74 -> 15.622738 | E75: =E72/$B$27+E74 -> 7.7609573 | F75: material to remove / removal rate + fine-feature time
A76: Complexity factor | B76: 1.1 | C76: 1.3 | D76: 1.3 | E76: 1.3 | F76: ESTIMATE: tray 1.10 and lid 1.30 as in v0.6 (texture and grooves on the facets and the ends need indexed set-ups; the lid is a cap with a 1.5 mm plate over the cavity and two bosses); aluminium mould plates 1.30 (0.6 mm end mill for the chevron grooves, +/-0.02 mm on cavities and parting faces)
A77: Machining cost (USD) | B77: =B75*$B$28*B76 -> 40.825301 | C77: =C75*$B$28*C76 -> 14.007461 | D77: =D75*$B$28*D76 -> 12.185736 | E77: =E75*$B$28*E76 -> 6.0535467 | F77: minutes x rate x complexity factor
A78: Threads to cut (number) | B78: 7 | C78: 0 | D78: 4 | E78: 0 | F78: Tray: 4 x M1.6 (lid screws) + 2 x M1.6 BLIND (key-board bosses) + 1 x M1.6 (laser set screw, from the head-block top under the lid). Lid: none (clearance holes). Aluminium mould cavity half: 4 x M3.
A79: Tapping cost (USD) | B79: =B78*$B$30 -> 1.75 | C79: =C78*$B$30 -> 0 | D79: =D78*$B$30 -> 1 | E79: =E78*$B$30 -> 0 | F79: threads x cost per thread
A80: Finish cost per part (USD) | B80: =$B$43 -> 2.5 | C80: =$B$44 -> 1.5 | D80: =$B$32 -> 1 | E80: 0 | F80: tray and lid: chosen finish (section 3); aluminium mould cavity half: bead blast (section 2); its lid: as machined
A81: Variable cost per part (USD) | B81: =B73+B77+B79+B80 -> 46.252276 | C81: =C73+C77+C79+C80 -> 16.084829 | D81: =D73+D77+D79+D80 -> 14.617116 | E81: =E73+E77+E79+E80 -> 6.5017844 | F81: aluminium + machining + tapping + finish
A82: Set-ups (number) | B82: 5 | C82: 3 | D82: 2 | E82: 2 | F82: ESTIMATE: tray 5 (top, bottom, -Y side, +Y side, ends; the diagonal facets from the bottom and side set-ups), lid 3 (top with its two diagonal facets, bottom with the pocket and the seat, ends), each aluminium mould plate 2 (both faces)
A83: Set-up cost per order (USD) | B83: =B82*$B$29 -> 17.5 | C83: =C82*$B$29 -> 10.5 | D83: =D82*$B$29 -> 7 | E83: =E82*$B$29 -> 7 | F83: set-ups x set-up cost, paid once per order
A85: 6. JLCCNC total for the tray and the lid (one set per light)
B86: Scenario A | C86: Scenario B | D86: Note
A87: Lights you build | B87: =Summary!$B$7 -> 1 | C87: =Summary!$B$8 -> 5
A88: Tray pieces = lights x per light + fixed per order | B88: =B87*$H$7+$I$7 -> 1 | C88: =C87*$H$7+$I$7 -> 5
A89: Lid pieces = lights x per light + fixed per order | B89: =B87*$H$8+$I$8 -> 1 | C89: =C87*$H$8+$I$8 -> 5
A90: Alu mould cavity half (option) pieces = lights x per light + fixed per order | B90: =B87*$H$16+$I$16 -> 1 | C90: =C87*$H$16+$I$16 -> 1
A91: Alu mould lid (option) pieces = lights x per light + fixed per order | B91: =B87*$H$17+$I$17 -> 1 | C91: =C87*$H$17+$I$17 -> 1
A92: Tray + lid: variable cost (pieces x cost per part) | B92: =B88*$B$81+B89*$C$81 -> 62.337105 | C92: =C88*$B$81+C89*$C$81 -> 311.68553
A93: Tray + lid: set-ups + anodizing lot fee (once per order) | B93: =$B$83+$C$83+$B$45 -> 36 | C93: =$B$83+$C$83+$B$45 -> 36
A94: ESTIMATE of tray + lid (USD) | B94: =B92+B93 -> 98.337105 | C94: =C92+C93 -> 347.68553 | D94: Ordering 5 sets at once is much cheaper per set than 1 set, because the set-ups and the anodizing lot fee are paid once.
A95: REAL instant-quote price for tray + lid (type it in, USD incl. finish, without shipping) | D95: Upload FlashKa_tray.step + FlashKa_tray.pdf and FlashKa_lid.step + FlashKa_lid.pdf from order_files/2_JLCCNC/ at https://jlccnc.com/cnc-machining-quote and type the price shown for your quantity here. Leave empty to use the estimate.
A96: Tray + lid used in the totals (USD) | B96: =IF(ISNUMBER(B95),B95,B94) -> 98.337105 | C96: =IF(ISNUMBER(C95),C95,C94) -> 347.68553
A97: of which the panel texture (USD, in the estimate above; 0 when 'texture_on' is 0) | B97: =B88*$E$57*$B$28*$B$76+B89*$F$57*$B$28*$C$76 -> 10.252296 | C97: =C88*$E$57*$B$28*$B$76+C89*$F$57*$B$28*$C$76 -> 51.26148 | D97: Texture minutes (section 4) x machine rate x complexity factor x pieces. Leaving the texture out saves this and the VAT and duty on it (options table of the Summary).
A99: 6b. Casting mould for the rubber side keys, once per builder: resin print from JLC3DP (default, in the totals) or aluminium from JLCCNC (option)
A100: Resin (default): two SLA plates printed by JLC3DP from order_files/3_rubber_keys/FlashKa_key_mould_resin_cavity.stl and order_files/3_rubber_keys/FlashKa_key_mould_resin_lid.stl, ordered with the JLCCNC parts as one merged order (one package, one shipping rate: https://jlccnc.com/news/merged-ordering, read 2026-10-22). JLC3DP publishes only the headline 'SLA from $0.30': the estimate is MAX(minimum per part, rate x model volume) per plate. Aluminium (option): the two 6061-T6 plates of drawing FK-H-08 priced with the aluminium model of sections 2-5; it holds +/-0.02 mm and lasts for many pours, the resin print is cheaper but does not hold that tolerance (try the first key in its opening).
A101: JLC3DP SLA resin, rate (USD per cm3 of model volume) | B101: 0.3 | C101: USD per cm3 | D101: ESTIMATE from JLC3DP's headline 'SLA from $0.30' (re-read 2026-10-22; the v0.6 workbook used the same rate for its resin parts). The instant quote shows the real price per part. Source: https://jlc3dp.com/ (read 2026-10-22)
A102: JLC3DP minimum price per part (USD) | B102: 0.6 | C102: USD per part | D102: ESTIMATE (as in v0.6): minimum price of one printed part. Source: https://jlc3dp.com/3d-printing-quote (read 2026-10-16)
A103: Resin cavity half: price per plate (USD) | B103: =MAX($B$102,$B$101*$F$14/1000) -> 1.87209 | D103: MAX(minimum, rate x 6.24 cm3); 1 plate per builder (section 1, 'Fixed per order').
A104: Resin lid: price per plate (USD) | B104: =MAX($B$102,$B$101*$F$15/1000) -> 1.44642 | D104: MAX(minimum, rate x 4.82 cm3); 1 plate per builder (section 1, 'Fixed per order').
A105: ESTIMATE of the resin mould (USD) | B105: =$I$14*$B$103+$I$15*$B$104 -> 3.31851 | C105: =$I$14*$B$103+$I$15*$B$104 -> 3.31851 | D105: Once per builder: the same in both scenarios. The four M3 x 16 bolts with washers and nuts are in sheet 'Bought parts'.
A106: Aluminium mould (option): variable cost of the two plates | B106: =B90*$D$81+B91*$E$81 -> 21.118901 | C106: =C90*$D$81+C91*$E$81 -> 21.118901
A107: Aluminium mould (option): set-ups (once per order) | B107: =$D$83+$E$83 -> 14 | C107: =$D$83+$E$83 -> 14
A108: ESTIMATE of the aluminium mould (option, NOT in the totals; USD) | B108: =B106+B107 -> 35.118901 | C108: =C106+C107 -> 35.118901 | D108: Research before the design was finished guessed $15-30 for a small two-plate mould; this estimate uses the same model as the tray and the lid (finer cutters, 4 cavities). Its hardware (2 dowel pins, 4 M3 x 12 screws) is listed in the options table of the Summary, not in 'Bought parts'.
...

Sheet Bought parts
A1: Bought parts and consumables (not on the JLCPCB panel, not from JLCCNC / JLC3DP)
A2: Everything the PCB and housing orders do not contain: the 14500 cell with its nickel strip, the LED board, the TIR optic, the laser, screws (two M1.6 x 2.5 pan-head screws for the key board), set screw, split ring, wire, thermal paste, tapes, foam, the two silicone hold-down pads, adhesives - and what you need to cast the two rubber side keys at home: the urethane rubber, black pigment, mould release, 0.3 mm stainless shim for the stiffeners, glue, cups, syringes and polishes, plus the M3 bolts, washers and nuts of the resin casting mould. Prices: the v0.5 items keep their AliExpress search-result prices of 2026-10-14 (item pages cannot be read automatically); the LED board, the TIR optic and the urethane rubber were read on 2026-10-22, the cell and the nickel strip on 2026-10-23; the other items are typical-price ESTIMATES (no listing read). Change the blue number when you see a real listing. 'Packs' = how many packs you must buy (rounded up): quantity needed = lights x 'per light' + 'fixed per order' (spares, one roll of tape, one sheet of pad material, one rubber kit...).
A3: Prices exclude VAT and shipping here; both are added on sheet 'Hidden costs' (21 % VAT, shipping per parcel, EUR 3 flat duty per customs line). Column R says which parcel an item travels in: the casting supplies come from an EU shop, the TIR optics from an electronics distributor and the cell with its nickel strip from an EU battery shop (all three inside the EU: no customs), everything else from AliExpress / web shops.
A5: # | B5: Item | C5: Used for | D5: Exact spec that matters | E5: Search term (AliExpress / web shop) | F5: Price per pack (USD) | G5: Pack size | H5: Pack unit | I5: Per light | J5: Fixed per order | K5: Packs A | L5: Cost A (USD) | M5: Packs B | N5: Cost B (USD) | O5: Category | P5: Price basis (source, date) | Q5: Link example | R5: Shop (parcel) | S5: Needed for
A6: 1 | B6: Li-ion cell Vapcell INR14500 F15, 1500 mAh, 3 A, flat top, no protection board | C6: Power (BT1). One cell lies in the cell bay on two floor rails (polyimide tape on the rails), + end towards the head, held by a foam strip under the lid and a foam pad at the tail end. Nickel strips are spot-welded to both ends; one 24 AWG wire goes from each strip to J2. The protection IC U6 and the MOSFET Q3 on the main PCB protect it (the cell has no protection board of its own). | D6: Maker's data: 1500 mAh typical, 1150 mAh minimum (at 0.2C to 2.5 V), 3.60 V nominal, 4.20 V charged, 2.5 V end, 3 A maximum continuous, about 60 mOhm (AC, 1 kHz), 14.0 +/-0.2 x 49.0 +/-0.3 mm, about 22 g, flat top, no protection circuit; standard charge 500 mA (the light charges at about 494 mA). The firmware limits the cell current to 2.8 A in turbo (93 % of the 3 A rating, a documented LuxLibre BAT-1 deviation; no independent test of the F15 at 3 A was found). The bay takes any FLAT-TOP 14500 up to 14.5 x 50.4 mm (button-top and protected cells are usually longer). Alternative: Vapcell INR14500 K10 (1000 mAh typical / 900 minimum, 8 A, 14.1 x 50.1 mm, flat top): sags less and keeps full turbo to a lower charge (not simulated), about a third less runtime; USD 4.30 at illumn.com (USA, https://illumn.com/14500-vapcell-inr14500-k10-1000mah-8a-high-discharge-flat-top-li-ion-battery.html), no EU shop found in stock (nkon.nl lists the similar H10, 1000 mAh 10 A, at EUR 3.26 excl. VAT: out of stock on 2026-10-23). Buy the cell with welded nickel tabs if the shop offers it; otherwise weld the strips (sheet 'Tools'). Never solder onto the cell; never use a dented cell or one with a torn sleeve. | E6: Vapcell F15 INR14500 1500mAh flat top | F6: 3.47 | G6: 1 | H6: cell | I6: 1 | J6: 1 | K6: =ROUNDUP(ROUND((Summary!$B$7*I6+J6)/G6,9),0) -> 2 | L6: =K6*F6 -> 6.94 | M6: =ROUNDUP(ROUND((Summary!$B$8*I6+J6)/G6,9),0) -> 6 | N6: =M6*F6 -> 20.82 | O6: Part | P6: nkon.nl, read 2026-10-23: EUR 3.10 excl. VAT (EUR 3.75 incl. VAT; EUR 2.85 excl. VAT from 10 cells), in stock; converted at 1.1188 USD/EUR. Maker's data: https://www.vapcelltech.com/h-pd-251.html. One spare cell per order (a weld can go wrong). | Q6: https://www.nkon.nl/en/vapcell-f15-inr14500-1500mah-3a.html | R6: EU battery shop | S6: every light
A7: 2 | B7: Nickel strip 0.2 x 5 mm, pure nickel, 1 m | C7: The cell's two tabs: a piece spot-welded to each end (BAT+ at the front, bent forward into the rebate of the antenna spacer; BAT- at the far end, bent into the lower -Y corner of the bay); the 24 AWG wires are soldered to the strips, never to the cell. Not needed for a cell bought with welded tabs. | D7: Pure nickel (>= 99.7 %, not nickel-plated steel), 0.2 mm thick, 5 mm wide; about 50 mm per light plus pieces to practise the weld. The bay allows 0.4 mm at each end for the strip with its fold and weld bumps. | E7: pure nickel strip 0.2x5mm | F7: 2.08 | G7: 1 | H7: 1 m | I7: 0.1 | J7: 0 | K7: =ROUNDUP(ROUND((Summary!$B$7*I7+J7)/G7,9),0) -> 1 | L7: =K7*F7 -> 2.08 | M7: =ROUNDUP(ROUND((Summary!$B$8*I7+J7)/G7,9),0) -> 1 | N7: =M7*F7 -> 2.08 | O7: Consumable | P7: nkon.nl, read 2026-10-23: EUR 1.86 excl. VAT per metre (EUR 2.25 incl. VAT), in stock; converted at 1.1188 USD/EUR. Bought with the cell (same parcel). | Q7: https://nkon.nl/en/1-meter-nikkel-batterijsoldeerstrip-5mm-0-2mm.html | R7: EU battery shop | S7: every light
A8: 3 | B8: Luminus SST-20 Gen 2 LED, 6500 K, on a 10 mm round copper DTP board (ready-made) | C8: The main white light (D2): lies on the floor of the head bore on a thin film of thermal paste, under the TIR optic; two 24 AWG wires go to the pads J3. | D8: Round board 10.0 mm diameter x 1.6 mm (the bore is 10.1 mm), copper core 'DTP' (direct thermal path), emitter SST-20 Gen 2 (data sheet: 3 A maximum, G1 bin at least 1,156 lm at 3 A and 85 C), 6500 K. Ask for the G1 bin (an F9 LED gives about 6 % less light: 1,088 lm at 3 A). Not the older SST-20 (Gen 1): it needs more current for the same light. A 16 or 20 mm board does NOT fit. | E8: SST-20 Gen 2 6500K 10mm DTP copper board | F8: 2.99 | G8: 1 | H8: board | I8: 1 | J8: 1 | K8: =ROUNDUP(ROUND((Summary!$B$7*I8+J8)/G8,9),0) -> 2 | L8: =K8*F8 -> 5.98 | M8: =ROUNDUP(ROUND((Summary!$B$8*I8+J8)/G8,9),0) -> 6 | N8: =M8*F8 -> 17.94 | O8: Part | P8: Kaidomain, read 2026-10-22: USD 1.99 for the LED + USD 1.00 mounted on a 10 mm copper DTP board = USD 2.99, in stock; the flux bin is not stated (the first v0.7 layout: USD 5.40 for an SST-20 on a DTP board from AliExpress). | Q8: https://kaidomain.com/SST-20-Gen-2-10W-3A-1100-Lumens-SMD-3535-LED | R8: AliExpress / web shop | S8: every light
A9: 4 | B9: TIR optic LEDiL LISA3-RS-PIN (FP16558), pack of 5 | C9: Focuses the LED into a narrow beam; it is also the light's front window. It stands on the LED board in the head bore and is glued with two-part epoxy on its holder rim (one per light; the rest are spares). | D9: LEDiL FP16558_LISA3-RS-PIN: round, 10.0 mm diameter, 6.9 mm high (6.93 +/-0.2 on the LEDiL drawing), clear PMMA lens in a black polycarbonate holder with two pins. Cut the two pins off flush: the 10 mm DTP board has no holes and the bore locates the optic. NOT the clip version LISA3-RS-CLIP16 (7.9 mm high: it would stand out of the head). LEDiL data for the SST-20 Gen 2 (simulated): 20 deg beam, 87 % efficiency, 5.5 cd/lm. No cyanoacrylate near it (white bloom on the PMMA). | E9: LEDiL FP16558 LISA3-RS-PIN | F9: 17.37 | G9: 5 | H9: pack of 5 | I9: 1 | J9: 1 | K9: =ROUNDUP(ROUND((Summary!$B$7*I9+J9)/G9,9),0) -> 1 | L9: =K9*F9 -> 17.37 | M9: =ROUNDUP(ROUND((Summary!$B$8*I9+J9)/G9,9),0) -> 2 | N9: =M9*F9 -> 34.74 | O9: Part | P9: RS Components UK, stock no. 186-2699, read 2026-10-22: GBP 13.11 per pack of 5 excl. VAT (GBP 2.622 each), 190 in stock; converted with the ECB reference rates of 13 Oct 2026 (0.8446 GBP and 1.1188 USD per EUR, https://www.ecb.europa.eu/stats/policy_and_exchange_rates/euro_reference_exchange_rates/html/eurofxref-graph-gbp.en.html). RS also sells it by 100 (186-2399, GBP 1.35 each); Mouser EU sells only the clip version FP18198 (EUR 2.82 for 1). | Q9: https://uk.rs-online.com/web/p/led-lenses-reflectors/1862699 | R9: Electronics distributor | S9: every light
A10: 5 | B10: Green laser module 520 nm, Class 2 (<= 1 mW), 6 x 12 mm, driver built in | C10: The laser pointer (LS1). Switched by Q1 and the slide-switch interlock S2; its two wire leads go to the pads J5. | D10: Body 6.0 mm diameter x 12 mm long (the tray bore is 6.1 mm), 520 nm green, output power <= 1 mW (Class 2, see the explanation below the table), constant-power (APC) driver inside, 3 V class supply (design note LS1 '3 V'; check that the seller's range includes 3.0-4.2 V), two wire leads. A module thinner than 6 mm needs the optional POM-C laser sleeve (FlashKa_laser_sleeve.step). Ask the seller for a measured output power. | E10: 520nm green laser module 6x12mm 1mW APC | F10: 23.5 | G10: 1 | H10: module | I10: 1 | J10: 0 | K10: =ROUNDUP(ROUND((Summary!$B$7*I10+J10)/G10,9),0) -> 1 | L10: =K10*F10 -> 23.5 | M10: =ROUNDUP(ROUND((Summary!$B$8*I10+J10)/G10,9),0) -> 5 | N10: =M10*F10 -> 117.5 | O10: Part | P10: ESTIMATE. AliExpress search result 2026-10-14: US $23.5 for a 6 mm 520 nm 1 mW APC module (item 32869119160). | Q10: https://www.aliexpress.com/item/32869119160.html | R10: AliExpress / web shop | S10: every light
A11: 6 | B11: Screw M1.6 x 6 mm, countersunk, stainless (lid) | C11: Four screws hold the lid (two at the front, two at the rear, at Y +/-4.5 mm on the top facet). | D11: ISO 7046 / DIN 965 M1.6 x 6, stainless steel, head diameter <= 3.1 mm (countersink 3.3 mm). The screw passes the 3.4 mm of solid lid over the head and the tail blocks and engages 2.6 mm of thread in the tray (M1.6, tap drill 1.25 mm); lid clearance hole 1.8 mm. Phillips or hex head - match your screwdriver. Buy extra: they are tiny and get lost. | E11: M1.6x6 countersunk screw stainless 100pcs | F11: 2 | G11: 100 | H11: 100 pcs | I11: 4 | J11: 4 | K11: =ROUNDUP(ROUND((Summary!$B$7*I11+J11)/G11,9),0) -> 1 | L11: =K11*F11 -> 2 | M11: =ROUNDUP(ROUND((Summary!$B$8*I11+J11)/G11,9),0) -> 1 | N11: =M11*F11 -> 2 | O11: Part | P11: ESTIMATE. AliExpress search result 2026-10-14: US $1.5 for 100 pcs M1.6 x 3 countersunk (item 32917852857); M1.6 x 6 priced slightly higher. | Q11: https://www.aliexpress.com/item/32917852857.html | R11: AliExpress / web shop | S11: every light
A12: 7 | B12: Screw M1.6 x 2.5 mm, pan head, stainless (key board) | C12: Two screws hold the key board on the two tapped bosses of the floor. | D12: ISO 7045 / DIN 7985 M1.6 x 2.5, stainless steel, pan head 3.0-3.2 mm diameter x 1.1-1.3 mm (the key board keeps a 3.8 mm circle free). NOT longer than 2.5 mm: the bosses are tapped blind and a 4 mm screw would hit the bottom of the hole (1.7 mm of thread engagement, 1.649 mm of metal under the drill point). | E12: M1.6x2.5 pan head screw stainless DIN 7985 | F12: 2 | G12: 100 | H12: 100 pcs | I12: 2 | J12: 4 | K12: =ROUNDUP(ROUND((Summary!$B$7*I12+J12)/G12,9),0) -> 1 | L12: =K12*F12 -> 2 | M12: =ROUNDUP(ROUND((Summary!$B$8*I12+J12)/G12,9),0) -> 1 | N12: =M12*F12 -> 2 | O12: Part | P12: ESTIMATE (research 2026-10-21): no M1.6 x 2.5 pan-head listing was verified; priced like the M1.6 lid screws (AliExpress anchor US $1.5 per 100, item 32917852857). Industrial sources (SFS, minimum 1,000 pcs; RS) cost about EUR 0.5 per screw. | Q12: https://www.aliexpress.com/wholesale?SearchText=M1.6x2.5+pan+head+screw+stainless | R12: AliExpress / web shop | S12: every light
A13: 8 | B13: Set screw M1.6 x 5 mm, hex socket, stainless (laser) | C13: Holds the laser module in its bore. Screwed in from the top of the head block, under the front end of the lid, with the lid off: no hole or screw shows on the closed light. | D13: ISO 4026 (flat point) or ISO 4029 (cup point) M1.6 x 5, stainless steel, hex socket for a 0.7 mm hex key. NOT longer than 5 mm: the thread runs 5.836 mm from the head-block top into the laser bore and the screw top stays 0.771 mm below the head-block top, so a longer screw would stop the lid from closing. Tray thread M1.6 (tap drill 1.25 mm). | E13: M1.6x5 set screw stainless hex socket | F13: 2 | G13: 50 | H13: 50 pcs | I13: 1 | J13: 4 | K13: =ROUNDUP(ROUND((Summary!$B$7*I13+J13)/G13,9),0) -> 1 | L13: =K13*F13 -> 2 | M13: =ROUNDUP(ROUND((Summary!$B$8*I13+J13)/G13,9),0) -> 1 | N13: =M13*F13 -> 2 | O13: Part | P13: ESTIMATE (typical price of a 50-pack set screw listing; no listing read). | Q13: https://www.aliexpress.com/wholesale?SearchText=M1.6x5+set+screw+stainless | R13: AliExpress / web shop | S13: every light
A14: 9 | B14: Split ring 20-25 mm, stainless | C14: Key ring through the lanyard slot in the tail (slot 3.6 x 4.6 mm, round a 1.45 mm bridge). | D14: Stainless split ring, inner diameter 20-25 mm, wire at most about 1.5 mm thick (its double coil must pass the 3.6 mm slot); a thin cord also fits. | E14: split key ring 25mm stainless steel | F14: 2 | G14: 20 | H14: 20 pcs | I14: 1 | J14: 1 | K14: =ROUNDUP(ROUND((Summary!$B$7*I14+J14)/G14,9),0) -> 1 | L14: =K14*F14 -> 2 | M14: =ROUNDUP(ROUND((Summary!$B$8*I14+J14)/G14,9),0) -> 1 | N14: =M14*F14 -> 2 | O14: Part | P14: ESTIMATE (typical price of a 20-pack key ring listing). | Q14: https://www.aliexpress.com/wholesale?SearchText=split+key+ring+25mm+stainless | R14: AliExpress / web shop | S14: every light
A15: 10 | B15: Socket head screws ISO 4762 M3 x 16 with M3 washers and nuts, stainless (resin casting mould) | C15: Bolt the two resin plates of the casting mould together (four screws through both plates, a washer under each head and each nut). Once per builder. | D15: 4 socket head screws ISO 4762 / DIN 912 M3 x 16 (hex socket 2.5 mm), 8 washers ISO 7089 M3, 4 hex nuts ISO 4032 M3, stainless steel. The resin carries no thread: tighten firmly, not hard. | E15: M3x16 socket head screw stainless washer nut set | F15: 4 | G15: 1 | H15: set (small packs) | I15: 0 | J15: 1 | K15: =ROUNDUP(ROUND((Summary!$B$7*I15+J15)/G15,9),0) -> 1 | L15: =K15*F15 -> 4 | M15: =ROUNDUP(ROUND((Summary!$B$8*I15+J15)/G15,9),0) -> 1 | N15: =M15*F15 -> 4 | O15: Part | P15: ESTIMATE (typical price of small packs: 10 screws, 20 washers, 20 nuts; no listing read). | Q15: https://www.aliexpress.com/wholesale?SearchText=M3x16+socket+head+screw+stainless | R15: AliExpress / web shop | S15: casting mould (once)
A16: 11 | B16: PTFE wire 24 AWG, red + black, 5 m of each | C16: The two cell wires (one per J2 pad: BAT+ from the strip at the front end, BAT- from the strip at the far end along the lower -Y corner of the bay) and the two LED wires (J3 to the LED board). About 0.3 m per light. The laser module's own leads go to J5. | D16: 24 AWG (0.2 mm2) tinned or silver-plated copper, thin-wall PTFE insulation, outer diameter <= 1.05 mm (the LED wire grooves and holes, the cell-wire rebate and the corner channel of the bay are sized for it). It carries the 2.8 A of turbo: thinner wire heats up and drops voltage. PTFE does not melt when you solder. | E16: 24AWG PTFE wire red black 5m silver plated | F16: 7 | G16: 5 | H16: 5 m | I16: 0.4 | J16: 0.6 | K16: =ROUNDUP(ROUND((Summary!$B$7*I16+J16)/G16,9),0) -> 1 | L16: =K16*F16 -> 7 | M16: =ROUNDUP(ROUND((Summary!$B$8*I16+J16)/G16,9),0) -> 1 | N16: =M16*F16 -> 7 | O16: Consumable | P16: ESTIMATE (typical price of a 5 m PTFE wire listing per colour pair; no listing read). | Q16: https://www.aliexpress.com/wholesale?SearchText=24AWG+PTFE+wire+red+black | R16: AliExpress / web shop | S16: every light
A17: 12 | B17: Thermal paste, non-curing silicone grease, small syringe | C17: A thin film (0.1 mm) between the LED board and the floor of the head bore carries the heat into the aluminium. | D17: Thermally conductive, electrically non-conductive, non-curing paste, at least 1 W/mK; a 1-2 g syringe is plenty. No thermal tape or pad: the optic's seat is set for a 0.1 mm film under the board. | E17: thermal paste syringe silicone grease | F17: 2.5 | G17: 1 | H17: syringe | I17: 0 | J17: 1 | K17: =ROUNDUP(ROUND((Summary!$B$7*I17+J17)/G17,9),0) -> 1 | L17: =K17*F17 -> 2.5 | M17: =ROUNDUP(ROUND((Summary!$B$8*I17+J17)/G17,9),0) -> 1 | N17: =M17*F17 -> 2.5 | O17: Consumable | P17: ESTIMATE (typical price of a small syringe; no listing read). | Q17: https://www.aliexpress.com/wholesale?SearchText=thermal+paste+syringe | R17: AliExpress / web shop | S17: every light
... A30: 25 | B30: Polishes and abrasive paper (plastic polish, metal polish, wet-and-dry 400-3000) | C30: Plastic polish for the PMMA keys after the tabs are cut (if the shop did not polish them); metal polish for the chevron grooves of the mould (once); 400-grit paper for the matte key faces of the resin mould (once). | D30: A plastic polish for acrylic, a metal polish (paste), wet-and-dry paper 400, 1000, 2000 and 3000 grit. The frosted ring of the main key stays matte. | E30: acrylic plastic polish kit metal polish | F30: 10 | G30: 1 | H30: set | I30: 0 | J30: 1 | K30: =ROUNDUP(ROUND((Summary!$B$7*I30+J30)/G30,9),0) -> 1 | L30: =K30*F30 -> 10 | M30: =ROUNDUP(ROUND((Summary!$B$8*I30+J30)/G30,9),0) -> 1 | N30: =M30*F30 -> 10 | O30: Consumable | P30: ESTIMATE (typical price; no listing read). | Q30: https://www.aliexpress.com/wholesale?SearchText=acrylic+polish+kit | R30: AliExpress / web shop | S30: casting the side keys
B31: Bought parts (the cell, LED board, TIR optic, laser, screws, set screw, ring, mould hardware) | L31: =SUMIF($O$6:$O$30,"Part",L6:L30) -> 65.79 | N31: =SUMIF($O$6:$O$30,"Part",N6:N30) -> 203
B32: Consumables (nickel strip, wire, thermal paste, tapes, foam, silicone pads, adhesives, casting supplies) | L32: =SUMIF($O$6:$O$30,"Consumable",L6:L30) -> 115.53 | N32: =SUMIF($O$6:$O$30,"Consumable",N6:N30) -> 115.53
B33: of which spares and left-over pack content (information) | L33: =SUM(L6:L30)-SUMPRODUCT(Summary!$B$7*I6:I30/G6:G30*F6:F30) -> 146.858 | N33: =SUM(N6:N30)-SUMPRODUCT(Summary!$B$8*I6:I30/G6:G30*F6:F30) -> 146.22
B34: of which bought from the EU casting shop (one parcel inside the EU, sheet 'Hidden costs') | L34: =SUMIF($R$6:$R$30,"EU casting shop",L6:L30) -> 61.95 | N34: =SUMIF($R$6:$R$30,"EU casting shop",N6:N30) -> 61.95
B35: of which bought from the electronics distributor (the TIR optics: one parcel inside the EU, sheet 'Hidden costs') | L35: =SUMIF($R$6:$R$30,"Electronics distributor",L6:L30) -> 17.37 | N35: =SUMIF($R$6:$R$30,"Electronics distributor",N6:N30) -> 34.74
B36: of which bought from the EU battery shop (the cell and the nickel strip: one parcel inside the EU, sheet 'Hidden costs') | L36: =SUMIF($R$6:$R$30,"EU battery shop",L6:L30) -> 9.02 | N36: =SUMIF($R$6:$R$30,"EU battery shop",N6:N30) -> 22.9
B37: of which casting supplies for the rubber side keys (information) | L37: =SUMIF($S$6:$S$30,"casting the side keys",L6:L30) -> 85.95 | N37: =SUMIF($S$6:$S$30,"casting the side keys",N6:N30) -> 85.95
A39: Why the laser must be Class 2 (<= 1 mW)
A40: Laser classes (IEC/EN 60825-1) for visible light (400-700 nm): Class 1 = harmless in normal use; Class 2 = up to 1 mW continuous - safe for accidental exposure because the blink / aversion reflex (about 0.25 s) closes the eye before damage; Class 3R = up to 5 mW - low risk but a direct look into the beam can hurt, it is not meant for a keychain; Class 3B and 4 = dangerous. (https://en.wikipedia.org/wiki/Laser_safety)
A41: This light is a keychain that people carry and use in public, so the module must be Class 2: 520 nm green at <= 1 mW. Green looks about five times brighter than red at the same power because the eye is most sensitive near 555 nm, so 1 mW green is already a clearly visible dot.
A42: Cheap modules sold as '1 mW' often emit several mW. v0.7 carries no marking: the Class 2 label (EN 60825-1) is printed in the manual and on the packaging. A light that you sell or give to other people needs the label on the light itself - then use the optional artwork order_files/optional_laser_label/FlashKa_laser_label_lid_class2.dxf (fibre-laser marking on the lid). The label is only true if the module really is <= 1 mW: buy from a seller that states a measured power, or measure it (optional laser power meter, sheet 'Tools'). A stronger module is not allowed in this design.
A43: For consumer laser products in the EU the standard EN 50689:2021 applies in addition (https://ul.com/insights/understand-new-laser-product-safety-standards-europe). If you only build for yourself this is a recommendation; if you sell or give lights away, read it first.
A44: Always wear 520 nm safety glasses (sheet 'Tools') when the laser is powered on the bench, and never point it at people, animals, aircraft or vehicles.
A46: Buying tips
A47: Search with the exact term in column E, sort by orders/rating, check the listed dimensions against the spec column, and read the reviews with photos. Ask the seller for the power measurement of the laser, the flux bin of the LED and the exact size of the LED board.
A48: Each seller ships its own parcel: 8 parcels mean 8 shipping fees and 8 x EUR 3 customs duty. Buy the small hardware (screws, rings, wire, paste, tapes, foam, silicone pads, epoxy, shim, glue) together in ONE EU web shop - see 'Hidden costs' for the saving.
A49: The cell and the nickel strip come from one EU battery shop, for example nkon.nl in the Netherlands (the shop the prices were read from; the cell ships by courier as dangerous goods). Ask whether the shop can weld tabs onto the cell; then no spot welder is needed. Any flat-top 14500 up to 14.5 x 50.4 mm fits the bay; the firmware's runtime estimate assumes an F15.
A50: The casting supplies (urethane rubber, pigment, release) come from one EU shop, for example kaupo.de in Germany (the shop the rubber price was read from). One 0.86 kg unit of ECON 80 casts many sets of keys: share it with other builders.
A51: The TIR optic comes in packs of 5 from an electronics distributor (RS, stock no. 186-2699). Below the distributor's free-shipping limit the courier fee is about EUR 15-20: order the optics for several lights at once, or together with other parts.
A52: Order the laser, the cell, the LED board and the optic FIRST (delivery 1-5 weeks), measure them with a caliper, and only then order the housing, so that a different part size does not waste a CNC order.

Sheet Hidden costs
A1: Hidden costs - shipping, EU VAT, customs, bank fees, spares and risk
A2: What you pay on top of the prices of the other sheets. JLCPCB ships one parcel; JLCCNC and JLC3DP ship one merged parcel (JLCCNC's 'merged ordering': one package, one shipping rate); the casting supplies come from an EU shop, the TIR optics from an electronics distributor and the cell with its nickel strip from an EU battery shop (three parcels from inside the EU: VAT only, no customs); every AliExpress seller ships its own parcel. For Lithuania (EU) each parcel from outside the EU gets VAT 21 % and, since 1 July 2026, a flat EUR 3 customs duty per customs line (up to EUR 150), or formal customs clearance with a carrier fee above EUR 150. All inputs are blue; everything marked ESTIMATE has no public price (JLC shows shipping only in the cart). The rules were read on 2026-10-14 (v0.5 price check) and checked again on 2026-10-22.
A4: 1. Inputs: EU import rules, bank fee, shipping choice, parcels
A5: VAT rate Lithuania | B5: 0.21 | C5: fraction | D5: Lithuania standard VAT 21 %. JLC collects it at checkout for individuals on orders up to EUR 150 (IOSS; https://jlcpcb.com/help/article/customs,-duties-and-taxes, read 2026-10-22). Source: https://jlcpcb.com/help/article/EU-VAT-E-commerce-Rules-%26-Adjustments (read 2026-10-14)
A6: IOSS limit: goods value per parcel (EUR) | B6: 150 | C6: EUR | D6: IOSS limit: intrinsic value (goods only, without shipping/VAT) up to EUR 150 per consignment. Source: https://jlcpcb.com/help/article/EU-VAT-E-commerce-Rules-%26-Adjustments (read 2026-10-14)
A7: Flat customs duty per customs line (EUR), up to the limit | B7: 3 | C7: EUR per customs line | D7: Flat customs duty on low-value consignments, EUR 3 per item category (HS code = one declaration line, whatever the quantity) per parcel, 1 Jul 2026 - 1 Jul 2028 (Council Reg. 2026/382; EU guidance https://taxation-customs.ec.europa.eu/document/download/053e5b4e-f0be-4f20-9a23-3e3b659a6676_en?filename=Customs+Guidance+on+EUR+3+customs+duty.pdf and JLC FAQ https://jlcpcb.com/help/article/eu-customs-reform-faq, read again 2026-10-22). Under IOSS JLC collects the VAT but not the EUR 3: you pay it at import unless the shipping channel is DDP. Source: https://trade.ec.europa.eu/access-to-markets/en/news/eu-applies-eu3-customs-duty-item-low-value-e-commerce-consignments (read 2026-10-14)
A8: Formal clearance: carrier fee minimum (EUR per parcel) | B8: 15 | C8: EUR per parcel | D8: Above EUR 150 the parcel goes through formal customs clearance; the carrier charges a disbursement fee, e.g. DHL Germany 2 % min EUR 15, UPS 3 % min EUR 15.70, FedEx 2.5 % min EUR 15 (JLC FAQ); UPS Lithuania 2 % min EUR 12 (https://ups.com/assets/resources/webcontent/en_GB/additional-service-charge-lt.pdf, read 2026-10-22). Source: https://jlcpcb.com/help/article/eu-customs-reform-faq (read 2026-10-14)
A9: Formal clearance: carrier fee percent of VAT + duty | B9: 0.02 | C9: fraction of VAT+duty | D9: See above (DHL Germany example). Source: https://jlcpcb.com/help/article/eu-customs-reform-faq (read 2026-10-14)
A10: Card / currency conversion fee on JLC payments | B10: 0.015 | C10: fraction | D10: ESTIMATE: card / currency-conversion fee of your bank on the USD payments to JLC (0-3 % depending on the bank). Set your own.
A11: Shipping mode (1 = economy, 2 = express) | B11: 2 | C11: 1 or 2 | D11: 1 = economy shipping, 2 = express (DHL/UPS/FedEx). Default express: fastest, and DDP (taxes paid at checkout) works most reliably.
A12: AliExpress shipping per seller parcel (USD) | B12: 2 | C12: USD per parcel | D12: ESTIMATE: AliExpress shipping to Lithuania per seller parcel (many items are free, some cost $1-4). (2026-10-14)
A13: Number of separate AliExpress / web-shop parcels | B13: 8 | C13: parcels | D13: ESTIMATE: separate seller parcels if you buy each item where it is cheapest: LED board, laser, screws, set screw and split rings, wire, tapes + paste + foam + epoxy + silicone pads, mould hardware (M3 screws, washers, nuts), shim + glue + cups + polishes (the first v0.7 layout had 10, with the glass window and the cells; the TIR optics come from a distributor and the cell from an EU battery shop, each its own parcel). (2026-10-23)
A14: parcels if the small hardware comes from ONE EU web shop | B14: 3 | C14: parcels | D14: ESTIMATE. Parcels if you buy the small hardware (screws, rings, wire, tapes, paste, foam, pads, epoxy, shim, glue) from ONE EU web shop.
A15: Risk reserve: share of a second PCB order | B15: 1 | C15: fraction | D15: Risk reserve = this fraction of the JLCPCB order (landed) as a second PCB order after a first-article problem. Not in the totals.
A16: Risk reserve: share of a second housing order | B16: 1 | C16: fraction | D16: Risk reserve = this fraction of the JLCCNC order (landed) as a second housing order. Not in the totals.
A18: 2. Shipping per parcel (USD, ESTIMATES - the JLC carts show the real 'Shipping Estimate' before you pay)
A19: Parcel | B19: Economy A | C19: Express A | D19: Economy B | E19: Express B | F19: Chosen A | G19: Chosen B | H19: Basis
A20: JLCPCB (panel: both PCBs, assembled) | B20: 6.5 | C20: 21.5 | D20: 6.5 | E20: 21.5 | F20: =IF($B$11=1,B20,C20) -> 21.5 | G20: =IF($B$11=1,D20,E20) -> 21.5 | H20: Anchors (Chiptron, 10 Jun 2025): DHL Express $21.50, EuroPacket $6.50, Global Standard Direct Line $1.50 for a small order; EEVblog 2024: FedEx about $16 to Spain. JLC publishes no rate table - the cart shows 'Shipping Estimate'.
A21: JLCCNC + JLC3DP, one merged order (aluminium, PMMA and POM-C parts, resin mould) | B21: 7 | C21: 22 | D21: 9 | E21: 25 | F21: =IF($B$11=1,B21,C21) -> 22 | G21: =IF($B$11=1,D21,E21) -> 25 | H21: ESTIMATE, as in v0.6. JLCCNC merges its orders with JLC3DP ('merged ordering': one package, one shipping rate, select 'All' in the cart; https://jlccnc.com/news/merged-ordering, read 2026-10-22), so the resin mould travels in the JLCCNC parcel. The price shows on the invoice after you accept the quote. Tray, lid and kits weigh about 40 g per light, the two resin plates about 13 g.
A22: EU shop: casting supplies (urethane rubber, pigment, release) | B22: 9 | C22: 18 | D22: 9 | E22: 18 | F22: =IF($B$11=1,B22,C22) -> 18 | G22: =IF($B$11=1,D22,E22) -> 18 | H22: ESTIMATE, not read: a parcel of about 1-1.5 kg inside the EU (kaupo.de ships from Germany); the shop shows its rate at the checkout.
A23: Electronics distributor: TIR optics (from a warehouse inside the EU) | B23: 20 | C23: 20 | D23: 20 | E23: 20 | F23: =IF($B$11=1,B23,C23) -> 20 | G23: =IF($B$11=1,D23,E23) -> 20 | H23: ESTIMATE, not read: distributors ship by courier and charge about EUR 15-20 below their free-shipping limit (orders for several lights or with other parts may pass it). The rate is the same in both shipping modes.
A24: EU battery shop: the 14500 cell and the nickel strip (nkon.nl) | B24: 13.43 | C24: 13.43 | D24: 13.43 | E24: 13.43 | F24: =IF($B$11=1,B24,C24) -> 13.43 | G24: =IF($B$11=1,D24,E24) -> 13.43 | H24: ESTIMATE, not read: nkon.nl (Netherlands) sends lithium cells inside the EU by courier as dangerous goods; its shipping page could not be opened on 2026-10-23. About EUR 12 assumed (converted at 1.1188 USD/EUR); the shop shows the real rate at the checkout. The rate is the same in both shipping modes.
A26: 3. Customs parameters per parcel
A27: Parcel | B27: Customs lines per parcel | C27: Duty rate in formal clearance | D27: Parcels | E27: Note (rates are ASSUMPTIONS - the invoice / HS code decides; in the flat-duty case the EUR 3 per line replaces the tariff)
A28: JLCPCB (panel: both PCBs, assembled) | B28: 2 | C28: 0 | D28: 1 | E28: Bare and assembled PCBs: HS 8534/8543, normally 0 % duty (assumption - check the invoice).
A29: JLCCNC + JLC3DP, one merged order (aluminium, PMMA and POM-C parts, resin mould) | B29: 2 | C29: 0.06 | D29: 1 | E29: Aluminium articles HS 7616 99 90 (6 %) and plastic articles HS 3926 90 (PMMA, POM-C, the resin mould, 6.5 %): two customs lines; 6 % is used for the whole parcel (assumption - check the invoice).
A30: EU shop: casting supplies (urethane rubber, pigment, release) | B30: 0 | C30: 0 | D30: 1 | E30: Inside the EU: no customs, no duty. 21 % VAT is added on goods and shipping; that is conservative if the shop's price already includes VAT (kaupo.de does not say).
A31: Electronics distributor: TIR optics (from a warehouse inside the EU) | B31: 0 | C31: 0 | D31: 1 | E31: An EU site of the distributor (the same RS stock number, or Distrelec): no customs, no duty; 21 % VAT on goods and shipping. ASSUMPTION: the RS UK price is used; a UK delivery would go through customs.
A32: EU battery shop: the 14500 cell and the nickel strip (nkon.nl) | B32: 0 | C32: 0 | D32: 1 | E32: Inside the EU: no customs, no duty; 21 % VAT on goods and shipping (nkon.nl shows its prices with and without VAT; the workbook uses the price without VAT, and the VAT of the Netherlands and of Lithuania is 21 % alike).
A33: AliExpress / web shops | B33: 1 | C33: 0 | D33: =$B$13 -> 8 | E33: Mixed small hardware; each parcel is far below EUR 150, so the flat EUR 3 per line applies.
A35: 4. Landed cost per parcel - scenario A (one light)
A36: Parcel | B36: Goods (USD) | C36: Parcels | D36: Goods per parcel (EUR) | E36: Route | F36: Shipping (USD) | G36: Duty (USD) | H36: VAT (USD) | I36: Carrier fee (USD) | J36: Landed cost (USD) | K36: How
A37: JLCPCB (panel: both PCBs, assembled) | B37: ='JLCPCB order'!$E$81 -> 236.89618 | C37: =$D$28 -> 1 | D37: =B37/C37/Summary!$B$6 -> 211.74131 | E37: =IF(D37>$B$6,"formal","IOSS") -> formal | F37: =$F$20 -> 21.5 | G37: =IF(E37="formal",$C$28*(B37+F37),$B$28*C37*$B$7*Summary!$B$6) -> 0 | H37: =$B$5*(B37+F37+IF(E37="formal",G37,0)) -> 54.263197 | I37: =IF(E37="formal",C37*MAX($B$8*Summary!$B$6,$B$9*(G37+H37)/C37),0) -> 16.782 | J37: =B37+F37+G37+H37+I37 -> 329.44137 | K37: Route = IOSS if goods per parcel <= EUR 150, otherwise formal clearance. IOSS: VAT on goods + shipping, flat duty per line. Formal: duty = rate x (goods + shipping), VAT on goods + shipping + duty, carrier fee = max(minimum, % of VAT + duty).
A38: JLCCNC + JLC3DP, one merged order (aluminium, PMMA and POM-C parts, resin mould) | B38: =Housing!$B$127 -> 132.90562 | C38: =$D$29 -> 1 | D38: =B38/C38/Summary!$B$6 -> 118.79301 | E38: =IF(D38>$B$6,"formal","IOSS") -> IOSS | F38: =$F$21 -> 22 | G38: =IF(E38="formal",$C$29*(B38+F38),$B$29*C38*$B$7*Summary!$B$6) -> 6.7128 | H38: =$B$5*(B38+F38+IF(E38="formal",G38,0)) -> 32.530179 | I38: =IF(E38="formal",C38*MAX($B$8*Summary!$B$6,$B$9*(G38+H38)/C38),0) -> 0 | J38: =B38+F38+G38+H38+I38 -> 194.14859 | K38: Same rules for the merged JLCCNC + JLC3DP parcel (aluminium and plastic parts, the resin mould: two customs lines).
A39: EU shop: casting supplies (urethane rubber, pigment, release) | B39: ='Bought parts'!$L$34 -> 61.95 | C39: =$D$30 -> 1 | D39: =B39/C39/Summary!$B$6 -> 55.371827 | E39: EU | F39: =$F$22 -> 18 | G39: =IF(E39="formal",$C$30*(B39+F39),$B$30*C39*$B$7*Summary!$B$6) -> 0 | H39: =$B$5*(B39+F39+IF(E39="formal",G39,0)) -> 16.7895 | I39: =IF(E39="formal",C39*MAX($B$8*Summary!$B$6,$B$9*(G39+H39)/C39),0) -> 0 | J39: =B39+F39+G39+H39+I39 -> 96.7395 | K39: Inside the EU: no customs, no duty, no carrier fee; 21 % VAT on goods + shipping (conservative if the shop's price already includes VAT).
A40: Electronics distributor: TIR optics (from a warehouse inside the EU) | B40: ='Bought parts'!$L$35 -> 17.37 | C40: =$D$31 -> 1 | D40: =B40/C40/Summary!$B$6 -> 15.525563 | E40: EU | F40: =$F$23 -> 20 | G40: =IF(E40="formal",$C$31*(B40+F40),$B$31*C40*$B$7*Summary!$B$6) -> 0 | H40: =$B$5*(B40+F40+IF(E40="formal",G40,0)) -> 7.8477 | I40: =IF(E40="formal",C40*MAX($B$8*Summary!$B$6,$B$9*(G40+H40)/C40),0) -> 0 | J40: =B40+F40+G40+H40+I40 -> 45.2177 | K40: Inside the EU (an EU site of the distributor): no customs; 21 % VAT on goods + shipping.
A41: EU battery shop: the 14500 cell and the nickel strip (nkon.nl) | B41: ='Bought parts'!$L$36 -> 9.02 | C41: =$D$32 -> 1 | D41: =B41/C41/Summary!$B$6 -> 8.0622095 | E41: EU | F41: =$F$24 -> 13.43 | G41: =IF(E41="formal",$C$32*(B41+F41),$B$32*C41*$B$7*Summary!$B$6) -> 0 | H41: =$B$5*(B41+F41+IF(E41="formal",G41,0)) -> 4.7145 | I41: =IF(E41="formal",C41*MAX($B$8*Summary!$B$6,$B$9*(G41+H41)/C41),0) -> 0 | J41: =B41+F41+G41+H41+I41 -> 27.1645 | K41: Inside the EU (nkon.nl ships from the Netherlands): no customs; 21 % VAT on goods + shipping.
A42: AliExpress / web shops | B42: ='Bought parts'!$L$31+'Bought parts'!$L$32-'Bought parts'!$L$34-'Bought parts'!$L$35-'Bought parts'!$L$36 -> 92.98 | C42: =$D$33 -> 8 | D42: =B42/C42/Summary!$B$6 -> 10.388363 | E42: =IF(D42>$B$6,"formal","IOSS") -> IOSS | F42: =$B$12*C42 -> 16 | G42: =IF(E42="formal",$C$33*(B42+F42),$B$33*C42*$B$7*Summary!$B$6) -> 26.8512 | H42: =$B$5*(B42+F42+IF(E42="formal",G42,0)) -> 22.8858 | I42: =IF(E42="formal",C42*MAX($B$8*Summary!$B$6,$B$9*(G42+H42)/C42),0) -> 0 | J42: =B42+F42+G42+H42+I42 -> 158.717 | K42: Goods = bought parts + consumables without the casting supplies, the optics, the cell and the nickel strip; shipping and flat duty are paid for every parcel.
A43: All parcels | B43: =SUM(B37:B42) -> 551.12179 | F43: =SUM(F37:F42) -> 110.93 | G43: =SUM(G37:G42) -> 33.564 | H43: =SUM(H37:H42) -> 139.03088 | I43: =SUM(I37:I42) -> 16.782 | J43: =SUM(J37:J42) -> 851.42867
A44: Card / currency fee on the two JLC payments (JLCPCB, JLCCNC + JLC3DP) | J44: =$B$10*(J37+J38) -> 7.8538495
A45: Shipping + VAT + duty + carrier fees + card fee (to the Summary) | J45: =F43+G43+H43+I43+J44 -> 308.16073
A47: 5. Landed cost per parcel - scenario B (the lights of cell 'Scenario B' on sheet 'Summary', five by default)
A48: Parcel | B48: Goods (USD) | C48: Parcels | D48: Goods per parcel (EUR) | E48: Route | F48: Shipping (USD) | G48: Duty (USD) | H48: VAT (USD) | I48: Carrier fee (USD) | J48: Landed cost (USD) | K48: How
A49: JLCPCB (panel: both PCBs, assembled) | B49: ='JLCPCB order'!$G$81 -> 282.06529 | C49: =$D$28 -> 1 | D49: =B49/C49/Summary!$B$6 -> 252.11413 | E49: =IF(D49>$B$6,"formal","IOSS") -> formal | F49: =$G$20 -> 21.5 | G49: =IF(E49="formal",$C$28*(B49+F49),$B$28*C49*$B$7*Summary!$B$6) -> 0 | H49: =$B$5*(B49+F49+IF(E49="formal",G49,0)) -> 63.748712 | I49: =IF(E49="formal",C49*MAX($B$8*Summary!$B$6,$B$9*(G49+H49)/C49),0) -> 16.782 | J49: =B49+F49+G49+H49+I49 -> 384.09601 | K49: Route = IOSS if goods per parcel <= EUR 150, otherwise formal clearance. IOSS: VAT on goods + shipping, flat duty per line. Formal: duty = rate x (goods + shipping), VAT on goods + shipping + duty, carrier fee = max(minimum, % of VAT + duty).
A50: JLCCNC + JLC3DP, one merged order (aluminium, PMMA and POM-C parts, resin mould) | B50: =Housing!$C$127 -> 432.50404 | C50: =$D$29 -> 1 | D50: =B50/C50/Summary!$B$6 -> 386.57851 | E50: =IF(D50>$B$6,"formal","IOSS") -> formal | F50: =$G$21 -> 25 | G50: =IF(E50="formal",$C$29*(B50+F50),$B$29*C50*$B$7*Summary!$B$6) -> 27.450242 | H50: =$B$5*(B50+F50+IF(E50="formal",G50,0)) -> 101.8404 | I50: =IF(E50="formal",C50*MAX($B$8*Summary!$B$6,$B$9*(G50+H50)/C50),0) -> 16.782 | J50: =B50+F50+G50+H50+I50 -> 603.57668 | K50: Same rules for the merged JLCCNC + JLC3DP parcel (aluminium and plastic parts, the resin mould: two customs lines).
A51: EU shop: casting supplies (urethane rubber, pigment, release) | B51: ='Bought parts'!$N$34 -> 61.95 | C51: =$D$30 -> 1 | D51: =B51/C51/Summary!$B$6 -> 55.371827 | E51: EU | F51: =$G$22 -> 18 | G51: =IF(E51="formal",$C$30*(B51+F51),$B$30*C51*$B$7*Summary!$B$6) -> 0 | H51: =$B$5*(B51+F51+IF(E51="formal",G51,0)) -> 16.7895 | I51: =IF(E51="formal",C51*MAX($B$8*Summary!$B$6,$B$9*(G51+H51)/C51),0) -> 0 | J51: =B51+F51+G51+H51+I51 -> 96.7395 | K51: Inside the EU: no customs, no duty, no carrier fee; 21 % VAT on goods + shipping (conservative if the shop's price already includes VAT).
A52: Electronics distributor: TIR optics (from a warehouse inside the EU) | B52: ='Bought parts'!$N$35 -> 34.74 | C52: =$D$31 -> 1 | D52: =B52/C52/Summary!$B$6 -> 31.051126 | E52: EU | F52: =$G$23 -> 20 | G52: =IF(E52="formal",$C$31*(B52+F52),$B$31*C52*$B$7*Summary!$B$6) -> 0 | H52: =$B$5*(B52+F52+IF(E52="formal",G52,0)) -> 11.4954 | I52: =IF(E52="formal",C52*MAX($B$8*Summary!$B$6,$B$9*(G52+H52)/C52),0) -> 0 | J52: =B52+F52+G52+H52+I52 -> 66.2354 | K52: Inside the EU (an EU site of the distributor): no customs; 21 % VAT on goods + shipping.
A53: EU battery shop: the 14500 cell and the nickel strip (nkon.nl) | B53: ='Bought parts'!$N$36 -> 22.9 | C53: =$D$32 -> 1 | D53: =B53/C53/Summary!$B$6 -> 20.468359 | E53: EU | F53: =$G$24 -> 13.43 | G53: =IF(E53="formal",$C$32*(B53+F53),$B$32*C53*$B$7*Summary!$B$6) -> 0 | H53: =$B$5*(B53+F53+IF(E53="formal",G53,0)) -> 7.6293 | I53: =IF(E53="formal",C53*MAX($B$8*Summary!$B$6,$B$9*(G53+H53)/C53),0) -> 0 | J53: =B53+F53+G53+H53+I53 -> 43.9593 | K53: Inside the EU (nkon.nl ships from the Netherlands): no customs; 21 % VAT on goods + shipping.
A54: AliExpress / web shops | B54: ='Bought parts'!$N$31+'Bought parts'!$N$32-'Bought parts'!$N$34-'Bought parts'!$N$35-'Bought parts'!$N$36 -> 198.94 | C54: =$D$33 -> 8 | D54: =B54/C54/Summary!$B$6 -> 22.22694 | E54: =IF(D54>$B$6,"formal","IOSS") -> IOSS | F54: =$B$12*C54 -> 16 | G54: =IF(E54="formal",$C$33*(B54+F54),$B$33*C54*$B$7*Summary!$B$6) -> 26.8512 | H54: =$B$5*(B54+F54+IF(E54="formal",G54,0)) -> 45.1374 | I54: =IF(E54="formal",C54*MAX($B$8*Summary!$B$6,$B$9*(G54+H54)/C54),0) -> 0 | J54: =B54+F54+G54+H54+I54 -> 286.9286 | K54: Goods = bought parts + consumables without the casting supplies, the optics, the cell and the nickel strip; shipping and flat duty are paid for every parcel.
A55: All parcels | B55: =SUM(B49:B54) -> 1033.0993 | F55: =SUM(F49:F54) -> 113.93 | G55: =SUM(G49:G54) -> 54.301442 | H55: =SUM(H49:H54) -> 246.64071 | I55: =SUM(I49:I54) -> 33.564 | J55: =SUM(J49:J54) -> 1481.5355
A56: Card / currency fee on the two JLC payments (JLCPCB, JLCCNC + JLC3DP) | J56: =$B$10*(J49+J50) -> 14.81509
A57: Shipping + VAT + duty + carrier fees + card fee (to the Summary) | J57: =F55+G55+H55+I55+J56 -> 463.25124
A59: 6. Savings and risk reserves (not in the totals)
A60: Saving if the small hardware comes from ONE EU web shop (USD) | B60: =($B$13-$B$14)*($B$12+$B$33*$B$7*Summary!$B$6) -> 26.782 | C60: Every avoided seller parcel saves its shipping and its flat EUR 3 customs duty. Look for an EU shop that sells M1.6 screws and set screws, split rings, PTFE wire, thermal paste, Kapton, foam, silicone sheet or pads, epoxy, stainless shim and cyanoacrylate (electronics and model-making shops).
A61: EUR 150 cliff: JLCPCB parcel A if it is on the IOSS route (USD, landed) | B61: =$B$37+$F$37+$B$28*$B$7*Summary!$B$6+$B$5*($B$37+$F$37) -> 319.37217 | C61: Goods + shipping + flat EUR 3 per customs line + VAT on goods and shipping.
A62: EUR 150 cliff: JLCPCB parcel A if it is on the formal-clearance route (USD, landed) | B62: =$B$37+$F$37+$C$28*($B$37+$F$37)+$B$5*($B$37+$F$37+$C$28*($B$37+$F$37))+MAX($B$8*Summary!$B$6,$B$9*($C$28*($B$37+$F$37)+$B$5*($B$37+$F$37+$C$28*($B$37+$F$37)))) -> 329.44137 | C62: Goods + shipping + tariff + VAT on goods, shipping and tariff + carrier disbursement fee (minimum EUR 15).
A63: EUR 150 cliff: formal route minus IOSS route (USD) | B63: =B62-B61 -> 10.0692 | C63: What the JLCPCB order would save if it were below EUR 150. It is far above the line (the panel and its assembly), so it stays on the formal route; the merged JLCCNC + JLC3DP order of one light is below the line (its route is in section 4).
A64: Risk reserve: second PCB + assembly order after a first-article problem (USD) | B64: =$B$15*$J$37 -> 329.44137 | C64: A new board design almost never works perfectly the first time (wrong footprint, rotation, missing pull-up) - and the key board, the pogo contact and the 1000 lm power stage are new in v0.7. The second order costs the same JLCPCB order again, with shipping and tax. The 3 spare bare panels of the first order can be re-assembled by hand, which saves the panel price but not the assembly.
A65: Risk reserve: second housing order (USD) | B65: =$B$16*$J$38 -> 194.14859 | C65: If the first tray does not fit the real laser / cell / optic, or a kit is refused and has to be re-ordered elsewhere. Reduce the risk by measuring the delivered parts before the order and ordering ONE set first.
A67: 7. The costs people forget (amounts for scenario A and B where they are in the totals)
A68: Cost | B68: A (USD) | C68: B (USD) | D68: What it is and what to do
A69: Shipping of the JLCPCB parcel, the merged JLCCNC + JLC3DP parcel, the EU casting-shop parcel, the optic distributor's parcel and the battery shop's parcel | B69: =$F$37+$F$38+$F$39+$F$40+$F$41 -> 94.93 | C69: =$F$49+$F$50+$F$51+$F$52+$F$53 -> 97.93 | D69: JLCPCB and JLCCNC ship separately (JLCCNC merges only with JLC3DP), two shipping fees; the EU casting shop, the distributor and the battery shop three more (the cell travels as dangerous goods by courier). JLC publishes no rate table; anchors: DHL Express about $21.50, EuroPacket about $6.50, Global Standard Direct Line about $1.50 for a small parcel (https://chiptron.eu/jlcpcb-reduces-shipping-costs-pcb-order-with-shipping-worth-bad-beer/, June 2025), FedEx about $16 to Spain (https://eevblog.com/forum/manufacture/jlcpcb-pcb-assembly-optimal-shipping-for-eu, 2024). Economy takes weeks and may be slow at customs: use express for the first order.
A70: EU VAT 21 % (Lithuania) | B70: =$H$43 -> 139.03088 | C70: =$H$55 -> 246.64071 | D70: VAT is charged on goods + shipping. Up to EUR 150 per parcel JLC collects it at checkout (IOSS, https://jlcpcb.com/help/article/EU-VAT-E-commerce-Rules-%26-Adjustments); above EUR 150 you pay VAT and customs fees to the carrier (or at checkout with DDP).
A71: Customs duty + carrier handling fees | B71: =$G$43+$I$43 -> 50.346 | C71: =$G$55+$I$55 -> 87.865442 | D71: Since 1 July 2026 every low-value parcel pays a flat EUR 3 duty per customs line (https://trade.ec.europa.eu/access-to-markets/en/news/eu-applies-eu3-customs-duty-item-low-value-e-commerce-consignments; JLC FAQ https://jlcpcb.com/help/article/eu-customs-reform-faq); under IOSS JLC collects the VAT but not the EUR 3, which is paid at import unless the channel is DDP. Above EUR 150 the normal tariff and formal clearance apply and the carrier adds a disbursement fee (DHL Germany 2 % min EUR 15, UPS 3 % min EUR 15.70, FedEx 2.5 % min EUR 15; UPS Lithuania 2 % min EUR 12). A unified EU handling fee (about EUR 2 per parcel) is planned from about Nov 2026 and is not included.
A72: THE EUR 150 CLIFF: JLCPCB order | B72: ='JLCPCB order'!$E$83 -> -61.74131 | C72: ='JLCPCB order'!$G$83 -> -102.11413 | D72: EUR left until the JLCPCB order passes the IOSS limit (negative = already above: formal clearance, a carrier fee of about EUR 15). The panel and its assembly cost far more than EUR 150, so this parcel cannot stay below the line.
A73: THE EUR 150 CLIFF: JLCCNC + JLC3DP order | B73: =Housing!$B$128 -> 31.206994 | C73: =Housing!$C$128 -> -236.57851 | D73: EUR left until the merged housing order passes the IOSS limit. For one light it stays below the line (VAT and EUR 3 per customs line only: no 6 % duty, no carrier fee); a real quote that is much higher can push it over. For two or more lights it is above the line; splitting it into two parcels below the line only pays with economy shipping (docs/bom_notes.md, section 2).
A74: AliExpress / web shops: shipping + flat duty | B74: =$F$42+$G$42 -> 42.8512 | C74: =$F$54+$G$54 -> 42.8512 | D74: Each seller parcel pays its own shipping and its own EUR 3 duty. See the saving in section 6.
A75: Card / currency conversion fee | B75: =$J$44 -> 7.8538495 | C75: =$J$56 -> 14.81509 | D75: JLC charges in USD. Your bank may add a conversion fee; use a card without one if you can.
A76: Spares already inside the totals: pieces JLC buys for placement loss | B76: ='Panel BOM'!$T$48 -> 11.3001 | C76: ='Panel BOM'!$W$48 -> 10.8501 | D76: JLC buys a few more resistors, capacitors, chips and pogo pins than the panels need (lost by the placement machine). You pay for them but do not receive them.
A77: Spares already inside the totals: bought parts and left-over packs | B77: ='Bought parts'!$L$33 -> 146.858 | C77: ='Bought parts'!$N$33 -> 146.22 | D77: The spare cell, the rest of the nickel strip, the second LED board, the other optics of the pack of 5, extra screws (you WILL lose an M1.6 screw), left-over pad and foam sheets, most of the rubber (one unit casts many keys). (The spare main key comes in the PMMA kit and the spare lid insert in the POM-C kit, both inside the housing total; two of the four keys of each pour are spares.)
A78: First-article risk: second PCB + assembly order (NOT in the totals) | B78: =$B$64 -> 329.44137 | D78: Budget for it. If a fix is needed, the same fees (set-up, stencil, feeder loading, panel fee) are paid again.
A79: First-article risk: second housing order (NOT in the totals) | B79: =$B$65 -> 194.14859 | D79: See section 6.
A80: USB-C DATA cable (in Tools, NOT in the per-light cost) | B80: =Tools!$I$16 -> 4 | D80: Needed to charge the light and update its firmware. A charge-only cable does not work for data. You only pay if you do not have one.
A81: Price changes between now and your order | D81: LCSC prices and stock change weekly; JLC re-prices in the cart. Re-open the LCSC links in sheet 'Panel BOM' and watch for red lines in the JLC BOM upload.
A82: Your time and mistakes | D82: Not counted: casting and trimming the side keys, soldering the wires, assembling the housing, testing, waiting 1-5 weeks for parcels.

Sheet Tools
A1: Tools you need once (not part of the per-light cost)
A2: JLCPCB solders all SMD parts, so you do NOT need a hot-air station, solder paste or a reflow oven. You solder a few wires by hand (cell strips, LED, laser), weld two nickel strips onto the cell (or buy it with welded tabs), screw the housing together, cut two small silicone pads and the foam for the cell and - new in v0.7 - cast the two rubber side keys and cut their stainless stiffeners (vice, tin snips, needle files; the default urethane is mixed 1:1 by volume, so the scale is only needed for PMC-780 DRY). Prices are typical 2026 web-shop prices (ESTIMATES, USD, excl. VAT and shipping). 'Needed' = 1 counts the tool in the Summary, 0 = optional, not counted. If you already own a tool, set its 'Needed' to 0.
A4: # | B4: Tool | C4: Why you need it | D4: Spec that matters | E4: Search term | F4: Price each (USD) | G4: Qty | H4: Needed (1/0) | I4: Cost (USD) | J4: Basis
A5: 1 | B5: Soldering iron with fine tip | C5: Solder the wires to the pads J2, J3, J5 and the two cell wires to the nickel strips (never to the cell itself), and fix small faults. | D5: Temperature controlled (about 300-350 C), conical or chisel tip 0.4-1 mm, e.g. Pinecil / TS101 / Hakko FX-888D class. | E5: pinecil soldering iron | F5: 35 | G5: 1 | H5: 1 | I5: =F5*G5*H5 -> 35 | J5: ESTIMATE (typical price; first priced 2026-10-14)
A6: 2 | B6: Solder wire 0.5 mm with flux core | C6: Hand soldering. | D6: 0.5 mm diameter, Sn63Pb37 or lead-free SAC305, flux core, 50 g reel. | E6: solder wire 0.5mm rosin core | F6: 8 | G6: 1 | H6: 1 | I6: =F6*G6*H6 -> 8 | J6: ESTIMATE (typical price; first priced 2026-10-14)
A7: 3 | B7: Flux (gel syringe or pen) | C7: Makes the solder flow on the small pads. | D7: No-clean flux gel in a syringe (e.g. Amtech NC-559 class) or flux pen. | E7: no clean flux gel syringe | F7: 6 | G7: 1 | H7: 1 | I7: =F7*G7*H7 -> 6 | J7: ESTIMATE (typical price; first priced 2026-10-14)
A8: 4 | B8: Fine tweezers | C8: Hold small parts and wires. | D8: ESD-safe, pointed tips, stainless; 2-3 shapes. | E8: ESD tweezers set precision | F8: 5 | G8: 1 | H8: 1 | I8: =F8*G8*H8 -> 5 | J8: ESTIMATE (typical price; first priced 2026-10-14)
A9: 5 | B9: Precision screwdriver and hex key set | C9: Lid screws and key-board screws (M1.6), the M1.6 laser set screw, the M3 screws of the mould (hold the nuts with pliers). | D9: Phillips PH000/PH00 bits (or the hex bits that match your screws), hex keys 0.7 mm (M1.6 set screw) and 2.5 mm (M3). | E9: precision screwdriver set hex 0.7mm | F9: 8 | G9: 1 | H9: 1 | I9: =F9*G9*H9 -> 8 | J9: ESTIMATE (typical price; first priced 2026-10-14)
A10: 6 | B10: Multimeter | C10: Check battery voltage, shorts and continuity before the first power-up. | D10: Any basic digital multimeter with continuity buzzer, DC voltage and current. | E10: digital multimeter | F10: 15 | G10: 1 | H10: 1 | I10: =F10*G10*H10 -> 15 | J10: ESTIMATE (typical price; first priced 2026-10-14)
A11: 7 | B11: Laser safety glasses for 520 nm | C11: Eye protection whenever the laser is powered on the bench. | D11: Rated for 520 nm green, OD 4+ (e.g. '190-540 nm OD4+' or 532 nm goggles); CE / EN 207 marked. | E11: laser safety glasses 520nm 532nm OD4 | F11: 14 | G11: 1 | H11: 1 | I11: =F11*G11*H11 -> 14 | J11: ESTIMATE (typical price; first priced 2026-10-14)
A12: 8 | B12: Side cutters (flush) | C12: Trim wires, cut the tabs of the two machining kits, the two pins of the TIR optic and the stubs of the cast keys. | D12: Small flush cutters. | E12: flush cutter mini | F12: 5 | G12: 1 | H12: 1 | I12: =F12*G12*H12 -> 5 | J12: ESTIMATE (typical price; first priced 2026-10-14)
A13: 9 | B13: Hobby knife and cutting mat | C13: Cut the two silicone hold-down pads and the foam strip and pad of the cell to size, and trim the cast keys. | D13: Scalpel or hobby knife with spare blades, small self-healing cutting mat (A5). | E13: hobby knife cutting mat set | F13: 7 | G13: 1 | H13: 1 | I13: =F13*G13*H13 -> 7 | J13: ESTIMATE (typical price; first priced 2026-10-18, added in v0.6)
A14: 10 | B14: Wire stripper (fine) | C14: Strip the 24 AWG PTFE wire and the laser's leads without cutting the strands. | D14: For 20-30 AWG wire. | E14: precision wire stripper 24AWG 28AWG | F14: 7 | G14: 1 | H14: 1 | I14: =F14*G14*H14 -> 7 | J14: ESTIMATE (typical price; first priced 2026-10-14)
A15: 11 | B15: Isopropyl alcohol 99 % and swabs | C15: Clean flux residue, the mould and the glue faces of the side keys and the stiffeners. | D15: 99 % isopropyl alcohol 100-250 ml, lint-free swabs. | E15: isopropyl alcohol 99 percent | F15: 6 | G15: 1 | H15: 1 | I15: =F15*G15*H15 -> 6 | J15: ESTIMATE (typical price; first priced 2026-10-14)
A16: 12 | B16: USB-C data cable | C16: Charge the light and update the firmware over USB. A charge-only cable will NOT work for data. | D16: USB-C to USB-A or USB-C, labelled 'data', 0.5-1 m. | E16: usb c data cable | F16: 4 | G16: 1 | H16: 1 | I16: =F16*G16*H16 -> 4 | J16: ESTIMATE (typical price; first priced 2026-10-14)
... A28: 24 | B28: Small spot welder for nickel strip | C28: Weld the two nickel strips onto the ends of the cell: never solder onto the cell (the heat damages it). Not needed if you buy the cell with welded tabs or have a battery shop weld the strips: then set 'Needed' to 0. | D28: Portable spot welder for 0.1-0.2 mm pure nickel strip (its own battery or capacitors, adjustable pulse). Practise strip on strip first; two or three weld spots per end; wear safety glasses. | E28: portable spot welder 0.2mm nickel strip | F28: 40 | G28: 1 | H28: 1 | I28: =F28*G28*H28 -> 40 | J28: ESTIMATE (typical price; first priced 2026-10-23, added in v0.7)
B29: TOOLS, one-time (needed = 1) | I29: =SUM(I5:I28) -> 204
B30: Optional tools not counted (needed = 0) | I30: =SUMPRODUCT(F5:F28,G5:G28,1-H5:H28) -> 170

Sheet Ordering checklist
A1: Ordering checklist - what to buy, in which order, which file goes where
A2: Follow the steps from top to bottom. Lead times are typical values (the shops show the real ones at the checkout). 'Charge' = what the order costs you in total at that shop (goods + shipping + VAT/duty), from sheet 'Hidden costs'; with DDP/IOSS the taxes are paid at the checkout.
A4: Step | B4: When | C4: Shop | D4: What to order | E4: Files to upload and settings | F4: Typical lead time | G4: Check before you pay | H4: Charge A (USD) | I4: Charge B (USD)
A5: 0 | B5: Today | C5: Your computer | D5: Nothing yet: update the prices. | E5: Open the LCSC links in sheet 'Panel BOM' (column E) and check the stock note column. Read sheet 'Summary' and change the blue cells you know better. | F5: 1 hour | G5: Is every line still in stock? Low retail stock at LCSC (read on the dates in sheet 'Panel BOM'): C15850, C15195, C1525, C22100007, C11702; stock NOT read (pages not readable): C238645, C25104, C115357 (see the stock notes).
A6: 1 | B6: Day 1 | C6: AliExpress / EU web shop | D6: Bought parts: LED board SST-20 Gen 2 10 mm (+1 spare, for example Kaidomain), laser module Class 2 (+ read its measured power), lid screws M1.6 x 6 and key-board screws M1.6 x 2.5, set screws, split rings, 24 AWG wire, thermal paste, Kapton tape, 0.5 mm foam sheet, silicone pad sheets (thermal gap pad 1.5 mm, rubber sheet 1.0 mm Shore A 70), silicone adhesive, epoxy, 0.3 mm stainless shim, cyanoacrylate, cups and syringes, polishes; once per builder the four M3 x 16 bolts, washers and nuts of the resin mould. | E6: Sheet 'Bought parts': search term, spec and link example for every item. Buy the small hardware from ONE web shop to save parcels. | F6: 1-5 weeks (AliExpress), 3-7 days (EU shop) | G6: Size of the LED board (10 mm, SST-20 Gen 2) in the listing; laser power stated; screw lengths (6 mm for the lid, 2.5 mm, not longer, for the key board); shipping to Lithuania included; VAT shown. | H6: ='Hidden costs'!$J$42 -> 158.717 | I6: ='Hidden costs'!$J$54 -> 286.9286
A7: 1b | B7: Day 1 | C7: Electronics distributor (RS / Distrelec) | D7: TIR optics: LEDiL LISA3-RS-PIN (FP16558), one pack of 5 (RS stock no. 186-2699) - enough for 4 lights with a spare. | E7: Sheet 'Bought parts', row 'TIR optic'. Not the clip version (7.9 mm high). | F7: 3-7 days | G7: The part number ends in -RS-PIN; the free-shipping limit of the shop (combine orders). | H7: ='Hidden costs'!$J$40 -> 45.2177 | I7: ='Hidden costs'!$J$52 -> 66.2354
A8: 1c | B8: Day 1 | C8: EU casting shop (for example kaupo.de) | D8: Casting supplies, once per builder: urethane rubber Smooth-On ECON 80 (0.86 kg trial unit), black pigment SO-Strong, Universal Mold Release. | E8: Sheet 'Bought parts' (rows with shop 'EU casting shop'). Read the technical bulletin and the safety data sheet of the rubber before you buy. | F8: 3-7 days | G8: Shore 80A, mix ratio 1A:1B by volume; the shop may sell to registered customers only. | H8: ='Hidden costs'!$J$39 -> 96.7395 | I8: ='Hidden costs'!$J$51 -> 96.7395
A9: 1d | B9: Day 1 | C9: EU battery shop (for example nkon.nl) | D9: One Vapcell INR14500 F15 per light + 1 spare, and 1 m of pure nickel strip 0.2 x 5 mm (or the cell with welded tabs, if the shop offers it). | E9: Sheet 'Bought parts', rows 'Li-ion cell' and 'Nickel strip'. Without welded tabs you need a spot welder (sheet 'Tools'). | F9: 3-7 days | G9: Flat top, no protection board, 14.0 x 49.0 mm (any flat-top 14500 up to 14.5 x 50.4 mm fits); pure nickel, not nickel-plated steel. | H9: ='Hidden costs'!$J$41 -> 27.1645 | I9: ='Hidden costs'!$J$53 -> 43.9593
A10: 2 | B10: Day 1 | C10: Your computer | D10: Check the order files of the package (nothing has to be generated). | E10: Ready to upload: order_files/1_JLCPCB/ (FlashKa_panel_gerbers.zip, BOM_JLCPCB.csv, CPL_JLCPCB.csv); order_files/2_JLCCNC/ (FlashKa_tray.step, FlashKa_tray.pdf, FlashKa_lid.step, FlashKa_lid.pdf, FlashKa_pmma_kit.step, FlashKa_pmma_kit.pdf, FlashKa_pom_kit.step, FlashKa_pom_kit.pdf, FlashKa_key_main.step, FlashKa_key_main.pdf, FlashKa_rf_window.step, FlashKa_antenna_spacer.step, FlashKa_pom_parts.pdf, FlashKa_laser_sleeve.step); order_files/3_rubber_keys/ (FlashKa_key_side.step, FlashKa_key_side.pdf, FlashKa_key_stiffener.step, FlashKa_key_side_with_plate.step, FlashKa_key_mould_resin_cavity.stl, FlashKa_key_mould_resin_lid.stl, FlashKa_key_mould_resin.step, FlashKa_key_mould.step, FlashKa_key_mould.pdf, FlashKa_key_mould_cavity.step, FlashKa_key_mould_lid.step). Only after a change of the design: re-run tools/kicad/build_all.py (re-routes both boards, takes long; writes production/) or the housing build, and replace the files in order_files/. | F10: 10 minutes | G10: order_files/1_JLCPCB/BOM_JLCPCB.csv must have 35 lines and 79 parts; its LCSC numbers are exactly column E of sheet 'Panel BOM'.
A11: 3 | B11: Day 1-2 | C11: jlcpcb.com | D11: 5 bare panels + PCB assembly (Standard PCBA, both sides) of 2 panels (one light) or 5 panels. Each panel holds the key board and the main PCB. | E11: Gerber: order_files/1_JLCPCB/FlashKa_panel_gerbers.zip. Settings: 4 layers, 0.8 mm, ENIG, BLACK solder mask, white silkscreen, Panel by Customer 1 x 1, Different design 2, qty 5, PCB Assembly ON, both sides, qty 2 or 5, confirm parts placement. Then upload order_files/1_JLCPCB/BOM_JLCPCB.csv and order_files/1_JLCPCB/CPL_JLCPCB.csv (see sheet 'JLCPCB order', section 1). | F11: PCB 3-5 days + assembly 3-5 days + express shipping 3-5 days = about 2 weeks (the cart shows the exact build time) | G11: All BOM lines matched; stock of the pogo pins C22100007 and of the power-stage parts C139643, C351410, C238645; part rotation and pin 1 in the placement preview (main PCB: J1, Q1, Q2, Q3, Q4, Q5, U1, U2, U3, U4, U5, U6; key board: LED3, LED4, P1, P2, P3, P4, P5, P6, SW1, SW2, SW3); shipping DDP. The order is far above EUR 150: formal clearance with a carrier fee. | H11: ='Hidden costs'!$J$37 -> 329.44137 | I11: ='Hidden costs'!$J$49 -> 384.09601
A12: 4 | B12: when the laser, the cell and the optic have arrived | C12: Your desk | D12: Measure the delivered parts with a caliper. | E12: Laser body 6.0 mm x 12 mm; cell 14.0 x 49.0 mm (the bay takes up to 14.5 x 50.4 mm); LED board 10.0 mm; optic 10.0 mm x 6.9 mm. Check the laser power if you have a meter. | F12: 30 minutes | G12: Everything fits the spec of sheet 'Bought parts'; otherwise change the housing BEFORE ordering it.
A13: 5 | B13: after step 4 | C13: jlccnc.com (one merged order with jlc3dp.com) | D13: Tray + lid, aluminium 6061-T6, bead blast + black anodize, NO marking; the PMMA kit (3 clear main keys, ROUNDUP((lights + 1) / 3) kits); the POM-C kit (one per light); once per builder the two resin plates of the casting mould (JLC3DP, SLA). | E13: Files from order_files/2_JLCCNC/: FlashKa_tray.step + FlashKa_tray.pdf, FlashKa_lid.step + FlashKa_lid.pdf, FlashKa_pmma_kit.step + FlashKa_pmma_kit.pdf, FlashKa_pom_kit.step + FlashKa_pom_kit.pdf (each drawing PDF has the SAME name as its STEP file); to JLC3DP from order_files/3_rubber_keys/: FlashKa_key_mould_resin_cavity.stl + FlashKa_key_mould_resin_lid.stl. Put both into ONE merged order (cart: 'All'). Settings: see sheet 'Housing', section 9. Order ONE set first. (Aluminium mould instead: FlashKa_key_mould_cavity.step + FlashKa_key_mould_lid.step + FlashKa_key_mould.pdf to JLCCNC.) | F13: Quote within 24 h, 3 working days + 1 day transfer + shipping 3-6 days = about 10-12 days | G13: Instant quote prices -> type them in sheet 'Housing' (sections 6, 6b and 7); M1.6 threads accepted (two of them blind); anodize tolerance note; the kits accepted with the parts on tabs; PMMA polish option (or polish at home); the texture (or 'texture_on' = 0 and a note to skip it); one light stays below EUR 150. | H13: ='Hidden costs'!$J$38 -> 194.14859 | I13: ='Hidden costs'!$J$50 -> 603.57668
A14: 6 | B14: when the mould and the casting supplies are there | C14: At home | D14: Cast the two rubber side keys (4 per pour: 2 + 2 spares) and glue in the stiffeners. | E14: Steps in order_files/3_rubber_keys/README.txt and in the build guide: sand the cavity floors with 400-grit paper and polish the chevron grooves once, release, mix 5 ml A + 5 ml B with the pigment, pour, close with the four M3 bolts, cure overnight (24 h), demould, trim. Cut the plate 3.6 x 9.4 mm and the doubler 2.0 x 2.0 mm from the 0.3 mm shim and glue them in with cyanoacrylate. | F14: 1 hour + 24 h cure | G14: Key face without bubbles, chevron complete; the first key fits its opening in the tray; the plate lies flat in its recess.
A15: 7 | B15: when everything is there | C15: At home | D15: Inspect, assemble, test. | E15: Check every delivery against this list. Cut the PMMA keys and the POM-C parts off their kits (flush cutters) and file the stubs flat; cut the two silicone pads to size (8.8 x 12.4 mm and 3.7 x 3.0 mm) and stick them on the lid bosses with a drop of silicone adhesive. LED board on thermal paste and the TIR optic (pins cut off) into the head bore, glued with epoxy. Fit the three keys into the floor, screw the key board onto its two bosses (M1.6 x 2.5), put the antenna spacer in, then fit the main PCB (it rests on the six pogo pins). Weld the nickel strips to the cell (or use a cell with welded tabs), solder one 24 AWG wire to each strip and to J2 (BAT+, BAT-), the LED wires to J3 and the laser to J5; tape the strips and joints; check for shorts with the multimeter BEFORE the cell goes in; pick the foam stacks for the cell; wear laser glasses when the laser is on. | F15: 1-2 evenings | G15: Multimeter: no short between BAT+ and BAT- or GND; the cell between 3.0 and 4.2 V (new cells arrive at about 3.6 V); every key clicks and the ring lights; the installer offers 'FlashKa v0.7'.
A16: 8 | B16: after the first light works | C16: - | D16: Order the other lights (scenario B). | E16: The one-time costs (set-ups, stencil, panel fee, anodizing lot, the mould, the casting supplies) are already paid, so every additional light costs much less (see 'Summary', extra cost per additional light). | F16: - | G16: Keep the first light as the reference for the next batch.
C17: Total of the checkout charges (without the card fee) | H17: =SUM(H5:H16) -> 851.42867 | I17: =SUM(I5:I16) -> 1481.5355
A19: File map
A20: JLCPCB | C20: order_files/1_JLCPCB/: FlashKa_panel_gerbers.zip, BOM_JLCPCB.csv, CPL_JLCPCB.csv (the panel files tools/kicad/build_all.py writes to production/; production/ also holds the single-board files FlashKa_main_gerbers.zip and FlashKa_keys_gerbers.zip with their BOM and CPL files, a fall-back only)
A21: JLCCNC | C21: order_files/2_JLCCNC/: FlashKa_tray, FlashKa_lid, FlashKa_pmma_kit, FlashKa_pom_kit (each as .step + .pdf; the PDFs are the drawings from cad/ renamed to the STEP names). Single parts for shops that take small parts: FlashKa_key_main (.step + .pdf), FlashKa_rf_window.step, FlashKa_antenna_spacer.step (drawing FlashKa_pom_parts.pdf); FlashKa_laser_sleeve.step only for a laser module thinner than 6 mm. The mould files are in order_files/3_rubber_keys/.
A22: Rubber keys | C22: order_files/3_rubber_keys/: FlashKa_key_mould_resin_cavity.stl + FlashKa_key_mould_resin_lid.stl (to JLC3DP, once, in the merged JLCCNC order; FlashKa_key_mould_resin.step is the closed resin mould for reference); the aluminium option FlashKa_key_mould_cavity.step + FlashKa_key_mould_lid.step (to JLCCNC) with FlashKa_key_mould.step (closed, reference); FlashKa_key_mould.pdf (drawing of both moulds); FlashKa_key_side.step + FlashKa_key_side.pdf, FlashKa_key_stiffener.step, FlashKa_key_side_with_plate.step and README.txt (casting at home).
A23: Optional | C23: order_files/optional_laser_label/: FlashKa_laser_label_lid_class2.dxf (+ .png preview) - only for a light that is sold or given to other people (laser label on the lid).
A24: Nowhere | C24: Upload only the files of order_files/. cad/ and production/ hold their sources; kicad/* and tools/* are for checking and re-building, not for ordering. The firmware is FlashKa firmware 0.7.0, built for the v0.7 board: choose 'FlashKa v0.7' in the web installer.
