Workbook

Sheet Summary
A1: FlashKa Keychain v0.6 - what it really costs
A2: Complete cost of building the light from scratch: electronics (JLCPCB), aluminium housing and stainless caps (JLCCNC), resin print kit (JLC3DP), bought parts, consumables, shipping, EU VAT and customs for Lithuania. Scenario A = you build ONE light (JLCPCB still sells 5 bare boards and assembles at least 2), scenario B = you build FIVE (change B to 2 to see two lights). Prices that did not change from v0.5 were read on 2026-10-14; the pages of the new parts could not be read on 2026-10-18, so those prices are ESTIMATES. Blue on amber cells are ESTIMATES because the shop shows its price only after you upload the files (or the page could not be read) - replace them with the real quote.
A3: Colour code: blue = typed-in number, blue on amber = ESTIMATE, black = formula, green = taken from another sheet. USD is the main currency, EUR = USD / rate.
A5: Inputs
A6: Exchange rate (USD per EUR) | B6: 1.1188 | C6: USD per EUR | D6: ECB euro reference rate of 13 Oct 2026. Change it to the rate of your bank/card. Source: https://www.ecb.europa.eu/stats/policy_and_exchange_rates/euro_reference_exchange_rates/html/eurofxref-graph-usd.en.html (read 2026-10-13)
A7: Scenario A: lights you build | B7: 1 | C7: lights | D7: Scenario A: you build one light.
A8: Scenario B: lights you build | B8: 5 | C8: lights | D8: Scenario B: you build five lights (all JLC minimums are used up).
A9: Price check date (v0.6) | B9: 2026-10-18 | C9: v0.6 check. Prices and fees that did not change keep the date they were read, 2026-10-14 (v0.5 check; LCSC and JLC pages). The JLCPCB and LCSC pages of the new parts (C115357, C25104) could not be read on this date: those lines are ESTIMATES. Re-check before ordering.
A11: Total cost
A12: Cost group | B12: A: total (USD) | C12: A: total (EUR) | D12: A: per light (USD) | E12: A: per light (EUR) | F12: B: total (USD) | G12: B: total (EUR) | H12: B: per light (USD) | I12: B: per light (EUR) | J12: Share of B | K12: Basis
A13: Lights built | B13: =$B$7 -> 1 | F13: =$B$8 -> 5
A14: 1. PCB + assembly (JLCPCB) | B14: ='JLCPCB order'!$E$77 -> 174.32774 | C14: =B14/$B$6 -> 155.81671 | D14: =B14/$B$7 -> 174.32774 | E14: =D14/$B$6 -> 155.81671 | F14: ='JLCPCB order'!$G$77 -> 194.68669 | G14: =F14/$B$6 -> 174.01385 | H14: =F14/$B$8 -> 38.937338 | I14: =H14/$B$6 -> 34.802769 | J14: =F14/F30 -> 0.16291952 | K14: Fees: JLCPCB price page, read 2026-10-14 (v0.5 check, not refreshed). Parts: LCSC prices read 2026-10-14; the two new lines are ESTIMATES (pages not readable on 2026-10-18). Bare PCB: ESTIMATE.
A15: of which bare PCBs (4 layers, 0.8 mm, ENIG) | B15: ='JLCPCB order'!$E$48 -> 25 | C15: =B15/$B$6 -> 22.34537 | D15: =B15/$B$7 -> 25 | E15: =D15/$B$6 -> 22.34537 | F15: ='JLCPCB order'!$G$48 -> 25 | G15: =F15/$B$6 -> 22.34537 | H15: =F15/$B$8 -> 5 | I15: =H15/$B$6 -> 4.469074 | K15: ESTIMATE - the price appears only after the Gerber upload.
A16: of which assembly fees (set-up, stencil, joints, feeder, X-ray, ...) | B16: ='JLCPCB order'!$E$69 -> 132.01264 | C16: =B16/$B$6 -> 117.99485 | D16: =B16/$B$7 -> 132.01264 | E16: =D16/$B$6 -> 117.99485 | F16: ='JLCPCB order'!$G$69 -> 136.96659 | G16: =F16/$B$6 -> 122.42277 | H16: =F16/$B$8 -> 27.393318 | I16: =H16/$B$6 -> 24.484553 | K16: JLCPCB fee page, sheet 'JLCPCB order'.
A17: of which components (34 lines, 68 parts per board, incl. spares for placement loss) | B17: ='Main PCB BOM'!$T$43 -> 17.3151 | C17: =B17/$B$6 -> 15.476493 | D17: =B17/$B$7 -> 17.3151 | E17: =D17/$B$6 -> 15.476493 | F17: ='Main PCB BOM'!$W$43 -> 32.7201 | G17: =F17/$B$6 -> 29.24571 | H17: =F17/$B$8 -> 6.54402 | I17: =H17/$B$6 -> 5.8491419 | K17: LCSC price tiers, sheet 'Main PCB BOM'.
A18: 2. Housing (aluminium tray + lid, stainless caps, resin print kit) | B18: =Housing!$E$118 -> 122.55751 | C18: =B18/$B$6 -> 109.54372 | D18: =B18/$B$7 -> 122.55751 | E18: =D18/$B$6 -> 109.54372 | F18: =Housing!$G$118 -> 382.38755 | G18: =F18/$B$6 -> 341.78365 | H18: =F18/$B$8 -> 76.477509 | I18: =H18/$B$6 -> 68.35673 | J18: =F18/F30 -> 0.31999308 | K18: ESTIMATE - replace by the JLCCNC / JLC3DP instant quotes.
A19: of which aluminium tray + lid (JLCCNC, bead blast + black anodize, laser marking) | B19: =Housing!$B$88 -> 93.357509 | C19: =B19/$B$6 -> 83.444324 | D19: =B19/$B$7 -> 93.357509 | E19: =D19/$B$6 -> 83.444324 | F19: =Housing!$C$88 -> 302.78755 | G19: =F19/$B$6 -> 270.63599 | H19: =F19/$B$8 -> 60.557509 | I19: =H19/$B$6 -> 54.127198 | K19: ESTIMATE from volume, box, finish and marking, sheet 'Housing'.
A20: of which stainless caps (JLCCNC, SUS304: main x1 + slide x2 per light, +1 spare of each) | B20: =Housing!$C$100 -> 28 | C20: =B20/$B$6 -> 25.026814 | D20: =B20/$B$7 -> 28 | E20: =D20/$B$6 -> 25.026814 | F20: =Housing!$E$100 -> 76 | G20: =F20/$B$6 -> 67.929925 | H20: =F20/$B$8 -> 15.2 | I20: =H20/$B$6 -> 13.585985 | K20: ESTIMATE - JLCCNC publishes no per-part price. Fallback: the resin caps in the print kit (0 extra); switch in sheet 'Housing', section 7.
A21: of which resin print kit (JLC3DP, one kit per light + one spare) | B21: =Housing!$E$117 -> 1.2 | C21: =B21/$B$6 -> 1.0725778 | D21: =B21/$B$7 -> 1.2 | E21: =D21/$B$6 -> 1.0725778 | F21: =Housing!$G$117 -> 3.6 | G21: =F21/$B$6 -> 3.2177333 | H21: =F21/$B$8 -> 0.72 | I21: =H21/$B$6 -> 0.64354666 | K21: ESTIMATE, sheet 'Housing'.
A22: 3. Bought parts (cells, LED board, laser, window, screws, split ring) | B22: ='Bought parts'!$L$21 -> 56.75 | C22: =B22/$B$6 -> 50.72399 | D22: =B22/$B$7 -> 56.75 | E22: =D22/$B$6 -> 50.72399 | F22: ='Bought parts'!$N$21 -> 211.3 | G22: =F22/$B$6 -> 188.86307 | H22: =F22/$B$8 -> 42.26 | I22: =H22/$B$6 -> 37.772614 | J22: =F22/F30 -> 0.17682202 | K22: Typical AliExpress prices (ESTIMATES), sheet 'Bought parts'.
A23: 4. Consumables (wire, thermal tape, Kapton, foam tape, silicone pads and adhesive, epoxy) | B23: ='Bought parts'!$L$22 -> 27.79 | C23: =B23/$B$6 -> 24.839113 | D23: =B23/$B$7 -> 27.79 | E23: =D23/$B$6 -> 24.839113 | F23: ='Bought parts'!$N$22 -> 27.79 | G23: =F23/$B$6 -> 24.839113 | H23: =F23/$B$8 -> 5.558 | I23: =H23/$B$6 -> 4.9678227 | J23: =F23/F30 -> 0.023255484 | K23: Typical prices (ESTIMATES), sheet 'Bought parts'.
A24: 5. Shipping, VAT, customs duty, carrier and bank fees | B24: ='Hidden costs'!$J$39 -> 238.78269 | C24: =B24/$B$6 -> 213.4275 | D24: =B24/$B$7 -> 238.78269 | E24: =D24/$B$6 -> 213.4275 | F24: ='Hidden costs'!$J$49 -> 378.82269 | G24: =F24/$B$6 -> 338.59733 | H24: =F24/$B$8 -> 75.764539 | I24: =H24/$B$6 -> 67.719466 | J24: =F24/F30 -> 0.31700991 | K24: Computed from EU rules and shipping ESTIMATES, sheet 'Hidden costs'.
A25: of which shipping (3 JLC parcels + AliExpress parcels) | B25: ='Hidden costs'!$F$37 -> 81 | C25: =B25/$B$6 -> 72.398999 | D25: =B25/$B$7 -> 81 | E25: =D25/$B$6 -> 72.398999 | F25: ='Hidden costs'!$F$47 -> 84 | G25: =F25/$B$6 -> 75.080443 | H25: =F25/$B$8 -> 16.8 | I25: =H25/$B$6 -> 15.016089 | K25: Shipping per parcel are ESTIMATES (JLC shows them in the cart).
A26: of which VAT 21 % | B26: ='Hidden costs'!$H$37 -> 97.109302 | C26: =B26/$B$6 -> 86.797731 | D26: =B26/$B$7 -> 97.109302 | E26: =D26/$B$6 -> 86.797731 | F26: ='Hidden costs'!$H$47 -> 194.12221 | G26: =F26/$B$6 -> 173.50931 | H26: =F26/$B$8 -> 38.824443 | I26: =H26/$B$6 -> 34.701861 | K26: Lithuania 21 %, collected by JLC at checkout up to EUR 150 per parcel.
A27: of which customs duty and carrier fees | B27: ='Hidden costs'!$G$37+'Hidden costs'!$I$37 -> 53.7024 | C27: =B27/$B$6 -> 48 | D27: =B27/$B$7 -> 53.7024 | E27: =D27/$B$6 -> 48 | F27: ='Hidden costs'!$G$47+'Hidden costs'!$I$47 -> 87.998853 | G27: =F27/$B$6 -> 78.654677 | H27: =F27/$B$8 -> 17.599771 | I27: =H27/$B$6 -> 15.730935 | K27: Flat EUR 3 per customs line up to EUR 150 per parcel; formal clearance + carrier fee above.
A28: of which card / currency conversion fee | B28: ='Hidden costs'!$J$38 -> 6.9709852 | C28: =B28/$B$6 -> 6.2307698 | D28: =B28/$B$7 -> 6.9709852 | E28: =D28/$B$6 -> 6.2307698 | F28: ='Hidden costs'!$J$48 -> 12.701628 | G28: =F28/$B$6 -> 11.352903 | H28: =F28/$B$8 -> 2.5403256 | I28: =H28/$B$6 -> 2.2705806 | K28: ESTIMATE 1.5 % on the USD payments to JLC.
A29: JLCPCB order vs the EUR 150 IOSS line (EUR left; negative = above, formal customs) | B29: ='JLCPCB order'!$E$79 -> -5.8167113 | F29: ='JLCPCB order'!$G$79 -> -24.013847 | G29: Above the line the JLCPCB parcel pays a carrier fee of about EUR 15 (sheet 'Hidden costs', section 6).
A30: TOTAL for the lights (1 + 2 + 3 + 4 + 5) | B30: =B14+B18+B22+B23+B24 -> 620.20793 | C30: =B30/$B$6 -> 554.35103 | D30: =B30/$B$7 -> 620.20793 | E30: =D30/$B$6 -> 554.35103 | F30: =F14+F18+F22+F23+F24 -> 1194.9869 | G30: =F30/$B$6 -> 1068.097 | H30: =F30/$B$8 -> 238.99739 | I30: =H30/$B$6 -> 213.6194 | K30: Per-light columns divide by the number of lights built.
A31: Extra cost of each additional light (scenario B vs A) | B31: =IF($B$8=$B$7,0,(F30-B30)/($B$8-$B$7)) -> 143.69475 | C31: =B31/$B$6 -> 128.43649 | D31: Set-up fees, stencil, feeder loading, the anodizing lot fee, the marking set-up and most shipping are paid once, so the 2nd to 5th light is much cheaper than the first.
A33: What changed from v0.5 (same scenarios and exchange rate; USD)
A34: The v0.5 values are typed in from the v0.5 cost workbook (sheet 'Summary', price check 2026-10-14; the v0.5 package keeps that workbook). Board: 34 BOM lines, 68 placements, 232 solder joints (v0.5: 33, 60, 217) - three push buttons instead of one, a second ring LED, five more resistors, no S1. Housing: new stainless caps and laser marking, a 5.2 mm lid with hold-down bosses, a print kit of seven parts instead of four.
A35: Cost group | B35: v0.5: A | C35: v0.6: A | D35: Change A | E35: v0.5: B | F35: v0.6: B | G35: Change B | H35: What changed
A36: 1. PCB + assembly (JLCPCB) | B36: 169.30974 | C36: =B14 -> 174.32774 | D36: =C36-B36 -> 5.018 | E36: 196.67159 | F36: =F14 -> 194.68669 | G36: =F36-E36 -> -1.9849 | H36: More parts per board (SW1-SW3, LED4, R30-R34; S1 gone): more joints and components, one more unique BOM line (feeder fee) and one more X-ray part per board; the two new price lines are ESTIMATES. With five lights the X-ray price per part falls to the next tier (15 inspected parts instead of 10), so scenario B is slightly cheaper than in v0.5.
A37: 2. Housing | B37: 65.959563 | C37: =B18 -> 122.55751 | D37: =C37-B37 -> 56.597946 | E37: 225.39781 | F37: =F18 -> 382.38755 | G37: =F37-E37 -> 156.98973 | H37: Stainless caps (ESTIMATE) and laser marking (ESTIMATE) are new; the lid is a 5.2 mm part with bosses (bigger block); more set-ups and a higher complexity factor (sheet 'Housing', sections 4 and 5); the print kit has seven parts instead of four, still at the minimum price.
A38: 3. Bought parts | B38: 56.75 | C38: =B22 -> 56.75 | D38: =C38-B38 -> 0 | E38: 211.3 | F38: =F22 -> 211.3 | G38: =F38-E38 -> 0 | H38: Unchanged: cells, LED board, laser, window, screws, ring.
A39: 4. Consumables | B39: 18.29 | C39: =B23 -> 27.79 | D39: =C39-B39 -> 9.5 | E39: 18.29 | F39: =F23 -> 27.79 | G39: =F39-E39 -> 9.5 | H39: New: two silicone hold-down pad sheets and silicone adhesive (ESTIMATES).
A40: 5. Shipping, VAT, customs, fees | B40: 219.32326 | C40: =B24 -> 238.78269 | D40: =C40-B40 -> 19.459424 | E40: 329.89492 | F40: =F24 -> 378.82269 | G40: =F40-E40 -> 48.927769 | H40: Follows from the larger orders: mostly VAT on the dearer housing and JLCPCB order, a second customs line for the stainless caps and a bigger card fee; shipping is unchanged (same parcels). Check the EUR 150 line of the JLCPCB order.
A41: TOTAL for the lights | B41: 529.63256 | C41: =B30 -> 620.20793 | D41: =C41-B41 -> 90.575371 | E41: 981.55433 | F41: =F30 -> 1194.9869 | G41: =F41-E41 -> 213.4326 | H41: Sum of the lines above.
A42: TOTAL per light (A: 1 light, B: 5 lights) | B42: 529.63256 | C42: =D30 -> 620.20793 | D42: =C42-B42 -> 90.575371 | E42: 196.31087 | F42: =H30 -> 238.99739 | G42: =F42-E42 -> 42.68652 | H42: Per-light price in USD; the EUR values are in the table above.
A44: Not in the per-light cost
A45: Tools (one-time purchase, only the tools marked 'needed') | B45: =Tools!$I$23 -> 135 | C45: =B45/$B$6 -> 120.665 | D45: Sheet 'Tools'. If you already own soldering equipment, set 'Needed' to 0 there.
A46: TOTAL including tools | B46: =B30+B45 -> 755.20793 | C46: =B46/$B$6 -> 675.01603 | F46: =F30+B45 -> 1329.9869 | G46: =F46/$B$6 -> 1188.762
A47: Optional tools not counted | B47: =Tools!$I$24 -> 100 | C47: =B47/$B$6 -> 89.38148
A48: Risk reserve: second PCB + assembly order (not in any total) | B48: ='Hidden costs'!$B$56 -> 253.73356 | C48: =B48/$B$6 -> 226.79081 | D48: A new board often needs a second round. Landed cost of a second JLCPCB order like scenario A.
A49: Risk reserve: second housing order (not in any total) | B49: ='Hidden costs'!$B$57 -> 180.17539 | C49: =B49/$B$6 -> 161.04343 | D49: If the first tray does not fit the delivered laser / cells.
A51: How reliable is each part of the total?
A52: Item | B52: Status | E52: Where to replace it with a real number
A53: JLCPCB assembly fees | B53: READ from the JLCPCB price page (last updated Sep 09, 2026) | E53: Sheet 'JLCPCB order' section 5; the cart shows the final fee list.
A54: Components at LCSC / JLC | B54: READ from the LCSC product pages on 2026-10-14 (v0.5 check) for 32 lines; ESTIMATE for the 2 new lines C25104 and C115357 (pages not readable on 2026-10-18) | E54: Sheet 'Main PCB BOM' (amber cells); the JLC cart shows the real component price after the BOM upload.
A55: Bare PCB price | B55: ESTIMATE (shown only after the Gerber upload) | E55: Sheet 'JLCPCB order' section 4: type the price from the cart.
A56: Aluminium tray + lid | B56: ESTIMATE from volume, box, finish and laser marking | E56: Sheet 'Housing' section 6: type the JLCCNC instant quote.
A57: Stainless caps | B57: ESTIMATE (JLCCNC publishes no per-part price; may be refused by size) | E57: Sheet 'Housing' section 7: type the JLCCNC instant quote, or switch to the resin caps.
A58: Resin print kit | B58: ESTIMATE | E58: Sheet 'Housing' section 8: type the JLC3DP instant quote.
A59: Bought parts and consumables | B59: ESTIMATES from AliExpress search snippets (2026-10-14) and typical prices; the new pads and adhesive are typical prices | E59: Sheet 'Bought parts': change the blue prices.
A60: Shipping | B60: ESTIMATES (JLC publishes no rate table) | E60: Sheet 'Hidden costs' section 2: type the 'Shipping Estimate' of each cart.
A61: VAT and customs | B61: COMPUTED from the EU rules; duty rates of the formal route are assumptions | E61: Sheet 'Hidden costs'. Watch the EUR 150 line of the JLCPCB order.
A62: Tools | B62: ESTIMATES (typical prices) | E62: Sheet 'Tools'.
A64: Sheets: Summary | JLCPCB order | Main PCB BOM | Housing | Bought parts | Hidden costs | Tools | Ordering checklist. Notes on sources, estimates and what to re-check: docs/bom_notes.md; rebuild: python3 tools/parts_list.py.

Sheet JLCPCB order
A1: JLCPCB order - bare PCB + Standard PCBA (parts on both sides)
A2: What you order at jlcpcb.com in ONE order: 5 bare 4-layer boards and the assembly (soldering of all SMD parts) of 2 or 5 of them. Column E = scenario A (you build 1 light), column G = scenario B (you build 5 lights). Every fee is a blue input with the date it was read and its URL: the fee page says 'Last updated on Sep 09, 2026' and was read on 2026-10-14 (v0.5 price check, not repeated in v0.6; only the X-ray count changed). Prices change - re-check before you pay.
A3: Colour code: blue = typed-in number, blue on amber = ESTIMATE (no public price), black = formula, green = taken from another sheet.
A5: 1. What to select in the JLCPCB cart (https://cart.jlcpcb.com/quote)
A6: Setting | B6: Value | E6: Why / what to watch
A7: Base material / layers | B7: FR-4, 4 layers | E7: The board is designed as a 4-layer stack-up. Do not change the layer count.
A8: Dimensions | B8: 24.0 x 16.5 mm (JLC reads it from the Gerber) | E8: Outline from housing_interface.json pcb_outline, see section 2.
A9: PCB quantity | B9: 5 | E9: JLCPCB minimum. Four spare boards cost almost nothing and cover first-article problems.
A10: Different designs | B10: 1
A11: PCB thickness | B11: 0.8 mm | E11: The housing is built around a 0.8 mm board (pcb_t 0.8).
A12: Surface finish | B12: ENIG (immersion gold) | E12: Flat pads for the fine-pitch module and LED; costs extra, included in the bare-PCB estimate.
A13: Solder mask / silkscreen / copper | B13: Defaults (green mask, white silkscreen, 1 oz outer, 0.5 oz inner) | E13: Default options carry no surcharge.
A14: Order number on the board | B14: Default (JLC prints a code in a free area) | E14: Removing the code costs extra.
A15: PCB Assembly | B15: ON - Standard PCBA, assemble BOTH sides | E15: Economic PCBA cannot do two-sided boards; set-up and stencil are charged per side.
A16: Assembly quantity | B16: 2 (for one light) or 5 | E16: JLCPCB assembles from 2 boards. The extra board is your spare.
A17: Upload | B17: order_files/1_JLCPCB/FlashKa_main_gerbers.zip, then order_files/1_JLCPCB/BOM_JLCPCB.csv and order_files/1_JLCPCB/CPL_JLCPCB.csv | E17: The three files of order_files/1_JLCPCB/ (written by tools/kicad/build_all.py, copied there by the packaging step). Check that all 34 BOM lines are matched (no red rows) and look at the placement preview.
A18: Confirm parts placement | B18: Yes (recommended for the first order) | E18: JLC sends you a photo of the placed parts for your OK; the rotation of U4, U1, U2, U3, U5, Q1, Q2, Q4, Q5, J1, SW1-SW3, LED3 and LED4 is the classic problem. For the new SW1-SW3 (SKRKAEE020) and LED3/LED4 (NH-B1010RGBT) the rotation and pin 1 in the JLC library are NOT verified: look at the placement preview.
A19: Shipping | B19: Your choice (see sheet 'Hidden costs') | E19: Choose DDP / 'taxes paid' so the VAT is collected at checkout and nothing is asked at your door.
A21: 2. Board outline (read from housing_interface.json -> pcb_outline, mm)
A22: Vertex | B22: x (mm) | C22: y (mm) | D22: next x | E22: next y | F22: x*next y - next x*y
A23: vertex 1 | B23: 10.1 | C23: -8.25 | D23: =B24 -> 32.8 | E23: =C24 -> -8.25 | F23: =B23*E23-D23*C23 -> 187.275
A24: vertex 2 | B24: 32.8 | C24: -8.25 | D24: =B25 -> 32.8 | E24: =C25 -> 8.25 | F24: =B24*E24-D24*C24 -> 541.2
A25: vertex 3 | B25: 32.8 | C25: 8.25 | D25: =B26 -> 10.1 | E25: =C26 -> 8.25 | F25: =B25*E25-D25*C25 -> 187.275
A26: vertex 4 | B26: 10.1 | C26: 8.25 | D26: =B27 -> 8.8 | E26: =C27 -> 6.95 | F26: =B26*E26-D26*C26 -> -2.405
A27: vertex 5 | B27: 8.8 | C27: 6.95 | D27: =B28 -> 8.8 | E27: =C28 -> -6.95 | F27: =B27*E27-D27*C27 -> -122.32
A28: vertex 6 | B28: 8.8 | C28: -6.95 | D28: =B23 -> 10.1 | E28: =C23 -> -8.25 | F28: =B28*E28-D28*C28 -> -2.405
A29: Board width (mm) | B29: =MAX(B23:B28)-MIN(B23:B28) -> 24
A30: Board height (mm) | B30: =MAX(C23:C28)-MIN(C23:C28) -> 16.5
A31: Board area (cm2, shoelace formula) | B31: =ABS(SUM(F23:F28))/2/100 -> 3.9431 | C31: Two corners are chamfered 1.3 mm, so the area is a little smaller than width x height. JLCPCB measures the Gerber itself; the area only feeds the tiny packing fee.
A33: 3. Quantities (JLCPCB minimums: 5 bare boards, assembly from 2 boards)
A34: Minimum boards JLCPCB assembles | B34: 2 | C34: boards | D34: JLCPCB assembles from 2 boards; one light therefore still pays for 2 assembled boards (1 spare). Source: https://jlcpcb.com/pcb-assembly (read 2026-10-14)
A35: Minimum bare boards per design | B35: 5 | C35: boards | D35: JLCPCB sells at least 5 bare boards per design. Source: https://cart.jlcpcb.com/quote (read 2026-10-14)
A36: Assembled sides (double-sided) | B36: 2 | C36: sides | D36: Parts are on both sides of the board = double-sided Standard PCBA (Economic PCBA is single-sided only).
A37: X-ray inspected parts per board (optional) | B37: 3 | C37: parts per board | D37: Fee page: 'X-ray inspection is required for components such as BGA, QFN and other leadless packages', charged per component. The COUNT is a v0.6 assumption (the fee page itself was not re-read in v0.6): v0.6 budgets the three parts of this board with hidden joints: U4 (ESP32 module, pads under it), LED3 and LED4 (pads under the package) = 3 per board (v0.5: 2, there was one ring LED). Set 0 if your cart does not ask for it. Source: https://jlcpcb.com/help/article/pcb-assembly-price (read 2026-10-14)
E38: Scenario A | G38: Scenario B
A39: Lights you build | E39: =Summary!$B$7 -> 1 | G39: =Summary!$B$8 -> 5
A40: Boards assembled by JLCPCB = MAX(lights, minimum) | E40: =MAX(E39,$B$34) -> 2 | G40: =MAX(G39,$B$34) -> 5
A41: Bare PCBs ordered (sold in steps of 5) | E41: =CEILING(MAX($B$35,E40),5) -> 5 | G41: =CEILING(MAX($B$35,G40),5) -> 5
A43: 4. Bare PCB fabrication (4 layers, 0.8 mm, ENIG, 24.0 x 16.5 mm) - the price is shown by JLCPCB only AFTER the Gerber upload
A44: Bare PCBs, price for 5 boards (ESTIMATE) | B44: 25 | C44: USD for 5 boards | D44: ESTIMATE. JLCPCB shows the price only after the Gerber upload. Anchors: 100 x 100 mm 4-layer x 5 is about $32.90 (pcbsync, Jul 2026); ENIG adds roughly $12-20 on small runs; 0.8 mm is a normal thickness; 24 x 16.5 mm is far smaller than 100 x 100 mm. Source: https://cart.jlcpcb.com/quote (read 2026-10-14)
A45: low end of the range (information) | B45: 12 | C45: USD for 5 boards | D45: ESTIMATE. Optimistic end of the estimate range (information only). (2026-10-14)
A46: high end of the range (information) | B46: 40 | C46: USD for 5 boards | D46: ESTIMATE. Pessimistic end of the estimate range (information only). (2026-10-14)
A47: Anchors used for the estimate: a 100 x 100 mm 4-layer board costs about $32.90 for 5 (https://pcbsync.com/pcb-prototype-services-compared/, 2026); ENIG adds roughly 12-20 % on small runs (same source) and one forum post quotes $16 for ENIG on a small run (https://forums.ghielectronics.com/t/enig-or-hasl-for-pcb-finish/23438, 2020); thickness 0.8 mm is a normal option; the board here is 16 times smaller than 100 x 100 mm. Real price: upload order_files/1_JLCPCB/FlashKa_main_gerbers.zip at https://cart.jlcpcb.com/quote, choose the options of section 1 and type the price shown for 5 boards into the amber cell above.
A48: Bare PCB cost (price for 5 x boards ordered / 5) | E48: =$B$44*$E$41/5 -> 25 | G48: =$B$44*$G$41/5 -> 25
A50: 5. Standard PCBA fees (JLCPCB 'PCB assembly price' page, last updated Sep 09, 2026, read 2026-10-14) - https://jlcpcb.com/help/article/pcb-assembly-price
A51: Fee | B51: Rate (USD) | C51: Unit | D51: Qty A | E51: Cost A (USD) | F51: Qty B | G51: Cost B (USD) | H51: Date read | I51: Source | J51: Note
A52: Set-up fee (Standard PCBA), per assembled side | B52: 25.56 | C52: USD per side | D52: =$B$36 -> 2 | E52: =B52*D52 -> 51.12 | F52: =$B$36 -> 2 | G52: =B52*F52 -> 51.12 | H52: 2026-10-14 | I52: https://jlcpcb.com/help/article/pcb-assembly-price | J52: Standard PCBA set-up fee: $25.56 single-sided / $51.12 double-sided. Covers the engineering check (no separate engineering fee).
A53: Stencil (Standard PCBA), per assembled side | B53: 8.21 | C53: USD per side | D53: =$B$36 -> 2 | E53: =B53*D53 -> 16.42 | F53: =$B$36 -> 2 | G53: =B53*F53 -> 16.42 | H53: 2026-10-14 | I53: https://jlcpcb.com/help/article/pcb-assembly-price | J53: Standard PCBA stencil: $8.21 single-sided / $16.42 double-sided.
A54: SMT assembly, per solder joint (joints per board x boards) | B54: 0.0016 | C54: USD per joint | D54: ='Main PCB BOM'!$K$43*$E$40 -> 464 | E54: =B54*D54 -> 0.7424 | F54: ='Main PCB BOM'!$K$43*$G$40 -> 1160 | G54: =B54*F54 -> 1.856 | H54: 2026-10-14 | I54: https://jlcpcb.com/help/article/pcb-assembly-price | J54: SMT assembly price per solder joint (1-50,000 joints).
A55: Feeder loading, per unique part (Basic and Extended alike) | B55: 1.53 | C55: USD per unique part | D55: ='Main PCB BOM'!$J$44 -> 34 | E55: =B55*D55 -> 52.02 | F55: ='Main PCB BOM'!$J$44 -> 34 | G55: =B55*F55 -> 52.02 | H55: 2026-10-14 | I55: https://jlcpcb.com/help/article/pcb-assembly-price | J55: Feeder loading, Standard PCBA: $1.53 for every unique part number, Basic and Extended alike (no separate engineering fee and no separate extended-part fee).
A56: Extra fee per unique Extended part (Economic PCBA only - none in Standard) | B56: 0 | C56: USD per unique Extended part | D56: ='Main PCB BOM'!$J$45 -> 14 | E56: =B56*D56 -> 0 | F56: ='Main PCB BOM'!$J$45 -> 14 | G56: =B56*F56 -> 0 | H56: 2026-10-14 | I56: https://jlcpcb.com/help/article/pcb-assembly-price | J56: Only Economic PCBA charges an extra $3.07 per Extended part. In Standard PCBA (this order) every unique part, Basic or Extended, pays the same feeder-loading fee instead, so there is no separate extended-part fee. Type 3.00 here to test the effect of such a fee.
A57: Engineering fee (not on the 2026 page) | B57: 0 | C57: USD per order | D57: 1 | E57: =B57*D57 -> 0 | F57: 1 | G57: =B57*F57 -> 0 | H57: 2026-10-14 | I57: https://jlcpcb.com/help/article/pcb-assembly-price | J57: No separate engineering fee on the 2026 page; the set-up fee covers it.
A58: Confirm parts placement (optional, recommended) | B58: 0.45 | C58: USD per order | D58: 1 | E58: =B58*D58 -> 0.45 | F58: 1 | G58: =B58*F58 -> 0.45 | H58: 2026-10-14 | I58: https://jlcpcb.com/help/article/pcb-assembly-price | J58: 'Confirm parts placement': JLC sends a photo of the placement for your OK. Strongly recommended for a first order.
A59: X-ray inspection (optional): parts inspected = parts per board x boards | B59: tiered (section 7) | C59: USD per part (tiered) | D59: =$B$37*$E$40 -> 6 | E59: =IF(D59=0,0,D59*INDEX($B$84:$B$90,MATCH(D59,$A$84:$A$90,1))) -> 9.84 | F59: =$B$37*$G$40 -> 15 | G59: =IF(F59=0,0,F59*INDEX($B$84:$B$90,MATCH(F59,$A$84:$A$90,1))) -> 12.3 | H59: 2026-10-14 | I59: https://jlcpcb.com/help/article/pcb-assembly-price | J59: Fee page: 'X-ray inspection is required for components such as BGA, QFN and other leadless packages', charged per component. The COUNT is a v0.6 assumption (the fee page itself was not re-read in v0.6): v0.6 budgets the three parts of this board with hidden joints: U4 (ESP32 module, pads under it), LED3 and LED4 (pads under the package) = 3 per board (v0.5: 2, there was one ring LED). Set 0 if your cart does not ask for it.
A60: Panelisation processing by JLC (small board), per board | B60: 0.46 | C60: USD per board | D60: =$E$40 -> 2 | E60: =B60*D60 -> 0.92 | F60: =$G$40 -> 5 | G60: =B60*F60 -> 2.3 | H60: 2026-10-14 | I60: https://jlcpcb.com/help/article/Panelizing-your-PCB-for-Assembly | J60: JLC panelises small boards for assembly; page quotes a minimum processing cost of $0.46 per board. ASSUMED to apply (24 x 16.5 mm is a small board).
A61: Packing (Standard PCBA), base per order | B61: 0.5 | C61: USD per order | D61: 1 | E61: =B61*D61 -> 0.5 | F61: 1 | G61: =B61*F61 -> 0.5 | H61: 2026-10-14 | I61: https://jlcpcb.com/help/article/pcb-assembly-price | J61: Packing, Standard PCBA: $0.50 + $0.00003 per cm2 of board.
A62: Packing, per cm2 of board (board area x boards) | B62: 3e-05 | C62: USD per cm2 | D62: =$B$31*$E$40 -> 7.8862 | E62: =B62*D62 -> 0.000236586 | F62: =$B$31*$G$40 -> 19.7155 | G62: =B62*F62 -> 0.000591465 | H62: 2026-10-14 | I62: https://jlcpcb.com/help/article/pcb-assembly-price | J62: See above (negligible for a 4 cm2 board).
A63: Hand-soldering labour (not needed) - quantity 0 | B63: 3.58 | C63: USD per order | D63: 0 | E63: =B63*D63 -> 0 | F63: 0 | G63: =B63*F63 -> 0 | H63: 2026-10-14 | I63: https://jlcpcb.com/help/article/pcb-assembly-price | J63: Hand-soldering labour. Not needed: no through-hole parts. Quantity 0.
A64: 'Pre-reflow soldering' per joint (unexplained row) - quantity 0 | B64: 0.016 | C64: USD per joint | D64: 0 | E64: =B64*D64 -> 0 | F64: 0 | G64: =B64*F64 -> 0 | H64: 2026-10-14 | I64: https://jlcpcb.com/help/article/pcb-assembly-price | J64: Row 'pre-reflow soldering' on the fee page, not explained there. Quantity 0 - check your quote.
A65: Single-board surcharge (prototypes exempt) - quantity 0 | B65: 0.48 | C65: USD per order | D65: 0 | E65: =B65*D65 -> 0 | F65: 0 | G65: =B65*F65 -> 0 | H65: 2026-10-14 | I65: https://jlcpcb.com/help/article/pcb-assembly-price | J65: Single-board surcharge; prototypes are exempt. Quantity 0.
A66: Fixtures (not needed) - quantity 0 | B66: 8.21 | C66: USD per fixture | D66: 0 | E66: =B66*D66 -> 0 | F66: 0 | G66: =B66*F66 -> 0 | H66: 2026-10-14 | I66: https://jlcpcb.com/help/article/pcb-assembly-price | J66: Test/assembly fixture (minimum 2). Not needed. Quantity 0.
A67: Stencil / fixture storage (not needed) - quantity 0 | B67: 4.93 | C67: USD per item | D67: 0 | E67: =B67*D67 -> 0 | F67: 0 | G67: =B67*F67 -> 0 | H67: 2026-10-14 | I67: https://jlcpcb.com/help/article/pcb-assembly-price | J67: Stencil or fixture storage. Not needed. Quantity 0.
A68: Large-size surcharge (not applicable) - quantity 0 | B68: 57.46 | C68: USD per order | D68: 0 | E68: =B68*D68 -> 0 | F68: 0 | G68: =B68*F68 -> 0 | H68: 2026-10-14 | I68: https://jlcpcb.com/help/article/pcb-assembly-price | J68: Large-size surcharge for boards above 650 cm2. Not applicable (board is 24 x 16.5 mm). Quantity 0.
A69: Assembly fees, subtotal | E69: =SUM(E52:E68) -> 132.01264 | G69: =SUM(G52:G68) -> 136.96659
A71: 6. Total of the JLCPCB order (before shipping, VAT and customs)
E72: Scenario A | G72: Scenario B
A73: Bare PCBs | E73: =$E$48 -> 25 | G73: =$G$48 -> 25
A74: Assembly fees (section 5) | E74: =$E$69 -> 132.01264 | G74: =$G$69 -> 136.96659
A75: Components bought by JLCPCB (sheet 'Main PCB BOM') | E75: ='Main PCB BOM'!$T$43 -> 17.3151 | G75: ='Main PCB BOM'!$W$43 -> 32.7201 | I75: Includes the extra pieces JLC buys for placement loss (they are billed and thrown away).
A76: of which extra pieces for placement loss (information) | E76: ='Main PCB BOM'!$T$47 -> 7.0451 | G76: ='Main PCB BOM'!$W$47 -> 7.0451
A77: TOTAL JLCPCB order before shipping/VAT (USD) | E77: =E73+E74+E75 -> 174.32774 | G77: =G73+G74+G75 -> 194.68669
A78: the same in EUR | E78: =E77/Summary!$B$6 -> 155.81671 | G78: =G77/Summary!$B$6 -> 174.01385
A79: Distance below the EUR 150 IOSS line (negative = above) | E79: ='Hidden costs'!$B$6-E78 -> -5.8167113 | G79: ='Hidden costs'!$B$6-G78 -> -24.013847 | I79: Up to EUR 150 JLC collects 21 % VAT at checkout and the flat EUR 3 duty; above EUR 150 the parcel needs formal customs clearance and the carrier adds a fee of about EUR 15. Scenario A sits very close to this line, so its VAT/customs cost can jump by about EUR 10-15 with a small price change - see sheet 'Hidden costs'.
A80: Route | E80: =IF(E79<0,"formal clearance","IOSS") -> formal clearance | G80: =IF(G79<0,"formal clearance","IOSS") -> formal clearance
A82: 7. X-ray price table (per inspected part, by the total number of inspected parts in the order) - https://jlcpcb.com/help/article/pcb-assembly-price, read 2026-10-14
A83: Total parts inspected from | B83: USD per part
A84: 1 | B84: 1.64
A85: 11 | B85: 0.82
A86: 51 | B86: 0.49
A87: 201 | B87: 0.33
A88: 501 | B88: 0.25
A89: 1001 | B89: 0.16
A90: 3001 | B90: 0.082
A92: 8. Things to know
A93: Basic vs Extended: 20 of the 34 BOM lines are Basic, 14 are Extended (JLC part type read on jlcpcb.com/partdetail/<LCSC> on 2026-10-14; the two new lines C115357 and C25104 are ASSUMED, their pages could not be read on 2026-10-18). In the 2026 Standard PCBA price list every unique part pays the same feeder-loading fee, Basic or Extended, so Extended parts cost no extra here (the separate $3.07 per Extended part belongs to Economic PCBA; the input above is kept at 0). Re-check this if your cart shows an extended-part line.
A94: Parts that JLC cannot supply (out of stock) stop the order: JLC tells you by e-mail and you may substitute. Low-stock lines are marked in sheet 'Main PCB BOM'. Retail stock at LCSC is not JLC's warehouse stock.
A95: Placement loss: JLC buys a few pieces more than needed (they are billed inside the component price, see https://jlcpcb.com/help/article/pcb-assembly-faqs-part-2). The extra counts are estimates in sheet 'Main PCB BOM'.
A96: JLC assembles from 2 boards (https://jlcpcb.com/pcb-assembly). Going from 2 to 5 assembled boards only adds the per-joint price, more components, the panelisation fee and the optional X-ray (compare columns E and G of section 6).
A97: Pre-reflow soldering, hand soldering, fixtures, storage and the large-size fee are listed on the fee page but do not apply to this board; they are kept at quantity 0 so you can switch them on if your quote shows them.
A98: ENIG, 0.8 mm and 4 layers are all standard options at JLCPCB (https://jlcpcb.com/capabilities/pcb-capabilities), only the price of the bare board is unknown until you upload the Gerber.

Sheet Main PCB BOM
A1: Main PCB bill of materials - what JLCPCB assembles on the board
A2: One line per component type (grouped by LCSC number), generated from tools/kicad/flashka_parts.py with the same grouping and ordering as tools/kicad/build_all.py, which writes the BOM you upload as order_files/1_JLCPCB/BOM_JLCPCB.csv: 34 lines, 68 placements, 232 solder joints per board. Wire pads (J2 cell, J3 LED, J5 laser) have no LCSC number: they are NOT assembled, you solder the wires by hand. The LED board, the cells and the laser are bought parts (sheet 'Bought parts'). New in v0.6: SW1-SW3 (Alps SKRKAEE020, three push buttons on the bottom side), LED4 (second ring LED), R30-R34 (button ladder and LED resistors); S1 is gone.
A3: Unit price = the LCSC price tier that matches the quantity JLCPCB has to buy = (quantity per board x boards assembled) + extra pieces for placement loss (columns P-Q). Prices were read from the LCSC product pages on 2026-10-14 (v0.5 price check; the lines that did not change keep that date) (columns X-AI hold the tier tables, typed in from the page). The two NEW lines whose pages could not be read on 2026-10-18 (C115357, C25104) are blue on amber = ESTIMATE: tiers copied from the sibling parts named in the 'Price source' column. JLC buys from LCSC/its own warehouse; the real component price shows in the JLC cart after the BOM upload.
A4: Basic / Extended = JLCPCB library type read on jlcpcb.com/partdetail/<LCSC number> on 2026-10-14 (assumed, amber, for the two new lines: Extended for C115357, Basic for C25104 - check them in the JLC BOM upload). In 2026 Standard PCBA every unique part costs the same feeder fee, Basic or Extended (see sheet 'JLCPCB order'); the 'Preferred' tag (only relevant for the single-sided Economic PCBA) was not shown on any of these pages. 'LCSC stock' is LCSC's retail stock, NOT JLC's warehouse; JLC flags real shortages when you upload the BOM.
B5: Boards assembled, scenario A | C5: ='JLCPCB order'!$E$40 -> 2
B6: Boards assembled, scenario B | C6: ='JLCPCB order'!$G$40 -> 5
A8: # | B8: Designators | C8: Value | D8: Footprint | E8: LCSC # | F8: Manufacturer part no. | G8: Manufacturer | H8: Description (flashka_parts.py) | I8: What it does | J8: Qty / board | K8: Solder joints / part | L8: JLC part type | M8: JLC part page | N8: LCSC stock (retail) | O8: Stock note | P8: Loss class | Q8: Extra pcs | R8: Buy qty A | S8: Unit USD A | T8: Line USD A | U8: Buy qty B | V8: Unit USD B | W8: Line USD B | X8: Tier 1 from qty | Y8: Tier 2 from qty | Z8: Tier 3 from qty | AA8: Tier 4 from qty | AB8: Tier 5 from qty | AC8: Tier 6 from qty | AD8: Tier 1 USD | AE8: Tier 2 USD | AF8: Tier 3 USD | AG8: Tier 4 USD | AH8: Tier 5 USD | AI8: Tier 6 USD | AJ8: Price source
A9: 1 | B9: C1 | C9: 10uF | D9: C_0805_2012Metric | E9: C15850 | F9: CL21A106KAYNNNE | G9: Samsung Electro-Mechanics | H9: 10uF 25V X5R 0805 | I9: Smoothing capacitor on the USB 5 V input (25 V rating needed). | J9: =LEN(B9)-LEN(SUBSTITUTE(B9,",",""))+1 -> 1 | K9: 2 | L9: Basic | M9: JLC page | N9: 20 | O9: LOW: only 20 pcs at LCSC retail; JLC's own stock is separate - the BOM upload flags a shortage. Any 10 uF 25 V X5R 0805 Basic part is a substitute. | P9: p0603 | Q9: =INDEX($C$52:$C$55,MATCH(P9,$B$52:$B$55,0)) -> 5 | R9: =J9*$C$5+Q9 -> 7 | S9: =INDEX($AD9:$AI9,MAX(1,COUNTIF($X9:$AC9,"<="&R9))) -> 0.0695 | T9: =R9*S9 -> 0.4865 | U9: =J9*$C$6+Q9 -> 10 | V9: =INDEX($AD9:$AI9,MAX(1,COUNTIF($X9:$AC9,"<="&U9))) -> 0.0695 | W9: =U9*V9 -> 0.695 | X9: 20 | Y9: 200 | Z9: 600 | AA9: 2000 | AB9: 10000 | AC9: 20000 | AD9: 0.0695 | AE9: 0.0513 | AF9: 0.0419 | AG9: 0.0342 | AH9: 0.0315 | AI9: 0.0297 | AJ9: https://www.lcsc.com/product-detail/C15850.html (read 2026-10-14)
A10: 2 | B10: C2,C13,C15 | C10: 10uF | D10: C_0603_1608Metric | E10: C19702 | F10: CL10A106KP8NNNC | G10: Samsung Electro-Mechanics | H10: 10uF 10V X5R 0603 | I10: 10 uF capacitors that smooth the supply next to the chips (C2, C13, C15). | J10: =LEN(B10)-LEN(SUBSTITUTE(B10,",",""))+1 -> 3 | K10: 2 | L10: Basic | M10: JLC page | N10: 181020 | O10: OK | P10: p0603 | Q10: =INDEX($C$52:$C$55,MATCH(P10,$B$52:$B$55,0)) -> 5 | R10: =J10*$C$5+Q10 -> 11 | S10: =INDEX($AD10:$AI10,MAX(1,COUNTIF($X10:$AC10,"<="&R10))) -> 0.0311 | T10: =R10*S10 -> 0.3421 | U10: =J10*$C$6+Q10 -> 20 | V10: =INDEX($AD10:$AI10,MAX(1,COUNTIF($X10:$AC10,"<="&U10))) -> 0.0311 | W10: =U10*V10 -> 0.622 | X10: 20 | Y10: 200 | Z10: 600 | AA10: 4000 | AB10: 8000 | AC10: 20000 | AD10: 0.0311 | AE10: 0.023 | AF10: 0.0195 | AG10: 0.0168 | AH10: 0.0157 | AI10: 0.015 | AJ10: https://www.lcsc.com/product-detail/C19702.html (read 2026-10-14)
A11: 3 | B11: C5,C8 | C11: 22uF | D11: C_0603_1608Metric | E11: C59461 | F11: CL10A226MQ8NRNC | G11: Samsung Electro-Mechanics | H11: 22uF 6.3V X5R 0603 | I11: 22 uF capacitors for the buck converter / power rails (C5, C8). | J11: =LEN(B11)-LEN(SUBSTITUTE(B11,",",""))+1 -> 2 | K11: 2 | L11: Basic | M11: JLC page | N11: 4416440 | O11: OK | P11: p0603 | Q11: =INDEX($C$52:$C$55,MATCH(P11,$B$52:$B$55,0)) -> 5 | R11: =J11*$C$5+Q11 -> 9 | S11: =INDEX($AD11:$AI11,MAX(1,COUNTIF($X11:$AC11,"<="&R11))) -> 0.0315 | T11: =R11*S11 -> 0.2835 | U11: =J11*$C$6+Q11 -> 15 | V11: =INDEX($AD11:$AI11,MAX(1,COUNTIF($X11:$AC11,"<="&U11))) -> 0.0315 | W11: =U11*V11 -> 0.4725 | X11: 20 | Y11: 200 | Z11: 600 | AA11: 4000 | AB11: 8000 | AC11: 20000 | AD11: 0.0315 | AE11: 0.0236 | AF11: 0.0201 | AG11: 0.0174 | AH11: 0.0164 | AI11: 0.0157 | AJ11: https://www.lcsc.com/product-detail/C59461.html (read 2026-10-14)
A12: 4 | B12: C9 | C12: 22pF | D12: C_0402_1005Metric | E12: C1555 | F12: 0402CG220J500NT | G12: FH | H12: 22pF 50V C0G 0402 | I12: 22 pF feed-forward capacitor in the LED-driver loop (C9). | J12: =LEN(B12)-LEN(SUBSTITUTE(B12,",",""))+1 -> 1 | K12: 2 | L12: Basic | M12: JLC page | N12: 798400 | O12: OK | P12: p0402 | Q12: =INDEX($C$52:$C$55,MATCH(P12,$B$52:$B$55,0)) -> 10 | R12: =J12*$C$5+Q12 -> 12 | S12: =INDEX($AD12:$AI12,MAX(1,COUNTIF($X12:$AC12,"<="&R12))) -> 0.0027 | T12: =R12*S12 -> 0.0324 | U12: =J12*$C$6+Q12 -> 15 | V12: =INDEX($AD12:$AI12,MAX(1,COUNTIF($X12:$AC12,"<="&U12))) -> 0.0027 | W12: =U12*V12 -> 0.0405 | X12: 100 | Y12: 1000 | Z12: 3000 | AA12: 10000 | AB12: 50000 | AD12: 0.0027 | AE12: 0.002 | AF12: 0.0017 | AG12: 0.0014 | AH12: 0.0012 | AJ12: https://www.lcsc.com/product-detail/C1555.html (read 2026-10-14)
A13: 5 | B13: C11 | C13: 10nF | D13: C_0402_1005Metric | E13: C15195 | F13: CL05B103KB5NNNC | G13: Samsung Electro-Mechanics | H13: 10nF 50V X7R 0402 | I13: 10 nF capacitor (C11, filter in the LED-current loop). | J13: =LEN(B13)-LEN(SUBSTITUTE(B13,",",""))+1 -> 1 | K13: 2 | L13: Basic | M13: JLC page | N13: 0 | O13: LCSC retail shows OUT OF STOCK; JLC lists it as Basic and has its own warehouse - the BOM upload shows the real JLC stock. If flagged, pick another Basic 10 nF 0402 and update flashka_parts.py. | P13: p0402 | Q13: =INDEX($C$52:$C$55,MATCH(P13,$B$52:$B$55,0)) -> 10 | R13: =J13*$C$5+Q13 -> 12 | S13: =INDEX($AD13:$AI13,MAX(1,COUNTIF($X13:$AC13,"<="&R13))) -> 0.005 | T13: =R13*S13 -> 0.06 | U13: =J13*$C$6+Q13 -> 15 | V13: =INDEX($AD13:$AI13,MAX(1,COUNTIF($X13:$AC13,"<="&U13))) -> 0.005 | W13: =U13*V13 -> 0.075 | X13: 100 | Y13: 1000 | Z13: 3000 | AA13: 10000 | AB13: 50000 | AC13: 100000 | AD13: 0.005 | AE13: 0.0038 | AF13: 0.0033 | AG13: 0.0029 | AH13: 0.0028 | AI13: 0.0027 | AJ13: https://www.lcsc.com/product-detail/C15195.html (read 2026-10-14)
A14: 6 | B14: C12,C14,C17,C18 | C14: 1uF | D14: C_0402_1005Metric | E14: C52923 | F14: CL05A105KA5NQNC | G14: Samsung Electro-Mechanics | H14: 1uF 25V X5R 0402 | I14: 1 uF 25 V capacitors for supply decoupling (C12, C14, C17, C18). | J14: =LEN(B14)-LEN(SUBSTITUTE(B14,",",""))+1 -> 4 | K14: 2 | L14: Basic | M14: JLC page | N14: 598000 | O14: OK | P14: p0402 | Q14: =INDEX($C$52:$C$55,MATCH(P14,$B$52:$B$55,0)) -> 10 | R14: =J14*$C$5+Q14 -> 18 | S14: =INDEX($AD14:$AI14,MAX(1,COUNTIF($X14:$AC14,"<="&R14))) -> 0.0085 | T14: =R14*S14 -> 0.153 | U14: =J14*$C$6+Q14 -> 30 | V14: =INDEX($AD14:$AI14,MAX(1,COUNTIF($X14:$AC14,"<="&U14))) -> 0.0085 | W14: =U14*V14 -> 0.255 | X14: 50 | Y14: 500 | Z14: 1500 | AA14: 10000 | AB14: 20000 | AC14: 50000 | AD14: 0.0085 | AE14: 0.0067 | AF14: 0.0059 | AG14: 0.0053 | AH14: 0.005 | AI14: 0.0049 | AJ14: https://www.lcsc.com/product-detail/C52923.html (read 2026-10-14)
A15: 7 | B15: C7,C10,C16,C19,C20 | C15: 100nF | D15: C_0402_1005Metric | E15: C1525 | F15: CL05B104KO5NNNC | G15: Samsung Electro-Mechanics | H15: 100nF 16V X7R 0402 | I15: 100 nF capacitors: one next to each chip's supply pin (C7, C10, C16, C19, C20). | J15: =LEN(B15)-LEN(SUBSTITUTE(B15,",",""))+1 -> 5 | K15: 2 | L15: Basic | M15: JLC page | N15: 0 | O15: LCSC retail shows OUT OF STOCK, but the JLC basic-parts list shows 23,496,493 pcs (read 2026-10-14), so JLC can assemble it. | P15: p0402 | Q15: =INDEX($C$52:$C$55,MATCH(P15,$B$52:$B$55,0)) -> 10 | R15: =J15*$C$5+Q15 -> 20 | S15: =INDEX($AD15:$AI15,MAX(1,COUNTIF($X15:$AC15,"<="&R15))) -> 0.0046 | T15: =R15*S15 -> 0.092 | U15: =J15*$C$6+Q15 -> 35 | V15: =INDEX($AD15:$AI15,MAX(1,COUNTIF($X15:$AC15,"<="&U15))) -> 0.0046 | W15: =U15*V15 -> 0.161 | X15: 100 | Y15: 1000 | Z15: 3000 | AA15: 10000 | AB15: 50000 | AC15: 100000 | AD15: 0.0046 | AE15: 0.0035 | AF15: 0.003 | AG15: 0.0026 | AH15: 0.0025 | AI15: 0.0024 | AJ15: https://www.lcsc.com/product-detail/C1525.html (read 2026-10-14)
A16: 8 | B16: D1 | C16: ESD5Z5.0T1G | D16: D_SOD-523 | E16: C82044 | F16: ESD5Z5.0T1G | G16: onsemi | H16: 5 V unidirectional TVS (VBUS), SOD-523 | I16: D1: protects the board from static / voltage spikes on the USB 5 V line. | J16: =LEN(B16)-LEN(SUBSTITUTE(B16,",",""))+1 -> 1 | K16: 2 | L16: Extended | M16: JLC page | N16: 370780 | O16: OK | P16: semi | Q16: =INDEX($C$52:$C$55,MATCH(P16,$B$52:$B$55,0)) -> 2 | R16: =J16*$C$5+Q16 -> 4 | S16: =INDEX($AD16:$AI16,MAX(1,COUNTIF($X16:$AC16,"<="&R16))) -> 0.0371 | T16: =R16*S16 -> 0.1484 | U16: =J16*$C$6+Q16 -> 7 | V16: =INDEX($AD16:$AI16,MAX(1,COUNTIF($X16:$AC16,"<="&U16))) -> 0.0371 | W16: =U16*V16 -> 0.2597 | X16: 20 | Y16: 200 | Z16: 600 | AA16: 3000 | AB16: 9000 | AC16: 21000 | AD16: 0.0371 | AE16: 0.029 | AF16: 0.0245 | AG16: 0.0204 | AH16: 0.0181 | AI16: 0.0168 | AJ16: https://www.lcsc.com/product-detail/C82044.html (read 2026-10-14)
A17: 9 | B17: J1 | C17: TYPE-C-31-M-12 | D17: USB_C_Receptacle_HRO_TYPE-C-31-M-12 | E17: C165948 | F17: TYPE-C-31-M-12 | G17: Korean Hroparts Elec | H17: USB-C 16P receptacle (USB 2.0 data), SMD + 4 shell legs | I17: J1: USB-C socket (charging and data). 16 signal pads + 4 shell legs = 20 joints. | J17: =LEN(B17)-LEN(SUBSTITUTE(B17,",",""))+1 -> 1 | K17: 20 | L17: Extended | M17: JLC page | N17: 375745 | O17: OK | P17: mod | Q17: =INDEX($C$52:$C$55,MATCH(P17,$B$52:$B$55,0)) -> 1 | R17: =J17*$C$5+Q17 -> 3 | S17: =INDEX($AD17:$AI17,MAX(1,COUNTIF($X17:$AC17,"<="&R17))) -> 0.1729 | T17: =R17*S17 -> 0.5187 | U17: =J17*$C$6+Q17 -> 6 | V17: =INDEX($AD17:$AI17,MAX(1,COUNTIF($X17:$AC17,"<="&U17))) -> 0.1729 | W17: =U17*V17 -> 1.0374 | X17: 5 | Y17: 50 | Z17: 150 | AA17: 1000 | AB17: 2000 | AC17: 5000 | AD17: 0.1729 | AE17: 0.1365 | AF17: 0.1187 | AG17: 0.0963 | AH17: 0.092 | AI17: 0.0894 | AJ17: https://www.lcsc.com/product-detail/C165948.html (read 2026-10-14)
A18: 10 | B18: L1 | C18: 1uH | D18: L_Changjiang_FNR4020S | E18: C602028 | F18: FHD4020S-1R0MT | G18: cjiang | H18: 1 uH 4x4 mm, Isat 11 A, 23 mOhm (cjiang FHD4020S-1R0MT) | I18: L1: 1 uH power inductor of the buck converter U2 (LED driver). | J18: =LEN(B18)-LEN(SUBSTITUTE(B18,",",""))+1 -> 1 | K18: 2 | L18: Extended | M18: JLC page | N18: 8210 | O18: OK | P18: mod | Q18: =INDEX($C$52:$C$55,MATCH(P18,$B$52:$B$55,0)) -> 1 | R18: =J18*$C$5+Q18 -> 3 | S18: =INDEX($AD18:$AI18,MAX(1,COUNTIF($X18:$AC18,"<="&R18))) -> 0.1102 | T18: =R18*S18 -> 0.3306 | U18: =J18*$C$6+Q18 -> 6 | V18: =INDEX($AD18:$AI18,MAX(1,COUNTIF($X18:$AC18,"<="&U18))) -> 0.1102 | W18: =U18*V18 -> 0.6612 | X18: 10 | Y18: 100 | Z18: 300 | AA18: 3000 | AB18: 6000 | AC18: 9000 | AD18: 0.1102 | AE18: 0.086 | AF18: 0.0726 | AG18: 0.0645 | AH18: 0.0575 | AI18: 0.0538 | AJ18: https://www.lcsc.com/product-detail/C602028.html (read 2026-10-14)
A19: 11 | B19: LED3,LED4 | C19: NH-B1010RGBT-HF | D19: LED_RGB_1010_NH-B1010RGBT | E19: C2874113 | F19: NH-B1010RGBT-HF | G19: NATIONSTAR | H19: ring RGB LED 1x1 mm, common anode (pin 1), bottom side, emits into the light pipe | I19: LED3, LED4: the two RGB ring LEDs (1 x 1 mm, 4 pads under the package) that light the ring around the main button. | J19: =LEN(B19)-LEN(SUBSTITUTE(B19,",",""))+1 -> 2 | K19: 4 | L19: Extended | M19: JLC page | N19: 345020 | O19: OK | P19: semi | Q19: =INDEX($C$52:$C$55,MATCH(P19,$B$52:$B$55,0)) -> 2 | R19: =J19*$C$5+Q19 -> 6 | S19: =INDEX($AD19:$AI19,MAX(1,COUNTIF($X19:$AC19,"<="&R19))) -> 0.0081 | T19: =R19*S19 -> 0.0486 | U19: =J19*$C$6+Q19 -> 12 | V19: =INDEX($AD19:$AI19,MAX(1,COUNTIF($X19:$AC19,"<="&U19))) -> 0.0081 | W19: =U19*V19 -> 0.0972 | X19: 20 | Y19: 200 | Z19: 600 | AA19: 2000 | AB19: 10000 | AC19: 20000 | AD19: 0.0081 | AE19: 0.0072 | AF19: 0.0068 | AG19: 0.0065 | AH19: 0.0063 | AI19: 0.0053 | AJ19: https://www.lcsc.com/product-detail/C2874113.html (read 2026-10-14)
A20: 12 | B20: Q1 | C20: AO3401A | D20: SOT-23 | E20: C15127 | F20: AO3401A | G20: AOS | H20: P-MOSFET laser load switch | I20: Q1: P-channel MOSFET, the on/off switch of the laser. | J20: =LEN(B20)-LEN(SUBSTITUTE(B20,",",""))+1 -> 1 | K20: 3 | L20: Basic | M20: JLC page | N20: 164910 | O20: OK | P20: semi | Q20: =INDEX($C$52:$C$55,MATCH(P20,$B$52:$B$55,0)) -> 2 | R20: =J20*$C$5+Q20 -> 4 | S20: =INDEX($AD20:$AI20,MAX(1,COUNTIF($X20:$AC20,"<="&R20))) -> 0.1026 | T20: =R20*S20 -> 0.4104 | U20: =J20*$C$6+Q20 -> 7 | V20: =INDEX($AD20:$AI20,MAX(1,COUNTIF($X20:$AC20,"<="&U20))) -> 0.1026 | W20: =U20*V20 -> 0.7182 | X20: 5 | Y20: 50 | Z20: 150 | AA20: 500 | AB20: 3000 | AC20: 6000 | AD20: 0.1026 | AE20: 0.0829 | AF20: 0.0728 | AG20: 0.0644 | AH20: 0.0615 | AI20: 0.0596 | AJ20: https://www.lcsc.com/product-detail/C15127.html (read 2026-10-14)
A21: 13 | B21: Q2,Q4,Q5 | C21: 2N7002W | D21: SOT-323_SC-70 | E21: C5224240 | F21: 2N7002W-7-F-ES | G21: ElecSuper | H21: Q2: N-MOSFET current sink into FB (SOT-323); Q4: N-MOSFET (SOT-323): 3.3 V LASER_ON -> pulls the Q1 gate path low; Q5: VBUS-edge reset (SOT-323): pulls EN low for ~0.1 s when USB is plugged in | I21: Q2, Q4, Q5: small N-channel MOSFET switches (LED current sink, laser gate, reset pulse). | J21: =LEN(B21)-LEN(SUBSTITUTE(B21,",",""))+1 -> 3 | K21: 3 | L21: Extended | M21: JLC page | N21: 17000 | O21: OK | P21: semi | Q21: =INDEX($C$52:$C$55,MATCH(P21,$B$52:$B$55,0)) -> 2 | R21: =J21*$C$5+Q21 -> 8 | S21: =INDEX($AD21:$AI21,MAX(1,COUNTIF($X21:$AC21,"<="&R21))) -> 0.0224 | T21: =R21*S21 -> 0.1792 | U21: =J21*$C$6+Q21 -> 17 | V21: =INDEX($AD21:$AI21,MAX(1,COUNTIF($X21:$AC21,"<="&U21))) -> 0.0224 | W21: =U21*V21 -> 0.3808 | X21: 50 | Y21: 500 | Z21: 3000 | AA21: 6000 | AB21: 24000 | AC21: 51000 | AD21: 0.0224 | AE21: 0.017 | AF21: 0.0141 | AG21: 0.0123 | AH21: 0.0108 | AI21: 0.0099 | AJ21: https://www.lcsc.com/product-detail/C5224240.html (read 2026-10-14)
A22: 14 | B22: R1,R2 | C22: 5.1k | D22: R_0402_1005Metric | E22: C25905 | F22: 0402WGF5101TCE | G22: UNI-ROYAL | H22: 5.1k 1% 0402 resistor | I22: R1, R2: 5.1 k resistors on the USB-C CC pins (tell a charger to supply 5 V). | J22: =LEN(B22)-LEN(SUBSTITUTE(B22,",",""))+1 -> 2 | K22: 2 | L22: Basic | M22: JLC page | N22: 2302500 | O22: OK | P22: p0402 | Q22: =INDEX($C$52:$C$55,MATCH(P22,$B$52:$B$55,0)) -> 10 | R22: =J22*$C$5+Q22 -> 14 | S22: =INDEX($AD22:$AI22,MAX(1,COUNTIF($X22:$AC22,"<="&R22))) -> 0.0024 | T22: =R22*S22 -> 0.0336 | U22: =J22*$C$6+Q22 -> 20 | V22: =INDEX($AD22:$AI22,MAX(1,COUNTIF($X22:$AC22,"<="&U22))) -> 0.0024 | W22: =U22*V22 -> 0.048 | X22: 100 | Y22: 1000 | Z22: 3000 | AA22: 10000 | AB22: 50000 | AD22: 0.0024 | AE22: 0.0019 | AF22: 0.0015 | AG22: 0.0014 | AH22: 0.0012 | AJ22: https://www.lcsc.com/product-detail/C25905.html (read 2026-10-14)
A23: 15 | B23: R3 | C23: 3.3k | D23: R_0402_1005Metric | E23: C25890 | F23: 0402WGF3301TCE | G23: UNI-ROYAL | H23: 3.3k 1% 0402 resistor | I23: R3: 3.3 k resistor, sets the battery charge current (about 280 mA). | J23: =LEN(B23)-LEN(SUBSTITUTE(B23,",",""))+1 -> 1 | K23: 2 | L23: Basic | M23: JLC page | N23: 867600 | O23: OK | P23: p0402 | Q23: =INDEX($C$52:$C$55,MATCH(P23,$B$52:$B$55,0)) -> 10 | R23: =J23*$C$5+Q23 -> 12 | S23: =INDEX($AD23:$AI23,MAX(1,COUNTIF($X23:$AC23,"<="&R23))) -> 0.0036 | T23: =R23*S23 -> 0.0432 | U23: =J23*$C$6+Q23 -> 15 | V23: =INDEX($AD23:$AI23,MAX(1,COUNTIF($X23:$AC23,"<="&U23))) -> 0.0036 | W23: =U23*V23 -> 0.054 | X23: 100 | Y23: 1000 | Z23: 3000 | AA23: 10000 | AB23: 50000 | AD23: 0.0036 | AE23: 0.0027 | AF23: 0.0023 | AG23: 0.002 | AH23: 0.0018 | AJ23: https://www.lcsc.com/product-detail/C25890.html (read 2026-10-14)
A24: 16 | B24: R10 | C24: 200k | D24: R_0402_1005Metric | E24: C25764 | F24: 0402WGF2003TCE | G24: UNI-ROYAL | H24: 200k 1% 0402 resistor | I24: R10: 200 k resistor (voltage divider of the buck converter). | J24: =LEN(B24)-LEN(SUBSTITUTE(B24,",",""))+1 -> 1 | K24: 2 | L24: Basic | M24: JLC page | N24: 1520700 | O24: OK | P24: p0402 | Q24: =INDEX($C$52:$C$55,MATCH(P24,$B$52:$B$55,0)) -> 10 | R24: =J24*$C$5+Q24 -> 12 | S24: =INDEX($AD24:$AI24,MAX(1,COUNTIF($X24:$AC24,"<="&R24))) -> 0.0018 | T24: =R24*S24 -> 0.0216 | U24: =J24*$C$6+Q24 -> 15 | V24: =INDEX($AD24:$AI24,MAX(1,COUNTIF($X24:$AC24,"<="&U24))) -> 0.0018 | W24: =U24*V24 -> 0.027 | X24: 100 | Y24: 1000 | Z24: 3000 | AA24: 10000 | AB24: 50000 | AD24: 0.0018 | AE24: 0.0014 | AF24: 0.0011 | AG24: 0.001 | AH24: 0.0009 | AJ24: https://www.lcsc.com/product-detail/C25764.html (read 2026-10-14)
A25: 17 | B25: R12 | C25: 47k | D25: R_0402_1005Metric | E25: C25792 | F25: 0402WGF4702TCE | G25: UNI-ROYAL | H25: 47k 1% 0402 resistor | I25: R12: 47 k resistor. | J25: =LEN(B25)-LEN(SUBSTITUTE(B25,",",""))+1 -> 1 | K25: 2 | L25: Basic | M25: JLC page | N25: 3114700 | O25: OK | P25: p0402 | Q25: =INDEX($C$52:$C$55,MATCH(P25,$B$52:$B$55,0)) -> 10 | R25: =J25*$C$5+Q25 -> 12 | S25: =INDEX($AD25:$AI25,MAX(1,COUNTIF($X25:$AC25,"<="&R25))) -> 0.0026 | T25: =R25*S25 -> 0.0312 | U25: =J25*$C$6+Q25 -> 15 | V25: =INDEX($AD25:$AI25,MAX(1,COUNTIF($X25:$AC25,"<="&U25))) -> 0.0026 | W25: =U25*V25 -> 0.039 | X25: 100 | Y25: 1000 | Z25: 3000 | AA25: 10000 | AB25: 50000 | AD25: 0.0026 | AE25: 0.002 | AF25: 0.0017 | AG25: 0.0015 | AH25: 0.0013 | AJ25: https://www.lcsc.com/product-detail/C25792.html (read 2026-10-14)
A26: 18 | B26: R8,R9,R13,R18,R21,R22 | C26: 10k | D26: R_0402_1005Metric | E26: C25744 | F26: 0402WGF1002TCE | G26: UNI-ROYAL | H26: 10k 1% 0402 resistor | I26: 10 k resistors: pull-ups / pull-downs (R8, R9, R13, R18, R21, R22). | J26: =LEN(B26)-LEN(SUBSTITUTE(B26,",",""))+1 -> 6 | K26: 2 | L26: Basic | M26: JLC page | N26: 2846900 | O26: OK | P26: p0402 | Q26: =INDEX($C$52:$C$55,MATCH(P26,$B$52:$B$55,0)) -> 10 | R26: =J26*$C$5+Q26 -> 22 | S26: =INDEX($AD26:$AI26,MAX(1,COUNTIF($X26:$AC26,"<="&R26))) -> 0.0033 | T26: =R26*S26 -> 0.0726 | U26: =J26*$C$6+Q26 -> 40 | V26: =INDEX($AD26:$AI26,MAX(1,COUNTIF($X26:$AC26,"<="&U26))) -> 0.0033 | W26: =U26*V26 -> 0.132 | X26: 100 | Y26: 1000 | Z26: 3000 | AA26: 10000 | AB26: 50000 | AD26: 0.0033 | AE26: 0.0026 | AF26: 0.0022 | AG26: 0.0021 | AH26: 0.0017 | AJ26: https://www.lcsc.com/product-detail/C25744.html (read 2026-10-14)
A27: 19 | B27: R14,R31 | C27: 2.2k | D27: R_0402_1005Metric | E27: C25879 | F27: 0402WGF2201TCE | G27: UNI-ROYAL | H27: 2.2k 1% 0402 resistor | I27: R14: 2.2 k resistor (LED-current loop). R31: 2.2 k resistor of the button ladder (previous button). | J27: =LEN(B27)-LEN(SUBSTITUTE(B27,",",""))+1 -> 2 | K27: 2 | L27: Basic | M27: JLC page | N27: 586000 | O27: OK | P27: p0402 | Q27: =INDEX($C$52:$C$55,MATCH(P27,$B$52:$B$55,0)) -> 10 | R27: =J27*$C$5+Q27 -> 14 | S27: =INDEX($AD27:$AI27,MAX(1,COUNTIF($X27:$AC27,"<="&R27))) -> 0.0018 | T27: =R27*S27 -> 0.0252 | U27: =J27*$C$6+Q27 -> 20 | V27: =INDEX($AD27:$AI27,MAX(1,COUNTIF($X27:$AC27,"<="&U27))) -> 0.0018 | W27: =U27*V27 -> 0.036 | X27: 100 | Y27: 1000 | Z27: 3000 | AA27: 50000 | AD27: 0.0018 | AE27: 0.0013 | AF27: 0.0011 | AG27: 0.0009 | AJ27: https://www.lcsc.com/product-detail/C25879.html (read 2026-10-14)
A28: 20 | B28: R16 | C28: 2k | D28: R_0402_1005Metric | E28: C4109 | F28: 0402WGF2001TCE | G28: UNI-ROYAL | H28: 2k 1% 0402 resistor | I28: R16: 2 k resistor. | J28: =LEN(B28)-LEN(SUBSTITUTE(B28,",",""))+1 -> 1 | K28: 2 | L28: Basic | M28: JLC page | N28: 5789500 | O28: OK | P28: p0402 | Q28: =INDEX($C$52:$C$55,MATCH(P28,$B$52:$B$55,0)) -> 10 | R28: =J28*$C$5+Q28 -> 12 | S28: =INDEX($AD28:$AI28,MAX(1,COUNTIF($X28:$AC28,"<="&R28))) -> 0.0026 | T28: =R28*S28 -> 0.0312 | U28: =J28*$C$6+Q28 -> 15 | V28: =INDEX($AD28:$AI28,MAX(1,COUNTIF($X28:$AC28,"<="&U28))) -> 0.0026 | W28: =U28*V28 -> 0.039 | X28: 100 | Y28: 1000 | Z28: 3000 | AA28: 10000 | AB28: 50000 | AD28: 0.0026 | AE28: 0.002 | AF28: 0.0016 | AG28: 0.0015 | AH28: 0.0012 | AJ28: https://www.lcsc.com/product-detail/C4109.html (read 2026-10-14)
A29: 21 | B29: R19,R30 | C29: 1k | D29: R_0402_1005Metric | E29: C11702 | F29: 0402WGF1001TCE | G29: UNI-ROYAL | H29: 1k 1% 0402 resistor | I29: R19: 1 k resistor (laser gate). R30: 1 k resistor of the button ladder (next button). | J29: =LEN(B29)-LEN(SUBSTITUTE(B29,",",""))+1 -> 2 | K29: 2 | L29: Basic | M29: JLC page | N29: 0 | O29: LCSC retail shows OUT OF STOCK; JLC lists it as Basic - check the JLC stock at BOM upload. | P29: p0402 | Q29: =INDEX($C$52:$C$55,MATCH(P29,$B$52:$B$55,0)) -> 10 | R29: =J29*$C$5+Q29 -> 14 | S29: =INDEX($AD29:$AI29,MAX(1,COUNTIF($X29:$AC29,"<="&R29))) -> 0.0031 | T29: =R29*S29 -> 0.0434 | U29: =J29*$C$6+Q29 -> 20 | V29: =INDEX($AD29:$AI29,MAX(1,COUNTIF($X29:$AC29,"<="&U29))) -> 0.0031 | W29: =U29*V29 -> 0.062 | X29: 100 | Y29: 1000 | Z29: 3000 | AA29: 10000 | AB29: 50000 | AD29: 0.0031 | AE29: 0.0024 | AF29: 0.002 | AG29: 0.0018 | AH29: 0.0016 | AJ29: https://www.lcsc.com/product-detail/C11702.html (read 2026-10-14)
A30: 22 | B30: R23,R32 | C30: 330Ω | D30: R_0402_1005Metric | E30: C25104 | F30: 0402WGF3300TCE | G30: UNI-ROYAL | H30: 330 1% 0402 resistor | I30: R23, R32: 330 ohm resistors (red leg of the two ring LEDs). | J30: =LEN(B30)-LEN(SUBSTITUTE(B30,",",""))+1 -> 2 | K30: 2 | L30: Basic | M30: JLC page | N30: unknown | O30: ESTIMATE, page not read: JLCPCB and LCSC pages of C25104 could not be read on 2026-10-18. Tiers copied from the sibling 5.1 k resistor C25905 (read 2026-10-14); part number inferred from the UNI-ROYAL naming; library type 'Basic' assumed (same series as the other Basic 0402 resistors). Stock unknown. | P30: p0402 | Q30: =INDEX($C$52:$C$55,MATCH(P30,$B$52:$B$55,0)) -> 10 | R30: =J30*$C$5+Q30 -> 14 | S30: =INDEX($AD30:$AI30,MAX(1,COUNTIF($X30:$AC30,"<="&R30))) -> 0.0024 | T30: =R30*S30 -> 0.0336 | U30: =J30*$C$6+Q30 -> 20 | V30: =INDEX($AD30:$AI30,MAX(1,COUNTIF($X30:$AC30,"<="&U30))) -> 0.0024 | W30: =U30*V30 -> 0.048 | X30: 100 | Y30: 1000 | Z30: 3000 | AA30: 10000 | AB30: 50000 | AD30: 0.0024 | AE30: 0.0019 | AF30: 0.0015 | AG30: 0.0014 | AH30: 0.0012 | AJ30: ESTIMATE - LCSC and JLCPCB pages of C25104 could not be read on 2026-10-18. Tiers of the sibling C25905 (LCSC, read 2026-10-14).
A31: 23 | B31: R24,R25,R33,R34 | C31: 100Ω | D31: R_0402_1005Metric | E31: C25076 | F31: 0402WGF1000TCE | G31: UNI-ROYAL | H31: 100 1% 0402 resistor | I31: R24, R25, R33, R34: 100 ohm resistors (green and blue leg of each ring LED). | J31: =LEN(B31)-LEN(SUBSTITUTE(B31,",",""))+1 -> 4 | K31: 2 | L31: Basic | M31: JLC page | N31: 4360400 | O31: OK | P31: p0402 | Q31: =INDEX($C$52:$C$55,MATCH(P31,$B$52:$B$55,0)) -> 10 | R31: =J31*$C$5+Q31 -> 18 | S31: =INDEX($AD31:$AI31,MAX(1,COUNTIF($X31:$AC31,"<="&R31))) -> 0.0013 | T31: =R31*S31 -> 0.0234 | U31: =J31*$C$6+Q31 -> 30 | V31: =INDEX($AD31:$AI31,MAX(1,COUNTIF($X31:$AC31,"<="&U31))) -> 0.0013 | W31: =U31*V31 -> 0.039 | X31: 100 | Y31: 1000 | Z31: 3000 | AA31: 10000 | AD31: 0.0013 | AE31: 0.001 | AF31: 0.0009 | AG31: 0.0008 | AJ31: https://www.lcsc.com/product-detail/C25076.html (read 2026-10-14)
A32: 24 | B32: R27,R28 | C32: 1M | D32: R_0402_1005Metric | E32: C26083 | F32: 0402WGF1004TCE | G32: UNI-ROYAL | H32: 1M 1% 0402 resistor | I32: R27, R28: 1 M resistors. | J32: =LEN(B32)-LEN(SUBSTITUTE(B32,",",""))+1 -> 2 | K32: 2 | L32: Basic | M32: JLC page | N32: 541000 | O32: OK | P32: p0402 | Q32: =INDEX($C$52:$C$55,MATCH(P32,$B$52:$B$55,0)) -> 10 | R32: =J32*$C$5+Q32 -> 14 | S32: =INDEX($AD32:$AI32,MAX(1,COUNTIF($X32:$AC32,"<="&R32))) -> 0.0024 | T32: =R32*S32 -> 0.0336 | U32: =J32*$C$6+Q32 -> 20 | V32: =INDEX($AD32:$AI32,MAX(1,COUNTIF($X32:$AC32,"<="&U32))) -> 0.0024 | W32: =U32*V32 -> 0.048 | X32: 100 | Y32: 1000 | Z32: 3000 | AA32: 10000 | AB32: 50000 | AD32: 0.0024 | AE32: 0.0018 | AF32: 0.0016 | AG32: 0.0014 | AH32: 0.0011 | AJ32: https://www.lcsc.com/product-detail/C26083.html (read 2026-10-14)
A33: 25 | B33: R7,R11,R15,R17,R20,R26,R29 | C33: 100k | D33: R_0402_1005Metric | E33: C25741 | F33: 0402WGF1003TCE | G33: UNI-ROYAL | H33: 100k 1% 0402 resistor | I33: 100 k resistors: pull-ups / dividers (7 of them). | J33: =LEN(B33)-LEN(SUBSTITUTE(B33,",",""))+1 -> 7 | K33: 2 | L33: Basic | M33: JLC page | N33: 3791500 | O33: OK | P33: p0402 | Q33: =INDEX($C$52:$C$55,MATCH(P33,$B$52:$B$55,0)) -> 10 | R33: =J33*$C$5+Q33 -> 24 | S33: =INDEX($AD33:$AI33,MAX(1,COUNTIF($X33:$AC33,"<="&R33))) -> 0.0015 | T33: =R33*S33 -> 0.036 | U33: =J33*$C$6+Q33 -> 45 | V33: =INDEX($AD33:$AI33,MAX(1,COUNTIF($X33:$AC33,"<="&U33))) -> 0.0015 | W33: =U33*V33 -> 0.0675 | X33: 100 | Y33: 1000 | Z33: 3000 | AA33: 10000 | AB33: 50000 | AD33: 0.0015 | AE33: 0.0012 | AF33: 0.001 | AG33: 0.0009 | AH33: 0.0008 | AJ33: https://www.lcsc.com/product-detail/C25741.html (read 2026-10-14)
A34: 26 | B34: RS1 | C34: 20mΩ | D34: R_0805_2012Metric | E34: C92740 | F34: MS05W2F200MT5E | G34: UNI-ROYAL | H34: 20 mOhm 1 % 0.5 W 0805 current sense (Kelvin) | I34: RS1: 20 milliohm current-sense resistor (measures the LED current). | J34: =LEN(B34)-LEN(SUBSTITUTE(B34,",",""))+1 -> 1 | K34: 2 | L34: Extended | M34: JLC page | N34: 4880 | O34: OK | P34: p0603 | Q34: =INDEX($C$52:$C$55,MATCH(P34,$B$52:$B$55,0)) -> 5 | R34: =J34*$C$5+Q34 -> 7 | S34: =INDEX($AD34:$AI34,MAX(1,COUNTIF($X34:$AC34,"<="&R34))) -> 0.0183 | T34: =R34*S34 -> 0.1281 | U34: =J34*$C$6+Q34 -> 10 | V34: =INDEX($AD34:$AI34,MAX(1,COUNTIF($X34:$AC34,"<="&U34))) -> 0.0183 | W34: =U34*V34 -> 0.183 | X34: 20 | Y34: 200 | Z34: 600 | AA34: 2000 | AD34: 0.0183 | AE34: 0.018 | AF34: 0.0177 | AG34: 0.0174 | AJ34: https://www.lcsc.com/product-detail/C92740.html (read 2026-10-14)
A35: 27 | B35: RT1 | C35: 100k B4250 | D35: R_0402_1005Metric | E35: C77130 | F35: NCP15WF104F03RC | G35: muRata | H35: NTC 100 k B25/50 4250 0402 (Murata NCP15WF104F03RC), PCB front edge | I35: RT1: 100 k NTC thermistor = temperature sensor at the front edge of the PCB. | J35: =LEN(B35)-LEN(SUBSTITUTE(B35,",",""))+1 -> 1 | K35: 2 | L35: Extended | M35: JLC page | N35: 298120 | O35: OK | P35: p0402 | Q35: =INDEX($C$52:$C$55,MATCH(P35,$B$52:$B$55,0)) -> 10 | R35: =J35*$C$5+Q35 -> 12 | S35: =INDEX($AD35:$AI35,MAX(1,COUNTIF($X35:$AC35,"<="&R35))) -> 0.0219 | T35: =R35*S35 -> 0.2628 | U35: =J35*$C$6+Q35 -> 15 | V35: =INDEX($AD35:$AI35,MAX(1,COUNTIF($X35:$AC35,"<="&U35))) -> 0.0219 | W35: =U35*V35 -> 0.3285 | X35: 20 | Y35: 200 | Z35: 600 | AA35: 2000 | AB35: 10000 | AC35: 20000 | AD35: 0.0219 | AE35: 0.0173 | AF35: 0.0147 | AG35: 0.0132 | AH35: 0.0119 | AI35: 0.0112 | AJ35: https://www.lcsc.com/product-detail/C77130.html (read 2026-10-14)
A36: 28 | B36: S2 | C36: MSK12C02 | D36: SW_SPDT_PCM12 | E36: C431540 | F36: MSK12C02 | G36: SHOU HAN | H36: SPDT slide switch, laser interlock (gate path only) | I36: S2: slide switch = the laser safety interlock. | J36: =LEN(B36)-LEN(SUBSTITUTE(B36,",",""))+1 -> 1 | K36: 7 | L36: Extended | M36: JLC page | N36: 170330 | O36: OK | P36: mod | Q36: =INDEX($C$52:$C$55,MATCH(P36,$B$52:$B$55,0)) -> 1 | R36: =J36*$C$5+Q36 -> 3 | S36: =INDEX($AD36:$AI36,MAX(1,COUNTIF($X36:$AC36,"<="&R36))) -> 0.0543 | T36: =R36*S36 -> 0.1629 | U36: =J36*$C$6+Q36 -> 6 | V36: =INDEX($AD36:$AI36,MAX(1,COUNTIF($X36:$AC36,"<="&U36))) -> 0.0543 | W36: =U36*V36 -> 0.3258 | X36: 10 | Y36: 100 | Z36: 300 | AA36: 3000 | AB36: 6000 | AC36: 9000 | AD36: 0.0543 | AE36: 0.0444 | AF36: 0.0394 | AG36: 0.0337 | AH36: 0.0323 | AI36: 0.0312 | AJ36: https://www.lcsc.com/product-detail/C431540.html (read 2026-10-14)
A37: 29 | B37: SW1,SW2,SW3 | C37: SKRKAEE020 | D37: SW_Push_SPST_NO_Alps_SKRK | E37: C115357 | F37: SKRKAEE020 | G37: ALPSALPINE | H37: SW1: main button: Alps top-push tact switch, 1.6 N, bottom side (ring centre); SW2: next button (>): Alps top-push tact switch, bottom side; SW3: previous button (<): Alps top-push tact switch, bottom side | I37: SW1, SW2, SW3: the three push buttons (main, next, previous). Alps top-push tact switch 3.9 x 2.9 x 2.0 mm, 1.6 N, 200k cycles, on the bottom side. | J37: =LEN(B37)-LEN(SUBSTITUTE(B37,",",""))+1 -> 3 | K37: 2 | L37: Extended | M37: JLC page | N37: unknown | O37: ESTIMATE, page not read: JLCPCB and LCSC pages of C115357 could not be read on 2026-10-18. Tiers = the sibling Alps SKRPABE010 (C115360) read on LCSC on 2026-10-16 (qty 10 $0.0759, qty 100 $0.0616). Stock unknown. Library type 'Extended' assumed (every Alps tact switch checked on JLCPCB is Extended). | P37: mod | Q37: =INDEX($C$52:$C$55,MATCH(P37,$B$52:$B$55,0)) -> 1 | R37: =J37*$C$5+Q37 -> 7 | S37: =INDEX($AD37:$AI37,MAX(1,COUNTIF($X37:$AC37,"<="&R37))) -> 0.0759 | T37: =R37*S37 -> 0.5313 | U37: =J37*$C$6+Q37 -> 16 | V37: =INDEX($AD37:$AI37,MAX(1,COUNTIF($X37:$AC37,"<="&U37))) -> 0.0759 | W37: =U37*V37 -> 1.2144 | X37: 10 | Y37: 100 | AD37: 0.0759 | AE37: 0.0616 | AJ37: ESTIMATE - LCSC and JLCPCB pages of C115357 could not be read on 2026-10-18. Tiers of the sibling C115360 (LCSC, read 2026-10-16): qty 10 $0.0759, qty 100 $0.0616.
A38: 30 | B38: U1 | C38: TP4057 | D38: SOT-23-6 | E38: C12044 | F38: TP4057-42-SOT26-R | G38: TOP POWER ASIC | H38: TP4057-42-SOT26-R 500 mA Li-ion linear charger (R3 3.3k = ~300 mA) | I38: U1: battery charger chip (500 mA linear Li-ion charger). | J38: =LEN(B38)-LEN(SUBSTITUTE(B38,",",""))+1 -> 1 | K38: 6 | L38: Extended | M38: JLC page | N38: 32025 | O38: OK | P38: semi | Q38: =INDEX($C$52:$C$55,MATCH(P38,$B$52:$B$55,0)) -> 2 | R38: =J38*$C$5+Q38 -> 4 | S38: =INDEX($AD38:$AI38,MAX(1,COUNTIF($X38:$AC38,"<="&R38))) -> 0.1426 | T38: =R38*S38 -> 0.5704 | U38: =J38*$C$6+Q38 -> 7 | V38: =INDEX($AD38:$AI38,MAX(1,COUNTIF($X38:$AC38,"<="&U38))) -> 0.1426 | W38: =U38*V38 -> 0.9982 | X38: 5 | Y38: 50 | Z38: 150 | AA38: 500 | AB38: 3000 | AC38: 6000 | AD38: 0.1426 | AE38: 0.1166 | AF38: 0.1036 | AG38: 0.0938 | AH38: 0.0761 | AI38: 0.0722 | AJ38: https://www.lcsc.com/product-detail/C12044.html (read 2026-10-14)
A39: 31 | B39: U2 | C39: TLV62585DRLR | D39: SOT-563 | E39: C485117 | F39: TLV62585DRLR | G39: Texas Instruments | H39: 3 A sync buck, 100 % duty mode, SOT-563 | I39: U2: 3 A buck converter that drives the LED. | J39: =LEN(B39)-LEN(SUBSTITUTE(B39,",",""))+1 -> 1 | K39: 6 | L39: Extended | M39: JLC page | N39: 925 | O39: LOW stock at LCSC (925 pcs) - fine for 5 boards, check at BOM upload. | P39: semi | Q39: =INDEX($C$52:$C$55,MATCH(P39,$B$52:$B$55,0)) -> 2 | R39: =J39*$C$5+Q39 -> 4 | S39: =INDEX($AD39:$AI39,MAX(1,COUNTIF($X39:$AC39,"<="&R39))) -> 0.261 | T39: =R39*S39 -> 1.044 | U39: =J39*$C$6+Q39 -> 7 | V39: =INDEX($AD39:$AI39,MAX(1,COUNTIF($X39:$AC39,"<="&U39))) -> 0.261 | W39: =U39*V39 -> 1.827 | X39: 5 | Y39: 50 | Z39: 150 | AA39: 500 | AB39: 3000 | AC39: 6000 | AD39: 0.261 | AE39: 0.2052 | AF39: 0.178 | AG39: 0.1537 | AH39: 0.147 | AI39: 0.143 | AJ39: https://www.lcsc.com/product-detail/C485117.html (read 2026-10-14)
A40: 32 | B40: U3 | C40: TLV333IDCKR | D40: SOT-353_SC-70-5 | E40: C181502 | F40: TLV333IDCKR | G40: Texas Instruments | H40: zero-drift op-amp SC-70-5 (DCK), powered from LED_EN | I40: U3: precision op-amp in the LED-current control loop. | J40: =LEN(B40)-LEN(SUBSTITUTE(B40,",",""))+1 -> 1 | K40: 5 | L40: Extended | M40: JLC page | N40: 18425 | O40: OK | P40: semi | Q40: =INDEX($C$52:$C$55,MATCH(P40,$B$52:$B$55,0)) -> 2 | R40: =J40*$C$5+Q40 -> 4 | S40: =INDEX($AD40:$AI40,MAX(1,COUNTIF($X40:$AC40,"<="&R40))) -> 0.3543 | T40: =R40*S40 -> 1.4172 | U40: =J40*$C$6+Q40 -> 7 | V40: =INDEX($AD40:$AI40,MAX(1,COUNTIF($X40:$AC40,"<="&U40))) -> 0.3543 | W40: =U40*V40 -> 2.4801 | X40: 5 | Y40: 50 | Z40: 150 | AA40: 500 | AB40: 3000 | AC40: 6000 | AD40: 0.3543 | AE40: 0.2788 | AF40: 0.2465 | AG40: 0.1927 | AH40: 0.1747 | AI40: 0.1639 | AJ40: https://www.lcsc.com/product-detail/C181502.html (read 2026-10-14)
A41: 33 | B41: U4 | C41: ESP32-C3-MINI-1-N4 | D41: ESP32-C3-MINI-1 | E41: C2838502 | F41: ESP32-C3-MINI-1-N4 | G41: Espressif | H41: ESP32-C3 BLE 5 / Wi-Fi module, 4 MB flash, PCB antenna (alt. -H4X C41349510) | I41: U4: the brain - ESP32-C3 module with Bluetooth LE / Wi-Fi, 4 MB flash and antenna. | J41: =LEN(B41)-LEN(SUBSTITUTE(B41,",",""))+1 -> 1 | K41: 53 | L41: Extended | M41: JLC page | N41: 8387 | O41: Marked NRND (not recommended for new designs) by Espressif; the successor ESP32-C3-MINI-1-H4X (C41349510) is the drop-in alternative if this one disappears. | P41: mod | Q41: =INDEX($C$52:$C$55,MATCH(P41,$B$52:$B$55,0)) -> 1 | R41: =J41*$C$5+Q41 -> 3 | S41: =INDEX($AD41:$AI41,MAX(1,COUNTIF($X41:$AC41,"<="&R41))) -> 3.0672 | T41: =R41*S41 -> 9.2016 | U41: =J41*$C$6+Q41 -> 6 | V41: =INDEX($AD41:$AI41,MAX(1,COUNTIF($X41:$AC41,"<="&U41))) -> 3.0672 | W41: =U41*V41 -> 18.4032 | X41: 1 | Y41: 10 | Z41: 30 | AA41: 100 | AB41: 650 | AC41: 1300 | AD41: 3.0672 | AE41: 2.7002 | AF41: 2.5127 | AG41: 2.1441 | AH41: 2.0536 | AI41: 2.0141 | AJ41: https://www.lcsc.com/product-detail/C2838502.html (read 2026-10-14)
A42: 34 | B42: U5 | C42: RT9080-33GJ5 | D42: TSOT-23-5 | E42: C841192 | F42: RT9080-33GJ5 | G42: Richtek | H42: 3.3 V 600 mA LDO, Iq 2 uA (EN tied to VIN) | I42: U5: 3.3 V voltage regulator for the ESP32 module. | J42: =LEN(B42)-LEN(SUBSTITUTE(B42,",",""))+1 -> 1 | K42: 5 | L42: Extended | M42: JLC page | N42: 27375 | O42: OK | P42: semi | Q42: =INDEX($C$52:$C$55,MATCH(P42,$B$52:$B$55,0)) -> 2 | R42: =J42*$C$5+Q42 -> 4 | S42: =INDEX($AD42:$AI42,MAX(1,COUNTIF($X42:$AC42,"<="&R42))) -> 0.1207 | T42: =R42*S42 -> 0.4828 | U42: =J42*$C$6+Q42 -> 7 | V42: =INDEX($AD42:$AI42,MAX(1,COUNTIF($X42:$AC42,"<="&U42))) -> 0.1207 | W42: =U42*V42 -> 0.8449 | X42: 5 | Y42: 50 | Z42: 150 | AA42: 500 | AB42: 3000 | AC42: 6000 | AD42: 0.1207 | AE42: 0.0982 | AF42: 0.087 | AG42: 0.0786 | AH42: 0.0613 | AI42: 0.058 | AJ42: https://www.lcsc.com/product-detail/C841192.html (read 2026-10-14)
B43: TOTAL per board / per order | J43: =SUM(J9:J42) -> 68 | K43: =SUMPRODUCT(J9:J42,K9:K42) -> 232 | T43: =SUM(T9:T42) -> 17.3151 | W43: =SUM(W9:W42) -> 32.7201
B44: Lines (unique LCSC numbers = feeder-fee count) | J44: =COUNTA(E9:E42) -> 34
B45: of which Extended library parts | J45: =COUNTIF(L9:L42,"Extended") -> 14
B46: of which Basic library parts | J46: =COUNTIF(L9:L42,"Basic") -> 20
B47: Extra pieces for placement loss, included in the totals above (USD) | T47: =SUMPRODUCT(Q9:Q42,S9:S42) -> 7.0451 | W47: =SUMPRODUCT(Q9:Q42,V9:V42) -> 7.0451
B50: Placement-loss classes (ESTIMATES - JLC publishes no table; the cart shows the real quantities)
B51: Class | C51: Extra pieces | D51: Applies to
B52: p0402 | C52: 10 | D52: 0402 resistors / capacitors / NTC (tiny, easily lost by the pick-and-place machine)
B53: p0603 | C53: 5 | D53: 0603 and 0805 capacitors, current-sense resistor
B54: semi | C54: 2 | D54: small semiconductors: MOSFETs, ICs, TVS diode, RGB LED
B55: mod | C55: 1 | D55: big or expensive parts: ESP32 module, USB-C socket, inductor, switches
B57: Parts without an LCSC number - NOT assembled by JLCPCB (hand-soldered wires)
B58: Ref | C58: Value | D58: Footprint | H58: Description
B59: J2 | C59: CELL | D59: WirePad_SMD_2_P3.0mm | H59: cell wire pads BAT+/BAT- (2 cells in parallel: 2 wires per pad)
B60: J3 | C60: LED | D60: WirePad_SMD_TopBottom_1.6x1.8 | H60: LED wire pads: LED+ top side, LED- bottom side (28 AWG PTFE to the DTP board)
B61: J5 | C61: LASER | D61: WirePad_SMD_2_P3.0mm_N | H61: laser module wire pads (+ nearer the front, 28 AWG)
B63: Bought parts (EXTERNAL_BOM in flashka_parts.py) - see sheet 'Bought parts'
B64: Ref | C64: What | H64: How it is bought
B65: D2 | C65: Luminus SST-20-W on 10 mm DTP copper board | H65: bought ready-made (AliExpress)
B66: BT1 | C66: 2 x LP601646 3.7 V LiPo with PCM and leads, in parallel | H66: bought (AliExpress)
B67: LS1 | C67: 6 x 12 mm laser module with driver, 3 V | H67: bought (AliExpress)

Sheet Housing
A1: Housing - aluminium tray + lid and stainless caps (JLCCNC), resin print kit (JLC3DP)
A2: Tray and lid are CNC-milled from aluminium 6061-T6 with bead blast + black anodize and laser marking at JLCCNC. The three caps (cap_main x1, cap_slide x2 per light) are turned from SUS304 stainless steel and bead blasted, also at JLCCNC. The RF window insert, LED spacer ring, antenna spacer with floor plug, light-pipe tube and the resin copies of the three caps are printed in translucent SLA resin 8001 at JLC3DP as ONE print kit: seven parts joined by 1 mm sprues, which you cut apart at home. JLCCNC and JLC3DP show their real price only after you upload the files, and JLCCNC publishes no per-part price at all, so every price on this sheet is an ESTIMATE made from the volume, the bounding box and the finish with the method written below. When you have the instant quote, type it into the 'real quote' cells (sections 6, 7 and 8): the workbook then uses your number.
A3: Geometry source: cad/housing_interface.json (version 0.6) + cad/*.stl. Files to upload: order_files/2_JLCCNC/ (JLCCNC) and order_files/3_JLC3DP/ (JLC3DP); the JLCCNC drawings there are cad/FlashKa_tray_drawing.pdf, FlashKa_lid_drawing.pdf, FlashKa_cap_main_drawing.pdf and FlashKa_cap_slide_drawing.pdf renamed to the names of their STEP files (FlashKa_tray.pdf, FlashKa_lid.pdf, FlashKa_cap_main.pdf, FlashKa_cap_slide.pdf).
A5: 1. Parts and geometry (volumes from housing_interface.json 'volumes_mm3', for the print kit and the laser sleeve from their STL files; boxes from 'tray_bbox' and the STL files)
A6: Part | B6: Process | C6: Box X (mm) | D6: Box Y (mm) | E6: Box Z (mm) | F6: Volume (mm3) | G6: Mass (g) | H6: Per light | I6: Spare per order | J6: File (STEP / STL) | K6: Note
A7: Tray (main body, 94.4 x 20 x 16 mm) | B7: CNC aluminium | C7: 94.4 | D7: 20 | E7: 16 | F7: 8401.2 | G7: 22.68 | H7: 1 | I7: 0 | J7: order_files/2_JLCCNC/FlashKa_tray.step + FlashKa_tray.pdf | K7: 4 x M1.6 lid threads + 1 x M2 laser set-screw thread, window and laser bores, cell bay, three floor holes for the caps and the tube, floor RF window, lanyard slot, skin seams (frames and stringers), laser marking of 3 faces (bottom, -Y, +Y).
A8: Lid (90.2 x 20 x 5.2 mm) | B8: CNC aluminium | C8: 90.2 | D8: 20 | E8: 5.2 | F8: 2643.3 | G8: 7.14 | H8: 1 | I8: 0 | J8: order_files/2_JLCCNC/FlashKa_lid.step + FlashKa_lid.pdf | K8: 1.5 mm plate with two hold-down bosses (up to 5.2 mm tall), 0.6 mm rabbet lip, 4 countersunk holes, RF-window pocket, skin seams and the label field (laser marking of the lid face). Thin parts are harder to clamp, hence the factor 1.30.
A9: Main cap, stainless SUS304 (head dia 5.8, flange dia 6.6, 6.6 x 6.6 x 7 mm) | B9: CNC stainless | C9: 6.6 | D9: 6.6 | E9: 7 | F9: 108.9 | G9: 0.86 | H9: 1 | I9: 1 | J9: order_files/2_JLCCNC/FlashKa_cap_main.step + FlashKa_cap_main.pdf | K9: Turned part with a domed head, bead blasted, no coating. 1 per light + 1 spare. Tiny: JLCCNC may refuse it by size (see section 10); the resin main cap of the print kit is the fallback.
A10: Slide cap, stainless SUS304 (head dia 3.4, flange dia 5.0, 5 x 5 x 7 mm) | B10: CNC stainless | C10: 5 | D10: 5 | E10: 7 | F10: 40 | G10: 0.32 | H10: 2 | I10: 1 | J10: order_files/2_JLCCNC/FlashKa_cap_slide.step + FlashKa_cap_slide.pdf | K10: Same turned part for the next and the previous button, bead blasted. 2 per light + 1 spare. The resin slide caps of the print kit are the fallback.
A11: Print kit = the 7 resin parts below on 1 mm sprues (ONE part at JLC3DP) | B11: SLA resin | C11: 57.2 | D11: 16.8 | E11: 14.15 | F11: 1576.2 | G11: 1.8 | H11: 1 | I11: 1 | J11: order_files/3_JLC3DP/FlashKa_print_kit.stl | K11: What you order at JLC3DP: the RF window insert, LED spacer ring, antenna spacer with floor plug, light-pipe tube, resin main cap and 2 resin slide caps joined by 1 mm sprues, because the RF window insert alone is below JLC3DP's minimum build size (5 x 5 x 5 mm or 10 x 2 x 2 mm); the other parts ride along, so that one part, one minimum price and one customs line cover all seven. One kit per light + one spare kit. Volume and box are measured from the kit's own STL; you cut the parts apart at home with flush cutters.
A12: RF window insert - in the print kit | B12: SLA resin | C12: 8.4 | D12: 15.5 | E12: 1.7 | F12: 184.1 | G12: 0.21 | H12: 0 | I12: 0 | J12: cad/FlashKa_rf_window.stl (geometry only - not uploaded, it is in the kit) | K12: Included in the print kit (cut apart at home). Translucent resin lets the Bluetooth signal out; glued into the lid with epoxy. Flange 0.8 mm thick. Alone it is below the minimum build size: that is why it is printed in the kit.
A13: LED spacer ring - in the print kit | B13: SLA resin | C13: 2.4 | D13: 10.1 | E13: 10.1 | F13: 83.9 | G13: 0.1 | H13: 0 | I13: 0 | J13: cad/FlashKa_spacer_ring.stl (geometry only - not uploaded, it is in the kit) | K13: Included in the print kit (cut apart at home). Ring OD 10.1 / ID 7.2 mm between the LED board and the glass window.
A14: Antenna spacer with floor plug - in the print kit | B14: SLA resin | C14: 6 | D14: 16.8 | E14: 14.15 | F14: 926.8 | G14: 1.07 | H14: 0 | I14: 0 | J14: cad/FlashKa_antenna_spacer.stl (geometry only - not uploaded, it is in the kit) | K14: Included in the print kit (cut apart at home). Keeps the cells away from the ESP32 antenna; its plug closes the floor RF window.
A15: Light-pipe tube - in the print kit | B15: SLA resin | C15: 8.8 | D15: 8.8 | E15: 8.2 | F15: 178.1 | G15: 0.2 | H15: 0 | I15: 0 | J15: cad/FlashKa_tube.stl (geometry only - not uploaded, it is in the kit) | K15: Included in the print kit (cut apart at home). Carries the light of the two ring LEDs round the main cap; OD 8.4, rim 8.8 mm, glued into the counterbore of the floor (clear epoxy, not cyanoacrylate).
A16: Main cap in resin (fallback of the steel cap) - in the print kit | B16: SLA resin | C16: 6.6 | D16: 6.6 | E16: 7 | F16: 108.9 | G16: 0.13 | H16: 0 | I16: 0 | J16: cad/FlashKa_cap_main.stl (geometry only - not uploaded, it is in the kit) | K16: Included in the print kit (cut apart at home). Same geometry as the steel main cap: fit check, or the replacement if the steel cap is refused or not wanted.
A17: Slide cap in resin, 2 per kit (fallback of the steel caps) - in the print kit | B17: SLA resin | C17: 5 | D17: 5 | E17: 7 | F17: 40 | G17: 0.05 | H17: 0 | I17: 0 | J17: cad/FlashKa_cap_slide.stl (geometry only - not uploaded, it is in the kit) | K17: Included in the print kit (cut apart at home). Two identical caps in each kit (next and previous button), same geometry as the steel slide cap.
A18: Laser sleeve (optional, separate print) | B18: SLA resin | C18: 10 | D18: 6 | E18: 5.97 | F18: 110.9 | G18: 0.1 | H18: 0 | I18: 0 | J18: order_files/3_JLC3DP/FlashKa_laser_sleeve.stl | K18: ONLY if your laser module is 4.5 mm instead of 6.0 mm: set 'Per light' to 1. Not part of the kit: it is a separate STL (order_files/3_JLC3DP/FlashKa_laser_sleeve.stl) and big enough to be printed on its own.
A20: 2. JLCCNC estimate - method (all inputs are ESTIMATES; JLCCNC publishes no price list, https://jlccnc.com/blog/cnc-machining-cost-factors)
A21: Cost of one aluminium part = aluminium (stock block weight x price) + machining (minutes x rate x complexity) + threads + finish + laser marking. Stock block = bounding box + allowance on every side. Machining minutes = material to remove / removal rate + minutes for fine features (grooves, holes, pockets: section 4). Per order you also pay set-ups (each re-clamping of the part), the anodizing lot fee and the marking set-up once. Calibrated in v0.5 so that one tray + lid costs about the same as the v0.4 estimate (tray $31, lid $12) plus finish and set-ups; v0.6 keeps these inputs and changes only what the new design changes (sections 4 and 5).
A22: Aluminium 6061 price (USD per kg) | B22: 8 | C22: USD per kg | D22: ESTIMATE: 6061-T6 plate/bar incl. cutting waste. JLCCNC publishes no price list. Source: https://jlccnc.com/blog/cnc-machining-cost-factors (read 2026-10-14)
A23: Aluminium density (g per cm3) | B23: 2.7 | C23: g per cm3 | D23: Density of 6061 aluminium.
A24: Stock allowance per side (mm) | B24: 2 | C24: mm per side | D24: ESTIMATE: stock block is the part's bounding box plus this on every side.
A25: Material removal rate (cm3 per minute) | B25: 6 | C25: cm3 per min | D25: ESTIMATE: material removal rate of a small 3-axis mill in aluminium.
A26: Machine time rate (USD per minute) | B26: 0.6 | C26: USD per min | D26: ESTIMATE: machine time rate (calibrated so that one tray+lid costs about what the v0.4 estimate gave: $31 + $12). Source: https://jlccnc.com/blog/cnc-machining-cost-factors (read 2026-10-14)
A27: Set-up cost (USD per set-up) | B27: 3.5 | C27: USD per set-up | D27: ESTIMATE: one-off cost per workpiece set-up (each re-clamping of the part).
A28: Tapping (USD per thread) | B28: 0.25 | C28: USD per thread | D28: ESTIMATE: tapping one M1.6 or M2 thread.
A29: V-groove machining time (minutes per metre) | B29: 6 | C29: min per metre | D29: ESTIMATE (new in v0.6): machine time per metre of V-groove (90 deg cutter, 0.25 mm deep, many short pieces and corner arcs). The SAME rate prices the v0.5 grooves that are removed and the v0.6 skin grooves that are added (section 4). Source: https://jlccnc.com/blog/cnc-machining-cost-factors (read 2026-10-16)
A30: Laser marking: 1 = ordered, 0 = not ordered | B30: 1 | C30: 1 or 0 | D30: v0.6: 1 = JLCCNC laser-marks the warning text and the artwork on 4 faces (lid, bottom, -Y side, +Y side). 0 = no laser marking (stick an adhesive label with the same text instead; section 10). v0.5 left the marking out of the estimate.
A31: Laser marking (USD per marked face) | B31: 2 | C31: USD per marked face | D31: ESTIMATE (new in v0.6): laser marking of one face of one part after anodising. JLCCNC lists laser marking as a finish but publishes no price. Faces per light: lid 1, tray 3 (bottom, -Y, +Y). Source: https://jlccnc.com/finishes (read 2026-10-16)
A32: Laser marking set-up (USD per order) | B32: 5 | C32: USD per order | D32: ESTIMATE (new in v0.6): one-off cost per order for loading the five DXF artworks and the marking set-up. Source: https://jlccnc.com/finishes (read 2026-10-16)
A34: 3. Surface finish choices at JLCCNC for aluminium (prices are ESTIMATES; https://jlccnc.com/finishes, read 2026-10-14 and again 2026-10-16)
A35: Finish | B35: Tray (USD per part) | C35: Lid (USD per part) | D35: Lot fee (USD per order) | E35: What you get
A36: As machined (no finish) | B36: 0 | C36: 0 | D36: 0 | E36: Tool marks visible, bare aluminium dulls and marks with fingerprints. Cheapest, fine for a fit test.
A37: Bead blast only | B37: 1.5 | C37: 1 | D37: 3 | E37: Uniform matt grey surface, hides tool marks. Not corrosion-protected.
A38: Black anodize only | B38: 2 | C38: 1.2 | D38: 8 | E38: Black coating on the machined surface (tool marks still visible); the drawings ask for type II, 8-12 um (JLCCNC range 8-25 um). Thickness changes the holes slightly: say so in the quote.
A39: Bead blast + black anodize | B39: 2.5 | C39: 1.5 | D39: 8 | E39: THE DESIGN CHOICE: matt black, scratch-resistant. On JLCCNC bead blast is not included in the plain anodize option - pick the combined option.
A40: Bead blast + clear anodize | B40: 2.5 | C40: 1.5 | D40: 8 | E40: Silver matt aluminium look, protected.
A41: Chosen finish (drop-down) | B41: Bead blast + black anodize | E41: Pick the finish here; the tray/lid/lot prices below follow. The design assumes 'Bead blast + black anodize' (type II, 8-12 um on the drawings; JLCCNC range 8-25 um). The V grooves of the skin are 0.25 mm deep and stay visible after blasting and anodizing. The stainless caps are bead blasted only (JLCCNC offers no anodizing, passivation or polishing for stainless): their price is in section 7.
A42: Finish cost per tray (USD) | B42: =INDEX($B$36:$B$40,MATCH($B$41,$A$36:$A$40,0)) -> 2.5
A43: Finish cost per lid (USD) | B43: =INDEX($C$36:$C$40,MATCH($B$41,$A$36:$A$40,0)) -> 1.5
A44: Anodizing lot fee per order (USD) | B44: =INDEX($D$36:$D$40,MATCH($B$41,$A$36:$A$40,0)) -> 8
A46: 4. Fine-feature time of the aluminium parts - what changed from v0.5 (ESTIMATES; the v0.6 skin adds V-groove seams and marking, the knurl and the side grooves are gone)
A47: v0.5 priced all fine work as one lump per part (tray 36 min, lid 8 min). v0.6 keeps that lump, takes out the features that no longer exist and adds the new ones. V-groove work is counted in millimetres at ONE rate (minutes per metre, section 2) for the grooves that go and the grooves that come, so the groove part of the change follows the real geometry (the skin lengths are read from housing_interface.json 'skin_layout'). Other changes are typed-in minutes. Laser marking is a separate cost (section 5).
A48: Feature | B48: Tray (mm or min) | C48: Lid (mm or min) | D48: Unit | E48: Tray (min) | F48: Lid (min) | G48: Basis
A49: v0.5 fine-feature time (one lump per part, from the v0.5 workbook) | B49: 36 | C49: 8 | D49: min | E49: =B49 -> 36 | F49: =C49 -> 8 | G49: Tray 36 min = diamond knurl on the bottom, four side grooves, V ring at the lid seam, thumb dish, lanyard slot and the holes. Lid 8 min = four countersunk holes, RF-window pocket and the knurl panel. Unchanged v0.5 ESTIMATE.
A50: minus the v0.5 diamond knurl (V-groove lines) | B50: -717 | C50: -717 | D50: mm of V-groove | E50: =B50/1000*$B$29 -> -4.302 | F50: =C50/1000*$B$29 -> -4.302 | G50: Knurl 41 x 12.4 mm, pitch 1.6 mm = 613 mm of lines + 103 mm of border = 717 mm on the tray bottom and 717 mm on the lid. Gone in v0.6.
A51: minus the four v0.5 side grooves | B51: -164 | C51: 0 | D51: mm of V-groove | E51: =B51/1000*$B$29 -> -0.984 | F51: =C51/1000*$B$29 -> 0 | G51: 2 per side x 2 sides x 41 mm. Gone in v0.6 (the side stringers of the skin take their place).
A52: plus the v0.6 skin seams (frames and stringers, V 90 deg, 0.25 deep) | B52: 646.5 | C52: 220.2 | D52: mm of V-groove | E52: =B52/1000*$B$29 -> 3.879 | F52: =C52/1000*$B$29 -> 1.3212 | G52: Length of the 19 entries of 'skin_layout' in housing_interface.json (6 frames in 11 pieces, 8 stringers): frames wrap round the section, so the lid takes only the part on its top, corners and 0.6 mm lip, plus the two top stringers; the rest is in the tray. The V ring at the lid front (v0.5 too) stays in the lump.
A53: plus the floor holes: main bore 8.45 with counterbore 8.85, two slide holes 3.6 with 0.2 mm chamfer | B53: 3 | C53: 0 | D53: min | E53: =B53 -> 3 | F53: =C53 -> 0 | G53: 3 stepped or chamfered holes, about 1 min each (new in v0.6: the push buttons are on the bottom face).
A54: plus the floor RF window 5.1 x 14.0 mm (through the 1.5 mm floor) | B54: 1 | C54: 0 | D54: min | E54: =B54 -> 1 | F54: =C54 -> 0 | G54: Rounded-rectangle opening, closed by the plug of the antenna spacer.
A55: plus the 0.6 mm lid rabbet and the 0.3 mm gussets in the cavity corners | B55: 1.5 | C55: 1 | D55: min | E55: =B55 -> 1.5 | F55: =C55 -> 1 | G55: Contour pass round the opening of the tray (about 190 mm) and the lip on the underside of the lid, so that the skin seams cross the joint on the flat side.
A56: plus the two hold-down bosses under the lid (8.8 x 12.4 x 1.3 and 3.7 x 3.2 x 3.7 mm) | B56: 0 | C56: 1.5 | D56: min | E56: =B56 -> 0 | F56: =C56 -> 1.5 | G56: The lid is now a 5.2 mm tall part: the bulk removal is in 'material to remove', the small contours of the bosses are fine work.
A57: minus the S1 hole, thumb dish and ledge gap (S1 is removed) | B57: -2 | C57: 0 | D57: min | E57: =B57 -> -2 | F57: =C57 -> 0 | G57: Side-button features of v0.5 that no longer exist.
A58: Fine-feature time, v0.6 (min) | E58: =SUM(E49:E57) -> 38.093 | F58: =SUM(F49:F57) -> 7.5192 | G58: v0.5 had 36.0 min (tray) and 8.0 min (lid). Total V-groove length: v0.5 1598 mm, v0.6 867 mm (tray 646 + lid 220).
A60: 5. JLCCNC estimate - one aluminium part
A61: Step | B61: Tray | C61: Lid | D61: How it is computed
A62: Stock block volume (cm3) | B62: =($C$7+2*$B$24)*($D$7+2*$B$24)*($E$7+2*$B$24)/1000 -> 47.232 | C62: =($C$8+2*$B$24)*($D$8+2*$B$24)*($E$8+2*$B$24)/1000 -> 20.79936 | D62: (X + 2 x allowance) x (Y + 2 x allowance) x (Z + 2 x allowance) / 1000. The v0.6 lid is 5.2 mm tall (hold-down bosses), so its block is much bigger than the 1.5 mm plate of v0.5.
A63: Part volume (cm3) | B63: =$F$7/1000 -> 8.4012 | C63: =$F$8/1000 -> 2.6433 | D63: volume / 1000
A64: Material to remove (cm3) | B64: =B62-B63 -> 38.8308 | C64: =C62-C63 -> 18.15606 | D64: stock block - part
A65: Aluminium cost (USD) | B65: =B62*$B$23/1000*$B$22 -> 1.0202112 | C65: =C62*$B$23/1000*$B$22 -> 0.44926618 | D65: stock volume x density / 1000 x price per kg (you pay for the whole block)
A66: Fine-feature time (min) | B66: =$E$58 -> 38.093 | C66: =$F$58 -> 7.5192 | D66: from section 4 (v0.5: tray 36.0, lid 8.0)
A67: Machining time (min) | B67: =B64/$B$25+B66 -> 44.5648 | C67: =C64/$B$25+C66 -> 10.54521 | D67: material to remove / removal rate + fine-feature time
A68: Complexity factor | B68: 1.1 | C68: 1.3 | D68: ESTIMATE, v0.5 -> v0.6: tray 1.00 -> 1.10, because the frames of the skin wrap round the rounded corners and the two sides (indexed or 4th-axis work), where v0.5 had four straight side grooves; lid 1.25 -> 1.30, a 1.5 mm plate that now also carries bosses up to 5.2 mm tall and a 0.6 mm lip (clamping, vibration)
A69: Machining cost (USD) | B69: =B67*$B$26*B68 -> 29.412768 | C69: =C67*$B$26*C68 -> 8.2252638 | D69: minutes x rate x complexity factor
A70: Threads to cut (number) | B70: 5 | C70: 0 | D70: Tray: 4 x M1.6 (lid screws) + 1 x M2 (laser set screw). Lid: none (clearance holes).
A71: Tapping cost (USD) | B71: =B70*$B$28 -> 1.25 | C71: =C70*$B$28 -> 0 | D71: threads x cost per thread
A72: Finish cost per part (USD) | B72: =$B$42 -> 2.5 | C72: =$B$43 -> 1.5 | D72: from section 3 (chosen finish)
A73: Faces to laser-mark (number) | B73: 3 | C73: 1 | D73: Tray: bottom, -Y side (USB-C side), +Y side (S2 side) = FlashKa_marking_bottom / _minus_y / _plus_y.dxf. Lid: top face = FlashKa_marking_lid_class2.dxf (or _class3R.dxf for a module above 1 mW).
A74: Laser marking cost (USD) | B74: =$B$30*B73*$B$31 -> 6 | C74: =$B$30*C73*$B$31 -> 2 | D74: marking switch x faces x cost per face (the set-up is paid once per order, section 6)
A75: Variable cost per part (USD) | B75: =B65+B69+B71+B72+B74 -> 40.182979 | C75: =C65+C69+C71+C72+C74 -> 12.17453 | D75: aluminium + machining + tapping + finish + laser marking
A76: Set-ups (number) | B76: 5 | C76: 3 | D76: ESTIMATE, v0.5 -> v0.6: tray 3 -> 5 (top, bottom, -Y side, +Y side, ends), lid 2 -> 3 (top, bottom, sides and lip); the skin needs the side faces
A77: Set-up cost per order (USD) | B77: =B76*$B$27 -> 17.5 | C77: =C76*$B$27 -> 10.5 | D77: set-ups x set-up cost, paid once per order
A79: 6. JLCCNC total for the order - tray and lid (aluminium)
B80: Scenario A | C80: Scenario B | D80: Note
A81: Lights you build | B81: =Summary!$B$7 -> 1 | C81: =Summary!$B$8 -> 5
A82: Tray pieces ordered = lights x per light + spare | B82: =B81*$H$7+$I$7 -> 1 | C82: =C81*$H$7+$I$7 -> 5
A83: Lid pieces ordered = lights x per light + spare | B83: =B81*$H$8+$I$8 -> 1 | C83: =C81*$H$8+$I$8 -> 5
A84: Variable cost (pieces x cost per part) | B84: =B82*$B$75+B83*$C$75 -> 52.357509 | C84: =C82*$B$75+C83*$C$75 -> 261.78755
A85: Set-ups + anodizing lot fee + marking set-up (once per order) | B85: =$B$77+$C$77+$B$44+$B$30*$B$32 -> 41 | C85: =$B$77+$C$77+$B$44+$B$30*$B$32 -> 41
A86: ESTIMATE of tray + lid (USD) | B86: =B84+B85 -> 93.357509 | C86: =C84+C85 -> 302.78755 | D86: Ordering 5 sets at once is much cheaper per set than 1 set, because the set-ups, the anodizing lot fee and the marking set-up are paid once.
A87: REAL instant-quote price for tray + lid (type it in, USD incl. finish and marking, without shipping) | D87: Upload FlashKa_tray.step + FlashKa_tray.pdf and FlashKa_lid.step + FlashKa_lid.pdf from order_files/2_JLCCNC/ (each drawing PDF has the name of its STEP file) at https://jlccnc.com/cnc-machining-quote and type the price shown for your quantity here. Leave empty to use the estimate.
A88: Tray + lid used in the totals (USD) | B88: =IF(ISNUMBER(B87),B87,B86) -> 93.357509 | C88: =IF(ISNUMBER(C87),C87,C86) -> 302.78755
A90: 7. JLCCNC stainless caps (SUS304, turned, bead blasted) - ESTIMATE; fallback: the resin caps that are already in the print kit (cost 0 extra)
A91: JLCCNC lists SUS304 as a CNC material (the only stainless grade) with bead blasting, brushing and laser marking as finishes; passivation and polishing are not offered for stainless (https://jlccnc.com/cnc-machining, https://jlccnc.com/finishes, read 2026-10-16). It publishes NO per-part price: only 'CNC milling/turning from $5.00' (https://jlccnc.com/) and a minimum order of one piece. The caps are tiny turned parts (flange dia 6.6 and 5.0 mm, 7.0 mm long, domed heads dia 5.8 and 3.4 mm): the price is dominated by the set-up and programming of each part number, so the estimate is a first-piece price plus a lower price for every further piece of the same cap in the same order. Instant quotes work up to 20 pieces.
A92: Stainless caps ordered: 1 = yes, 0 = use the resin caps of the kit | B92: 1 | C92: 1 or 0 | D92: v0.6: 1 = order the three caps in SUS304 stainless from JLCCNC (cap_main x1 and cap_slide x2 per light + 1 spare of each, bead blasted). 0 = use the resin caps of the print kit instead: no extra cost (the kit holds them in both cases).
A93: First piece of one cap type (USD) | B93: 8 | C93: USD per cap type | D93: ESTIMATE (new in v0.6): first piece of one cap type, set-up, programming and bead blast included. JLCCNC publishes no per-part price, only 'CNC milling/turning from $5.00'; tiny turned stainless parts usually quote at $5-15 for one piece. Source: https://jlccnc.com/ (read 2026-10-16)
A94: Each further piece of the same cap type (USD) | B94: 4 | C94: USD per further piece | D94: ESTIMATE (new in v0.6): each further piece of the same cap type in the same order (set-up already paid), about half of the first piece. Source: https://jlccnc.com/ (read 2026-10-16)
A95: Cap | B95: Pieces A | C95: Cost A (USD) | D95: Pieces B | E95: Cost B (USD) | F95: How
A96: Main cap, stainless SUS304 (head dia 5.8, flange dia 6.6, 6.6 x 6.6 x 7 mm) | B96: =Summary!$B$7*$H$9+$I$9 -> 2 | C96: =$B$92*($B$93+MAX(0,B96-1)*$B$94) -> 12 | D96: =Summary!$B$8*$H$9+$I$9 -> 6 | E96: =$B$92*($B$93+MAX(0,D96-1)*$B$94) -> 28 | F96: pieces = lights x per light + spare (section 1); cost = switch x (first piece + (pieces - 1) x further piece)
A97: Slide cap, stainless SUS304 (head dia 3.4, flange dia 5.0, 5 x 5 x 7 mm) | B97: =Summary!$B$7*$H$10+$I$10 -> 3 | C97: =$B$92*($B$93+MAX(0,B97-1)*$B$94) -> 16 | D97: =Summary!$B$8*$H$10+$I$10 -> 11 | E97: =$B$92*($B$93+MAX(0,D97-1)*$B$94) -> 48 | F97: pieces = lights x per light + spare (section 1); cost = switch x (first piece + (pieces - 1) x further piece)
A98: ESTIMATE of the stainless caps (USD) | C98: =SUM(C96:C97) -> 28 | E98: =SUM(E96:E97) -> 76
A99: REAL instant-quote price for the caps (type it in, USD, without shipping) | F99: Upload FlashKa_cap_main.step + FlashKa_cap_main.pdf and FlashKa_cap_slide.step + FlashKa_cap_slide.pdf (order_files/2_JLCCNC/), material SUS304, finish bead blasting, and type the price shown for the pieces above. If the instant quote refuses the parts by size, leave this empty and use another CNC service or the resin caps (section 10).
A100: Stainless caps used in the totals (USD) | C100: =IF($B$92=0,0,IF(ISNUMBER(C99),C99,C98)) -> 28 | E100: =IF($B$92=0,0,IF(ISNUMBER(E99),E99,E98)) -> 76
A101: JLCCNC ORDER used in the totals: tray + lid + caps (USD) | C101: =$B$88+$C$100 -> 121.35751 | E101: =$C$88+$E$100 -> 378.78755 | F101: Scenario A in column C, scenario B in column E.
A103: 8. JLC3DP print kit (SLA 8001 translucent) - ESTIMATE; real price from the instant quote after uploading order_files/3_JLC3DP/FlashKa_print_kit.stl (https://jlc3dp.com/3d-printing-quote)
A104: Resin price (USD per cm3) | B104: 0.3 | C104: USD per cm3 | D104: ESTIMATE from the headline 'SLA from $0.30'. The instant quote shows the real price per part. Source: https://jlc3dp.com/ (read 2026-10-14)
A105: Minimum price per part (USD) | B105: 0.6 | C105: USD per part | D105: ESTIMATE: minimum price of one printed part. The print kit (the seven resin parts on sprues, ONE part for JLC3DP) and the laser sleeve are so small that this minimum decides. Source: https://jlc3dp.com/3d-printing-quote (read 2026-10-14)
A106: Part | B106: Volume (cm3) | C106: Unit price (USD) | D106: Qty A | E106: Cost A (USD) | F106: Qty B | G106: Cost B (USD) | H106: Size check | I106: Note. Size check: JLC3DP builds parts with a box of at least 5 x 5 x 5 mm or 10 x 2 x 2 mm (red = a part that is too small and is ordered on its own)
A107: Print kit = the 7 resin parts below on 1 mm sprues (ONE part at JLC3DP) | B107: =$F$11/1000 -> 1.5762 | C107: =MAX($B$105,$B$104*B107) -> 0.6 | D107: =Summary!$B$7*$H$11+$I$11 -> 2 | E107: =C107*D107 -> 1.2 | F107: =Summary!$B$8*$H$11+$I$11 -> 6 | G107: =C107*F107 -> 3.6 | H107: =IF(OR(MIN($C$11,$D$11,$E$11)>=5,AND(MAX($C$11,$D$11,$E$11)>=10,MIN($C$11,$D$11,$E$11)>=2)),"OK","TOO SMALL") -> OK | I107: Quantity = lights x per light + spare (section 1). What you order at JLC3DP: the RF window insert, LED spacer ring, antenna spacer with floor plug, light-pipe tube, resin main cap and 2 resin slide caps joined by 1 mm sprues, because the RF window insert alone is below JLC3DP's minimum build size (5 x 5 x 5 mm or 10 x 2 x 2 mm); the other parts ride along, so that one part, one minimum price and one customs line cover all seven. One kit per light + one spare kit. Volume and box are measured from the kit's own STL; you cut the parts apart at home with flush cutters.
A108: RF window insert - in the print kit | B108: =$F$12/1000 -> 0.1841 | C108: =MAX($B$105,$B$104*B108) -> 0.6 | D108: =Summary!$B$7*$H$12+$I$12 -> 0 | E108: =C108*D108 -> 0 | F108: =Summary!$B$8*$H$12+$I$12 -> 0 | G108: =C108*F108 -> 0 | H108: =IF(OR(MIN($C$12,$D$12,$E$12)>=5,AND(MAX($C$12,$D$12,$E$12)>=10,MIN($C$12,$D$12,$E$12)>=2)),"OK","TOO SMALL") -> TOO SMALL | I108: Quantity = lights x per light + spare (section 1). Included in the print kit (cut apart at home). Translucent resin lets the Bluetooth signal out; glued into the lid with epoxy. Flange 0.8 mm thick. Alone it is below the minimum build size: that is why it is printed in the kit.
...

Sheet Bought parts
A1: Bought parts and consumables (not on the JLCPCB board)
A2: Everything the PCB order does not contain: cells, LED board, laser, window, screws, wire, tapes, the two silicone hold-down pads (new in v0.6), adhesives. Prices are typical AliExpress/web-shop prices found with search on 2026-10-14 (AliExpress item pages cannot be read automatically, so the prices come from search-result snippets; v0.6 kept them, and the new pads and adhesive are typical-price ESTIMATES that were not looked up) - they are ESTIMATES, change the blue number when you see a real listing. 'Packs' = how many packs you must buy (rounded up): quantity needed = lights x 'per light' + 'fixed per order' (spares, one roll of tape, one sheet of pad material...).
A3: Prices exclude VAT and shipping here; both are added on sheet 'Hidden costs' (21 % VAT, shipping per parcel, EUR 3 flat duty per parcel).
A5: # | B5: Item | C5: Used for | D5: Exact spec that matters | E5: Search term (AliExpress / web shop) | F5: Price per pack (USD) | G5: Pack size | H5: Pack unit | I5: Per light | J5: Fixed per order | K5: Packs A | L5: Cost A (USD) | M5: Packs B | N5: Cost B (USD) | O5: Category | P5: Price basis (source, date) | Q5: Link example
A6: 1 | B6: LiPo cell LP601646 with protection board (PCM) and wire leads | C6: Power. Two cells in parallel lie flat on top of each other in the cell bay of the tray, protection-board end towards the PCB (BT1). | D6: 3.7 V lithium-polymer pouch cell, ~400 mAh each (pair ~800 mAh). Size LP601646 = about 6.0 x 16 x 46 mm; the bay takes 6.0 x 16 x 47 mm INCLUDING the protection board, so a cell with a bigger board will not fit. Must already have the protection board (PCM) and two wire leads (red +, black -). Never use a bare cell. Buy both cells of a light together from one seller. Check the listed continuous discharge rating: >= 2C (0.8 A per cell, the Balanced profile allows 1.6 A for the pair), >= 3C for the Extreme profile (2.6 A) - docs/ble_protocol.md lists the limits. | E6: LP601646 400mAh 3.7V lipo battery with protection board wire | F6: 4.5 | G6: 1 | H6: cell | I6: 2 | J6: 1 | K6: =ROUNDUP(ROUND((Summary!$B$7*I6+J6)/G6,9),0) -> 3 | L6: =K6*F6 -> 13.5 | M6: =ROUNDUP(ROUND((Summary!$B$8*I6+J6)/G6,9),0) -> 11 | N6: =M6*F6 -> 49.5 | O6: Part | P6: ESTIMATE. AliExpress search result 2026-10-14: US $4.76 for a 400 mAh 071740 cell with PCM (item 32662761434) - same price class but a DIFFERENT size (7 x 17 x 40 mm, too thick for this bay); search for LP601646 by name. | Q6: https://www.aliexpress.com/item/32662761434.html
A7: 2 | B7: Luminus SST-20-W LED on a 10 mm round DTP copper board (ready-made) | C7: The main white light (D2): sits in the head behind the glass window, wires go to pads J3. | D7: Round board 10.0 mm diameter x 1.6 mm thick (the head bore takes 10.0 + 0.2 mm), copper-core 'DTP' (direct thermal path) so the heat leaves through the copper, emitter Luminus SST-20 white (5000-6500 K), two solder pads for wires. If the seller only has 16 or 20 mm boards the tray will NOT fit - ask for 10 mm. | E7: SST-20 DTP 10mm led board copper | F7: 5.4 | G7: 1 | H7: board | I7: 1 | J7: 1 | K7: =ROUNDUP(ROUND((Summary!$B$7*I7+J7)/G7,9),0) -> 2 | L7: =K7*F7 -> 10.8 | M7: =ROUNDUP(ROUND((Summary!$B$8*I7+J7)/G7,9),0) -> 6 | N7: =M7*F7 -> 32.4 | O7: Part | P7: ESTIMATE. AliExpress search result 2026-10-14: US $5.42 for an SST-20 6500K on a 16/20 mm DTP board (item 32884236179); a 10 mm board may cost a little more or be rarer. | Q7: https://www.aliexpress.com/item/32884236179.html
A8: 3 | B8: Green laser module 520 nm, Class 2 (<= 1 mW), 6 x 12 mm, driver built in | C8: The laser pointer (LS1). Switched by Q1 and the slide-switch interlock S2; wires go to pads J5. | D8: Body 6.0 mm diameter x 12 mm long (the tray bore is 6.1 mm), 520 nm green, output power <= 1 mW (Class 2, see the explanation below the table), constant-power (APC) driver inside, 3 V class supply (design note LS1 '3 V'; check that the seller's range includes 3.0-4.2 V), two wire leads. A 4.5 mm module needs the printed sleeve. Ask the seller for a measured output power. | E8: 520nm green laser module 6x12mm 1mW APC | F8: 23.5 | G8: 1 | H8: module | I8: 1 | J8: 0 | K8: =ROUNDUP(ROUND((Summary!$B$7*I8+J8)/G8,9),0) -> 1 | L8: =K8*F8 -> 23.5 | M8: =ROUNDUP(ROUND((Summary!$B$8*I8+J8)/G8,9),0) -> 5 | N8: =M8*F8 -> 117.5 | O8: Part | P8: ESTIMATE. AliExpress search result 2026-10-14: US $23.5 for a 6 mm 520 nm 1 mW APC module (item 32869119160). | Q8: https://www.aliexpress.com/item/32869119160.html
A9: 4 | B9: Round glass window 10.0 x 1.0 mm (flat, clear) | C9: Closes the head in front of the LED (window 10.0 mm, 1.0 mm thick, sits 0.2 mm recessed). | D9: Flat round glass disc 10.0 mm diameter (tolerance -0.1 mm, the bore is 10.2 mm), 1.0 mm thick, clear or anti-reflection coated; no curved lens. | E9: 10mm x 1mm round glass lens flat flashlight | F9: 2.95 | G9: 5 | H9: 5 pcs | I9: 1 | J9: 1 | K9: =ROUNDUP(ROUND((Summary!$B$7*I9+J9)/G9,9),0) -> 1 | L9: =K9*F9 -> 2.95 | M9: =ROUNDUP(ROUND((Summary!$B$8*I9+J9)/G9,9),0) -> 2 | N9: =M9*F9 -> 5.9 | O9: Part | P9: ESTIMATE. AliExpress search result 2026-10-14: US $2.95 for 5 pcs flat glass lens (item 4001014613249); the exact size of that listing was not verified. | Q9: https://www.aliexpress.com/item/4001014613249.html
A10: 5 | B10: Screw M1.6 x 4 mm, countersunk, stainless (lid) | C10: Four screws hold the lid (two at the front, two at the rear). | D10: ISO 7046 / DIN 965 M1.6 x 4, A2 stainless, head diameter <= 3.1 mm (countersink 3.3 mm). Tray thread M1.6 (tap drill 1.25 mm), lid clearance hole 1.8 mm. Phillips or hex head - match your screwdriver. Buy extra: they are tiny and get lost. | E10: M1.6x4 countersunk screw A2 stainless 100pcs | F10: 2 | G10: 100 | H10: 100 pcs | I10: 4 | J10: 10 | K10: =ROUNDUP(ROUND((Summary!$B$7*I10+J10)/G10,9),0) -> 1 | L10: =K10*F10 -> 2 | M10: =ROUNDUP(ROUND((Summary!$B$8*I10+J10)/G10,9),0) -> 1 | N10: =M10*F10 -> 2 | O10: Part | P10: ESTIMATE. AliExpress search result 2026-10-14: US $1.5 for 100 pcs M1.6 x 3 countersunk (item 32917852857); M1.6 x 4 priced slightly higher. | Q10: https://www.aliexpress.com/item/32917852857.html
A11: 6 | B11: Set screw M2 x 2 mm, cup point, hex socket | C11: Locks the laser module in its bore from the bottom face (thread length 2.85 mm). | D11: M2 x 2 (M2 x 2.5 also fits), cup point, A2 or steel, hex socket for a 0.9 mm hex key. The thread is only 2.85 mm long: an M2 x 3 or longer screw sticks out of the bottom face when it clamps the module. The tray tap is 1.6 mm. | E11: M2x2 set screw cup point hex socket | F11: 2 | G11: 50 | H11: 50 pcs | I11: 1 | J11: 4 | K11: =ROUNDUP(ROUND((Summary!$B$7*I11+J11)/G11,9),0) -> 1 | L11: =K11*F11 -> 2 | M11: =ROUNDUP(ROUND((Summary!$B$8*I11+J11)/G11,9),0) -> 1 | N11: =M11*F11 -> 2 | O11: Part | P11: ESTIMATE (typical price of a 50-pack set screw listing). | Q11: https://www.aliexpress.com/wholesale?SearchText=M2x2+set+screw+cup+point
A12: 7 | B12: Split ring 20-25 mm, stainless | C12: Key ring through the lanyard slot in the tail (slot 4.4 x 7.6 mm). | D12: Stainless split ring, inner diameter 20-25 mm, wire thickness <= 3 mm so that it fits the 4.4 mm slot. | E12: split key ring 25mm stainless steel | F12: 2 | G12: 20 | H12: 20 pcs | I12: 1 | J12: 1 | K12: =ROUNDUP(ROUND((Summary!$B$7*I12+J12)/G12,9),0) -> 1 | L12: =K12*F12 -> 2 | M12: =ROUNDUP(ROUND((Summary!$B$8*I12+J12)/G12,9),0) -> 1 | N12: =M12*F12 -> 2 | O12: Part | P12: ESTIMATE (typical price of a 20-pack key ring listing). | Q12: https://www.aliexpress.com/wholesale?SearchText=split+key+ring+25mm+stainless
A13: 8 | B13: PTFE wire 28 AWG, red + black, 5 m of each | C13: LED wires (J3 to the LED board), laser wires (J5), cell wires (J2). About 0.3 m per light. | D13: 28 AWG (about 0.08 mm2) tinned copper with PTFE (Teflon) insulation, outer diameter <= 0.8 mm (the LED wire hole in the tray is 1.3 mm). PTFE does not melt when you solder. Keep the LED leads short (60 mm). | E13: 28AWG PTFE wire red black 5m | F13: 6 | G13: 5 | H13: 5 m | I13: 0.3 | J13: 0.7 | K13: =ROUNDUP(ROUND((Summary!$B$7*I13+J13)/G13,9),0) -> 1 | L13: =K13*F13 -> 6 | M13: =ROUNDUP(ROUND((Summary!$B$8*I13+J13)/G13,9),0) -> 1 | N13: =M13*F13 -> 6 | O13: Consumable | P13: ESTIMATE (typical price of a 5 m PTFE wire listing). | Q13: https://www.aliexpress.com/wholesale?SearchText=28AWG+PTFE+wire+red+black
A14: 9 | B14: Thermal transfer tape 0.15 mm, double-sided, 1 roll | C14: Sticks the LED board to the floor of the head and carries the heat into the aluminium (a disc of 10 mm). | D14: Thickness 0.15 mm (the design uses 0.15 mm), thermally conductive double-sided adhesive, >= 1 W/mK, width >= 10 mm (3M 8805 class). | E14: thermal conductive double sided tape 0.15mm | F14: 3.79 | G14: 1 | H14: roll | I14: 0 | J14: 1 | K14: =ROUNDUP(ROUND((Summary!$B$7*I14+J14)/G14,9),0) -> 1 | L14: =K14*F14 -> 3.79 | M14: =ROUNDUP(ROUND((Summary!$B$8*I14+J14)/G14,9),0) -> 1 | N14: =M14*F14 -> 3.79 | O14: Consumable | P14: AliExpress search result 2026-10-14: US $3.79 for thermal tape (item 33014898122). | Q14: https://www.aliexpress.com/item/33014898122.html
A15: 10 | B15: Kapton (polyimide) tape 5-10 mm wide, 1 roll | C15: Insulates bare metal near the PCB and the laser module's back. | D15: Polyimide tape (amber), 5-10 mm wide, about 0.06 mm thick, heat resistant. | E15: kapton tape 10mm polyimide | F15: 2.5 | G15: 1 | H15: roll | I15: 0 | J15: 1 | K15: =ROUNDUP(ROUND((Summary!$B$7*I15+J15)/G15,9),0) -> 1 | L15: =K15*F15 -> 2.5 | M15: =ROUNDUP(ROUND((Summary!$B$8*I15+J15)/G15,9),0) -> 1 | N15: =M15*F15 -> 2.5 | O15: Consumable | P15: ESTIMATE (typical price). | Q15: https://www.aliexpress.com/wholesale?SearchText=kapton+tape+10mm
A16: 11 | B16: Double-sided foam tape 1 mm x 10 mm, 1 roll | C16: Holds the two cells in the bay without squeezing them. | D16: Soft foam core, about 1 mm thick, 10 mm wide, double-sided adhesive. | E16: double sided foam tape 1mm 10mm | F16: 2.5 | G16: 1 | H16: roll | I16: 0 | J16: 1 | K16: =ROUNDUP(ROUND((Summary!$B$7*I16+J16)/G16,9),0) -> 1 | L16: =K16*F16 -> 2.5 | M16: =ROUNDUP(ROUND((Summary!$B$8*I16+J16)/G16,9),0) -> 1 | N16: =M16*F16 -> 2.5 | O16: Consumable | P16: ESTIMATE (typical price). | Q16: https://www.aliexpress.com/wholesale?SearchText=double+sided+foam+tape+1mm
A17: 12 | B17: Clear two-part epoxy, 5 minute, small syringe (or UV-curing clear adhesive) | C17: Glues the glass window and the RF window (resin) into their pockets and the light-pipe tube into its counterbore in the floor. | D17: Clear, 5-minute cure, small syringe or sachets (a clear UV-curing adhesive with a UV torch also works). Use a thin bead only. Do NOT use cyanoacrylate (super glue) on the clear resin parts: its vapour leaves a white bloom. The tube sits in the 8.45 mm hole with 0.025 mm per side and a 0.2 mm ledge: glue it, do not press it. | E17: clear epoxy 5 minute syringe AB glue | F17: 3.5 | G17: 1 | H17: syringe | I17: 0 | J17: 1 | K17: =ROUNDUP(ROUND((Summary!$B$7*I17+J17)/G17,9),0) -> 1 | L17: =K17*F17 -> 3.5 | M17: =ROUNDUP(ROUND((Summary!$B$8*I17+J17)/G17,9),0) -> 1 | N17: =M17*F17 -> 3.5 | O17: Consumable | P17: ESTIMATE (typical price). | Q17: https://www.aliexpress.com/wholesale?SearchText=clear+epoxy+AB+glue+5+minute
... A20: 15 | B20: Silicone adhesive (small tube, clear or neutral-cure RTV) | C20: Sticks the two hold-down pads onto their lid bosses (a drop on each boss), so that they stay on the lid when it is opened. | D20: Neutral-cure silicone (no acetic acid smell: acetic cure can attack the copper of the PCB). A drop per boss only; keep it off the board. | E20: neutral cure silicone adhesive small tube 20ml | F20: 2.5 | G20: 1 | H20: tube | I20: 0 | J20: 1 | K20: =ROUNDUP(ROUND((Summary!$B$7*I20+J20)/G20,9),0) -> 1 | L20: =K20*F20 -> 2.5 | M20: =ROUNDUP(ROUND((Summary!$B$8*I20+J20)/G20,9),0) -> 1 | N20: =M20*F20 -> 2.5 | O20: Consumable | P20: ESTIMATE (typical price). | Q20: https://www.aliexpress.com/wholesale?SearchText=silicone+adhesive+tube+neutral+cure
B21: Bought parts (cells, LED, laser, window, screws, ring) | L21: =SUMIF($O$6:$O$20,"Part",L6:L20) -> 56.75 | N21: =SUMIF($O$6:$O$20,"Part",N6:N20) -> 211.3
B22: Consumables (wire, tapes, silicone pads, adhesives) | L22: =SUMIF($O$6:$O$20,"Consumable",L6:L20) -> 27.79 | N22: =SUMIF($O$6:$O$20,"Consumable",N6:N20) -> 27.79
B23: of which spares and left-over pack content (information) | L23: =SUM(L6:L20)-SUMPRODUCT(Summary!$B$7*I6:I20/G6:G20*F6:F20) -> 45.47 | N23: =SUM(N6:N20)-SUMPRODUCT(Summary!$B$8*I6:I20/G6:G20*F6:F20) -> 43.74
A25: Why the laser must be Class 2 (<= 1 mW)
A26: Laser classes (IEC/EN 60825-1) for visible light (400-700 nm): Class 1 = harmless in normal use; Class 2 = up to 1 mW continuous - safe for accidental exposure because the blink / aversion reflex (about 0.25 s) closes the eye before damage; Class 3R = up to 5 mW - low risk but a direct look into the beam can hurt, it is not meant for a keychain; Class 3B and 4 = dangerous. (https://en.wikipedia.org/wiki/Laser_safety)
A27: This light is a keychain that people carry and use in public, so the module must be Class 2: 520 nm green at <= 1 mW. Green looks about five times brighter than red at the same power because the eye is most sensitive near 555 nm, so 1 mW green is already a clearly visible dot.
A28: Cheap modules sold as '1 mW' often emit several mW. The housing marking text (FlashKa_marking_lid_class2.dxf: 'CLASS 2 LASER PRODUCT, 520 nm P < 1 mW EN 60825-1:2014') is only true if the module really is <= 1 mW. Buy from a seller that states a measured power, or measure it (optional laser power meter, sheet 'Tools'). If it is stronger it is a Class 3R product: do not use the Class 2 marking.
A29: For consumer laser products in the EU the standard EN 50689:2021 applies in addition (https://ul.com/insights/understand-new-laser-product-safety-standards-europe). If you only build for yourself this is a recommendation; if you sell or give lights away, read it first.
A30: Always wear 520 nm safety glasses (sheet 'Tools') when the laser is powered on the bench, and never point it at people, animals, aircraft or vehicles.
A32: Buying tips
A33: Search with the exact term in column E, sort by orders/rating, check the listed dimensions against the spec column, and read the reviews with photos. Ask the seller for the power measurement of the laser and the exact size of the LED board.
A34: Each seller ships its own parcel: 8 parcels mean 8 shipping fees and 8 x EUR 3 customs duty. Buy the small hardware (screws, rings, wire, tapes, silicone pads, epoxy) together in ONE EU web shop - see 'Hidden costs' for the saving.
A35: Order the laser, cells and LED board FIRST (delivery 2-5 weeks), measure them with a caliper, and only then order the housing, so that a different module size does not waste a CNC order.

Sheet Hidden costs
A1: Hidden costs - shipping, EU VAT, customs, bank fees, spares and risk
A2: What you pay on top of the prices of the other sheets. JLCPCB, JLCCNC and JLC3DP are three separate shops and ship three separate parcels; every AliExpress seller ships its own parcel. For Lithuania (EU) each parcel gets VAT 21 % and, since 1 July 2026, a flat EUR 3 customs duty per customs line (up to EUR 150), or formal customs clearance with a carrier fee above EUR 150. All inputs are blue; everything marked ESTIMATE has no public price (JLC shows shipping only in the cart). Read 2026-10-14 (v0.5 price check; v0.6 changed nothing here except the stainless-caps customs line).
A4: 1. Inputs: EU import rules, bank fee, shipping choice, parcels
A5: VAT rate Lithuania | B5: 0.21 | C5: fraction | D5: Lithuania standard VAT 21 %. JLC collects it at checkout for orders up to EUR 150 (IOSS). Source: https://jlcpcb.com/help/article/EU-VAT-E-commerce-Rules-%26-Adjustments (read 2026-10-14)
A6: IOSS limit: goods value per parcel (EUR) | B6: 150 | C6: EUR | D6: IOSS limit: intrinsic value (goods only, without shipping/VAT) up to EUR 150 per consignment. Source: https://jlcpcb.com/help/article/EU-VAT-E-commerce-Rules-%26-Adjustments (read 2026-10-14)
A7: Flat customs duty per customs line (EUR), up to the limit | B7: 3 | C7: EUR per customs line | D7: Flat customs duty on low-value consignments, EUR 3 per item category (HS code) per parcel, 1 Jul 2026 - 1 Jul 2028 (Council Reg. 2026/382; JLC FAQ https://jlcpcb.com/help/article/eu-customs-reform-faq). Source: https://trade.ec.europa.eu/access-to-markets/en/news/eu-applies-eu3-customs-duty-item-low-value-e-commerce-consignments (read 2026-10-14)
A8: Formal clearance: carrier fee minimum (EUR per parcel) | B8: 15 | C8: EUR per parcel | D8: Above EUR 150 the parcel goes through formal customs clearance; the carrier charges a disbursement fee, e.g. DHL Germany 2 % min EUR 15, UPS 3 % min EUR 15.70, FedEx 2.5 % min EUR 15. Source: https://jlcpcb.com/help/article/eu-customs-reform-faq (read 2026-10-14)
A9: Formal clearance: carrier fee percent of VAT + duty | B9: 0.02 | C9: fraction of VAT+duty | D9: See above (DHL Germany example). Source: https://jlcpcb.com/help/article/eu-customs-reform-faq (read 2026-10-14)
A10: Card / currency conversion fee on JLC payments | B10: 0.015 | C10: fraction | D10: ESTIMATE: card / currency-conversion fee of your bank on the USD payments to JLC (0-3 % depending on the bank). Set your own.
A11: Shipping mode (1 = economy, 2 = express) | B11: 2 | C11: 1 or 2 | D11: 1 = economy shipping, 2 = express (DHL/UPS/FedEx). Default express: fastest, and DDP (taxes paid at checkout) works most reliably.
A12: AliExpress shipping per seller parcel (USD) | B12: 2 | C12: USD per parcel | D12: ESTIMATE: AliExpress shipping to Lithuania per seller parcel (many items are free, some cost $1-4). (2026-10-14)
A13: Number of separate AliExpress / web-shop parcels | B13: 8 | C13: parcels | D13: ESTIMATE: number of separate seller parcels if you buy each item where it is cheapest (cells, LED board, laser, window, screws, rings, wire, tapes+epoxy+silicone pads).
A14: parcels if the small hardware comes from ONE EU web shop | B14: 3 | C14: parcels | D14: ESTIMATE. Parcels if you buy the small hardware (screws, rings, wire, tapes, silicone pads, epoxy) from ONE EU web shop.
A15: Risk reserve: share of a second PCB order | B15: 1 | C15: fraction | D15: Risk reserve = this fraction of the JLCPCB order (landed) as a second PCB order after a first-article problem. Not in the totals.
A16: Risk reserve: share of a second housing order | B16: 1 | C16: fraction | D16: Risk reserve = this fraction of the JLCCNC order (landed) as a second housing order. Not in the totals.
A18: 2. Shipping per parcel (USD, ESTIMATES - the JLC cart shows the real 'Shipping Estimate' before you pay)
A19: Parcel | B19: Economy A | C19: Express A | D19: Economy B | E19: Express B | F19: Chosen A | G19: Chosen B | H19: Basis
A20: JLCPCB (PCB + assembly) | B20: 6.5 | C20: 21.5 | D20: 6.5 | E20: 21.5 | F20: =IF($B$11=1,B20,C20) -> 21.5 | G20: =IF($B$11=1,D20,E20) -> 21.5 | H20: Anchors (Chiptron, 10 Jun 2025): DHL Express $21.50, EuroPacket $6.50, Global Standard Direct Line $1.50 for a small order; EEVblog 2024: FedEx about $16 to Spain. JLC publishes no rate table - the cart shows 'Shipping Estimate'.
A21: JLCCNC (tray, lid, steel caps) | B21: 7 | C21: 22 | D21: 9 | E21: 25 | F21: =IF($B$11=1,B21,C21) -> 22 | G21: =IF($B$11=1,D21,E21) -> 25 | H21: ESTIMATE. JLCCNC shows the shipping price on the invoice after you accept the quote. Aluminium parts are heavier than PCBs: 5 sets weigh about 0.2 kg; the stainless caps add a few grams.
A22: JLC3DP (resin print kit) | B22: 6.5 | C22: 21.5 | D22: 6.5 | E22: 21.5 | F22: =IF($B$11=1,B22,C22) -> 21.5 | G22: =IF($B$11=1,D22,E22) -> 21.5 | H22: ESTIMATE. A few grams of resin: shipping is the same as for a small JLCPCB parcel.
A24: 3. Customs parameters per parcel
A25: Parcel | B25: Customs lines per parcel | C25: Duty rate in formal clearance | D25: Parcels | E25: Note (rates are ASSUMPTIONS - the invoice / HS code decides; in the flat-duty case the EUR 3 per line replaces the tariff)
A26: JLCPCB (PCB + assembly) | B26: 2 | C26: 0 | D26: 1 | E26: Bare and assembled PCBs: HS 8534/8543, normally 0 % duty (assumption - check the invoice).
A27: JLCCNC (tray, lid, steel caps) | B27: =1+Housing!$B$92 -> 2 | C27: 0.06 | D27: 1 | E27: Aluminium articles HS 7616 99 90, 6 %; the three stainless caps are a second customs line (steel articles, HS 7326, about 3 %): 6 % is used for the whole parcel (assumption - check the invoice). The line count is 1 + the stainless-caps switch.
A28: JLC3DP (resin print kit) | B28: 1 | C28: 0.065 | D28: 1 | E28: Plastic articles HS 3926 90, 6.5 % (assumption - check the invoice).
A29: AliExpress / web shops | B29: 1 | C29: 0 | D29: =$B$13 -> 8 | E29: Mixed small hardware; each parcel is far below EUR 150, so the flat EUR 3 per line applies.
A31: 4. Landed cost per parcel - scenario A (one light)
A32: Parcel | B32: Goods (USD) | C32: Parcels | D32: Goods per parcel (EUR) | E32: Route | F32: Shipping (USD) | G32: Duty (USD) | H32: VAT (USD) | I32: Carrier fee (USD) | J32: Landed cost (USD) | K32: How
A33: JLCPCB (PCB + assembly) | B33: ='JLCPCB order'!$E$77 -> 174.32774 | C33: =$D$26 -> 1 | D33: =B33/C33/Summary!$B$6 -> 155.81671 | E33: =IF(D33>$B$6,"formal","IOSS") -> formal | F33: =$F$20 -> 21.5 | G33: =IF(E33="formal",$C$26*(B33+F33),$B$26*C33*$B$7*Summary!$B$6) -> 0 | H33: =$B$5*(B33+F33+IF(E33="formal",G33,0)) -> 41.123825 | I33: =IF(E33="formal",C33*MAX($B$8*Summary!$B$6,$B$9*(G33+H33)/C33),0) -> 16.782 | J33: =B33+F33+G33+H33+I33 -> 253.73356 | K33: Route = IOSS if goods per parcel <= EUR 150, otherwise formal clearance. IOSS: VAT on goods + shipping, flat duty per line. Formal: duty = rate x (goods + shipping), VAT on goods + shipping + duty, carrier fee = max(minimum, % of VAT + duty).
A34: JLCCNC (tray, lid, steel caps) | B34: =Housing!$C$101 -> 121.35751 | C34: =$D$27 -> 1 | D34: =B34/C34/Summary!$B$6 -> 108.47114 | E34: =IF(D34>$B$6,"formal","IOSS") -> IOSS | F34: =$F$21 -> 22 | G34: =IF(E34="formal",$C$27*(B34+F34),$B$27*C34*$B$7*Summary!$B$6) -> 6.7128 | H34: =$B$5*(B34+F34+IF(E34="formal",G34,0)) -> 30.105077 | I34: =IF(E34="formal",C34*MAX($B$8*Summary!$B$6,$B$9*(G34+H34)/C34),0) -> 0 | J34: =B34+F34+G34+H34+I34 -> 180.17539 | K34: Same rules for the aluminium parts and the stainless caps (two customs lines).
A35: JLC3DP (resin print kit) | B35: =Housing!$E$117 -> 1.2 | C35: =$D$28 -> 1 | D35: =B35/C35/Summary!$B$6 -> 1.0725778 | E35: =IF(D35>$B$6,"formal","IOSS") -> IOSS | F35: =$F$22 -> 21.5 | G35: =IF(E35="formal",$C$28*(B35+F35),$B$28*C35*$B$7*Summary!$B$6) -> 3.3564 | H35: =$B$5*(B35+F35+IF(E35="formal",G35,0)) -> 4.767 | I35: =IF(E35="formal",C35*MAX($B$8*Summary!$B$6,$B$9*(G35+H35)/C35),0) -> 0 | J35: =B35+F35+G35+H35+I35 -> 30.8234 | K35: Same rules for the resin print kit.
A36: AliExpress / web shops | B36: ='Bought parts'!$L$21+'Bought parts'!$L$22 -> 84.54 | C36: =$D$29 -> 8 | D36: =B36/C36/Summary!$B$6 -> 9.4453879 | E36: =IF(D36>$B$6,"formal","IOSS") -> IOSS | F36: =$B$12*C36 -> 16 | G36: =IF(E36="formal",$C$29*(B36+F36),$B$29*C36*$B$7*Summary!$B$6) -> 26.8512 | H36: =$B$5*(B36+F36+IF(E36="formal",G36,0)) -> 21.1134 | I36: =IF(E36="formal",C36*MAX($B$8*Summary!$B$6,$B$9*(G36+H36)/C36),0) -> 0 | J36: =B36+F36+G36+H36+I36 -> 148.5046 | K36: Goods = bought parts + consumables; shipping and flat duty are paid for every parcel.
A37: All parcels | B37: =SUM(B33:B36) -> 381.42525 | F37: =SUM(F33:F36) -> 81 | G37: =SUM(G33:G36) -> 36.9204 | H37: =SUM(H33:H36) -> 97.109302 | I37: =SUM(I33:I36) -> 16.782 | J37: =SUM(J33:J36) -> 613.23695
A38: Card / currency fee on the three JLC payments | J38: =$B$10*(J33+J34+J35) -> 6.9709852
A39: Shipping + VAT + duty + carrier fees + card fee (to the Summary) | J39: =F37+G37+H37+I37+J38 -> 238.78269
A41: 5. Landed cost per parcel - scenario B (five lights)
A42: Parcel | B42: Goods (USD) | C42: Parcels | D42: Goods per parcel (EUR) | E42: Route | F42: Shipping (USD) | G42: Duty (USD) | H42: VAT (USD) | I42: Carrier fee (USD) | J42: Landed cost (USD) | K42: How
A43: JLCPCB (PCB + assembly) | B43: ='JLCPCB order'!$G$77 -> 194.68669 | C43: =$D$26 -> 1 | D43: =B43/C43/Summary!$B$6 -> 174.01385 | E43: =IF(D43>$B$6,"formal","IOSS") -> formal | F43: =$G$20 -> 21.5 | G43: =IF(E43="formal",$C$26*(B43+F43),$B$26*C43*$B$7*Summary!$B$6) -> 0 | H43: =$B$5*(B43+F43+IF(E43="formal",G43,0)) -> 45.399205 | I43: =IF(E43="formal",C43*MAX($B$8*Summary!$B$6,$B$9*(G43+H43)/C43),0) -> 16.782 | J43: =B43+F43+G43+H43+I43 -> 278.3679 | K43: Route = IOSS if goods per parcel <= EUR 150, otherwise formal clearance. IOSS: VAT on goods + shipping, flat duty per line. Formal: duty = rate x (goods + shipping), VAT on goods + shipping + duty, carrier fee = max(minimum, % of VAT + duty).
A44: JLCCNC (tray, lid, steel caps) | B44: =Housing!$E$101 -> 378.78755 | C44: =$D$27 -> 1 | D44: =B44/C44/Summary!$B$6 -> 338.56592 | E44: =IF(D44>$B$6,"formal","IOSS") -> formal | F44: =$G$21 -> 25 | G44: =IF(E44="formal",$C$27*(B44+F44),$B$27*C44*$B$7*Summary!$B$6) -> 24.227253 | H44: =$B$5*(B44+F44+IF(E44="formal",G44,0)) -> 89.883108 | I44: =IF(E44="formal",C44*MAX($B$8*Summary!$B$6,$B$9*(G44+H44)/C44),0) -> 16.782 | J44: =B44+F44+G44+H44+I44 -> 534.67991 | K44: Same rules for the aluminium parts and the stainless caps (two customs lines).
A45: JLC3DP (resin print kit) | B45: =Housing!$G$117 -> 3.6 | C45: =$D$28 -> 1 | D45: =B45/C45/Summary!$B$6 -> 3.2177333 | E45: =IF(D45>$B$6,"formal","IOSS") -> IOSS | F45: =$G$22 -> 21.5 | G45: =IF(E45="formal",$C$28*(B45+F45),$B$28*C45*$B$7*Summary!$B$6) -> 3.3564 | H45: =$B$5*(B45+F45+IF(E45="formal",G45,0)) -> 5.271 | I45: =IF(E45="formal",C45*MAX($B$8*Summary!$B$6,$B$9*(G45+H45)/C45),0) -> 0 | J45: =B45+F45+G45+H45+I45 -> 33.7274 | K45: Same rules for the resin print kit.
A46: AliExpress / web shops | B46: ='Bought parts'!$N$21+'Bought parts'!$N$22 -> 239.09 | C46: =$D$29 -> 8 | D46: =B46/C46/Summary!$B$6 -> 26.712773 | E46: =IF(D46>$B$6,"formal","IOSS") -> IOSS | F46: =$B$12*C46 -> 16 | G46: =IF(E46="formal",$C$29*(B46+F46),$B$29*C46*$B$7*Summary!$B$6) -> 26.8512 | H46: =$B$5*(B46+F46+IF(E46="formal",G46,0)) -> 53.5689 | I46: =IF(E46="formal",C46*MAX($B$8*Summary!$B$6,$B$9*(G46+H46)/C46),0) -> 0 | J46: =B46+F46+G46+H46+I46 -> 335.5101 | K46: Goods = bought parts + consumables; shipping and flat duty are paid for every parcel.
A47: All parcels | B47: =SUM(B43:B46) -> 816.16424 | F47: =SUM(F43:F46) -> 84 | G47: =SUM(G43:G46) -> 54.434853 | H47: =SUM(H43:H46) -> 194.12221 | I47: =SUM(I43:I46) -> 33.564 | J47: =SUM(J43:J46) -> 1182.2853
A48: Card / currency fee on the three JLC payments | J48: =$B$10*(J43+J44+J45) -> 12.701628
A49: Shipping + VAT + duty + carrier fees + card fee (to the Summary) | J49: =F47+G47+H47+I47+J48 -> 378.82269
A51: 6. Savings and risk reserves (not in the totals)
A52: Saving if the small hardware comes from ONE EU web shop (USD) | B52: =($B$13-$B$14)*($B$12+$B$29*$B$7*Summary!$B$6) -> 26.782 | C52: Every avoided seller parcel saves its shipping and its flat EUR 3 customs duty. Look for an EU shop that sells M1.6 screws, M2 set screws, split rings, PTFE wire, Kapton, foam tape, silicone sheet or pads and epoxy (electronics and model-making shops).
A53: EUR 150 cliff: JLCPCB parcel A if it is on the IOSS route (USD, landed) | B53: =$B$33+$F$33+$B$26*$B$7*Summary!$B$6+$B$5*($B$33+$F$33) -> 243.66436 | C53: Goods + shipping + flat EUR 3 per customs line + VAT on goods and shipping.
A54: EUR 150 cliff: JLCPCB parcel A if it is on the formal-clearance route (USD, landed) | B54: =$B$33+$F$33+$C$26*($B$33+$F$33)+$B$5*($B$33+$F$33+$C$26*($B$33+$F$33))+MAX($B$8*Summary!$B$6,$B$9*($C$26*($B$33+$F$33)+$B$5*($B$33+$F$33+$C$26*($B$33+$F$33)))) -> 253.73356 | C54: Goods + shipping + tariff + VAT on goods, shipping and tariff + carrier disbursement fee (minimum EUR 15).
A55: EUR 150 cliff: formal route minus IOSS route (USD) | B55: =B54-B53 -> 10.0692 | C55: How much the first order costs MORE when the JLCPCB goods value is above EUR 150. If the real PCB price or the component prices are a few euros lower, the bill drops by about this amount.
A56: Risk reserve: second PCB + assembly order after a first-article problem (USD) | B56: =$B$15*$J$33 -> 253.73356 | C56: A new board design almost never works perfectly the first time (wrong footprint, rotation, missing pull-up). The second order costs the same JLCPCB order again, with shipping and tax. The 4 spare bare boards of the first order can be re-assembled by hand, which saves the PCB price but not the assembly.
A57: Risk reserve: second housing order (USD) | B57: =$B$16*$J$34 -> 180.17539 | C57: If the first tray does not fit the real laser/cells (or the stainless caps are refused and must be re-ordered elsewhere). Reduce the risk by measuring the delivered parts before the order and ordering ONE set first.
A59: 7. The costs people forget (amounts for scenario A and B where they are in the totals)
A60: Cost | B60: A (USD) | C60: B (USD) | D60: What it is and what to do
A61: Shipping of the 3 JLC parcels (JLCPCB, JLCCNC, JLC3DP) | B61: =$F$33+$F$34+$F$35 -> 65 | C61: =$F$43+$F$44+$F$45 -> 68 | D61: JLCPCB, JLCCNC and JLC3DP ship separately, three shipping fees. JLC publishes no rate table; anchors: DHL Express about $21.50, EuroPacket about $6.50, Global Standard Direct Line about $1.50 for a small parcel (https://chiptron.eu/jlcpcb-reduces-shipping-costs-pcb-order-with-shipping-worth-bad-beer/, June 2025), FedEx about $16 to Spain (https://eevblog.com/forum/manufacture/jlcpcb-pcb-assembly-optimal-shipping-for-eu, 2024). Economy takes weeks and may be slow at customs: use express for the first order.
A62: EU VAT 21 % (Lithuania) | B62: =$H$37 -> 97.109302 | C62: =$H$47 -> 194.12221 | D62: VAT is charged on goods + shipping. Up to EUR 150 per parcel JLC collects it at checkout (IOSS, https://jlcpcb.com/help/article/EU-VAT-E-commerce-Rules-%26-Adjustments); above EUR 150 you pay VAT and customs fees to the carrier (or at checkout with DDP).
A63: Customs duty + carrier handling fees | B63: =$G$37+$I$37 -> 53.7024 | C63: =$G$47+$I$47 -> 87.998853 | D63: Since 1 July 2026 every low-value parcel pays a flat EUR 3 duty per customs line (https://trade.ec.europa.eu/access-to-markets/en/news/eu-applies-eu3-customs-duty-item-low-value-e-commerce-consignments; JLC FAQ https://jlcpcb.com/help/article/eu-customs-reform-faq). Above EUR 150 the normal tariff and formal clearance apply and the carrier adds a disbursement fee (DHL Germany 2 % min EUR 15, UPS 3 % min EUR 15.70, FedEx 2.5 % min EUR 15). A unified EU handling fee (about EUR 2 per parcel) is planned from about Nov 2026 and is not included.
A64: THE EUR 150 CLIFF | B64: ='JLCPCB order'!$E$79 -> -5.8167113 | C64: ='JLCPCB order'!$G$79 -> -24.013847 | D64: EUR left until the JLCPCB order passes the IOSS limit (negative = already above). Close to the line a few euros of price change can switch the parcel to formal clearance (about EUR 10-15 more). Keep the three JLC orders separate parcels and below EUR 150 where you can (for example do not add optional services you do not need).
A65: AliExpress / web shops: shipping + flat duty | B65: =$F$36+$G$36 -> 42.8512 | C65: =$F$46+$G$46 -> 42.8512 | D65: Each seller parcel pays its own shipping and its own EUR 3 duty. See the saving in section 6.
A66: Card / currency conversion fee | B66: =$J$38 -> 6.9709852 | C66: =$J$48 -> 12.701628 | D66: JLC charges in USD. Your bank may add a conversion fee; use a card without one if you can.
A67: Spares already inside the totals: pieces JLC buys for placement loss | B67: ='Main PCB BOM'!$T$47 -> 7.0451 | C67: ='Main PCB BOM'!$W$47 -> 7.0451 | D67: JLC buys a few more resistors, capacitors and chips than the boards need (lost by the placement machine). You pay for them but do not receive them.
A68: Spares already inside the totals: bought parts and left-over packs | B68: ='Bought parts'!$L$23 -> 45.47 | C68: ='Bought parts'!$N$23 -> 43.74 | D68: Third cell, second LED board, extra screws (you WILL lose an M1.6 screw), spare glass windows, left-over pad sheets. Screws and rings come in packs of 20-100. (The spare resin parts come as one spare print kit and the spare caps as +1 piece each, both inside the housing total.)
A69: First-article risk: second PCB + assembly order (NOT in the totals) | B69: =$B$56 -> 253.73356 | D69: Budget for it. If a fix is needed, the same fees (set-up, stencil, feeder loading) are paid again.
A70: First-article risk: second housing order (NOT in the totals) | B70: =$B$57 -> 180.17539 | D70: See section 6.
A71: USB-C DATA cable (in Tools, NOT in the per-light cost) | B71: =Tools!$I$16 -> 4 | D71: Needed to charge the light and update its firmware. A charge-only cable does not work for data. You only pay if you do not have one.
A72: Price changes between now and your order | D72: LCSC prices and stock change weekly; JLC re-prices in the cart. Re-open the LCSC links in sheet 'Main PCB BOM' and watch for red lines in the JLC BOM upload.
A73: Your time and mistakes | D73: Not counted: soldering the wires, assembling the housing, testing, waiting 2-5 weeks for parcels.

Sheet Tools
A1: Tools you need once (not part of the per-light cost)
A2: JLCPCB solders all SMD parts, so you do NOT need a hot-air station, solder paste or a reflow oven. You only solder a few wires by hand (cells, LED, laser) and screw the housing together (and cut two small silicone pads). Prices are typical 2026 web-shop prices (ESTIMATES, USD, excl. VAT and shipping). 'Needed' = 1 counts the tool in the Summary, 0 = optional, not counted. If you already own a tool, set its 'Needed' to 0.
A4: # | B4: Tool | C4: Why you need it | D4: Spec that matters | E4: Search term | F4: Price each (USD) | G4: Qty | H4: Needed (1/0) | I4: Cost (USD) | J4: Basis
A5: 1 | B5: Soldering iron with fine tip | C5: Solder the wires to the pads J2, J3, J5 and fix small faults. | D5: Temperature controlled (about 300-350 C), conical or chisel tip 0.4-1 mm, e.g. Pinecil / TS101 / Hakko FX-888D class. | E5: pinecil soldering iron | F5: 35 | G5: 1 | H5: 1 | I5: =F5*G5*H5 -> 35 | J5: ESTIMATE (typical price; first priced 2026-10-14)
A6: 2 | B6: Solder wire 0.5 mm with flux core | C6: Hand soldering. | D6: 0.5 mm diameter, Sn63Pb37 or lead-free SAC305, flux core, 50 g reel. | E6: solder wire 0.5mm rosin core | F6: 8 | G6: 1 | H6: 1 | I6: =F6*G6*H6 -> 8 | J6: ESTIMATE (typical price; first priced 2026-10-14)
A7: 3 | B7: Flux (gel syringe or pen) | C7: Makes the solder flow on the small pads. | D7: No-clean flux gel in a syringe (e.g. Amtech NC-559 class) or flux pen. | E7: no clean flux gel syringe | F7: 6 | G7: 1 | H7: 1 | I7: =F7*G7*H7 -> 6 | J7: ESTIMATE (typical price; first priced 2026-10-14)
A8: 4 | B8: Fine tweezers | C8: Hold small parts and wires. | D8: ESD-safe, pointed tips, stainless; 2-3 shapes. | E8: ESD tweezers set precision | F8: 5 | G8: 1 | H8: 1 | I8: =F8*G8*H8 -> 5 | J8: ESTIMATE (typical price; first priced 2026-10-14)
A9: 5 | B9: Precision screwdriver and hex key set | C9: Lid screws (M1.6) and the M2 laser set screw. | D9: Phillips PH000/PH00 or hex 0.9 mm bits, hex key 0.9 mm for the M2 set screw. | E9: precision screwdriver set hex 0.9mm | F9: 8 | G9: 1 | H9: 1 | I9: =F9*G9*H9 -> 8 | J9: ESTIMATE (typical price; first priced 2026-10-14)
A10: 6 | B10: Multimeter | C10: Check battery voltage, shorts and continuity before the first power-up. | D10: Any basic digital multimeter with continuity buzzer, DC voltage and current. | E10: digital multimeter | F10: 15 | G10: 1 | H10: 1 | I10: =F10*G10*H10 -> 15 | J10: ESTIMATE (typical price; first priced 2026-10-14)
A11: 7 | B11: Laser safety glasses for 520 nm | C11: Eye protection whenever the laser is powered on the bench. | D11: Rated for 520 nm green, OD 4+ (e.g. '190-540 nm OD4+' or 532 nm goggles); CE / EN 207 marked. | E11: laser safety glasses 520nm 532nm OD4 | F11: 14 | G11: 1 | H11: 1 | I11: =F11*G11*H11 -> 14 | J11: ESTIMATE (typical price; first priced 2026-10-14)
A12: 8 | B12: Side cutters (flush) | C12: Trim wires and cut the resin parts off the sprues of the print kit. | D12: Small flush cutters. | E12: flush cutter mini | F12: 5 | G12: 1 | H12: 1 | I12: =F12*G12*H12 -> 5 | J12: ESTIMATE (typical price; first priced 2026-10-14)
A13: 9 | B13: Hobby knife and cutting mat | C13: Cut the two silicone hold-down pads to size (8.8 x 12.4 mm and 3.7 x 3.2 mm). | D13: Scalpel or hobby knife with spare blades, small self-healing cutting mat (A5). | E13: hobby knife cutting mat set | F13: 7 | G13: 1 | H13: 1 | I13: =F13*G13*H13 -> 7 | J13: ESTIMATE (typical price; first priced 2026-10-14, added in v0.6 on 2026-10-18)
A14: 10 | B14: Wire stripper (fine) | C14: Strip 28 AWG PTFE wire without cutting the strands. | D14: For 20-30 AWG wire. | E14: precision wire stripper 28AWG | F14: 7 | G14: 1 | H14: 1 | I14: =F14*G14*H14 -> 7 | J14: ESTIMATE (typical price; first priced 2026-10-14)
A15: 11 | B15: Isopropyl alcohol 99 % and swabs | C15: Clean flux residue and the contact surfaces before taping. | D15: 99 % isopropyl alcohol 100-250 ml, lint-free swabs. | E15: isopropyl alcohol 99 percent | F15: 6 | G15: 1 | H15: 1 | I15: =F15*G15*H15 -> 6 | J15: ESTIMATE (typical price; first priced 2026-10-14)
A16: 12 | B16: USB-C data cable | C16: Charge the light and update the firmware over USB. A charge-only cable will NOT work for data. | D16: USB-C to USB-A or USB-C, labelled 'data', 0.5-1 m. | E16: usb c data cable | F16: 4 | G16: 1 | H16: 1 | I16: =F16*G16*H16 -> 4 | J16: ESTIMATE (typical price; first priced 2026-10-14)
... A22: 18 | B22: Hand taps M1.6 and M2 with wrench | C22: Only if JLCCNC cannot cut M1.6 threads: order plain 1.25 mm / 1.6 mm holes and tap them yourself. | D22: M1.6 x 0.35 and M2 x 0.4 taps. | E22: M1.6 M2 hand tap set | F22: 10 | G22: 1 | H22: 0 | I22: =F22*G22*H22 -> 0 | J22: ESTIMATE (typical price; first priced 2026-10-14)
B23: TOOLS, one-time (needed = 1) | I23: =SUM(I5:I22) -> 135
B24: Optional tools not counted (needed = 0) | I24: =SUMPRODUCT(F5:F22,G5:G22,1-H5:H22) -> 100

Sheet Ordering checklist
A1: Ordering checklist - what to buy, in which order, which file goes where
A2: Follow the steps from top to bottom. Lead times are typical values (the shops show the real ones at the checkout). 'Charge' = what the order costs you in total at that shop (goods + shipping + VAT/duty), from sheet 'Hidden costs'; with DDP/IOSS the taxes are paid at the checkout.
A4: Step | B4: When | C4: Shop | D4: What to order | E4: Files to upload and settings | F4: Typical lead time | G4: Check before you pay | H4: Charge A (USD) | I4: Charge B (USD)
A5: 0 | B5: Today | C5: Your computer | D5: Nothing yet: update the prices. | E5: Open the LCSC links in sheet 'Main PCB BOM' (column E) and check the stock note column. Read sheet 'Summary' and change the blue cells you know better. | F5: 1 hour | G5: Is every line still in stock? Low or zero retail stock at LCSC on 2026-10-14: C15850, C15195, C1525, C11702, C485117; stock NOT read (pages not readable on 2026-10-18): C25104, C115357 (see the stock notes).
A6: 1 | B6: Day 1 | C6: AliExpress / EU web shop | D6: Bought parts: 2 cells per light + 1 spare, LED board 10 mm (+1 spare), laser module Class 2 (+ read its measured power), glass windows, screws, split rings, wire, tapes, silicone pad sheets (thermal gap pad 1.0 mm, rubber sheet 1.0 mm Shore A 70) and silicone adhesive, epoxy. | E6: Sheet 'Bought parts': search term, spec and link example for every item. Buy the small hardware from ONE web shop to save parcels. | F6: 2-5 weeks (AliExpress), 3-7 days (EU shop) | G6: Size of the cells and of the LED board in the listing; laser power stated; shipping to Lithuania included; VAT shown. | H6: ='Hidden costs'!$J$36 -> 148.5046 | I6: ='Hidden costs'!$J$46 -> 335.5101
A7: 2 | B7: Day 1 | C7: Your computer | D7: Check the order files of the package (nothing has to be generated). | E7: Ready to upload: order_files/1_JLCPCB/ (FlashKa_main_gerbers.zip, BOM_JLCPCB.csv, CPL_JLCPCB.csv); order_files/2_JLCCNC/ (FlashKa_tray.step, FlashKa_tray.pdf, FlashKa_lid.step, FlashKa_lid.pdf, FlashKa_cap_main.step, FlashKa_cap_main.pdf, FlashKa_cap_slide.step, FlashKa_cap_slide.pdf, FlashKa_marking_lid_class2.dxf, FlashKa_marking_lid_class3R.dxf, FlashKa_marking_bottom.dxf, FlashKa_marking_minus_y.dxf, FlashKa_marking_plus_y.dxf); order_files/3_JLC3DP/ (FlashKa_print_kit.stl, FlashKa_laser_sleeve.stl). Only after a change of the design: re-run tools/kicad/build_all.py (re-routes the PCB, takes long; writes production/) or the housing build, and replace the files in order_files/. | F7: 10 minutes | G7: order_files/1_JLCPCB/BOM_JLCPCB.csv must have 34 lines and 68 parts; its LCSC numbers are exactly column E of sheet 'Main PCB BOM'.
A8: 3 | B8: Day 1-2 | C8: jlcpcb.com | D8: 5 bare PCBs + PCB assembly (Standard PCBA, both sides) of 2 boards (one light) or 5 boards. | E8: Gerber: order_files/1_JLCPCB/FlashKa_main_gerbers.zip. Settings: 4 layers, 0.8 mm, ENIG, qty 5, PCB Assembly ON, both sides, qty 2 or 5, confirm parts placement. Then upload order_files/1_JLCPCB/BOM_JLCPCB.csv and order_files/1_JLCPCB/CPL_JLCPCB.csv (see sheet 'JLCPCB order', section 1). | F8: PCB 3-5 days + assembly 3-5 days + express shipping 3-5 days = about 2 weeks (the cart shows the exact build time) | G8: All BOM lines matched; part rotation and pin 1 in the placement preview (U4, U1, U2, U3, U5, Q1, Q2, Q4, Q5, J1, SW1-SW3, LED3, LED4); total below EUR 150 or accept the formal-clearance fee; shipping DDP. | H8: ='Hidden costs'!$J$33 -> 253.73356 | I8: ='Hidden costs'!$J$43 -> 278.3679
A9: 4 | B9: when the laser and cells have arrived | C9: Your desk | D9: Measure the delivered parts with a caliper. | E9: Laser body 6.0 mm x 12 mm; cell 6.0 x 16 x 47 mm incl. protection board; LED board 10.0 mm; glass 10.0 x 1.0 mm. Check the laser power if you have a meter. | F9: 30 minutes | G9: Everything fits the spec of sheet 'Bought parts'; otherwise change the housing BEFORE ordering it.
A10: 5 | B10: after step 4 | C10: jlccnc.com | D10: Tray + lid, aluminium 6061-T6, bead blast + black anodize, laser marking; the three stainless caps (cap_main x1, cap_slide x2 per light, +1 spare of each), SUS304, bead blast. | E10: Files from order_files/2_JLCCNC/: FlashKa_tray.step + FlashKa_tray.pdf, FlashKa_lid.step + FlashKa_lid.pdf, FlashKa_cap_main.step + FlashKa_cap_main.pdf, FlashKa_cap_slide.step + FlashKa_cap_slide.pdf (each drawing PDF has the SAME name as its STEP file); laser marking FlashKa_marking_lid_class2.dxf (or _class3R), FlashKa_marking_bottom.dxf, FlashKa_marking_minus_y.dxf, FlashKa_marking_plus_y.dxf. Settings: see sheet 'Housing', section 9. Order ONE set first. | F10: Quote within 24 h, 3 working days (SUS304: as fast as 5 days) + 1 day transfer + shipping 3-6 days = about 10-12 days | G10: Instant quote price -> type it in sheet 'Housing' (sections 6 and 7); M1.6 threads accepted; anodize tolerance note; the caps may be refused by size - then use another CNC service or the resin caps. | H10: ='Hidden costs'!$J$34 -> 180.17539 | I10: ='Hidden costs'!$J$44 -> 534.67991
A11: 6 | B11: after step 4 | C11: jlc3dp.com | D11: Print kit: RF window insert, LED spacer ring, antenna spacer with floor plug, light-pipe tube, resin main cap and 2 resin slide caps on 1 mm sprues, ONE part - one kit per light + one spare kit. Laser sleeve only for a 4.5 mm laser. | E11: File: order_files/3_JLC3DP/FlashKa_print_kit.stl (+ order_files/3_JLC3DP/FlashKa_laser_sleeve.stl only for a 4.5 mm laser). SLA resin 8001 translucent, as printed. | F11: build 2 days + shipping 3-6 days = about 1 week | G11: Quantity = kits (one per light + one spare). The kit is above the minimum build size; the quote may still warn about the 0.6 mm thin flanges of the resin caps (see 'Housing' section 10). | H11: ='Hidden costs'!$J$35 -> 30.8234 | I11: ='Hidden costs'!$J$45 -> 33.7274
A12: 7 | B12: when everything is there | C12: At home | D12: Inspect, assemble, test. | E12: Check every delivery against this list. Cut the resin parts off the print kit (flush cutters) and file the stubs flat; cut the two silicone pads to size (8.8 x 12.4 mm and 3.7 x 3.2 mm) and stick them on the lid bosses with a drop of silicone adhesive; glue the tube into the floor with clear epoxy (no cyanoacrylate). Solder the wires to J2 (cells), J3 (LED) and J5 (laser); check for shorts with the multimeter BEFORE connecting the cells; wear laser glasses when the laser is on. | F12: 1-2 evenings | G12: Multimeter: no short between BAT+ and GND; cells at 3.6-4.2 V.
A13: 8 | B13: after the first light works | C13: - | D13: Order the other lights (scenario B). | E13: The one-time costs (set-ups, stencil, anodizing lot, marking set-up) are already paid, so every additional light costs much less (see 'Summary', extra cost per additional light). | F13: - | G13: Keep the first light as the reference for the next batch.
C14: Total of the checkout charges (without the card fee) | H14: =SUM(H5:H13) -> 613.23695 | I14: =SUM(I5:I13) -> 1182.2853
A16: File map
A17: JLCPCB | C17: order_files/1_JLCPCB/: FlashKa_main_gerbers.zip, BOM_JLCPCB.csv, CPL_JLCPCB.csv (the files tools/kicad/build_all.py writes to production/)
A18: JLCCNC | C18: order_files/2_JLCCNC/: FlashKa_tray, FlashKa_lid, FlashKa_cap_main, FlashKa_cap_slide (each as .step + .pdf); laser marking FlashKa_marking_lid_class2.dxf (Class 2 module) or FlashKa_marking_lid_class3R.dxf (only for a module measured above 1 mW), FlashKa_marking_bottom.dxf, FlashKa_marking_minus_y.dxf, FlashKa_marking_plus_y.dxf (from cad/; the PDFs are cad/FlashKa_tray_drawing.pdf, FlashKa_lid_drawing.pdf, FlashKa_cap_main_drawing.pdf and FlashKa_cap_slide_drawing.pdf renamed to the STEP names)
A19: JLC3DP | C19: order_files/3_JLC3DP/: FlashKa_print_kit.stl (one kit per light + one spare kit); FlashKa_laser_sleeve.stl only for a 4.5 mm laser (from cad/)
A20: Nowhere | C20: Upload only the files of order_files/. cad/ and production/ hold their sources (and the parts of the kit as single files); kicad/*, firmware/*, app/* are for assembly and programming, not for ordering.
